Workbook

Sheet 29 - FIA
B1: =COUNTIF(B9:B222,">0") -> 70 | E1: =COUNTIF(E9:E222,">0") -> 79 | K1: Act Share | L1: Bmk | M1: Mandato | N1: Modelo 2.0 | O1: Meta | R1: Modelos | AE1: Interações | AK1: Clusters
K2: Meta | L2: =SQRT(SUMSQ(L9:L222)^2) -> 0.027432 | M2: =SQRT(SUMSQ(N9:N222)^2) -> 0.011518785 | N2: =SQRT(SUMSQ(Q9:Q222)^2) -> 0.019144169
E3: MF - Meta | F3: =SUMPRODUCT($D$9:$D$222,F9:F222) -> 0.03804 | K3: MF | L3: =SQRT(SUMSQ(C9:C222)^2) -> 0.02671025 | M3: =SQRT(SUMSQ(O9:O222)^2) -> 0.007646534 | O3: =SQRT(SUMSQ(D9:D222)^2) -> 0.00220325
E4: Meta - 2.0 | F4: =SUMPRODUCT($Q$9:$Q$222,F9:F222) -> 0.003124216 | Q4: MF - Meta | R4: =SUMPRODUCT($D$9:$D$222,R9:R222) -> -0.009286 | S4: =SUMPRODUCT($D$9:$D$222,S9:S222) -> 0.0183195 | T4: =SUMPRODUCT($D$9:$D$222,T9:T222) -> -0.0313 | U4: =SUMPRODUCT($D$9:$D$222,U9:U222) -> 0.0113745 | V4: =SUMPRODUCT($D$9:$D$222,V9:V222) -> 0.0011465 | W4: =SUMPRODUCT($D$9:$D$222,W9:W222) -> 0.02305 | X4: =SUMPRODUCT($D$9:$D$222,X9:X222) -> 0.025756 | Y4: =SUMPRODUCT($D$9:$D$222,Y9:Y222) -> 0.0449465 | ... BK4: =SUMPRODUCT($D$9:$D$222,BK9:BK222) -> -0.01505
E5: Meta - Mandato | F5: =SUMPRODUCT($N$9:$N$222,F9:F222) -> -0.34741047 | Q5: Meta - 2.0 | R5: =SUMPRODUCT($Q$9:$Q$222,R8:R221) -> -0.046471056 | S5: =SUMPRODUCT($Q$9:$Q$222,S8:S221) -> -0.040007952 | T5: =SUMPRODUCT($Q$9:$Q$222,T8:T221) -> -0.017175456 | U5: =SUMPRODUCT($Q$9:$Q$222,U8:U221) -> -0.014608024 | V5: =SUMPRODUCT($Q$9:$Q$222,V8:V221) -> -0.012961558 | W5: =SUMPRODUCT($Q$9:$Q$222,W8:W221) -> 0.00034341668 | X5: =SUMPRODUCT($Q$9:$Q$222,X8:X221) -> 0.014721161 | Y5: =SUMPRODUCT($Q$9:$Q$222,Y8:Y221) -> 0.049570181 | ... BK5: =SUMPRODUCT($Q$9:$Q$222,BK8:BK221) -> -0.072709137 | BM5: =SUMPRODUCT($E$9:$E$226,BM9:BM226) -> 0.095587825
E6: Meta - Bmk | F6: =SUMPRODUCT($L$9:$L$222,F9:F222) -> 0.906315 | G6: =SUMPRODUCT($L$9:$L$222,G9:G222) -> 0.452853 | Q6: Meta - Mandato | R6: =SUMPRODUCT($N$9:$N$222,R9:R222) -> -0.17557389 | S6: =SUMPRODUCT($N$9:$N$222,S9:S222) -> -0.18900412 | T6: =SUMPRODUCT($N$9:$N$222,T9:T222) -> -0.13280321 | U6: =SUMPRODUCT($N$9:$N$222,U9:U222) -> -0.19234175 | V6: =SUMPRODUCT($N$9:$N$222,V9:V222) -> -0.1852904 | W6: =SUMPRODUCT($N$9:$N$222,W9:W222) -> -0.16435662 | X6: =SUMPRODUCT($N$9:$N$222,X9:X222) -> -0.12849361 | Y6: =SUMPRODUCT($N$9:$N$222,Y9:Y222) -> -0.16076573 | ... BK6: =SUMPRODUCT($N$9:$N$222,BK9:BK222) -> -0.084940392 | BM6: =SUMPRODUCT($M$9:$M$226,BM9:BM226) -> 0.21611196
B7: =SUM(B9:B222) -> 0.9995 | E7: =SUM(E9:E222) -> 0.999 | K7: =SUM(K9:K222) -> 1.001 | M7: =SUM(M9:M222) -> 1 | P7: =SUM(P9:P222) -> 1 | Q7: Meta - Bmk | R7: =SUMPRODUCT($L$9:$L$226,R9:R226) -> 0.597192 | S7: =SUMPRODUCT($L$9:$L$226,S9:S226) -> 0.518743 | T7: =SUMPRODUCT($L$9:$L$226,T9:T226) -> 0.634127 | U7: =SUMPRODUCT($L$9:$L$226,U9:U226) -> 0.537394 | V7: =SUMPRODUCT($L$9:$L$226,V9:V226) -> 0.594603 | W7: =SUMPRODUCT($L$9:$L$226,W9:W226) -> 0.483733 | X7: =SUMPRODUCT($L$9:$L$226,X9:X226) -> 0.386664 | Y7: =SUMPRODUCT($L$9:$L$226,Y9:Y226) -> 0.425033 | ... BK7: =SUMPRODUCT($L$9:$L$226,BK9:BK226) -> 0.571743 | BM7: =SUMPRODUCT($K$9:$K$226,BM9:BM226) -> 0.1768178
A8: tickers | B8: MF | C8: MF - Ibov | D8: MF - META | E8: Bmk | F8: exp_ret_score_raw | G8: exp_ret_score | H8: sectors_c2 | I8: sectors_c1 | J8: sectors_dyn | K8: META | L8: act_weights | M8: mandato | N8: META - Mandato | O8: MF - Mandao | P8: modelo 2.0 | Q8: Meta - 2.0 | R8: ew | S8: sw_mom | T8: sw_val | U8: sw_lt_perf | V8: sw_overall | W8: rp_cc | X8: hrp_cc | Y8: mvo_overall_cc_con | Z8: ols | AA8: glmnet_bayes | AB8: rf_bayes | AC8: xgb_bayes | AD8: nn1_bayes | AE8: qv | AF8: garp | AG8: vm | AH8: sv | AI8: sm | AJ8: smcj | AK8: fac_inc_cs_value | AL8: fac_payout_yield | AM8: fac_bs_cs_value | AN8: fac_ts_value | AO8: fac_interm_momentum | AP8: fac_st_momentum | AQ8: fac_lt_profit_growth | AR8: fac_st_profit_growth | AS8: fac_surprise | AT8: fac_bs_profitability | AU8: fac_profit_margins | AV8: fac_quality | AW8: fac_mkt_risk | AX8: fac_leverage | AY8: fac_profit_vol | AZ8: fac_seasonality | BA8: fac_short_interest | BB8: fac_acc_growth | BC8: fac_accruals | BD8: fac_issuance | BE8: fac_st_reversal | BF8: fac_skewness | BG8: fac_max | BH8: fac_lt_reversal | BI8: fac_macro | BJ8: fac_liquidity | BK8: fac_size | BM8: Pessoal
A9: LOGG3 | B9: =K9 -> 0.01 | C9: =B9-E9 -> 0.01 | D9: =B9-K9 -> 0 | E9: =K9-L9 -> 0 | F9: 3.612 | G9: 3.907 | H9: bond_proxies | I9: =VLOOKUP(A9,Setores!$A$2:$C$215,2,0) -> real_estate | J9: =VLOOKUP(A9,Setores!$A$2:$C$215,3,0) -> neutral_beta | K9: 0.01 | L9: 0.01 | M9: =VLOOKUP(A9,'Mandato Ibov'!$B$1:$C$215,2,0) -> 0.017075746 | N9: =K9-M9 -> -0.0070757461 | O9: =B9-M9 -> -0.0070757461 | P9: =VLOOKUP(A9,'Mandato Ibov'!$B$2:$D$215,3,0) -> 0.0094309658 | Q9: =K9-P9 -> 0.00056903422 | R9: 0.753 | S9: 1 | T9: 0.511 | U9: 0.896 | V9: 0.882 | W9: 0.996 | X9: 1 | Y9: 1 | Z9: 0.535 | AA9: 0.54 | AB9: 1 | AC9: 0.991 | AD9: 1 | AE9: 1 | AF9: 0.092 | AG9: 0.797 | AH9: 0.298 | AI9: 0.918 | AJ9: -0.122 | AK9: -0.204 | AL9: 0.327 | AM9: -0.17 | AN9: 0.033 | AO9: 0.439 | AP9: 0.023 | AQ9: -0.072 | AR9: 0.527 | AS9: 0.52 | AT9: -0.109 | AU9: 0.759 | AV9: 0.419 | AW9: 0.344 | AX9: -0.735 | AY9: 0.03 | AZ9: -0.262 | BA9: -0.245 | BB9: 0.135 | BC9: 0.593 | BD9: 0.51 | BE9: -0.351 | BF9: -0.122 | BG9: 0.728 | BH9: -0.416 | BI9: 0.223 | BJ9: 0.369 | BK9: 0.297 | BM9: =10%*AK9+5%*AL9+2.5%*AM9+2.5%*AN9+10%*AO9+10%*AP9+10%*AQ9+5%*AR9+5%*AS9+10%*AT9+5%*AU9+5%*AY9+10%*AV9+10%*AW9 -> 0.188725
A10: FIQE3 | B10: =K10 -> 0.011 | C10: =B10-E10 -> 0.011 | D10: =B10-K10 -> 0 | E10: =K10-L10 -> 0 | F10: 3.612 | G10: 3.66 | H10: bond_proxies | I10: =VLOOKUP(A10,Setores!$A$2:$C$215,2,0) -> telecom | J10: =VLOOKUP(A10,Setores!$A$2:$C$215,3,0) -> low_beta | K10: 0.011 | L10: 0.011 | M10: =VLOOKUP(A10,'Mandato Ibov'!$B$1:$C$215,2,0) -> 0.017075746 | N10: =K10-M10 -> -0.0060757461 | O10: =B10-M10 -> -0.0060757461 | P10: =VLOOKUP(A10,'Mandato Ibov'!$B$2:$D$215,3,0) -> 0.013333522 | Q10: =K10-P10 -> -0.0023335222 | R10: 1 | S10: 1 | T10: 0.642 | U10: 1 | V10: 0.938 | W10: 1 | X10: 1 | Y10: 1 | Z10: 0.687 | AA10: 0.689 | AB10: 1 | AC10: 1 | AD10: 1 | AE10: 0.557 | AF10: 0.002 | AG10: 0.805 | AH10: -0.261 | AI10: 1 | AJ10: 0.752 | AK10: -0.205 | AL10: 0.133 | AM10: -0.805 | AN10: 0.064 | AO10: 0.751 | AP10: 1 | AQ10: 0.293 | AR10: 0.405 | AS10: 0.475 | AT10: 0.417 | AU10: 0.26 | AV10: 0.767 | AW10: 0.426 | AX10: 0.179 | AY10: 0.885 | AZ10: 0.104 | BA10: 0.583 | BB10: -0.299 | BC10: -0.201 | BD10: 0.293 | BE10: -0.371 | BF10: 0.371 | BG10: 0.682 | BH10: -0.527 | BI10: -0.401 | BJ10: 0.717 | BK10: 0.495 | BM10: =10%*AK10+5%*AL10+2.5%*AM10+2.5%*AN10+10%*AO10+10%*AP10+10%*AQ10+5%*AR10+5%*AS10+10%*AT10+5%*AU10+5%*AY10+10%*AV10+10%*AW10 -> 0.434275
A11: BMGB4 | B11: =K11 -> 0.012 | C11: =B11-E11 -> 0.012 | D11: =B11-K11 -> 0 | E11: =K11-L11 -> 0 | F11: 3.612 | G11: 3.634 | H11: pro_cyclicals | I11: =VLOOKUP(A11,Setores!$A$2:$C$215,2,0) -> banks | J11: =VLOOKUP(A11,Setores!$A$2:$C$215,3,0) -> high_beta | K11: 0.012 | L11: 0.012 | M11: =VLOOKUP(A11,'Mandato Ibov'!$B$1:$C$215,2,0) -> 0.017075746 | N11: =K11-M11 -> -0.0050757461 | O11: =B11-M11 -> -0.0050757461 | P11: =VLOOKUP(A11,'Mandato Ibov'!$B$2:$D$215,3,0) -> 0.013333522 | Q11: =K11-P11 -> -0.0013335222 | R11: 0.902 | S11: 1 | T11: 0.817 | U11: 0.911 | V11: 1 | W11: 1 | X11: 1 | Y11: 1 | Z11: 1 | AA11: 1 | AB11: 1 | AC11: 1 | AD11: 1 | AE11: 0.194 | AF11: 1 | AG11: 1 | AH11: 0.251 | AI11: 1 | AJ11: 0.23 | AK11: 0.073 | AL11: 0.54 | AM11: 0.42 | AN11: 0.223 | AO11: 0.561 | AP11: 0.813 | AQ11: 0.557 | AR11: 0.25 | AS11: -0.139 | AT11: 0.002 | AU11: -0.267 | AV11: -0.131 | AW11: 0.515 | AX11: -0.09 | AY11: 0.655 | AZ11: 0.249 | BA11: -0.003 | BB11: 0.126 | BC11: 0.215 | BD11: -0.732 | BE11: -0.363 | BF11: 0.186 | BG11: 0.936 | BH11: -0.81 | BI11: 0.082 | BJ11: 0.64 | BK11: 0.679 | BM11: =10%*AK11+5%*AL11+2.5%*AM11+2.5%*AN11+10%*AO11+10%*AP11+10%*AQ11+5%*AR11+5%*AS11+10%*AT11+5%*AU11+5%*AY11+10%*AV11+10%*AW11 -> 0.307025
A12: WIZC3 | B12: =K12 -> 0.013 | C12: =B12-E12 -> 0.013 | D12: =B12-K12 -> 0 | E12: =K12-L12 -> 0 | F12: 3.612 | G12: 3.59 | H12: defensives | I12: =VLOOKUP(A12,Setores!$A$2:$C$215,2,0) -> financial_services | J12: =VLOOKUP(A12,Setores!$A$2:$C$215,3,0) -> very_low_beta | K12: 0.013 | L12: 0.013 | M12: =VLOOKUP(A12,'Mandato Ibov'!$B$1:$C$215,2,0) -> 0.017075746 | N12: =K12-M12 -> -0.0040757461 | O12: =B12-M12 -> -0.0040757461 | P12: =VLOOKUP(A12,'Mandato Ibov'!$B$2:$D$215,3,0) -> 0.012109689 | Q12: =K12-P12 -> 0.00089031105 | R12: 1 | S12: 0.966 | T12: 1 | U12: 1 | V12: 1 | W12: 1 | X12: 1 | Y12: 0.631 | Z12: 0.724 | AA12: 0.723 | AB12: 1 | AC12: 1 | AD12: 0.99 | AE12: 1 | AF12: 0.205 | AG12: 0.421 | AH12: 0.546 | AI12: 0.997 | AJ12: 1 | AK12: 0.551 | AL12: -0.187 | AM12: -0.263 | AN12: 0.055 | AO12: 0.036 | AP12: 0.118 | AQ12: 0.271 | AR12: 0.157 | AS12: -0.346 | AT12: 0.724 | AU12: 0.403 | AV12: 1 | AW12: 0.363 | AX12: -0.062 | AY12: 0.804 | AZ12: 0.496 | BA12: -0.043 | BB12: 0.05 | BC12: 0.06 | BD12: 0.535 | BE12: -0.021 | BF12: 1 | BG12: 0.641 | BH12: -0.361 | BI12: -0.367 | BJ12: 0.614 | BK12: 0.693 | BM12: =10%*AK12+5%*AL12+2.5%*AM12+2.5%*AN12+10%*AO12+10%*AP12+10%*AQ12+5%*AR12+5%*AS12+10%*AT12+5%*AU12+5%*AY12+10%*AV12+10%*AW12 -> 0.34265
A13: JHSF3 | B13: =K13 -> 0.009 | C13: =B13-E13 -> 0.009 | D13: =B13-K13 -> 0 | E13: =K13-L13 -> 0 | F13: 3.612 | G13: 3.401 | H13: pro_cyclicals | I13: =VLOOKUP(A13,Setores!$A$2:$C$215,2,0) -> homebuilders | J13: =VLOOKUP(A13,Setores!$A$2:$C$215,3,0) -> very_high_beta | K13: 0.009 | L13: 0.009 | M13: =VLOOKUP(A13,'Mandato Ibov'!$B$1:$C$215,2,0) -> 0.017075746 | N13: =K13-M13 -> -0.0080757461 | O13: =B13-M13 -> -0.0080757461 | P13: =VLOOKUP(A13,'Mandato Ibov'!$B$2:$D$215,3,0) -> 0.013333522 | Q13: =K13-P13 -> -0.0043335222 | R13: 1 | S13: 1 | T13: 0.606 | U13: 1 | V13: 1 | W13: 1 | X13: 0.973 | Y13: 1 | Z13: 0.695 | AA13: 0.691 | AB13: 0.929 | AC13: 0.859 | AD13: 1 | AE13: 1 | AF13: 0.938 | AG13: 1 | AH13: -0.415 | AI13: 0.728 | AJ13: 0.253 | AK13: 0.296 | AL13: -0.053 | AM13: -0.411 | AN13: 0.313 | AO13: 0.632 | AP13: 0.927 | AQ13: 0.532 | AR13: 0.182 | AS13: 0.309 | AT13: 0.33 | AU13: 0.414 | AV13: 0.908 | AW13: -0.045 | AX13: 0.136 | AY13: -0.176 | AZ13: 0.537 | BA13: -0.253 | BB13: 0.008 | BC13: 0.541 | BD13: 0.647 | BE13: 0.217 | BF13: 0.151 | BG13: 0.142 | BH13: -0.857 | BI13: 0.704 | BJ13: -0.051 | BK13: -0.258 | BM13: =10%*AK13+5%*AL13+2.5%*AM13+2.5%*AN13+10%*AO13+10%*AP13+10%*AQ13+5%*AR13+5%*AS13+10%*AT13+5%*AU13+5%*AY13+10%*AV13+10%*AW13 -> 0.38935
A14: ALLD3 | B14: =K14 -> 0.007 | C14: =B14-E14 -> 0.007 | D14: =B14-K14 -> 0 | E14: =K14-L14 -> 0 | F14: 3.612 | G14: 2.765 | H14: pro_cyclicals | I14: =VLOOKUP(A14,Setores!$A$2:$C$215,2,0) -> consumer_durables | J14: =VLOOKUP(A14,Setores!$A$2:$C$215,3,0) -> very_low_beta | K14: 0.007 | L14: 0.007 | M14: =VLOOKUP(A14,'Mandato Ibov'!$B$1:$C$215,2,0) -> 0.017075746 | N14: =K14-M14 -> -0.010075746 | O14: =B14-M14 -> -0.010075746 | P14: =VLOOKUP(A14,'Mandato Ibov'!$B$2:$D$215,3,0) -> 0.013333522 | Q14: =K14-P14 -> -0.0063335222 | R14: 1 | S14: 0.646 | T14: 1 | U14: 1 | V14: 1 | W14: 1 | X14: 1 | Y14: 0.737 | Z14: 1 | AA14: 1 | AB14: 0.735 | AC14: 0.749 | AD14: 0.928 | AE14: 1 | AF14: 1 | AG14: -0.138 | AH14: 1 | AI14: -0.315 | AJ14: 1 | AK14: 0.882 | AL14: 1 | AM14: 0.451 | AN14: 0.652 | AO14: -0.808 | AP14: -0.665 | AQ14: 0.303 | AR14: 0.594 | AS14: 0.097 | AT14: 0.697 | AU14: -0.548 | AV14: 0.908 | AW14: 0.326 | AX14: 0.054 | AY14: 0.47 | AZ14: 0.604 | BA14: 0.25 | BB14: 0.292 | BC14: 0.303 | BD14: 0.594 | BE14: 0.043 | BF14: 0.097 | BG14: 0.907 | BH14: -0.345 | BI14: -0.437 | BJ14: 0.521 | BK14: 0.802 | BM14: =10%*AK14+5%*AL14+2.5%*AM14+2.5%*AN14+10%*AO14+10%*AP14+10%*AQ14+5%*AR14+5%*AS14+10%*AT14+5%*AU14+5%*AY14+10%*AV14+10%*AW14 -> 0.272525
A15: RIAA3 | B15: =K15 -> 0.01 | C15: =B15-E15 -> 0.01 | D15: =B15-K15 -> 0 | E15: =K15-L15 -> 0 | F15: 3.529 | G15: 2.727 | H15: pro_cyclicals | I15: =VLOOKUP(A15,Setores!$A$2:$C$215,2,0) -> apparel | J15: =VLOOKUP(A15,Setores!$A$2:$C$215,3,0) -> very_high_beta | K15: 0.01 | L15: 0.01 | M15: =VLOOKUP(A15,'Mandato Ibov'!$B$1:$C$215,2,0) -> 0.016684757 | N15: =K15-M15 -> -0.0066847573 | O15: =B15-M15 -> -0.0066847573 | P15: =VLOOKUP(A15,'Mandato Ibov'!$B$2:$D$215,3,0) -> 0.0098152609 | Q15: =K15-P15 -> 0.00018473915 | R15: 0.993 | S15: 0.849 | T15: 0.797 | U15: 1 | V15: 0.969 | W15: 0.786 | X15: 0.514 | Y15: 0.755 | Z15: 0.757 | AA15: 0.752 | AB15: 0.778 | AC15: 0.798 | AD15: 0.956 | AE15: 1 | AF15: 1 | AG15: 0.418 | AH15: 0.137 | AI15: 0.133 | AJ15: 0.61 | AK15: 0.556 | AL15: 0.091 | AM15: -0.118 | AN15: 0.478 | AO15: 0.227 | AP15: -0.081 | AQ15: 0.584 | AR15: 0.768 | AS15: 0.384 | AT15: 0.428 | AU15: -0.1 | AV15: 0.958 | AW15: -0.591 | AX15: 0.077 | AY15: 0.423 | AZ15: 0.629 | BA15: -0.314 | BB15: 0.211 | BC15: 0.019 | BD15: 0.625 | BE15: 0.234 | BF15: -0.288 | BG15: 0.204 | BH15: -0.488 | BI15: 0.292 | BJ15: 0.253 | BK15: 0.206 | BM15: =10%*AK15+5%*AL15+2.5%*AM15+2.5%*AN15+10%*AO15+10%*AP15+10%*AQ15+5%*AR15+5%*AS15+10%*AT15+5%*AU15+5%*AY15+10%*AV15+10%*AW15 -> 0.2954
A16: GRND3 | B16: =K16 -> 0.012 | C16: =B16-E16 -> 0.012 | D16: =B16-K16 -> 0 | E16: =K16-L16 -> 0 | F16: 3.497 | G16: 3.76 | H16: pro_cyclicals | I16: =VLOOKUP(A16,Setores!$A$2:$C$215,2,0) -> apparel | J16: =VLOOKUP(A16,Setores!$A$2:$C$215,3,0) -> very_low_beta | K16: 0.012 | L16: 0.012 | M16: =VLOOKUP(A16,'Mandato Ibov'!$B$1:$C$215,2,0) -> 0.016533418 | N16: =K16-M16 -> -0.0045334184 | O16: =B16-M16 -> -0.0045334184 | P16: =VLOOKUP(A16,'Mandato Ibov'!$B$2:$D$215,3,0) -> 0.010017892 | Q16: =K16-P16 -> 0.0019821083 | R16: 0.737 | S16: 0.61 | T16: 0.678 | U16: 0.687 | V16: 0.675 | W16: 1 | X16: 1 | Y16: 0.978 | Z16: 0.556 | AA16: 0.559 | AB16: 0.894 | AC16: 0.839 | AD16: 0.891 | AE16: 0.847 | AF16: 0.063 | AG16: -0.123 | AH16: 0.027 | AI16: 0.129 | AJ16: 0.847 | AK16: 0.135 | AL16: 0.948 | AM16: -0.477 | AN16: 0.54 | AO16: 0.169 | AP16: -0.258 | AQ16: -0.023 | AR16: 0.299 | AS16: -0.168 | AT16: 0.205 | AU16: 0.159 | AV16: 0.17 | AW16: 0.518 | AX16: 0.774 | AY16: 0.495 | AZ16: -0.049 | BA16: 0.102 | BB16: 0.553 | BC16: 0.507 | BD16: 0.546 | BE16: 0.211 | BF16: 0.048 | BG16: 0.829 | BH16: -0.075 | BI16: -0.358 | BJ16: 0.197 | BK16: 0.347 | BM16: =10%*AK16+5%*AL16+2.5%*AM16+2.5%*AN16+10%*AO16+10%*AP16+10%*AQ16+5%*AR16+5%*AS16+10%*AT16+5%*AU16+5%*AY16+10%*AV16+10%*AW16 -> 0.179825
A17: HBRE3 | B17: =K17 -> 0.008 | C17: =B17-E17 -> 0.008 | D17: =B17-K17 -> 0 | E17: =K17-L17 -> 0 | F17: 3.378 | G17: 2.579 | H17: bond_proxies | I17: =VLOOKUP(A17,Setores!$A$2:$C$215,2,0) -> real_estate | J17: =VLOOKUP(A17,Setores!$A$2:$C$215,3,0) -> very_high_beta | K17: 0.008 | L17: 0.008 | M17: =VLOOKUP(A17,'Mandato Ibov'!$B$1:$C$215,2,0) -> 0.015969711 | N17: =K17-M17 -> -0.0079697112 | O17: =B17-M17 -> -0.0079697112 | P17: =VLOOKUP(A17,'Mandato Ibov'!$B$2:$D$215,3,0) -> 0.0062313314 | Q17: =K17-P17 -> 0.0017686686 | R17: 1 | S17: 1 | T17: 1 | U17: 0.702 | V17: 1 | W17: 0.86 | X17: 0.81 | Y17: 0.47 | Z17: 0.557 | AA17: 0.556 | AB17: 0.644 | AC17: 0.81 | AD17: 0.978 | AE17: 0.237 | AF17: 1 | AG17: 1 | AH17: 1 | AI17: 0.384 | AJ17: -0.225 | AK17: 0.75 | AL17: -0.02 | AM17: 1 | AN17: 0.775 | AO17: -0.097 | AP17: -0.185 | AQ17: -0.221 | AR17: 0.343 | AS17: 0.114 | AT17: -0.228 | AU17: 0.47 | AV17: -0.336 | AW17: -0.048 | AX17: -0.714 | AY17: -0.344 | AZ17: 0.126 | BA17: 0.847 | BB17: 0.166 | BC17: 0.739 | BD17: 0.326 | BE17: -0.001 | BF17: 0.315 | BG17: 0.283 | BH17: 0.154 | BI17: 0.819 | BJ17: 0.621 | BK17: 0.974 | BM17: =10%*AK17+5%*AL17+2.5%*AM17+2.5%*AN17+10%*AO17+10%*AP17+10%*AQ17+5%*AR17+5%*AS17+10%*AT17+5%*AU17+5%*AY17+10%*AV17+10%*AW17 -> 0.036025
A18: POMO3 | B18: =K18 -> 0.009 | C18: =B18-E18 -> 0.009 | D18: =B18-K18 -> 0 | E18: =K18-L18 -> 0 | F18: 3.324 | G18: 2.979 | H18: industrials | I18: =VLOOKUP(A18,Setores!$A$2:$C$215,2,0) -> capital_goods | J18: =VLOOKUP(A18,Setores!$A$2:$C$215,3,0) -> neutral_beta | K18: 0.009 | L18: 0.009 | M18: =VLOOKUP(A18,'Mandato Ibov'!$B$1:$C$215,2,0) -> 0.015715049 | N18: =K18-M18 -> -0.0067150492 | O18: =B18-M18 -> -0.0067150492 | P18: =VLOOKUP(A18,'Mandato Ibov'!$B$2:$D$215,3,0) -> 0.010094922 | Q18: =K18-P18 -> -0.0010949224 | R18: 0.621 | S18: 0.14 | T18: 0.397 | U18: 0.923 | V18: 0.539 | W18: 0.848 | X18: 0.816 | Y18: 1 | Z18: 0.632 | AA18: 0.633 | AB18: 0.946 | AC18: 0.86 | AD18: 0.854 | AE18: 1 | AF18: 0.59 | AG18: 0.154 | AH18: -0.454 | AI18: -0.03 | AJ18: 0.096 | AK18: -0.035 | AL18: 0.628 | AM18: -0.685 | AN18: 0.375 | AO18: 0.287 | AP18: 0.448 | AQ18: 0.599 | AR18: 0.283 | AS18: -0.498 | AT18: 0.614 | AU18: -0.337 | AV18: 0.644 | AW18: 0.41 | AX18: 0.114 | AY18: 0.843 | AZ18: 0.741 | BA18: 0.226 | BB18: -0.159 | BC18: -0.188 | BD18: 0.438 | BE18: -0.417 | BF18: 0.146 | BG18: 0.346 | BH18: -0.961 | BI18: 0.172 | BJ18: 0.73 | BK18: -0.151 | BM18: =10%*AK18+5%*AL18+2.5%*AM18+2.5%*AN18+10%*AO18+10%*AP18+10%*AQ18+5%*AR18+5%*AS18+10%*AT18+5%*AU18+5%*AY18+10%*AV18+10%*AW18 -> 0.3349
A19: MTRE3 | B19: =K19 -> 0.017 | C19: =B19-E19 -> 0.017 | D19: =B19-K19 -> 0 | E19: =K19-L19 -> 0 | F19: 3.23 | G19: 3.533 | H19: pro_cyclicals | I19: =VLOOKUP(A19,Setores!$A$2:$C$215,2,0) -> homebuilders | J19: =VLOOKUP(A19,Setores!$A$2:$C$215,3,0) -> low_beta | K19: 0.017 | L19: 0.017 | M19: =VLOOKUP(A19,'Mandato Ibov'!$B$1:$C$215,2,0) -> 0.015271697 | N19: =K19-M19 -> 0.0017283027 | O19: =B19-M19 -> 0.0017283027 | P19: =VLOOKUP(A19,'Mandato Ibov'!$B$2:$D$215,3,0) -> 0.011876963 | Q19: =K19-P19 -> 0.0051230374 | R19: 0.688 | S19: 0.794 | T19: 0.801 | U19: 0.52 | V19: 0.767 | W19: 0.688 | X19: 0.667 | Y19: 0.602 | Z19: 0.676 | AA19: 0.672 | AB19: 1 | AC19: 0.934 | AD19: 0.937 | AE19: -0.026 | AF19: 1 | AG19: 0.535 | AH19: 1 | AI19: 0.456 | AJ19: 0.016 | AK19: 0.147 | AL19: 0.699 | AM19: 0.319 | AN19: 0.416 | AO19: -0.131 | AP19: -0.245 | AQ19: 0.252 | AR19: 0.546 | AS19: 0.171 | AT19: -0.031 | AU19: -0.327 | AV19: -0.239 | AW19: -0.015 | AX19: -0.326 | AY19: 0.678 | AZ19: 0.185 | BA19: 0.058 | BB19: -0.186 | BC19: -0.07 | BD19: 0.244 | BE19: -0.151 | BF19: 0.367 | BG19: 0.853 | BH19: -0.061 | BI19: 0.12 | BJ19: 0.609 | BK19: 0.875 | BM19: =10%*AK19+5%*AL19+2.5%*AM19+2.5%*AN19+10%*AO19+10%*AP19+10%*AQ19+5%*AR19+5%*AS19+10%*AT19+5%*AU19+5%*AY19+10%*AV19+10%*AW19 -> 0.080525
A20: MLAS3 | B20: =K20 -> 0.006 | C20: =B20-E20 -> 0.006 | D20: =B20-K20 -> 0 | E20: =K20-L20 -> 0 | F20: 2.937 | G20: 2.169 | H20: pro_cyclicals | I20: =VLOOKUP(A20,Setores!$A$2:$C$215,2,0) -> tech | J20: =VLOOKUP(A20,Setores!$A$2:$C$215,3,0) -> high_beta | K20: 0.006 | L20: 0.006 | M20: =VLOOKUP(A20,'Mandato Ibov'!$B$1:$C$215,2,0) -> 0.013885916 | N20: =K20-M20 -> -0.0078859164 | O20: =B20-M20 -> -0.0078859164 | P20: =VLOOKUP(A20,'Mandato Ibov'!$B$2:$D$215,3,0) -> 0.010388373 | Q20: =K20-P20 -> -0.0043883734 | R20: 1 | S20: 1 | T20: 1 | U20: 1 | V20: 1 | W20: 0.184 | X20: -0.575 | Y20: 0.389 | Z20: 0.348 | AA20: 0.347 | AB20: 0.766 | AC20: 0.793 | AD20: 1 | AE20: 1 | AF20: 1 | AG20: 1 | AH20: 0.588 | AI20: 0.898 | AJ20: 1 | AK20: 0.424 | AL20: -0.809 | AM20: 0.445 | AN20: 0.341 | AO20: 0.355 | AP20: 0.382 | AQ20: 0.7 | AR20: 0.664 | AS20: 0.366 | AT20: 0.137 | AU20: -0.445 | AV20: 0.858 | AW20: -0.528 | AX20: 0.358 | AY20: 0.413 | AZ20: -0.318 | BA20: 0.932 | BB20: 0.336 | BC20: 0.234 | BD20: 0.799 | BE20: -1 | BF20: -0.382 | BG20: -1 | BH20: 0.533 | BI20: -0.127 | BJ20: 0.917 | BK20: 0.464 | BM20: =10%*AK20+5%*AL20+2.5%*AM20+2.5%*AN20+10%*AO20+10%*AP20+10%*AQ20+5%*AR20+5%*AS20+10%*AT20+5%*AU20+5%*AY20+10%*AV20+10%*AW20 -> 0.2619
... A24: MILS3 | B24: =K24 -> 0.014 | C24: =B24-E24 -> 0.014 | D24: =B24-K24 -> 0 | E24: =K24-L24 -> 0 | F24: 2.64 | G24: 3.318 | H24: industrials | I24: =VLOOKUP(A24,Setores!$A$2:$C$215,2,0) -> building_materials | J24: =VLOOKUP(A24,Setores!$A$2:$C$215,3,0) -> neutral_beta | K24: 0.014 | L24: 0.014 | M24: =VLOOKUP(A24,'Mandato Ibov'!$B$1:$C$215,2,0) -> 0.012479044 | N24: =K24-M24 -> 0.0015209563 | O24: =B24-M24 -> 0.0015209563 | P24: =VLOOKUP(A24,'Mandato Ibov'!$B$2:$D$215,3,0) -> 0.0065569514 | Q24: =K24-P24 -> 0.0074430486 | R24: 0.499 | S24: 0.281 | T24: 0.11 | U24: 0.375 | V24: 0.126 | W24: 0.673 | X24: 0.953 | Y24: 0.191 | Z24: 0.702 | AA24: 0.697 | AB24: 0.904 | AC24: 0.888 | AD24: 0.845 | AE24: 0.022 | AF24: 0.116 | AG24: -0.165 | AH24: -0.341 | AI24: 0.346 | AJ24: 0.006 | AK24: -0.056 | AL24: -0.236 | AM24: -0.617 | AN24: 0.825 | AO24: 0.209 | AP24: -0.249 | AQ24: 0.34 | AR24: 0.864 | AS24: 0.258 | AT24: 0.436 | AU24: 0.442 | AV24: 0.325 | AW24: 0.397 | AX24: 0.044 | AY24: 0.384 | AZ24: 0.607 | BA24: 0.466 | BB24: -0.293 | BC24: -0.375 | BD24: 0.399 | BE24: -0.373 | BF24: -0.309 | BG24: 0.808 | BH24: -0.483 | BI24: 0.215 | BJ24: 0.295 | BK24: 0.047 | BM24: =10%*AK24+5%*AL24+2.5%*AM24+2.5%*AN24+10%*AO24+10%*AP24+10%*AQ24+5%*AR24+5%*AS24+10%*AT24+5%*AU24+5%*AY24+10%*AV24+10%*AW24 -> 0.231
A25: AURA33 | B25: 0.005 | C25: =B25-E25 -> 0.005 | D25: =B25-K25 -> 0 | E25: =K25-L25 -> 0 | F25: 2.624 | G25: 1.869 | H25: commodities | I25: =VLOOKUP(A25,Setores!$A$2:$C$215,2,0) -> basic_materials | J25: =VLOOKUP(A25,Setores!$A$2:$C$215,3,0) -> very_high_beta | K25: 0.005 | L25: 0.005 | M25: =VLOOKUP(A25,'Mandato Ibov'!$B$1:$C$215,2,0) -> 0.012407119 | N25: =K25-M25 -> -0.0074071192 | O25: =B25-M25 -> -0.0074071192 | P25: =VLOOKUP(A25,'Mandato Ibov'!$B$2:$D$215,3,0) -> 0.011528512 | Q25: =K25-P25 -> -0.0065285117 | R25: 0.33 | S25: 0.658 | T25: -0.467 | U25: 0.589 | V25: 0.203 | W25: 0.227 | X25: -0.08 | Y25: 0.47 | Z25: 1 | AA25: 1 | AB25: 0.871 | AC25: 0.996 | AD25: 0.966 | AE25: -0.265 | AF25: -0.508 | AG25: 1 | AH25: -0.754 | AI25: 0.041 | AJ25: -0.678 | AK25: 0.101 | AL25: -0.546 | AM25: -0.202 | AN25: -0.543 | AO25: 0.834 | AP25: 0.811 | AQ25: 0.495 | AR25: 0.922 | AS25: 0.363 | AT25: 0.956 | AU25: 0.373 | AV25: 0.835 | AW25: 0.046 | AX25: 0.167 | AY25: -0.353 | AZ25: 0.141 | BA25: 0.657 | BB25: -0.282 | BC25: 0.33 | BD25: 0.646 | BE25: 1 | BF25: -0.364 | BG25: -0.786 | BH25: -1 | BI25: 0.361 | BJ25: -0.019 | BK25: -0.455 | BM25: =10%*AK25+5%*AL25+2.5%*AM25+2.5%*AN25+10%*AO25+10%*AP25+10%*AQ25+5%*AR25+5%*AS25+10%*AT25+5%*AU25+5%*AY25+10%*AV25+10%*AW25 -> 0.427125
A26: BRAP4 | B26: 0.015 | C26: =B26-E26 -> 0.013 | D26: =B26-K26 -> 0.015 | E26: =K26-L26 -> 0.002 | F26: 2.61 | G26: 3.517 | H26: commodities | I26: =VLOOKUP(A26,Setores!$A$2:$C$215,2,0) -> basic_materials | J26: =VLOOKUP(A26,Setores!$A$2:$C$215,3,0) -> neutral_beta | K26: 0 | L26: -0.002 | M26: =VLOOKUP(A26,'Mandato Ibov'!$B$1:$C$215,2,0) -> 0.014702989 | N26: =K26-M26 -> -0.014702989 | O26: =B26-M26 -> 0.00029701084 | P26: =VLOOKUP(A26,'Mandato Ibov'!$B$2:$D$215,3,0) -> 0.010668914 | Q26: =K26-P26 -> -0.010668914 | R26: -0.117 | S26: 0.408 | T26: -0.566 | U26: 0.127 | V26: 0.055 | W26: 0.433 | X26: 0.593 | Y26: 0.848 | Z26: 0.813 | AA26: 0.809 | AB26: 0.865 | AC26: 0.767 | AD26: 0.939 | AE26: -0.158 | AF26: -0.605 | AG26: 0.574 | AH26: -0.65 | AI26: 0.298 | AJ26: -0.491 | AK26: -0.306 | AL26: 0.621 | AM26: -0.439 | AN26: -0.491 | AO26: 0.871 | AP26: 0.225 | AQ26: -0.772 | AR26: 0.686 | AS26: 0.403 | AT26: 0.044 | AU26: 0.12 | AV26: 0.119 | AW26: 0.563 | AX26: 0.02 | AY26: 0.553 | AZ26: -0.787 | BA26: 0.341 | BB26: -0.091 | BC26: 0.377 | BD26: 0.602 | BE26: -0.327 | BF26: 0.335 | BG26: 0.673 | BH26: -0.403 | BI26: -0.36 | BJ26: -0.277 | BK26: 0.096 | BM26: =10%*AK26+5%*AL26+2.5%*AM26+2.5%*AN26+10%*AO26+10%*AP26+10%*AQ26+5%*AR26+5%*AS26+10%*AT26+5%*AU26+5%*AY26+10%*AV26+10%*AW26 -> 0.1703
A27: INTB3 | B27: =K27 -> 0.009 | C27: =B27-E27 -> 0.009 | D27: =B27-K27 -> 0 | E27: =K27-L27 -> 0 | F27: 2.602 | G27: 2.255 | H27: pro_cyclicals | I27: =VLOOKUP(A27,Setores!$A$2:$C$215,2,0) -> tech | J27: =VLOOKUP(A27,Setores!$A$2:$C$215,3,0) -> high_beta | K27: 0.009 | L27: 0.009 | M27: =VLOOKUP(A27,'Mandato Ibov'!$B$1:$C$215,2,0) -> 0.012303015 | N27: =K27-M27 -> -0.0033030146 | O27: =B27-M27 -> -0.0033030146 | P27: =VLOOKUP(A27,'Mandato Ibov'!$B$2:$D$215,3,0) -> 0.0088324624 | Q27: =K27-P27 -> 0.00016753762 | R27: 0.713 | S27: 0.611 | T27: 0.232 | U27: 0.683 | V27: 0.433 | W27: 0.275 | X27: -0.007 | Y27: 0.343 | Z27: 0.233 | AA27: 0.236 | AB27: 0.994 | AC27: 0.89 | AD27: 0.877 | AE27: 0.834 | AF27: -0.139 | AG27: 0.116 | AH27: -0.401 | AI27: 0.139 | AJ27: 0.278 | AK27: 0.113 | AL27: -0.288 | AM27: -0.698 | AN27: 0.721 | AO27: 0.292 | AP27: 0.791 | AQ27: 0.076 | AR27: 0.815 | AS27: 0.804 | AT27: 0.594 | AU27: -0.229 | AV27: 0.842 | AW27: 0.182 | AX27: 0.495 | AY27: 0.755 | AZ27: -0.271 | BA27: 0.618 | BB27: 0.087 | BC27: 0.413 | BD27: 0.444 | BE27: -0.994 | BF27: -1 | BG27: -0.447 | BH27: 0.165 | BI27: 0.038 | BJ27: 0.025 | BK27: -0.151 | BM27: =10%*AK27+5%*AL27+2.5%*AM27+2.5%*AN27+10%*AO27+10%*AP27+10%*AQ27+5%*AR27+5%*AS27+10%*AT27+5%*AU27+5%*AY27+10%*AV27+10%*AW27 -> 0.382425
A28: SEER3 | B28: =K28 -> 0.007 | C28: =B28-E28 -> 0.007 | D28: =B28-K28 -> 0 | E28: =K28-L28 -> 0 | F28: 2.593 | G28: 1.861 | H28: pro_cyclicals | I28: =VLOOKUP(A28,Setores!$A$2:$C$215,2,0) -> education | J28: =VLOOKUP(A28,Setores!$A$2:$C$215,3,0) -> high_beta | K28: 0.007 | L28: 0.007 | M28: =VLOOKUP(A28,'Mandato Ibov'!$B$1:$C$215,2,0) -> 0.012257287 | N28: =K28-M28 -> -0.0052572869 | O28: =B28-M28 -> -0.0052572869 | P28: =VLOOKUP(A28,'Mandato Ibov'!$B$2:$D$215,3,0) -> 0.008440764 | Q28: =K28-P28 -> -0.001440764 | R28: 0.799 | S28: 0.628 | T28: 0.588 | U28: 0.725 | V28: 0.601 | W28: 0.413 | X28: 0.161 | Y28: 0.164 | Z28: 0.2 | AA28: 0.2 | AB28: 0.822 | AC28: 0.583 | AD28: 0.888 | AE28: 0.877 | AF28: 0.457 | AG28: 0.337 | AH28: -0.034 | AI28: 1 | AJ28: 1 | AK28: 0.184 | AL28: -0.76 | AM28: -0.528 | AN28: 0.457 | AO28: 0.25 | AP28: 0.472 | AQ28: 0.472 | AR28: 0.559 | AS28: 0.038 | AT28: 0.459 | AU28: 0.08 | AV28: 0.998 | AW28: -0.629 | AX28: 0.002 | AY28: 0.747 | AZ28: 0.525 | BA28: 0.273 | BB28: -0.008 | BC28: 0.049 | BD28: 0.526 | BE28: -0.135 | BF28: 0.544 | BG28: 0.223 | BH28: -0.623 | BI28: 0.273 | BJ28: -0.049 | BK28: 0.547 | BM28: =10%*AK28+5%*AL28+2.5%*AM28+2.5%*AN28+10%*AO28+10%*AP28+10%*AQ28+5%*AR28+5%*AS28+10%*AT28+5%*AU28+5%*AY28+10%*AV28+10%*AW28 -> 0.252025
A29: PETR4 | B29: 0.05 | C29: =B29-E29 -> -0.03 | D29: =B29-K29 -> 0.02 | E29: =K29-L29 -> 0.08 | F29: 2.559 | G29: 5.077 | H29: commodities | I29: =VLOOKUP(A29,Setores!$A$2:$C$215,2,0) -> crude_oil | J29: =VLOOKUP(A29,Setores!$A$2:$C$215,3,0) -> very_low_beta | K29: 0.03 | L29: -0.05 | M29: =VLOOKUP(A29,'Mandato Ibov'!$B$1:$C$215,2,0) -> 0.066604102 | N29: =K29-M29 -> -0.036604102 | O29: =B29-M29 -> -0.016604102 | P29: =VLOOKUP(A29,'Mandato Ibov'!$B$2:$D$215,3,0) -> 0.073419563 | Q29: =K29-P29 -> -0.043419563 | R29: -0.294 | S29: 0.28 | T29: -0.853 | U29: 0.315 | V29: -0.04 | W29: 0.447 | X29: 0.531 | Y29: 1 | Z29: 1 | AA29: 1 | AB29: 0.561 | AC29: 0.73 | AD29: 0.889 | AE29: -0.018 | AF29: -0.745 | AG29: 1 | AH29: -0.935 | AI29: -0.544 | AJ29: -0.922 | AK29: 0.151 | AL29: 0.432 | AM29: -0.542 | AN29: -0.647 | AO29: 0.944 | AP29: 1 | AQ29: -0.335 | AR29: 0.145 | AS29: 0.035 | AT29: 0.412 | AU29: 0.269 | AV29: 0.23 | AW29: 0.503 | AX29: -0.212 | AY29: 0.743 | AZ29: 0.389 | BA29: 0.391 | BB29: -0.151 | BC29: -0.213 | BD29: 0.601 | BE29: -0.679 | BF29: 0.293 | BG29: 0.392 | BH29: -0.907 | BI29: -1 | BJ29: -0.247 | BK29: -0.898 | BM29: =10%*AK29+5%*AL29+2.5%*AM29+2.5%*AN29+10%*AO29+10%*AP29+10%*AQ29+5%*AR29+5%*AS29+10%*AT29+5%*AU29+5%*AY29+10%*AV29+10%*AW29 -> 0.341975
A30: PINE4 | B30: =K30 -> 0.008 | C30: =B30-E30 -> 0.008 | D30: =B30-K30 -> 0 | E30: =K30-L30 -> 0 | F30: 2.523 | G30: 1.934 | H30: pro_cyclicals | I30: =VLOOKUP(A30,Setores!$A$2:$C$215,2,0) -> banks | J30: =VLOOKUP(A30,Setores!$A$2:$C$215,3,0) -> neutral_beta | K30: 0.008 | L30: 0.008 | M30: =VLOOKUP(A30,'Mandato Ibov'!$B$1:$C$215,2,0) -> 0.011926821 | N30: =K30-M30 -> -0.0039268207 | O30: =B30-M30 -> -0.0039268207 | P30: =VLOOKUP(A30,'Mandato Ibov'!$B$2:$D$215,3,0) -> 0.013333522 | Q30: =K30-P30 -> -0.0053335222 | R30: 0.326 | S30: 0.392 | T30: 0.235 | U30: 0.476 | V30: 0.399 | W30: 0.138 | X30: -0.048 | Y30: 0.493 | Z30: 0.473 | AA30: 0.47 | AB30: 0.884 | AC30: 0.924 | AD30: 0.946 | AE30: -0.175 | AF30: 0.657 | AG30: 0.655 | AH30: -0.403 | AI30: 1 | AJ30: 0.653 | AK30: -0.112 | AL30: -0.07 | AM30: -0.407 | AN30: 0.058 | AO30: 0.543 | AP30: 0.466 | AQ30: 0.992 | AR30: 0.512 | AS30: -0.163 | AT30: 0.192 | AU30: -0.232 | AV30: 0.085 | AW30: 0.364 | AX30: -0.141 | AY30: 0.476 | AZ30: 0.444 | BA30: 0.333 | BB30: -0.502 | BC30: -0.023 | BD30: -0.603 | BE30: -0.496 | BF30: 0.188 | BG30: -0.108 | BH30: -1 | BI30: -0.204 | BJ30: 0.437 | BK30: 0.638 | BM30: =10%*AK30+5%*AL30+2.5%*AM30+2.5%*AN30+10%*AO30+10%*AP30+10%*AQ30+5%*AR30+5%*AS30+10%*AT30+5%*AU30+5%*AY30+10%*AV30+10%*AW30 -> 0.270425
A31: POMO4 | B31: 0.01 | C31: =B31-E31 -> 0.008 | D31: =B31-K31 -> -0.001 | E31: =K31-L31 -> 0.002 | F31: 2.518 | G31: 2.471 | H31: industrials | I31: =VLOOKUP(A31,Setores!$A$2:$C$215,2,0) -> capital_goods | J31: =VLOOKUP(A31,Setores!$A$2:$C$215,3,0) -> high_beta | K31: 0.011 | L31: 0.009 | M31: =VLOOKUP(A31,'Mandato Ibov'!$B$1:$C$215,2,0) -> 0.013461488 | N31: =K31-M31 -> -0.0024614881 | O31: =B31-M31 -> -0.0034614881 | P31: =VLOOKUP(A31,'Mandato Ibov'!$B$2:$D$215,3,0) -> 0.0083488415 | Q31: =K31-P31 -> 0.0026511585 | R31: 0.34 | S31: -0.216 | T31: -0.007 | U31: 0.643 | V31: 0.168 | W31: 0.679 | X31: 0.757 | Y31: 0.581 | Z31: 0.311 | AA31: 0.313 | AB31: 0.798 | AC31: 0.779 | AD31: 0.693 | AE31: 1 | AF31: 0.575 | AG31: -0.214 | AH31: -0.459 | AI31: -0.306 | AJ31: 0.088 | AK31: -0.035 | AL31: 0.433 | AM31: -0.685 | AN31: 0.428 | AO31: 0.057 | AP31: 0.312 | AQ31: 0.599 | AR31: 0.283 | AS31: -0.498 | AT31: 0.614 | AU31: -0.337 | AV31: 0.639 | AW31: 0.414 | AX31: 0.114 | AY31: 0.843 | AZ31: 0.561 | BA31: 0.448 | BB31: -0.159 | BC31: -0.188 | BD31: 0.3 | BE31: -0.187 | BF31: 0.027 | BG31: 0.588 | BH31: -0.854 | BI31: 0.346 | BJ31: -0.382 | BK31: -0.151 | BM31: =10%*AK31+5%*AL31+2.5%*AM31+2.5%*AN31+10%*AO31+10%*AP31+10%*AQ31+5%*AR31+5%*AS31+10%*AT31+5%*AU31+5%*AY31+10%*AV31+10%*AW31 -> 0.289775
A32: PETR3 | B32: 0.044 | C32: =B32-E32 -> 0 | D32: =B32-K32 -> 0.014 | E32: =K32-L32 -> 0.044 | F32: 2.471 | G32: 4.491 | H32: commodities | I32: =VLOOKUP(A32,Setores!$A$2:$C$215,2,0) -> crude_oil | J32: =VLOOKUP(A32,Setores!$A$2:$C$215,3,0) -> very_low_beta | K32: 0.03 | L32: -0.014 | M32: =VLOOKUP(A32,'Mandato Ibov'!$B$1:$C$215,2,0) -> 0.064329874 | N32: =K32-M32 -> -0.034329874 | O32: =B32-M32 -> -0.020329874 | P32: =VLOOKUP(A32,'Mandato Ibov'!$B$2:$D$215,3,0) -> 0.072962312 | Q32: =K32-P32 -> -0.042962312 | R32: -0.308 | S32: 0.263 | T32: -0.848 | U32: 0.265 | V32: -0.067 | W32: 0.358 | X32: 0.396 | Y32: 0.946 | Z32: 1 | AA32: 1 | AB32: 0.596 | AC32: 0.756 | AD32: 0.885 | AE32: -0.089 | AF32: -0.771 | AG32: 1 | AH32: -0.944 | AI32: -0.568 | AJ32: -0.926 | AK32: 0.151 | AL32: 0.357 | AM32: -0.542 | AN32: -0.658 | AO32: 0.935 | AP32: 1 | AQ32: -0.335 | AR32: 0.145 | AS32: 0.035 | AT32: 0.412 | AU32: 0.269 | AV32: 0.223 | AW32: 0.409 | AX32: -0.212 | AY32: 0.743 | AZ32: 0.438 | BA32: 0.498 | BB32: -0.151 | BC32: -0.213 | BD32: 0.624 | BE32: -0.705 | BF32: 0.311 | BG32: 0.27 | BH32: -0.893 | BI32: -1 | BJ32: -0.085 | BK32: -0.898 | BM32: =10%*AK32+5%*AL32+2.5%*AM32+2.5%*AN32+10%*AO32+10%*AP32+10%*AQ32+5%*AR32+5%*AS32+10%*AT32+5%*AU32+5%*AY32+10%*AV32+10%*AW32 -> 0.32695
A33: CSED3 | B33: =K33 -> 0.009 | C33: =B33-E33 -> 0.009 | D33: =B33-K33 -> 0 | E33: =K33-L33 -> 0 | F33: 2.425 | G33: 1.842 | H33: pro_cyclicals | I33: =VLOOKUP(A33,Setores!$A$2:$C$215,2,0) -> education | J33: =VLOOKUP(A33,Setores!$A$2:$C$215,3,0) -> very_high_beta | K33: 0.009 | L33: 0.009 | M33: =VLOOKUP(A33,'Mandato Ibov'!$B$1:$C$215,2,0) -> 0.011465595 | N33: =K33-M33 -> -0.0024655947 | O33: =B33-M33 -> -0.0024655947 | P33: =VLOOKUP(A33,'Mandato Ibov'!$B$2:$D$215,3,0) -> 0.0089832565 | Q33: =K33-P33 -> 1.6743491e-05 | R33: 0.691 | S33: -0.014 | T33: 0.99 | U33: 0.688 | V33: 0.603 | W33: 0.487 | X33: 0.433 | Y33: 0.112 | Z33: 0.149 | AA33: 0.148 | AB33: 0.905 | AC33: 0.701 | AD33: 0.643 | AE33: 1 | AF33: 1 | AG33: -0.461 | AH33: 0.728 | AI33: -0.228 | AJ33: 1 | AK33: 0.633 | AL33: 0.309 | AM33: -0.392 | AN33: 0.609 | AO33: -0.624 | AP33: -0.604 | AQ33: 0.734 | AR33: 0.021 | AS33: -0.567 | AT33: 0.41 | AU33: 0.08 | AV33: 0.897 | AW33: -0.286 | AX33: 0.03 | AY33: 0.744 | AZ33: 0.218 | BA33: 0.45 | BB33: 0.098 | BC33: 0.171 | BD33: 0.268 | BE33: 1 | BF33: 1 | BG33: 0.056 | BH33: -0.295 | BI33: 0.285 | BJ33: 0.734 | BK33: 0.557 | BM33: =10%*AK33+5%*AL33+2.5%*AM33+2.5%*AN33+10%*AO33+10%*AP33+10%*AQ33+5%*AR33+5%*AS33+10%*AT33+5%*AU33+5%*AY33+10%*AV33+10%*AW33 -> 0.150775
A34: OPCT3 | B34: =K34 -> 0.013 | C34: =B34-E34 -> 0.013 | D34: =B34-K34 -> 0 | E34: =K34-L34 -> 0 | F34: 2.366 | G34: 2.579 | H34: commodities | I34: =VLOOKUP(A34,Setores!$A$2:$C$215,2,0) -> crude_oil | J34: =VLOOKUP(A34,Setores!$A$2:$C$215,3,0) -> very_low_beta | K34: 0.013 | L34: 0.013 | M34: =VLOOKUP(A34,'Mandato Ibov'!$B$1:$C$215,2,0) -> 0.011187025 | N34: =K34-M34 -> 0.0018129752 | O34: =B34-M34 -> 0.0018129752 | P34: =VLOOKUP(A34,'Mandato Ibov'!$B$2:$D$215,3,0) -> 0.010894229 | Q34: =K34-P34 -> 0.0021057713 | R34: 0.331 | S34: 0.409 | T34: -0.131 | U34: 0.324 | V34: 0.119 | W34: 0.484 | X34: 0.35 | Y34: 0.062 | Z34: 0.723 | AA34: 0.718 | AB34: 0.75 | AC34: 0.86 | AD34: 0.991 | AE34: -0.318 | AF34: -0.084 | AG34: 0.574 | AH34: -0.499 | AI34: 1 | AJ34: 0.29 | AK34: -0.305 | AL34: -0.943 | AM34: -0.722 | AN34: 0.556 | AO34: 0.765 | AP34: 0.74 | AQ34: 0.813 | AR34: 0.696 | AS34: 0.12 | AT34: 0.191 | AU34: -0.289 | AV34: 0.546 | AW34: 0.503 | AX34: -0.163 | AY34: 0.671 | AZ34: -0.49 | BA34: 0.966 | BB34: -0.371 | BC34: -0.73 | BD34: 0.546 | BE34: -0.593 | BF34: 0.241 | BG34: 0.809 | BH34: -0.615 | BI34: -0.838 | BJ34: 0.66 | BK34: 0.645 | BM34: =10%*AK34+5%*AL34+2.5%*AM34+2.5%*AN34+10%*AO34+10%*AP34+10%*AQ34+5%*AR34+5%*AS34+10%*AT34+5%*AU34+5%*AY34+10%*AV34+10%*AW34 -> 0.3339
A35: ESPA3 | B35: 0.003 | C35: =B35-E35 -> 0.003 | D35: =B35-K35 -> -0.007 | E35: =K35-L35 -> 0 | F35: 2.359 | G35: 1.747 | H35: pro_cyclicals | I35: =VLOOKUP(A35,Setores!$A$2:$C$215,2,0) -> consumer_services | J35: =VLOOKUP(A35,Setores!$A$2:$C$215,3,0) -> very_low_beta | K35: 0.01 | L35: 0.01 | M35: =VLOOKUP(A35,'Mandato Ibov'!$B$1:$C$215,2,0) -> 0.011150627 | N35: =K35-M35 -> -0.0011506275 | O35: =B35-M35 -> -0.0081506275 | P35: =VLOOKUP(A35,'Mandato Ibov'!$B$2:$D$215,3,0) -> 0 | Q35: =K35-P35 -> 0.01 | R35: 0.847 | S35: 0.872 | T35: 1 | U35: 0.537 | V35: 0.863 | W35: 0.231 | X35: -0.08 | Y35: -0.224 | Z35: 0.215 | AA35: 0.214 | AB35: 0.807 | AC35: 0.766 | AD35: 0.792 | AE35: 0.964 | AF35: 1 | AG35: 0.189 | AH35: 1 | AI35: 0.649 | AJ35: 0.617 | AK35: 0.176 | AL35: -0.723 | AM35: 0.641 | AN35: 0.601 | AO35: -0.322 | AP35: 0.136 | AQ35: 0.471 | AR35: 0.252 | AS35: -0.143 | AT35: -0.041 | AU35: -0.282 | AV35: 0.462 | AW35: -0.194 | AX35: -0.33 | AY35: 0.943 | AZ35: -0.359 | BA35: 0.985 | BB35: 0.148 | BC35: 0.035 | BD35: 0.35 | BE35: 1 | BF35: 0.468 | BG35: 0.3 | BH35: 0.645 | BI35: -0.68 | BJ35: 0.815 | BK35: 1 | BM35: =10%*AK35+5%*AL35+2.5%*AM35+2.5%*AN35+10%*AO35+10%*AP35+10%*AQ35+5%*AR35+5%*AS35+10%*AT35+5%*AU35+5%*AY35+10%*AV35+10%*AW35 -> 0.1022
A36: VTRU3 | B36: =K36 -> 0.007 | C36: =B36-E36 -> 0.007 | D36: =B36-K36 -> 0 | E36: =K36-L36 -> 0 | F36: 2.358 | G36: 1.836 | H36: pro_cyclicals | I36: =VLOOKUP(A36,Setores!$A$2:$C$215,2,0) -> education | J36: =VLOOKUP(A36,Setores!$A$2:$C$215,3,0) -> neutral_beta | K36: 0.007 | L36: 0.007 | M36: =VLOOKUP(A36,'Mandato Ibov'!$B$1:$C$215,2,0) -> 0.011147111 | N36: =K36-M36 -> -0.0041471111 | O36: =B36-M36 -> -0.0041471111 | P36: =VLOOKUP(A36,'Mandato Ibov'!$B$2:$D$215,3,0) -> 0.010586825 | Q36: =K36-P36 -> -0.0035868248 | R36: 0.55 | S36: 0.588 | T36: 0.402 | U36: 0.602 | V36: 0.547 | W36: 0.17 | X36: 0.128 | Y36: -0.117 | Z36: 0.564 | AA36: 0.565 | AB36: 0.926 | AC36: 0.911 | AD36: 0.882 | AE36: 0.504 | AF36: 1 | AG36: 0.472 | AH36: 0.102 | AI36: 0.195 | AJ36: 0.479 | AK36: -0.04 | AL36: -0.912 | AM36: 0.172 | AN36: 0.367 | AO36: -0.056 | AP36: -0.225 | AQ36: 0.617 | AR36: 1 | AS36: 0.251 | AT36: 0.432 | AU36: 0.659 | AV36: 0.518 | AW36: -0.34 | AX36: -0.298 | AY36: 0.583 | AZ36: 0.238 | BA36: 0.65 | BB36: -0.21 | BC36: -0.646 | BD36: 0.424 | BE36: -0.813 | BF36: 0.372 | BG36: -0.075 | BH36: -0.44 | BI36: -0.157 | BJ36: 0.347 | BK36: 0.387 | BM36: =10%*AK36+5%*AL36+2.5%*AM36+2.5%*AN36+10%*AO36+10%*AP36+10%*AQ36+5%*AR36+5%*AS36+10%*AT36+5%*AU36+5%*AY36+10%*AV36+10%*AW36 -> 0.183125
A37: ITSA3 | B37: 0 | C37: =B37-E37 -> 0 | D37: =B37-K37 -> -0.024 | E37: =K37-L37 -> 0 | F37: 2.34 | G37: 3.177 | H37: pro_cyclicals | I37: =VLOOKUP(A37,Setores!$A$2:$C$215,2,0) -> banks | J37: =VLOOKUP(A37,Setores!$A$2:$C$215,3,0) -> neutral_beta | K37: 0.024 | L37: 0.024 | M37: =VLOOKUP(A37,'Mandato Ibov'!$B$1:$C$215,2,0) -> 0.011060813 | N37: =K37-M37 -> 0.012939187 | O37: =B37-M37 -> -0.011060813 | P37: =VLOOKUP(A37,'Mandato Ibov'!$B$2:$D$215,3,0) -> 0.0071802677 | Q37: =K37-P37 -> 0.016819732 | R37: -0.02 | S37: -0.124 | T37: -0.477 | U37: 0.216 | V37: -0.156 | W37: 0.425 | X37: 0.67 | Y37: 0.54 | Z37: 0.676 | AA37: 0.675 | AB37: 0.872 | AC37: 0.845 | AD37: 0.864 | AE37: 0.147 | AF37: -0.222 | AG37: 0.09 | AH37: -0.964 | AI37: -0.758 | AJ37: -0.816 | AK37: -0.174 | AL37: 0.211 | AM37: -0.679 | AN37: -0.208 | AO37: 0.498 | AP37: -0.056 | AQ37: 0.009 | AR37: 0.306 | AS37: 0.413 | AT37: -0.001 | AU37: -0.002 | AV37: 0.403 | AW37: 0.499 | AX37: -0.401 | AY37: 0.91 | AZ37: 0.668 | BA37: 0.967 | BB37: -0.207 | BC37: 0.014 | BD37: 0.557 | BE37: -0.215 | BF37: -0.339 | BG37: 0.841 | BH37: -0.656 | BI37: -0.146 | BJ37: 0.903 | BK37: -0.709 | BM37: =10%*AK37+5%*AL37+2.5%*AM37+2.5%*AN37+10%*AO37+10%*AP37+10%*AQ37+5%*AR37+5%*AS37+10%*AT37+5%*AU37+5%*AY37+10%*AV37+10%*AW37 -> 0.187525
A38: ABCB4 | B38: =K38 -> 0.016 | C38: =B38-E38 -> 0.016 | D38: =B38-K38 -> 0 | E38: =K38-L38 -> 0 | F38: 2.264 | G38: 2.965 | H38: pro_cyclicals | I38: =VLOOKUP(A38,Setores!$A$2:$C$215,2,0) -> banks | J38: =VLOOKUP(A38,Setores!$A$2:$C$215,3,0) -> low_beta | K38: 0.016 | L38: 0.016 | M38: =VLOOKUP(A38,'Mandato Ibov'!$B$1:$C$215,2,0) -> 0.010702296 | N38: =K38-M38 -> 0.0052977041 | O38: =B38-M38 -> 0.0052977041 | P38: =VLOOKUP(A38,'Mandato Ibov'!$B$2:$D$215,3,0) -> 0.0055117039 | Q38: =K38-P38 -> 0.010488296 | R38: -0.02 | S38: 0.153 | T38: -0.277 | U38: -0.017 | V38: -0.049 | W38: 0.306 | X38: 0.439 | Y38: 0.384 | Z38: 0.757 | AA38: 0.753 | AB38: 0.848 | AC38: 0.874 | AD38: 0.903 | AE38: -0.611 | AF38: 0.412 | AG38: 0.618 | AH38: -0.285 | AI38: 0.053 | AJ38: -0.779 | AK38: -0.119 | AL38: 0.261 | AM38: -0.092 | AN38: 0.169 | AO38: 0.277 | AP38: -0.112 | AQ38: 0.043 | AR38: 0.208 | AS38: -0.34 | AT38: -0.135 | AU38: -0.277 | AV38: -0.551 | AW38: 0.648 | AX38: 0.097 | AY38: 0.807 | AZ38: 0.584 | BA38: 0.52 | BB38: -0.337 | BC38: -0.107 | BD38: 0.472 | BE38: -0.176 | BF38: 0.848 | BG38: 0.921 | BH38: -0.594 | BI38: -0.251 | BJ38: 0.419 | BK38: 0.433 | BM38: =10%*AK38+5%*AL38+2.5%*AM38+2.5%*AN38+10%*AO38+10%*AP38+10%*AQ38+5%*AR38+5%*AS38+10%*AT38+5%*AU38+5%*AY38+10%*AV38+10%*AW38 -> 0.039975
A39: MELK3 | B39: =K39 -> 0.014 | C39: =B39-E39 -> 0.014 | D39: =B39-K39 -> 0 | E39: =K39-L39 -> 0 | F39: 2.248 | G39: 2.456 | H39: pro_cyclicals | I39: =VLOOKUP(A39,Setores!$A$2:$C$215,2,0) -> homebuilders | J39: =VLOOKUP(A39,Setores!$A$2:$C$215,3,0) -> low_beta | K39: 0.014 | L39: 0.014 | M39: =VLOOKUP(A39,'Mandato Ibov'!$B$1:$C$215,2,0) -> 0.0106272 | N39: =K39-M39 -> 0.0033727999 | O39: =B39-M39 -> 0.0033727999 | P39: =VLOOKUP(A39,'Mandato Ibov'!$B$2:$D$215,3,0) -> 0.0087400116 | Q39: =K39-P39 -> 0.0052599884 | R39: 0.059 | S39: -0.075 | T39: 0.403 | U39: 0.029 | V39: 0.168 | W39: 0.288 | X39: 0.456 | Y39: 0.35 | Z39: 0.568 | AA39: 0.566 | AB39: 0.854 | AC39: 0.908 | AD39: 0.771 | AE39: 0.137 | AF39: 0.117 | AG39: -0.407 | AH39: 0.853 | AI39: 0.068 | AJ39: -0.022 | AK39: -0.361 | AL39: 0.978 | AM39: -0.036 | AN39: -0.103 | AO39: -0.282 | AP39: -0.551 | AQ39: 0.006 | AR39: 0.554 | AS39: 0.476 | AT39: -0.105 | AU39: -0.446 | AV39: -0.04 | AW39: 0.591 | AX39: -0.293 | AY39: 0.534 | AZ39: 0.366 | BA39: -0.034 | BB39: -0.383 | BC39: -0.692 | BD39: -0.154 | BE39: -0.43 | BF39: -0.336 | BG39: 0.788 | BH39: -0.278 | BI39: 0.104 | BJ39: 0.737 | BK39: 0.693 | BM39: =10%*AK39+5%*AL39+2.5%*AM39+2.5%*AN39+10%*AO39+10%*AP39+10%*AQ39+5%*AR39+5%*AS39+10%*AT39+5%*AU39+5%*AY39+10%*AV39+10%*AW39 -> 0.027125
A40: BMOB3 | B40: =K40 -> 0.014 | C40: =B40-E40 -> 0.014 | D40: =B40-K40 -> 0 | E40: =K40-L40 -> 0 | F40: 2.205 | G40: 2.151 | H40: pro_cyclicals | I40: =VLOOKUP(A40,Setores!$A$2:$C$215,2,0) -> tech | J40: =VLOOKUP(A40,Setores!$A$2:$C$215,3,0) -> neutral_beta | K40: 0.014 | L40: 0.014 | M40: =VLOOKUP(A40,'Mandato Ibov'!$B$1:$C$215,2,0) -> 0.010425588 | N40: =K40-M40 -> 0.0035744123 | O40: =B40-M40 -> 0.0035744123 | P40: =VLOOKUP(A40,'Mandato Ibov'!$B$2:$D$215,3,0) -> 0.0091537294 | Q40: =K40-P40 -> 0.0048462706 | R40: 0.416 | S40: 0.146 | T40: 0.371 | U40: 0.236 | V40: 0.135 | W40: 0.381 | X40: 0.26 | Y40: 0.126 | Z40: 0.144 | AA40: 0.141 | AB40: 0.777 | AC40: 0.938 | AD40: 0.844 | AE40: 0.222 | AF40: -0.113 | AG40: -0.274 | AH40: -0.377 | AI40: 0.998 | AJ40: 1 | AK40: -0.342 | AL40: -0.163 | AM40: -0.866 | AN40: -0.075 | AO40: 0.182 | AP40: 0.683 | AQ40: 0.432 | AR40: 0.367 | AS40: 0.391 | AT40: 0.381 | AU40: -0.434 | AV40: 0.663 | AW40: 0.22 | AX40: 0.517 | AY40: 0.928 | AZ40: 0.551 | BA40: 0.902 | BB40: -0.032 | BC40: -0.052 | BD40: -0.782 | BE40: -0.45 | BF40: 0.568 | BG40: 0.69 | BH40: -0.583 | BI40: -0.098 | BJ40: 0.304 | BK40: 0.208 | BM40: =10%*AK40+5%*AL40+2.5%*AM40+2.5%*AN40+10%*AO40+10%*AP40+10%*AQ40+5%*AR40+5%*AS40+10%*AT40+5%*AU40+5%*AY40+10%*AV40+10%*AW40 -> 0.252825
A41: LEVE3 | B41: =K41 -> 0.012 | C41: =B41-E41 -> 0.012 | D41: =B41-K41 -> 0 | E41: =K41-L41 -> 0 | F41: 2.179 | G41: 2.562 | H41: industrials | I41: =VLOOKUP(A41,Setores!$A$2:$C$215,2,0) -> capital_goods | J41: =VLOOKUP(A41,Setores!$A$2:$C$215,3,0) -> very_low_beta | K41: 0.012 | L41: 0.012 | M41: =VLOOKUP(A41,'Mandato Ibov'!$B$1:$C$215,2,0) -> 0.010299107 | N41: =K41-M41 -> 0.0017008928 | O41: =B41-M41 -> 0.0017008928 | P41: =VLOOKUP(A41,'Mandato Ibov'!$B$2:$D$215,3,0) -> 0.011600843 | Q41: =K41-P41 -> 0.00039915689 | R41: 0.03 | S41: -0.222 | T41: -0.037 | U41: 0.252 | V41: -0.023 | W41: 0.34 | X41: 0.51 | Y41: 0.333 | Z41: 0.715 | AA41: 0.714 | AB41: 0.836 | AC41: 0.765 | AD41: 0.736 | AE41: 0.228 | AF41: -0.329 | AG41: -0.275 | AH41: -0.49 | AI41: 0.063 | AJ41: 0.273 | AK41: -0.146 | AL41: 0.28 | AM41: -0.886 | AN41: 0.019 | AO41: 0.088 | AP41: 0.331 | AQ41: 0.237 | AR41: 0.377 | AS41: -0.077 | AT41: 0.995 | AU41: -0.306 | AV41: 0.542 | AW41: 0.654 | AX41: -0.048 | AY41: 0.71 | AZ41: 0.696 | BA41: -0.584 | BB41: -0.238 | BC41: -0.558 | BD41: 0.076 | BE41: -0.569 | BF41: 0.086 | BG41: 0.664 | BH41: -0.472 | BI41: -0.04 | BJ41: 0.472 | BK41: 0.034 | BM41: =10%*AK41+5%*AL41+2.5%*AM41+2.5%*AN41+10%*AO41+10%*AP41+10%*AQ41+5%*AR41+5%*AS41+10%*AT41+5%*AU41+5%*AY41+10%*AV41+10%*AW41 -> 0.297625
A42: EUCA4 | B42: =K42 -> 0.009 | C42: =B42-E42 -> 0.009 | D42: =B42-K42 -> 0 | E42: =K42-L42 -> 0 | F42: 2.174 | G42: 2.337 | H42: industrials | I42: =VLOOKUP(A42,Setores!$A$2:$C$215,2,0) -> building_materials | J42: =VLOOKUP(A42,Setores!$A$2:$C$215,3,0) -> very_low_beta | K42: 0.009 | L42: 0.009 | M42: =VLOOKUP(A42,'Mandato Ibov'!$B$1:$C$215,2,0) -> 0.010277042 | N42: =K42-M42 -> -0.0012770424 | O42: =B42-M42 -> -0.0012770424 | P42: =VLOOKUP(A42,'Mandato Ibov'!$B$2:$D$215,3,0) -> 0.0080345058 | Q42: =K42-P42 -> 0.00096549416 | R42: 0.285 | S42: 0.098 | T42: 0.184 | U42: 0.269 | V42: 0.104 | W42: 0.074 | X42: -0.014 | Y42: 0.023 | Z42: 0.772 | AA42: 0.768 | AB42: 1 | AC42: 0.912 | AD42: 0.897 | AE42: 0.07 | AF42: -0.052 | AG42: -0.122 | AH42: -0.228 | AI42: -0.026 | AJ42: 0.157 | AK42: 0.144 | AL42: -0.28 | AM42: -0.201 | AN42: -0.511 | AO42: 0.139 | AP42: 0.035 | AQ42: 0.334 | AR42: 0.636 | AS42: 0.342 | AT42: 0.361 | AU42: -0.133 | AV42: 0.346 | AW42: 0.61 | AX42: 0.124 | AY42: 0.762 | AZ42: 0.511 | BA42: 0.663 | BB42: -0.267 | BC42: -0.322 | BD42: 0.682 | BE42: -1 | BF42: -0.024 | BG42: -0.069 | BH42: -0.693 | BI42: -0.025 | BJ42: 0.979 | BK42: 0.14 | BM42: =10%*AK42+5%*AL42+2.5%*AM42+2.5%*AN42+10%*AO42+10%*AP42+10%*AQ42+5%*AR42+5%*AS42+10%*AT42+5%*AU42+5%*AY42+10%*AV42+10%*AW42 -> 0.24545
A43: CSUD3 | B43: =K43 -> 0.013 | C43: =B43-E43 -> 0.013 | D43: =B43-K43 -> 0 | E43: =K43-L43 -> 0 | F43: 2.159 | G43: 2.298 | H43: pro_cyclicals | I43: =VLOOKUP(A43,Setores!$A$2:$C$215,2,0) -> financial_services | J43: =VLOOKUP(A43,Setores!$A$2:$C$215,3,0) -> very_low_beta | K43: 0.013 | L43: 0.013 | M43: =VLOOKUP(A43,'Mandato Ibov'!$B$1:$C$215,2,0) -> 0.010205892 | N43: =K43-M43 -> 0.0027941085 | O43: =B43-M43 -> 0.0027941085 | P43: =VLOOKUP(A43,'Mandato Ibov'!$B$2:$D$215,3,0) -> 0.0062863823 | Q43: =K43-P43 -> 0.0067136177 | R43: 0.23 | S43: -0.169 | T43: 0.541 | U43: 0.184 | V43: 0.206 | W43: 0.298 | X43: 0.467 | Y43: 0.17 | Z43: 0.41 | AA43: 0.411 | AB43: 0.785 | AC43: 0.709 | AD43: 0.752 | AE43: 0.527 | AF43: -0.121 | AG43: -0.722 | AH43: 0.476 | AI43: 0.028 | AJ43: 1 | AK43: -0.072 | AL43: 0.325 | AM43: -0.604 | AN43: 0.364 | AO43: -0.131 | AP43: -0.337 | AQ43: 0.006 | AR43: 0.096 | AS43: -0.35 | AT43: 0.572 | AU43: 0.023 | AV43: 0.43 | AW43: 0.646 | AX43: -0.078 | AY43: 0.889 | AZ43: 0.367 | BA43: 0.907 | BB43: -0.3 | BC43: -0.32 | BD43: -0.096 | BE43: -0.632 | BF43: 0.044 | BG43: 0.376 | BH43: -0.394 | BI43: -0.68 | BJ43: 0.874 | BK43: 0.903 | BM43: =10%*AK43+5%*AL43+2.5%*AM43+2.5%*AN43+10%*AO43+10%*AP43+10%*AQ43+5%*AR43+5%*AS43+10%*AT43+5%*AU43+5%*AY43+10%*AV43+10%*AW43 -> 0.15455
A44: PNVL3 | B44: =K44 -> 0.011 | C44: =B44-E44 -> 0.011 | D44: =B44-K44 -> 0 | E44: =K44-L44 -> 0 | F44: 2.105 | G44: 2.21 | H44: defensives | I44: =VLOOKUP(A44,Setores!$A$2:$C$215,2,0) -> healthcare | J44: =VLOOKUP(A44,Setores!$A$2:$C$215,3,0) -> high_beta | K44: 0.011 | L44: 0.011 | M44: =VLOOKUP(A44,'Mandato Ibov'!$B$1:$C$215,2,0) -> 0.0099530478 | N44: =K44-M44 -> 0.0010469522 | O44: =B44-M44 -> 0.0010469522 | P44: =VLOOKUP(A44,'Mandato Ibov'!$B$2:$D$215,3,0) -> 0.0083576656 | Q44: =K44-P44 -> 0.0026423344 | R44: 0.297 | S44: 0.329 | T44: 0.066 | U44: 0.167 | V44: 0.085 | W44: 0.188 | X44: 0.156 | Y44: 0.022 | Z44: 0.415 | AA44: 0.409 | AB44: 0.853 | AC44: 0.913 | AD44: 0.882 | AE44: -0.127 | AF44: -0.369 | AG44: 0.111 | AH44: -0.345 | AI44: 1 | AJ44: 0.242 | AK44: -0.068 | AL44: -0.581 | AM44: -0.569 | AN44: 0.231 | AO44: 0.472 | AP44: -0.386 | AQ44: 0.245 | AR44: 0.367 | AS44: 0.423 | AT44: 0.436 | AU44: -0.443 | AV44: 0.514 | AW44: 0.334 | AX44: -0.168 | AY44: 0.997 | AZ44: 0.652 | BA44: 0.697 | BB44: -0.255 | BC44: -0.244 | BD44: 0.463 | BE44: 0.332 | BF44: 0.458 | BG44: 0.558 | BH44: -0.172 | BI44: 0.044 | BJ44: 0.236 | BK44: 0.446 | BM44: =10%*AK44+5%*AL44+2.5%*AM44+2.5%*AN44+10%*AO44+10%*AP44+10%*AQ44+5%*AR44+5%*AS44+10%*AT44+5%*AU44+5%*AY44+10%*AV44+10%*AW44 -> 0.1844
A45: SAPR3 | B45: 0 | C45: =B45-E45 -> 0 | D45: =B45-K45 -> -0.008 | E45: =K45-L45 -> 0 | F45: 2.053 | G45: 1.708 | H45: bond_proxies | I45: =VLOOKUP(A45,Setores!$A$2:$C$215,2,0) -> utilities | J45: =VLOOKUP(A45,Setores!$A$2:$C$215,3,0) -> high_beta | K45: 0.008 | L45: 0.008 | M45: =VLOOKUP(A45,'Mandato Ibov'!$B$1:$C$215,2,0) -> 0.0097034554 | N45: =K45-M45 -> -0.0017034554 | O45: =B45-M45 -> -0.0097034554 | P45: =VLOOKUP(A45,'Mandato Ibov'!$B$2:$D$215,3,0) -> 0 | Q45: =K45-P45 -> 0.008 | R45: -0.024 | S45: -0.046 | T45: -0.154 | U45: 0.249 | V45: 0.06 | W45: 0.17 | X45: 0.287 | Y45: 0.304 | Z45: 0.505 | AA45: 0.508 | AB45: 0.856 | AC45: 0.787 | AD45: 0.788 | AE45: 0.363 | AF45: -0.16 | AG45: 0.621 | AH45: -0.561 | AI45: -0.476 | AJ45: -0.407 | AK45: 0.408 | AL45: -0.325 | AM45: -0.343 | AN45: -0.32 | AO45: 0.29 | AP45: -0.624 | AQ45: -0.014 | AR45: -0.524 | AS45: -0.791 | AT45: 0.172 | AU45: 0.264 | AV45: 0.44 | AW45: 0.609 | AX45: -0.095 | AY45: -0.214 | AZ45: 0.702 | BA45: 0.76 | BB45: 0.018 | BC45: 0.477 | BD45: 0.502 | BE45: -0.107 | BF45: 0.72 | BG45: 0.098 | BH45: -0.791 | BI45: 0.164 | BJ45: 0.981 | BK45: 0.109 | BM45: =10%*AK45+5%*AL45+2.5%*AM45+2.5%*AN45+10%*AO45+10%*AP45+10%*AQ45+5%*AR45+5%*AS45+10%*AT45+5%*AU45+5%*AY45+10%*AV45+10%*AW45 -> 0.032025
A46: MDNE3 | B46: =K46 -> 0.007 | C46: =B46-E46 -> 0.007 | D46: =B46-K46 -> 0 | E46: =K46-L46 -> 0 | F46: 2.016 | G46: 1.559 | H46: pro_cyclicals | I46: =VLOOKUP(A46,Setores!$A$2:$C$215,2,0) -> homebuilders | J46: =VLOOKUP(A46,Setores!$A$2:$C$215,3,0) -> very_high_beta | K46: 0.007 | L46: 0.007 | M46: =VLOOKUP(A46,'Mandato Ibov'!$B$1:$C$215,2,0) -> 0.0095300223 | N46: =K46-M46 -> -0.0025300223 | O46: =B46-M46 -> -0.0025300223 | P46: =VLOOKUP(A46,'Mandato Ibov'!$B$2:$D$215,3,0) -> 0.0078945349 | Q46: =K46-P46 -> -0.00089453487 | R46: 0.169 | S46: -0.09 | T46: -0.027 | U46: 0.287 | V46: 0.05 | W46: 0.208 | X46: 0.098 | Y46: 0.302 | Z46: 0.182 | AA46: 0.177 | AB46: 0.877 | AC46: 0.781 | AD46: 0.755 | AE46: 0.355 | AF46: 0.695 | AG46: -0.047 | AH46: -0.119 | AI46: 0.691 | AJ46: -0.139 | AK46: -0.27 | AL46: 0.255 | AM46: -0.562 | AN46: 0.21 | AO46: 0.114 | AP46: 0.089 | AQ46: 0.485 | AR46: 0.557 | AS46: 0.38 | AT46: 0.14 | AU46: -0.239 | AV46: 0.26 | AW46: -0.306 | AX46: 0.045 | AY46: 0.804 | AZ46: 0.918 | BA46: -0.078 | BB46: -0.782 | BC46: -0.479 | BD46: 0.123 | BE46: 0.266 | BF46: 0.276 | BG46: 0.276 | BH46: -0.987 | BI46: 0.904 | BJ46: -0.565 | BK46: 0.113 | BM46: =10%*AK46+5%*AL46+2.5%*AM46+2.5%*AN46+10%*AO46+10%*AP46+10%*AQ46+5%*AR46+5%*AS46+10%*AT46+5%*AU46+5%*AY46+10%*AV46+10%*AW46 -> 0.13025
A47: SHUL4 | B47: =K47 -> 0.012 | C47: =B47-E47 -> 0.012 | D47: =B47-K47 -> 0 | E47: =K47-L47 -> 0 | F47: 1.992 | G47: 2.425 | H47: industrials | I47: =VLOOKUP(A47,Setores!$A$2:$C$215,2,0) -> capital_goods | J47: =VLOOKUP(A47,Setores!$A$2:$C$215,3,0) -> low_beta | K47: 0.012 | L47: 0.012 | M47: =VLOOKUP(A47,'Mandato Ibov'!$B$1:$C$215,2,0) -> 0.009417545 | N47: =K47-M47 -> 0.002582455 | O47: =B47-M47 -> 0.002582455 | P47: =VLOOKUP(A47,'Mandato Ibov'!$B$2:$D$215,3,0) -> 0.0066476975 | Q47: =K47-P47 -> 0.0053523025 | R47: 0.059 | S47: 0.004 | T47: 0.079 | U47: -0.235 | V47: -0.139 | W47: 0.152 | X47: 0.215 | Y47: 0.223 | Z47: 0.589 | AA47: 0.585 | AB47: 0.792 | AC47: 0.698 | AD47: 0.806 | AE47: -0.425 | AF47: -0.64 | AG47: -0.228 | AH47: 0.052 | AI47: 0.232 | AJ47: -0.252 | AK47: -0.069 | AL47: 0.329 | AM47: -0.487 | AN47: 0.342 | AO47: 0.262 | AP47: -0.161 | AQ47: -0.322 | AR47: 0.064 | AS47: -0.524 | AT47: 0.207 | AU47: -0.329 | AV47: -0.209 | AW47: 0.69 | AX47: 0.51 | AY47: 0.908 | AZ47: 0.902 | BA47: 0.613 | BB47: -0.026 | BC47: -0.089 | BD47: 0.366 | BE47: -0.431 | BF47: -0.098 | BG47: 0.515 | BH47: -0.287 | BI47: 0.027 | BJ47: 0.882 | BK47: 0.371 | BM47: =10%*AK47+5%*AL47+2.5%*AM47+2.5%*AN47+10%*AO47+10%*AP47+10%*AQ47+5%*AR47+5%*AS47+10%*AT47+5%*AU47+5%*AY47+10%*AV47+10%*AW47 -> 0.058575
A48: POSI3 | B48: 0.013 | C48: =B48-E48 -> 0.013 | D48: =B48-K48 -> -0.001 | E48: =K48-L48 -> 0 | F48: 1.989 | G48: 1.642 | H48: pro_cyclicals | I48: =VLOOKUP(A48,Setores!$A$2:$C$215,2,0) -> tech | J48: =VLOOKUP(A48,Setores!$A$2:$C$215,3,0) -> neutral_beta | K48: 0.014 | L48: 0.014 | M48: =VLOOKUP(A48,'Mandato Ibov'!$B$1:$C$215,2,0) -> 0.0094015787 | N48: =K48-M48 -> 0.0045984213 | O48: =B48-M48 -> 0.0035984213 | P48: =VLOOKUP(A48,'Mandato Ibov'!$B$2:$D$215,3,0) -> 0 | Q48: =K48-P48 -> 0.014 | R48: 0.35 | S48: 0.724 | T48: 0.424 | U48: 0.081 | V48: 0.435 | W48: -0.189 | X48: -0.519 | Y48: -0.148 | Z48: 0.466 | AA48: 0.461 | AB48: 0.814 | AC48: 0.899 | AD48: 0.94 | AE48: -0.119 | AF48: 0.568 | AG48: 0.604 | AH48: 1 | AI48: 0.57 | AJ48: -0.421 | AK48: 0.75 | AL48: -0.176 | AM48: 0.689 | AN48: -0.204 | AO48: -0.211 | AP48: 0.387 | AQ48: -0.483 | AR48: 0.271 | AS48: 0.199 | AT48: 0.006 | AU48: -0.434 | AV48: -0.262 | AW48: -0.132 | AX48: -0.109 | AY48: 0.596 | AZ48: -0.177 | BA48: 0.455 | BB48: 0.178 | BC48: 0.504 | BD48: 0.296 | BE48: 0.073 | BF48: 0.418 | BG48: -0.05 | BH48: 0.179 | BI48: -0.007 | BJ48: 0.212 | BK48: 0.851 | BM48: =10%*AK48+5%*AL48+2.5%*AM48+2.5%*AN48+10%*AO48+10%*AP48+10%*AQ48+5%*AR48+5%*AS48+10%*AT48+5%*AU48+5%*AY48+10%*AV48+10%*AW48 -> 0.040425
A49: PFRM3 | B49: =K49 -> 0.009 | C49: =B49-E49 -> 0.009 | D49: =B49-K49 -> 0 | E49: =K49-L49 -> 0 | F49: 1.97 | G49: 1.547 | H49: defensives | I49: =VLOOKUP(A49,Setores!$A$2:$C$215,2,0) -> healthcare | J49: =VLOOKUP(A49,Setores!$A$2:$C$215,3,0) -> high_beta | K49: 0.009 | L49: 0.009 | M49: =VLOOKUP(A49,'Mandato Ibov'!$B$1:$C$215,2,0) -> 0.0093139248 | N49: =K49-M49 -> -0.00031392481 | O49: =B49-M49 -> -0.00031392481 | P49: =VLOOKUP(A49,'Mandato Ibov'!$B$2:$D$215,3,0) -> 0.0071644843 | Q49: =K49-P49 -> 0.0018355157 | R49: 0.235 | S49: -0.099 | T49: 0.586 | U49: 0.274 | V49: 0.333 | W49: 0.125 | X49: 0.005 | Y49: 0.019 | Z49: 0.453 | AA49: 0.452 | AB49: 0.641 | AC49: 0.754 | AD49: 0.723 | AE49: 0.619 | AF49: 0.497 | AG49: -0.12 | AH49: 1 | AI49: 0.025 | AJ49: 0.158 | AK49: 0.786 | AL49: 0.155 | AM49: 0.136 | AN49: 0.145 | AO49: -0.306 | AP49: -0.238 | AQ49: 0.186 | AR49: -0.232 | AS49: -0.62 | AT49: 0.33 | AU49: -0.607 | AV49: 0.213 | AW49: 0.234 | AX49: -0.128 | AY49: 0.878 | AZ49: 0.286 | BA49: 0.162 | BB49: -0.067 | BC49: 0.043 | BD49: 0.164 | BE49: 0.342 | BF49: -0.142 | BG49: 0.241 | BH49: -0.702 | BI49: -0.116 | BJ49: 0.832 | BK49: 0.745 | BM49: =10%*AK49+5%*AL49+2.5%*AM49+2.5%*AN49+10%*AO49+10%*AP49+10%*AQ49+5%*AR49+5%*AS49+10%*AT49+5%*AU49+5%*AY49+10%*AV49+10%*AW49 -> 0.106225
A50: GOAU4 | B50: =K50 -> 0.013 | C50: =B50-E50 -> 0.01 | D50: =B50-K50 -> 0 | E50: =K50-L50 -> 0.003 | F50: 1.969 | G50: 2.553 | H50: commodities | I50: =VLOOKUP(A50,Setores!$A$2:$C$215,2,0) -> basic_materials | J50: =VLOOKUP(A50,Setores!$A$2:$C$215,3,0) -> low_beta | K50: 0.013 | L50: 0.01 | M50: =VLOOKUP(A50,'Mandato Ibov'!$B$1:$C$215,2,0) -> 0.012601679 | N50: =K50-M50 -> 0.00039832142 | O50: =B50-M50 -> 0.00039832142 | P50: =VLOOKUP(A50,'Mandato Ibov'!$B$2:$D$215,3,0) -> 0.01011111 | Q50: =K50-P50 -> 0.0028888902 | R50: -0.275 | S50: 0.456 | T50: -0.634 | U50: -0.021 | V50: 0.004 | W50: -0.05 | X50: -0.326 | Y50: 0.258 | Z50: 1 | AA50: 1 | AB50: 0.905 | AC50: 0.972 | AD50: 0.957 | AE50: -0.144 | AF50: -0.364 | AG50: 1 | AH50: -0.455 | AI50: -0.218 | AJ50: -0.874 | AK50: 0.552 | AL50: -0.198 | AM50: 0.556 | AN50: -0.623 | AO50: 0.55 | AP50: 0.301 | AQ50: -0.86 | AR50: 0.48 | AS50: 0.402 | AT50: 0.097 | AU50: -0.535 | AV50: -0.152 | AW50: 0.412 | AX50: -0.061 | AY50: 0.8 | AZ50: -0.158 | BA50: -0.095 | BB50: 0.201 | BC50: 0.073 | BD50: 0.693 | BE50: -1 | BF50: -0.67 | BG50: 0.365 | BH50: -0.351 | BI50: -0.459 | BJ50: -0.183 | BK50: -0.079 | BM50: =10%*AK50+5%*AL50+2.5%*AM50+2.5%*AN50+10%*AO50+10%*AP50+10%*AQ50+5%*AR50+5%*AS50+10%*AT50+5%*AU50+5%*AY50+10%*AV50+10%*AW50 -> 0.135775
A51: ITSA4 | B51: 0.042 | C51: =B51-E51 -> 0.01 | D51: =B51-K51 -> 0.015 | E51: =K51-L51 -> 0.032 | F51: 1.908 | G51: 4.155 | H51: pro_cyclicals | I51: =VLOOKUP(A51,Setores!$A$2:$C$215,2,0) -> banks | J51: =VLOOKUP(A51,Setores!$A$2:$C$215,3,0) -> neutral_beta | K51: 0.027 | L51: -0.005 | M51: =VLOOKUP(A51,'Mandato Ibov'!$B$1:$C$215,2,0) -> 0.049679965 | N51: =K51-M51 -> -0.022679965 | O51: =B51-M51 -> -0.0076799655 | P51: =VLOOKUP(A51,'Mandato Ibov'!$B$2:$D$215,3,0) -> 0.038434195 | Q51: =K51-P51 -> -0.011434195 | R51: -0.25 | S51: -0.266 | T51: -0.772 | U51: 0.092 | V51: -0.343 | W51: 0.261 | X51: 0.533 | Y51: 0.429 | Z51: 0.508 | AA51: 0.508 | AB51: 0.777 | AC51: 0.831 | AD51: 0.771 | AE51: 0.123 | AF51: -0.218 | AG51: 0.063 | AH51: -0.964 | AI51: -0.762 | AJ51: -0.83 | AK51: -0.174 | AL51: 0.221 | AM51: -0.679 | AN51: -0.206 | AO51: 0.463 | AP51: -0.046 | AQ51: 0.009 | AR51: 0.306 | AS51: 0.413 | AT51: -0.001 | AU51: -0.002 | AV51: 0.379 | AW51: 0.436 | AX51: -0.401 | AY51: 0.91 | AZ51: 0.688 | BA51: 0.653 | BB51: -0.207 | BC51: 0.014 | BD51: 0.55 | BE51: -0.128 | BF51: -0.395 | BG51: 0.824 | BH51: -0.68 | BI51: -0.08 | BJ51: -0.182 | BK51: -0.709 | BM51: =10%*AK51+5%*AL51+2.5%*AM51+2.5%*AN51+10%*AO51+10%*AP51+10%*AQ51+5%*AR51+5%*AS51+10%*AT51+5%*AU51+5%*AY51+10%*AV51+10%*AW51 -> 0.176875
A52: ALPA4 | B52: =K52 -> 0.009 | C52: =B52-E52 -> 0.009 | D52: =B52-K52 -> 0 | E52: =K52-L52 -> 0 | F52: 1.904 | G52: 1.56 | H52: pro_cyclicals | I52: =VLOOKUP(A52,Setores!$A$2:$C$215,2,0) -> apparel | J52: =VLOOKUP(A52,Setores!$A$2:$C$215,3,0) -> high_beta | K52: 0.009 | L52: 0.009 | M52: =VLOOKUP(A52,'Mandato Ibov'!$B$1:$C$215,2,0) -> 0.0090014531 | N52: =K52-M52 -> -1.4530795e-06 | O52: =B52-M52 -> -1.4530795e-06 | P52: =VLOOKUP(A52,'Mandato Ibov'!$B$2:$D$215,3,0) -> 0.0064494607 | Q52: =K52-P52 -> 0.0025505393 | R52: 0.266 | S52: -0.213 | T52: 0.12 | U52: 0.493 | V52: 0.151 | W52: 0.207 | X52: 0.206 | Y52: 0.092 | Z52: 0.086 | AA52: 0.085 | AB52: 0.776 | AC52: 0.759 | AD52: 0.672 | AE52: 0.908 | AF52: 0.925 | AG52: -0.601 | AH52: -0.524 | AI52: -0.456 | AJ52: 0.244 | AK52: -0.342 | AL52: -0.068 | AM52: -0.791 | AN52: 0.497 | AO52: 0.018 | AP52: -0.702 | AQ52: 0.821 | AR52: 0.552 | AS52: 0.511 | AT52: 0.303 | AU52: -0.021 | AV52: 0.714 | AW52: -0.017 | AX52: 0.072 | AY52: -0.053 | AZ52: 0.061 | BA52: 0.35 | BB52: 0.338 | BC52: -0.091 | BD52: 0.456 | BE52: -0.384 | BF52: -0.018 | BG52: 0.098 | BH52: -0.008 | BI52: 0.219 | BJ52: 0.221 | BK52: -0.241 | BM52: =10%*AK52+5%*AL52+2.5%*AM52+2.5%*AN52+10%*AO52+10%*AP52+10%*AQ52+5%*AR52+5%*AS52+10%*AT52+5%*AU52+5%*AY52+10%*AV52+10%*AW52 -> 0.1182
A53: SAPR4 | B53: 0.02 | C53: =B53-E53 -> 0.02 | D53: =B53-K53 -> 0.008 | E53: =K53-L53 -> 0 | F53: 1.892 | G53: 2.004 | H53: bond_proxies | I53: =VLOOKUP(A53,Setores!$A$2:$C$215,2,0) -> utilities | J53: =VLOOKUP(A53,Setores!$A$2:$C$215,3,0) -> neutral_beta | K53: 0.012 | L53: 0.012 | M53: =VLOOKUP(A53,'Mandato Ibov'!$B$1:$C$215,2,0) -> 0.0089446895 | N53: =K53-M53 -> 0.0030553105 | O53: =B53-M53 -> 0.01105531 | P53: =VLOOKUP(A53,'Mandato Ibov'!$B$2:$D$215,3,0) -> 0 | Q53: =K53-P53 -> 0.012 | R53: -0.071 | S53: -0.203 | T53: -0.267 | U53: 0.173 | V53: -0.075 | W53: 0.266 | X53: 0.486 | Y53: 0.177 | Z53: 0.436 | AA53: 0.438 | AB53: 0.889 | AC53: 0.682 | AD53: 0.735 | AE53: 0.414 | AF53: -0.133 | AG53: 0.265 | AH53: -0.548 | AI53: -0.588 | AJ53: -0.408 | AK53: 0.408 | AL53: -0.203 | AM53: -0.343 | AN53: -0.254 | AO53: 0.109 | AP53: -0.3 | AQ53: -0.014 | AR53: -0.524 | AS53: -0.791 | AT53: 0.172 | AU53: 0.264 | AV53: 0.44 | AW53: 0.735 | AX53: -0.095 | AY53: -0.214 | AZ53: 0.426 | BA53: 1 | BB53: 0.018 | BC53: 0.477 | BD53: 0.395 | BE53: -0.257 | BF53: 0.461 | BG53: 0.374 | BH53: -0.684 | BI53: -0.103 | BJ53: 0.621 | BK53: 0.109 | BM53: =10%*AK53+5%*AL53+2.5%*AM53+2.5%*AN53+10%*AO53+10%*AP53+10%*AQ53+5%*AR53+5%*AS53+10%*AT53+5%*AU53+5%*AY53+10%*AV53+10%*AW53 -> 0.066675
A54: TIMS3 | B54: =K54 -> 0.025 | C54: =B54-E54 -> 0.018 | D54: =B54-K54 -> 0 | E54: =K54-L54 -> 0.007 | F54: 1.88 | G54: 2.726 | H54: bond_proxies | I54: =VLOOKUP(A54,Setores!$A$2:$C$215,2,0) -> telecom | J54: =VLOOKUP(A54,Setores!$A$2:$C$215,3,0) -> very_low_beta | K54: 0.025 | L54: 0.018 | M54: =VLOOKUP(A54,'Mandato Ibov'!$B$1:$C$215,2,0) -> 0.017856406 | N54: =K54-M54 -> 0.0071435939 | O54: =B54-M54 -> 0.0071435939 | P54: =VLOOKUP(A54,'Mandato Ibov'!$B$2:$D$215,3,0) -> 0.010715158 | Q54: =K54-P54 -> 0.014284842 | R54: 0.026 | S54: -0.562 | T54: -0.479 | U54: 0.404 | V54: -0.261 | W54: 0.491 | X54: 0.74 | Y54: 0.122 | Z54: 0.45 | AA54: 0.447 | AB54: 0.813 | AC54: 0.789 | AD54: 0.633 | AE54: 0.752 | AF54: 0.088 | AG54: -0.534 | AH54: -0.904 | AI54: -0.86 | AJ54: -0.492 | AK54: 0.325 | AL54: -0.021 | AM54: -0.827 | AN54: -0.128 | AO54: -0.071 | AP54: -0.251 | AQ54: 0.538 | AR54: 0.264 | AS54: -0.314 | AT54: 0.433 | AU54: 0.246 | AV54: 1 | AW54: 0.727 | AX54: 0.173 | AY54: 0.775 | AZ54: 0.393 | BA54: 0.895 | BB54: 0.284 | BC54: 0.397 | BD54: 0.613 | BE54: 0.27 | BF54: 0.663 | BG54: 0.354 | BH54: -0.703 | BI54: -0.362 | BJ54: 0.021 | BK54: -0.536 | BM54: =10%*AK54+5%*AL54+2.5%*AM54+2.5%*AN54+10%*AO54+10%*AP54+10%*AQ54+5%*AR54+5%*AS54+10%*AT54+5%*AU54+5%*AY54+10%*AV54+10%*AW54 -> 0.293725
A55: BBSE3 | B55: 0.022 | C55: =B55-E55 -> 0.014 | D55: =B55-K55 -> -0.001 | E55: =K55-L55 -> 0.008 | F55: 1.865 | G55: 3.372 | H55: defensives | I55: =VLOOKUP(A55,Setores!$A$2:$C$215,2,0) -> float_financials | J55: =VLOOKUP(A55,Setores!$A$2:$C$215,3,0) -> very_low_beta | K55: 0.023 | L55: 0.015 | M55: =VLOOKUP(A55,'Mandato Ibov'!$B$1:$C$215,2,0) -> 0.020076536 | N55: =K55-M55 -> 0.0029234636 | O55: =B55-M55 -> 0.0019234636 | P55: =VLOOKUP(A55,'Mandato Ibov'!$B$2:$D$215,3,0) -> 0.020993034 | Q55: =K55-P55 -> 0.0020069656 | R55: -0.419 | S55: -0.452 | T55: -0.644 | U55: 0.107 | V55: -0.237 | W55: 0.377 | X55: 0.89 | Y55: 0.462 | Z55: 0.552 | AA55: 0.554 | AB55: 0.757 | AC55: 0.75 | AD55: 0.61 | AE55: 0.084 | AF55: 0.686 | AG55: -0.183 | AH55: -0.825 | AI55: -0.848 | AJ55: -0.649 | AK55: -0.279 | AL55: 0.576 | AM55: -0.942 | AN55: 0.267 | AO55: 0.23 | AP55: 0.343 | AQ55: 0.051 | AR55: 0.266 | AS55: -0.354 | AT55: 0.715 | AU55: 0.21 | AV55: -0.185 | AW55: 0.951 | AX55: 0.719 | AY55: 0.716 | AZ55: -0.237 | BA55: -0.649 | BB55: -0.103 | BC55: 0.02 | BD55: -1 | BE55: -0.632 | BF55: -0.071 | BG55: 0.928 | BH55: -0.408 | BI55: -0.628 | BJ55: -0.067 | BK55: -0.603 | BM55: =10%*AK55+5%*AL55+2.5%*AM55+2.5%*AN55+10%*AO55+10%*AP55+10%*AQ55+5%*AR55+5%*AS55+10%*AT55+5%*AU55+5%*AY55+10%*AV55+10%*AW55 -> 0.236425
A56: EZTC3 | B56: =K56 -> 0.01 | C56: =B56-E56 -> 0.01 | D56: =B56-K56 -> 0 | E56: =K56-L56 -> 0 | F56: 1.851 | G56: 1.738 | H56: pro_cyclicals | I56: =VLOOKUP(A56,Setores!$A$2:$C$215,2,0) -> homebuilders | J56: =VLOOKUP(A56,Setores!$A$2:$C$215,3,0) -> high_beta | K56: 0.01 | L56: 0.01 | M56: =VLOOKUP(A56,'Mandato Ibov'!$B$1:$C$215,2,0) -> 0.0087508554 | N56: =K56-M56 -> 0.0012491446 | O56: =B56-M56 -> 0.0012491446 | P56: =VLOOKUP(A56,'Mandato Ibov'!$B$2:$D$215,3,0) -> 0 | Q56: =K56-P56 -> 0.01 | R56: 0.297 | S56: 0.095 | T56: 0.105 | U56: 0.201 | V56: 0.055 | W56: 0.229 | X56: 0.281 | Y56: -0.139 | Z56: 0.208 | AA56: 0.206 | AB56: 0.822 | AC56: 0.881 | AD56: 0.697 | AE56: 0.408 | AF56: 0.467 | AG56: -0.235 | AH56: -0.194 | AI56: -0.09 | AJ56: -0.021 | AK56: -0.102 | AL56: -0.213 | AM56: -0.186 | AN56: 0.743 | AO56: -0.309 | AP56: -0.017 | AQ56: 0.479 | AR56: 0.392 | AS56: 0.353 | AT56: -0.054 | AU56: 0.432 | AV56: 0.345 | AW56: -0.111 | AX56: 0.186 | AY56: 0.442 | AZ56: 0.631 | BA56: 0 | BB56: -0.049 | BC56: -0.085 | BD56: 0.244 | BE56: 0.335 | BF56: -0.154 | BG56: 0.203 | BH56: -0.156 | BI56: 0.457 | BJ56: -0.012 | BK56: 0.03 | BM56: =10%*AK56+5%*AL56+2.5%*AM56+2.5%*AN56+10%*AO56+10%*AP56+10%*AQ56+5%*AR56+5%*AS56+10%*AT56+5%*AU56+5%*AY56+10%*AV56+10%*AW56 -> 0.107325
A57: IGTI11 | B57: =K57 -> 0.014 | C57: =B57-E57 -> 0.012 | D57: =B57-K57 -> 0 | E57: =K57-L57 -> 0.002 | F57: 1.809 | G57: 2.555 | H57: bond_proxies | I57: =VLOOKUP(A57,Setores!$A$2:$C$215,2,0) -> real_estate | J57: =VLOOKUP(A57,Setores!$A$2:$C$215,3,0) -> high_beta | K57: 0.014 | L57: 0.012 | M57: =VLOOKUP(A57,'Mandato Ibov'!$B$1:$C$215,2,0) -> 0.01007051 | N57: =K57-M57 -> 0.0039294895 | O57: =B57-M57 -> 0.0039294895 | P57: =VLOOKUP(A57,'Mandato Ibov'!$B$2:$D$215,3,0) -> 0.0098198344 | Q57: =K57-P57 -> 0.0041801656 | R57: 0.253 | S57: 0.042 | T57: -0.324 | U57: 0.225 | V57: -0.195 | W57: 0.498 | X57: 0.816 | Y57: -0.22 | Z57: 0.249 | AA57: 0.247 | AB57: 0.811 | AC57: 0.78 | AD57: 0.63 | AE57: 0.077 | AF57: -0.052 | AG57: -0.321 | AH57: -0.791 | AI57: -0.162 | AJ57: 0.028 | AK57: -0.31 | AL57: -0.696 | AM57: -0.679 | AN57: -0.209 | AO57: 0.062 | AP57: 0.363 | AQ57: 0.803 | AR57: 0.716 | AS57: 0.37 | AT57: 0.204 | AU57: 0.928 | AV57: 0.811 | AW57: 0.224 | AX57: -0.163 | AY57: 0.484 | AZ57: 0.549 | BA57: 0.512 | BB57: 0.406 | BC57: 0.091 | BD57: 0.522 | BE57: -0.296 | BF57: -0.233 | BG57: 0.553 | BH57: -0.4 | BI57: 0.465 | BJ57: -0.238 | BK57: -0.179 | BM57: =10%*AK57+5%*AL57+2.5%*AM57+2.5%*AN57+10%*AO57+10%*AP57+10%*AQ57+5%*AR57+5%*AS57+10%*AT57+5%*AU57+5%*AY57+10%*AV57+10%*AW57 -> 0.2836
A58: PSSA3 | B58: =K58 -> 0.013 | C58: =B58-E58 -> 0.009 | D58: =B58-K58 -> 0 | E58: =K58-L58 -> 0.004 | F58: 1.731 | G58: 2.259 | H58: defensives | I58: =VLOOKUP(A58,Setores!$A$2:$C$215,2,0) -> float_financials | J58: =VLOOKUP(A58,Setores!$A$2:$C$215,3,0) -> very_low_beta | K58: 0.013 | L58: 0.009 | M58: =VLOOKUP(A58,'Mandato Ibov'!$B$1:$C$215,2,0) -> 0.011170638 | N58: =K58-M58 -> 0.0018293621 | O58: =B58-M58 -> 0.0018293621 | P58: =VLOOKUP(A58,'Mandato Ibov'!$B$2:$D$215,3,0) -> 0.011771554 | Q58: =K58-P58 -> 0.001228446 | R58: -0.063 | S58: -0.332 | T58: -0.539 | U58: 0.136 | V58: -0.342 | W58: 0.361 | X58: 0.594 | Y58: 0.025 | Z58: 0.457 | AA58: 0.456 | AB58: 0.769 | AC58: 0.801 | AD58: 0.682 | AE58: -0.024 | AF58: 0.213 | AG58: -0.292 | AH58: -0.874 | AI58: -0.774 | AJ58: -0.384 | AK58: -0.052 | AL58: -0.262 | AM58: -0.737 | AN58: 0.194 | AO58: 0.16 | AP58: 0.222 | AQ58: 0.491 | AR58: 0.361 | AS58: 0.12 | AT58: 0.37 | AU58: 0.136 | AV58: 0.354 | AW58: 0.786 | AX58: 0.238 | AY58: 0.908 | AZ58: 1 | BA58: 0.467 | BB58: -0.13 | BC58: 0.096 | BD58: -0.185 | BE58: -0.39 | BF58: 0.441 | BG58: 0.585 | BH58: -0.734 | BI58: -0.392 | BJ58: 0.079 | BK58: -0.262 | BM58: =10%*AK58+5%*AL58+2.5%*AM58+2.5%*AN58+10%*AO58+10%*AP58+10%*AQ58+5%*AR58+5%*AS58+10%*AT58+5%*AU58+5%*AY58+10%*AV58+10%*AW58 -> 0.282675
A59: BMEB4 | B59: =K59 -> 0.008 | C59: =B59-E59 -> 0.008 | D59: =B59-K59 -> 0 | E59: =K59-L59 -> 0 | F59: 1.71 | G59: 1.266 | H59: pro_cyclicals | I59: =VLOOKUP(A59,Setores!$A$2:$C$215,2,0) -> banks | J59: =VLOOKUP(A59,Setores!$A$2:$C$215,3,0) -> high_beta | K59: 0.008 | L59: 0.008 | M59: =VLOOKUP(A59,'Mandato Ibov'!$B$1:$C$215,2,0) -> 0.0080843905 | N59: =K59-M59 -> -8.4390492e-05 | O59: =B59-M59 -> -8.4390492e-05 | P59: =VLOOKUP(A59,'Mandato Ibov'!$B$2:$D$215,3,0) -> 0.0092208309 | Q59: =K59-P59 -> -0.0012208309 | R59: 0.006 | S59: -0.094 | T59: -0.16 | U59: -0.034 | V59: -0.221 | W59: -0.013 | X59: -0.098 | Y59: -0.051 | Z59: 0.507 | AA59: 0.505 | AB59: 0.902 | AC59: 0.857 | AD59: 0.852 | AE59: -0.41 | AF59: -0.117 | AG59: 0.061 | AH59: -0.724 | AI59: 0.127 | AJ59: -0.04 | AK59: -0.216 | AL59: -0.402 | AM59: -0.588 | AN59: -0.481 | AO59: 0.263 | AP59: 0.692 | AQ59: 0.432 | AR59: 0.58 | AS59: 0.416 | AT59: 0.29 | AU59: -0.11 | AV59: 0.166 | AW59: 0.346 | AX59: 0.185 | AY59: 0.668 | AZ59: 1 | BA59: 0.485 | BB59: -0.682 | BC59: -0.147 | BD59: -0.604 | BE59: 0.259 | BF59: -0.671 | BG59: 0.221 | BH59: -1 | BI59: 0.274 | BJ59: 0.923 | BK59: 0.388 | BM59: =10%*AK59+5%*AL59+2.5%*AM59+2.5%*AN59+10%*AO59+10%*AP59+10%*AQ59+5%*AR59+5%*AS59+10%*AT59+5%*AU59+5%*AY59+10%*AV59+10%*AW59 -> 0.228175
A60: JSLG3 | B60: 0.004 | C60: =B60-E60 -> 0.004 | D60: =B60-K60 -> -0.001 | E60: =K60-L60 -> 0 | F60: 1.71 | G60: 1.257 | H60: pro_cyclicals | I60: =VLOOKUP(A60,Setores!$A$2:$C$215,2,0) -> transportation | J60: =VLOOKUP(A60,Setores!$A$2:$C$215,3,0) -> very_high_beta | K60: 0.005 | L60: 0.005 | M60: =VLOOKUP(A60,'Mandato Ibov'!$B$1:$C$215,2,0) -> 0.0080837608 | N60: =K60-M60 -> -0.0030837608 | O60: =B60-M60 -> -0.0040837608 | P60: =VLOOKUP(A60,'Mandato Ibov'!$B$2:$D$215,3,0) -> 0.0062173202 | Q60: =K60-P60 -> -0.0012173202 | R60: -0.153 | S60: 0.294 | T60: 0.073 | U60: -0.18 | V60: 0.225 | W60: -0.408 | X60: -0.516 | Y60: 0.445 | Z60: 0.071 | AA60: 0.07 | AB60: 0.587 | AC60: 0.798 | AD60: 0.786 | AE60: -0.443 | AF60: -0.075 | AG60: 1 | AH60: 0.953 | AI60: 0.973 | AJ60: -0.733 | AK60: 0.705 | AL60: 0.541 | AM60: -0.299 | AN60: 0.087 | AO60: 0.527 | AP60: 0.081 | AQ60: -0.33 | AR60: -1 | AS60: -1 | AT60: -0.098 | AU60: -0.422 | AV60: -0.605 | AW60: -0.568 | AX60: -0.593 | AY60: 0.109 | AZ60: -0.235 | BA60: 0.045 | BB60: 0.277 | BC60: 0.412 | BD60: 0.469 | BE60: 0.567 | BF60: 0.386 | BG60: 0.037 | BH60: -0.27 | BI60: 1 | BJ60: 0.405 | BK60: 0.626 | BM60: =10%*AK60+5%*AL60+2.5%*AM60+2.5%*AN60+10%*AO60+10%*AP60+10%*AQ60+5%*AR60+5%*AS60+10%*AT60+5%*AU60+5%*AY60+10%*AV60+10%*AW60 -> -0.1227
A61: SAPR11 | B61: =K61 -> 0.011 | C61: =B61-E61 -> 0.011 | D61: =B61-K61 -> 0 | E61: =K61-L61 -> 0 | F61: 1.603 | G61: 1.691 | H61: bond_proxies | I61: =VLOOKUP(A61,Setores!$A$2:$C$215,2,0) -> utilities | J61: =VLOOKUP(A61,Setores!$A$2:$C$215,3,0) -> neutral_beta | K61: 0.011 | L61: 0.011 | M61: =VLOOKUP(A61,'Mandato Ibov'!$B$1:$C$215,2,0) -> 0.0075780778 | N61: =K61-M61 -> 0.0034219222 | O61: =B61-M61 -> 0.0034219222 | P61: =VLOOKUP(A61,'Mandato Ibov'!$B$2:$D$215,3,0) -> 0 | Q61: =K61-P61 -> 0.011 | R61: -0.302 | S61: -0.313 | T61: -0.528 | U61: 0.095 | V61: -0.189 | W61: 0.093 | X61: 0.352 | Y61: 0.125 | Z61: 0.421 | AA61: 0.423 | AB61: 0.841 | AC61: 0.788 | AD61: 0.68 | AE61: 0.398 | AF61: -0.14 | AG61: 0.355 | AH61: -0.552 | AI61: -0.554 | AJ61: -0.411 | AK61: 0.408 | AL61: -0.222 | AM61: -0.343 | AN61: -0.269 | AO61: 0.138 | AP61: -0.398 | AQ61: -0.014 | AR61: -0.524 | AS61: -0.791 | AT61: 0.172 | AU61: 0.264 | AV61: 0.438 | AW61: 0.71 | AX61: -0.095 | AY61: -0.214 | AZ61: 0.363 | BA61: 0.21 | BB61: 0.018 | BC61: 0.477 | BD61: 0.411 | BE61: -0.21 | BF61: 0.591 | BG61: 0.379 | BH61: -0.767 | BI61: -0.002 | BJ61: -0.07 | BK61: 0.109 | BM61: =10%*AK61+5%*AL61+2.5%*AM61+2.5%*AN61+10%*AO61+10%*AP61+10%*AQ61+5%*AR61+5%*AS61+10%*AT61+5%*AU61+5%*AY61+10%*AV61+10%*AW61 -> 0.05575
A62: CURY3 | B62: =K62 -> 0.009 | C62: =B62-E62 -> 0.007 | D62: =B62-K62 -> 0 | E62: =K62-L62 -> 0.002 | F62: 1.573 | G62: 1.557 | H62: pro_cyclicals | I62: =VLOOKUP(A62,Setores!$A$2:$C$215,2,0) -> homebuilders | J62: =VLOOKUP(A62,Setores!$A$2:$C$215,3,0) -> neutral_beta | K62: 0.009 | L62: 0.007 | M62: =VLOOKUP(A62,'Mandato Ibov'!$B$1:$C$215,2,0) -> 0.0085717034 | N62: =K62-M62 -> 0.00042829664 | O62: =B62-M62 -> 0.00042829664 | P62: =VLOOKUP(A62,'Mandato Ibov'!$B$2:$D$215,3,0) -> 0 | Q62: =K62-P62 -> 0.009 | R62: -0.071 | S62: -0.742 | T62: -0.291 | U62: 0.33 | V62: -0.255 | W62: 0.197 | X62: 0.278 | Y62: 0.136 | Z62: 0.296 | AA62: 0.296 | AB62: 0.761 | AC62: 0.564 | AD62: 0.546 | AE62: 1 | AF62: 0.298 | AG62: -0.858 | AH62: -0.617 | AI62: -0.755 | AJ62: -0.003 | AK62: -0.074 | AL62: 0.391 | AM62: -0.874 | AN62: 0.27 | AO62: -0.329 | AP62: -0.573 | AQ62: 0.388 | AR62: 0.334 | AS62: 0.043 | AT62: 1 | AU62: -0.053 | AV62: 0.856 | AW62: 0.111 | AX62: 0.34 | AY62: 0.769 | AZ62: 0.985 | BA62: 0.355 | BB62: -0.814 | BC62: -0.158 | BD62: 0.202 | BE62: 0.133 | BF62: -0.207 | BG62: 0.001 | BH62: -0.944 | BI62: 0.304 | BJ62: -0.531 | BK62: -0.358 | BM62: =10%*AK62+5%*AL62+2.5%*AM62+2.5%*AN62+10%*AO62+10%*AP62+10%*AQ62+5%*AR62+5%*AS62+10%*AT62+5%*AU62+5%*AY62+10%*AV62+10%*AW62 -> 0.197
A63: AXIA6 | B63: 0.028 | C63: =B63-E63 -> 0.021 | D63: =B63-K63 -> 0.002 | E63: =K63-L63 -> 0.007 | F63: 1.499 | G63: 2.371 | H63: bond_proxies | I63: =VLOOKUP(A63,Setores!$A$2:$C$215,2,0) -> utilities | J63: =VLOOKUP(A63,Setores!$A$2:$C$215,3,0) -> high_beta | K63: 0.026 | L63: 0.019 | M63: =VLOOKUP(A63,'Mandato Ibov'!$B$1:$C$215,2,0) -> 0.013541127 | N63: =K63-M63 -> 0.012458873 | O63: =B63-M63 -> 0.014458873 | P63: =VLOOKUP(A63,'Mandato Ibov'!$B$2:$D$215,3,0) -> 0.018209434 | Q63: =K63-P63 -> 0.0077905662 | R63: -0.214 | S63: -0.21 | T63: -0.804 | U63: -0.109 | V63: -0.515 | W63: 0.174 | X63: 0.362 | Y63: -0.029 | Z63: 0.405 | AA63: 0.407 | AB63: 0.804 | AC63: 0.818 | AD63: 0.728 | AE63: -0.429 | AF63: -0.252 | AG63: 0.149 | AH63: -1 | AI63: -0.65 | AJ63: -0.846 | AK63: -0.378 | AL63: -0.336 | AM63: -0.553 | AN63: -0.317 | AO63: 0.413 | AP63: 0.529 | AQ63: 0.469 | AR63: 1 | AS63: 0.65 | AT63: -0.216 | AU63: 0.002 | AV63: 0.179 | AW63: 0.33 | AX63: -0.582 | AY63: 0.639 | AZ63: 0.43 | BA63: 0.805 | BB63: -0.074 | BC63: -0.295 | BD63: 0.709 | BE63: 0.242 | BF63: 0.614 | BG63: 0.753 | BH63: -0.719 | BI63: 0.097 | BJ63: 0.213 | BK63: -1 | BM63: =10%*AK63+5%*AL63+2.5%*AM63+2.5%*AN63+10%*AO63+10%*AP63+10%*AQ63+5%*AR63+5%*AS63+10%*AT63+5%*AU63+5%*AY63+10%*AV63+10%*AW63 -> 0.2086
A64: ALOS3 | B64: 0.014 | C64: =B64-E64 -> 0.008 | D64: =B64-K64 -> -0.002 | E64: =K64-L64 -> 0.006 | F64: 1.488 | G64: 2.479 | H64: bond_proxies | I64: =VLOOKUP(A64,Setores!$A$2:$C$215,2,0) -> real_estate | J64: =VLOOKUP(A64,Setores!$A$2:$C$215,3,0) -> high_beta | K64: 0.016 | L64: 0.01 | M64: =VLOOKUP(A64,'Mandato Ibov'!$B$1:$C$215,2,0) -> 0.012212999 | N64: =K64-M64 -> 0.003787001 | O64: =B64-M64 -> 0.001787001 | P64: =VLOOKUP(A64,'Mandato Ibov'!$B$2:$D$215,3,0) -> 0 | Q64: =K64-P64 -> 0.016 | R64: -0.263 | S64: -0.164 | T64: -0.697 | U64: -0.217 | V64: -0.445 | W64: 0.257 | X64: 0.686 | Y64: -0.013 | Z64: 0.314 | AA64: 0.313 | AB64: 0.77 | AC64: 0.764 | AD64: 0.624 | AE64: -0.085 | AF64: -0.385 | AG64: -0.037 | AH64: -0.768 | AI64: -0.25 | AJ64: -0.531 | AK64: -0.117 | AL64: -0.122 | AM64: -0.534 | AN64: 0.129 | AO64: 0.129 | AP64: 0.329 | AQ64: -0.251 | AR64: 0.278 | AS64: -0.414 | AT64: -0.103 | AU64: 0.812 | AV64: 0.206 | AW64: 0.316 | AX64: 0.294 | AY64: 0.51 | AZ64: 0.453 | BA64: -0.314 | BB64: 0.216 | BC64: 0.216 | BD64: 0.503 | BE64: -0.108 | BF64: -0.226 | BG64: 0.761 | BH64: -0.457 | BI64: 0.382 | BJ64: -0.607 | BK64: -0.404 | BM64: =10%*AK64+5%*AL64+2.5%*AM64+2.5%*AN64+10%*AO64+10%*AP64+10%*AQ64+5%*AR64+5%*AS64+10%*AT64+5%*AU64+5%*AY64+10%*AV64+10%*AW64 -> 0.093975
A65: RECV3 | B65: =K65 -> 0.016 | C65: =B65-E65 -> 0.015 | D65: =B65-K65 -> 0 | E65: =K65-L65 -> 0.001 | F65: 1.459 | G65: 1.506 | H65: commodities | I65: =VLOOKUP(A65,Setores!$A$2:$C$215,2,0) -> crude_oil | J65: =VLOOKUP(A65,Setores!$A$2:$C$215,3,0) -> very_low_beta | K65: 0.016 | L65: 0.015 | M65: =VLOOKUP(A65,'Mandato Ibov'!$B$1:$C$215,2,0) -> 0.0074838148 | N65: =K65-M65 -> 0.0085161852 | O65: =B65-M65 -> 0.0085161852 | P65: =VLOOKUP(A65,'Mandato Ibov'!$B$2:$D$215,3,0) -> 0.011137704 | Q65: =K65-P65 -> 0.004862296 | R65: -0.62 | S65: 0.302 | T65: -0.769 | U65: -0.524 | V65: -0.274 | W65: -0.138 | X65: -0.117 | Y65: 0.367 | Z65: 0.542 | AA65: 0.542 | AB65: 0.503 | AC65: 0.632 | AD65: 0.767 | AE65: -0.846 | AF65: -0.829 | AG65: 1 | AH65: -0.275 | AI65: 0.75 | AJ65: -0.721 | AK65: -0.316 | AL65: 0.358 | AM65: -0.127 | AN65: 0.03 | AO65: 0.496 | AP65: 0.983 | AQ65: -0.511 | AR65: -0.16 | AS65: -0.521 | AT65: 0.002 | AU65: 0.088 | AV65: -0.798 | AW65: 0.338 | AX65: 0.156 | AY65: 0.804 | AZ65: 0.281 | BA65: -0.175 | BB65: -0.081 | BC65: -0.474 | BD65: -0.242 | BE65: -0.229 | BF65: 0.028 | BG65: 0.483 | BH65: -0.136 | BI65: -0.957 | BJ65: -0.49 | BK65: 0.465 | BM65: =10%*AK65+5%*AL65+2.5%*AM65+2.5%*AN65+10%*AO65+10%*AP65+10%*AQ65+5%*AR65+5%*AS65+10%*AT65+5%*AU65+5%*AY65+10%*AV65+10%*AW65 -> 0.045425
A66: JALL3 | B66: 0.0125 | C66: =B66-E66 -> 0.0125 | D66: =B66-K66 -> -0.0025 | E66: =K66-L66 -> 0 | F66: 1.44 | G66: 1.112 | H66: commodities | I66: =VLOOKUP(A66,Setores!$A$2:$C$215,2,0) -> food | J66: =VLOOKUP(A66,Setores!$A$2:$C$215,3,0) -> very_low_beta | K66: 0.015 | L66: 0.015 | M66: =VLOOKUP(A66,'Mandato Ibov'!$B$1:$C$215,2,0) -> 0.0068086575 | N66: =K66-M66 -> 0.0081913425 | O66: =B66-M66 -> 0.0056913425 | P66: =VLOOKUP(A66,'Mandato Ibov'!$B$2:$D$215,3,0) -> 0 | Q66: =K66-P66 -> 0.015 | R66: 0.002 | S66: 0.643 | T66: 0.04 | U66: -0.309 | V66: 0.133 | W66: -0.262 | X66: -0.558 | Y66: -0.477 | Z66: 0.341 | AA66: 0.342 | AB66: 0.963 | AC66: 1 | AD66: 0.906 | AE66: -0.151 | AF66: -0.185 | AG66: 0.869 | AH66: 0.809 | AI66: 0.67 | AJ66: -0.657 | AK66: 0.331 | AL66: -0.864 | AM66: 0.449 | AN66: -0.167 | AO66: -0.029 | AP66: 0.522 | AQ66: -1 | AR66: 0.917 | AS66: 0.07 | AT66: -0.212 | AU66: -0.398 | AV66: -0.262 | AW66: 0.226 | AX66: -0.132 | AY66: -0.039 | AZ66: -0.925 | BA66: 0.72 | BB66: 0.034 | BC66: 0.064 | BD66: 0.023 | BE66: 0.017 | BF66: 0.339 | BG66: 0.397 | BH66: 0.444 | BI66: -0.568 | BJ66: 0.627 | BK66: 0.828 | BM66: =10%*AK66+5%*AL66+2.5%*AM66+2.5%*AN66+10%*AO66+10%*AP66+10%*AQ66+5%*AR66+5%*AS66+10%*AT66+5%*AU66+5%*AY66+10%*AV66+10%*AW66 -> -0.05105
A67: B3SA3 | B67: 0.02 | C67: =B67-E67 -> -0.014 | D67: =B67-K67 -> 0.002 | E67: =K67-L67 -> 0.034 | F67: 1.433 | G67: 3.043 | H67: pro_cyclicals | I67: =VLOOKUP(A67,Setores!$A$2:$C$215,2,0) -> financial_services | J67: =VLOOKUP(A67,Setores!$A$2:$C$215,3,0) -> very_high_beta | K67: 0.018 | L67: -0.016 | M67: =VLOOKUP(A67,'Mandato Ibov'!$B$1:$C$215,2,0) -> 0.037303716 | N67: =K67-M67 -> -0.019303716 | O67: =B67-M67 -> -0.017303716 | P67: =VLOOKUP(A67,'Mandato Ibov'!$B$2:$D$215,3,0) -> 0.029710474 | Q67: =K67-P67 -> -0.011710474 | R67: -0.181 | S67: -0.201 | T67: -0.825 | U67: -0.037 | V67: -0.534 | W67: 0.226 | X67: 0.749 | Y67: -0.175 | Z67: 0.395 | AA67: 0.396 | AB67: 0.701 | AC67: 0.724 | AD67: 0.626 | AE67: -0.031 | AF67: -0.596 | AG67: -0.32 | AH67: -0.999 | AI67: -0.751 | AJ67: -0.736 | AK67: -0.38 | AL67: -0.529 | AM67: -0.998 | AN67: -0.205 | AO67: 0.314 | AP67: 0.408 | AQ67: 0.225 | AR67: 0.435 | AS67: 0.78 | AT67: 0.452 | AU67: 1 | AV67: 0.74 | AW67: -0.021 | AX67: 0.161 | AY67: 0.177 | AZ67: -0.069 | BA67: 0.446 | BB67: 0.237 | BC67: 0.28 | BD67: 0.411 | BE67: 0.039 | BF67: 0.233 | BG67: 0.906 | BH67: -0.358 | BI67: 0.315 | BJ67: -0.504 | BK67: -0.789 | BM67: =10%*AK67+5%*AL67+2.5%*AM67+2.5%*AN67+10%*AO67+10%*AP67+10%*AQ67+5%*AR67+5%*AS67+10%*AT67+5%*AU67+5%*AY67+10%*AV67+10%*AW67 -> 0.236875
A68: VBBR3 | B68: =K68 -> 0.022 | C68: =B68-E68 -> 0.006 | D68: =B68-K68 -> 0 | E68: =K68-L68 -> 0.016 | F68: 1.381 | G68: 2.577 | H68: pro_cyclicals | I68: =VLOOKUP(A68,Setores!$A$2:$C$215,2,0) -> consumer_services | J68: =VLOOKUP(A68,Setores!$A$2:$C$215,3,0) -> low_beta | K68: 0.022 | L68: 0.006 | M68: =VLOOKUP(A68,'Mandato Ibov'!$B$1:$C$215,2,0) -> 0.023701553 | N68: =K68-M68 -> -0.0017015528 | O68: =B68-M68 -> -0.0017015528 | P68: =VLOOKUP(A68,'Mandato Ibov'!$B$2:$D$215,3,0) -> 0.038800322 | Q68: =K68-P68 -> -0.016800322 | R68: -0.399 | S68: -0.157 | T68: -0.886 | U68: -0.088 | V68: -0.482 | W68: -0.265 | X68: -0.348 | Y68: 0.103 | Z68: 0.643 | AA68: 0.645 | AB68: 0.726 | AC68: 0.8 | AD68: 0.81 | AE68: -0.469 | AF68: -0.348 | AG68: 0.529 | AH68: -0.922 | AI68: -0.398 | AJ68: -0.97 | AK68: -0.048 | AL68: -0.378 | AM68: -0.651 | AN68: -0.28 | AO68: 0.707 | AP68: 0.444 | AQ68: 0.278 | AR68: 0.885 | AS68: 0.397 | AT68: 0.529 | AU68: -0.616 | AV68: -0.007 | AW68: 0.184 | AX68: -0.367 | AY68: 0.532 | AZ68: 0.578 | BA68: -0.043 | BB68: -0.117 | BC68: 0.119 | BD68: 0.781 | BE68: -0.87 | BF68: -0.646 | BG68: 0.417 | BH68: -0.701 | BI68: -0.314 | BJ68: -0.411 | BK68: -0.577 | BM68: =10%*AK68+5%*AL68+2.5%*AM68+2.5%*AN68+10%*AO68+10%*AP68+10%*AQ68+5%*AR68+5%*AS68+10%*AT68+5%*AU68+5%*AY68+10%*AV68+10%*AW68 -> 0.226425
A69: UGPA3 | B69: =K69 -> 0.021 | C69: =B69-E69 -> 0.008 | D69: =B69-K69 -> 0 | E69: =K69-L69 -> 0.013 | F69: 1.349 | G69: 2.166 | H69: pro_cyclicals | I69: =VLOOKUP(A69,Setores!$A$2:$C$215,2,0) -> consumer_services | J69: =VLOOKUP(A69,Setores!$A$2:$C$215,3,0) -> very_low_beta | K69: 0.021 | L69: 0.008 | M69: =VLOOKUP(A69,'Mandato Ibov'!$B$1:$C$215,2,0) -> 0.019311292 | N69: =K69-M69 -> 0.0016887075 | O69: =B69-M69 -> 0.0016887075 | P69: =VLOOKUP(A69,'Mandato Ibov'!$B$2:$D$215,3,0) -> 0.024527828 | Q69: =K69-P69 -> -0.0035278277 | R69: -0.412 | S69: -0.088 | T69: -0.885 | U69: -0.134 | V69: -0.452 | W69: -0.253 | X69: -0.243 | Y69: 0.016 | Z69: 0.667 | AA69: 0.669 | AB69: 0.541 | AC69: 0.834 | AD69: 0.829 | AE69: -0.638 | AF69: -0.309 | AG69: 0.707 | AH69: -0.913 | AI69: -0.276 | AJ69: -0.933 | AK69: -0.095 | AL69: -0.463 | AM69: -0.644 | AN69: 0.102 | AO69: 0.706 | AP69: 0.65 | AQ69: 0.315 | AR69: 0.717 | AS69: 0.418 | AT69: 0.547 | AU69: -0.619 | AV69: -0.122 | AW69: 0.097 | AX69: -0.154 | AY69: 0.898 | AZ69: -0.258 | BA69: 0.58 | BB69: -0.514 | BC69: -0.501 | BD69: 0.529 | BE69: -0.701 | BF69: -0.165 | BG69: 0.686 | BH69: -0.529 | BI69: -0.579 | BJ69: -0.178 | BK69: -0.502 | BM69: =10%*AK69+5%*AL69+2.5%*AM69+2.5%*AN69+10%*AO69+10%*AP69+10%*AQ69+5%*AR69+5%*AS69+10%*AT69+5%*AU69+5%*AY69+10%*AV69+10%*AW69 -> 0.2438
A70: TEND3 | B70: 0.007 | C70: =B70-E70 -> 0.007 | D70: =B70-K70 -> -0.002 | E70: =K70-L70 -> 0 | F70: 1.322 | G70: 1.004 | H70: pro_cyclicals | I70: =VLOOKUP(A70,Setores!$A$2:$C$215,2,0) -> homebuilders | J70: =VLOOKUP(A70,Setores!$A$2:$C$215,3,0) -> high_beta | K70: 0.009 | L70: 0.009 | M70: =VLOOKUP(A70,'Mandato Ibov'!$B$1:$C$215,2,0) -> 0.0062474644 | N70: =K70-M70 -> 0.0027525356 | O70: =B70-M70 -> 0.00075253565 | P70: =VLOOKUP(A70,'Mandato Ibov'!$B$2:$D$215,3,0) -> 0.010570877 | Q70: =K70-P70 -> -0.0015708775 | R70: 0.19 | S70: -0.061 | T70: -0.242 | U70: 0.265 | V70: -0.096 | W70: -0.204 | X70: -0.51 | Y70: -0.221 | Z70: 0.027 | AA70: 0.024 | AB70: 0.828 | AC70: 0.765 | AD70: 0.577 | AE70: 0.144 | AF70: 0.404 | AG70: -0.034 | AH70: -0.53 | AI70: 0.404 | AJ70: 0.371 | AK70: -0.112 | AL70: -0.752 | AM70: -0.737 | AN70: 0.377 | AO70: 0.267 | AP70: 0.214 | AQ70: 1 | AR70: 0.585 | AS70: 0.293 | AT70: 0.472 | AU70: -0.235 | AV70: 0.702 | AW70: -0.304 | AX70: 0.019 | AY70: -0.476 | AZ70: 0.852 | BA70: 0.519 | BB70: -0.496 | BC70: -0.142 | BD70: 0.477 | BE70: 0.11 | BF70: -0.522 | BG70: -0.433 | BH70: -0.67 | BI70: 0.418 | BJ70: -0.729 | BK70: 0.025 | BM70: =10%*AK70+5%*AL70+2.5%*AM70+2.5%*AN70+10%*AO70+10%*AP70+10%*AQ70+5%*AR70+5%*AS70+10%*AT70+5%*AU70+5%*AY70+10%*AV70+10%*AW70 -> 0.18565
A71: CXSE3 | B71: 0.014 | C71: =B71-E71 -> 0.01 | D71: =B71-K71 -> -0.004 | E71: =K71-L71 -> 0.004 | F71: 1.308 | G71: 2.006 | H71: defensives | I71: =VLOOKUP(A71,Setores!$A$2:$C$215,2,0) -> float_financials | J71: =VLOOKUP(A71,Setores!$A$2:$C$215,3,0) -> very_low_beta | K71: 0.018 | L71: 0.014 | M71: =VLOOKUP(A71,'Mandato Ibov'!$B$1:$C$215,2,0) -> 0.0092528809 | N71: =K71-M71 -> 0.0087471191 | O71: =B71-M71 -> 0.0047471191 | P71: =VLOOKUP(A71,'Mandato Ibov'!$B$2:$D$215,3,0) -> 0.014492653 | Q71: =K71-P71 -> 0.0035073467 | R71: -0.643 | S71: -0.5 | T71: -0.818 | U71: -0.169 | V71: -0.459 | W71: -0.075 | X71: 0.45 | Y71: 0.165 | Z71: 0.39 | AA71: 0.394 | AB71: 0.755 | AC71: 0.775 | AD71: 0.661 | AE71: -0.246 | AF71: -0.112 | AG71: 0.116 | AH71: -0.916 | AI71: -0.575 | AJ71: -0.58 | AK71: -0.231 | AL71: 0.094 | AM71: -0.9 | AN71: -0.165 | AO71: 0.49 | AP71: 0.343 | AQ71: 0.052 | AR71: 0.305 | AS71: 0.099 | AT71: 0.212 | AU71: 0.156 | AV71: 0.051 | AW71: 0.817 | AX71: -0.15 | AY71: 0.857 | AZ71: -0.666 | BA71: -0.157 | BB71: -0.178 | BC71: -0.03 | BD71: -0.894 | BE71: -0.272 | BF71: 0.726 | BG71: 0.849 | BH71: -0.63 | BI71: -0.379 | BJ71: 0.227 | BK71: -0.496 | BM71: =10%*AK71+5%*AL71+2.5%*AM71+2.5%*AN71+10%*AO71+10%*AP71+10%*AQ71+5%*AR71+5%*AS71+10%*AT71+5%*AU71+5%*AY71+10%*AV71+10%*AW71 -> 0.222325
A72: VIVT3 | B72: 0.015 | C72: =B72-E72 -> 0.005 | D72: =B72-K72 -> -0.005 | E72: =K72-L72 -> 0.01 | F72: 1.306 | G72: 2.249 | H72: bond_proxies | I72: =VLOOKUP(A72,Setores!$A$2:$C$215,2,0) -> telecom | J72: =VLOOKUP(A72,Setores!$A$2:$C$215,3,0) -> very_low_beta | K72: 0.02 | L72: 0.01 | M72: =VLOOKUP(A72,'Mandato Ibov'!$B$1:$C$215,2,0) -> 0.015823876 | N72: =K72-M72 -> 0.0041761245 | O72: =B72-M72 -> -0.00082387552 | P72: =VLOOKUP(A72,'Mandato Ibov'!$B$2:$D$215,3,0) -> 0 | Q72: =K72-P72 -> 0.02 | R72: -0.361 | S72: -0.573 | T72: -0.79 | U72: -0.055 | V72: -0.577 | W72: 0.112 | X72: 0.38 | Y72: -0.194 | Z72: 0.601 | AA72: 0.597 | AB72: 0.77 | AC72: 0.835 | AD72: 0.687 | AE72: 0.061 | AF72: -0.311 | AG72: -0.376 | AH72: -0.996 | AI72: -0.842 | AJ72: -0.744 | AK72: -0.208 | AL72: -0.384 | AM72: -0.525 | AN72: -0.54 | AO72: 0.134 | AP72: -0.147 | AQ72: 0.329 | AR72: 0.349 | AS72: 0.379 | AT72: 0.135 | AU72: 0.03 | AV72: 0.771 | AW72: 0.837 | AX72: -0.11 | AY72: 0.994 | AZ72: 0.406 | BA72: 0.724 | BB72: 0.042 | BC72: -0.036 | BD72: 0.544 | BE72: -0.036 | BF72: 0.593 | BG72: 0.643 | BH72: -0.638 | BI72: -0.375 | BJ72: 0.069 | BK72: -0.798 | BM72: =10%*AK72+5%*AL72+2.5%*AM72+2.5%*AN72+10%*AO72+10%*AP72+10%*AQ72+5%*AR72+5%*AS72+10%*AT72+5%*AU72+5%*AY72+10%*AV72+10%*AW72 -> 0.226875
A73: VULC3 | B73: 0.01 | C73: =B73-E73 -> 0.01 | D73: =B73-K73 -> -0.003 | E73: =K73-L73 -> 0 | F73: 1.253 | G73: 1.493 | H73: pro_cyclicals | I73: =VLOOKUP(A73,Setores!$A$2:$C$215,2,0) -> apparel | J73: =VLOOKUP(A73,Setores!$A$2:$C$215,3,0) -> low_beta | K73: 0.013 | L73: 0.013 | M73: =VLOOKUP(A73,'Mandato Ibov'!$B$1:$C$215,2,0) -> 0.0059259027 | N73: =K73-M73 -> 0.0070740973 | O73: =B73-M73 -> 0.0040740973 | P73: =VLOOKUP(A73,'Mandato Ibov'!$B$2:$D$215,3,0) -> 0 | Q73: =K73-P73 -> 0.013 | R73: -0.446 | S73: -0.817 | T73: -0.201 | U73: -0.23 | V73: -0.438 | W73: 0.198 | X73: 0.624 | Y73: 0.05 | Z73: 0.305 | AA73: 0.308 | AB73: 0.637 | AC73: 0.505 | AD73: 0.44 | AE73: 0.268 | AF73: 0.007 | AG73: -0.933 | AH73: -0.231 | AI73: -0.766 | AJ73: 0.243 | AK73: -0.251 | AL73: 1 | AM73: -0.744 | AN73: 0.527 | AO73: -0.711 | AP73: -0.317 | AQ73: 0.151 | AR73: -0.056 | AS73: -0.5 | AT73: 0.67 | AU73: 0.114 | AV73: -0.011 | AW73: 0.422 | AX73: 0.031 | AY73: 0.583 | AZ73: 1 | BA73: -0.193 | BB73: -0.799 | BC73: -0.777 | BD73: -0.519 | BE73: 0.064 | BF73: 0.239 | BG73: 0.752 | BH73: -0.603 | BI73: -0.171 | BJ73: 0.209 | BK73: 0.115 | BM73: =10%*AK73+5%*AL73+2.5%*AM73+2.5%*AN73+10%*AO73+10%*AP73+10%*AQ73+5%*AR73+5%*AS73+10%*AT73+5%*AU73+5%*AY73+10%*AV73+10%*AW73 -> 0.046925
A74: TRIS3 | B74: 0.004 | C74: =B74-E74 -> 0.004 | D74: =B74-K74 -> -0.001 | E74: =K74-L74 -> 0 | F74: 1.231 | G74: 0.897 | H74: pro_cyclicals | I74: =VLOOKUP(A74,Setores!$A$2:$C$215,2,0) -> homebuilders | J74: =VLOOKUP(A74,Setores!$A$2:$C$215,3,0) -> very_high_beta | K74: 0.005 | L74: 0.005 | M74: =VLOOKUP(A74,'Mandato Ibov'!$B$1:$C$215,2,0) -> 0.0058206888 | N74: =K74-M74 -> -0.0008206888 | O74: =B74-M74 -> -0.0018206888 | P74: =VLOOKUP(A74,'Mandato Ibov'!$B$2:$D$215,3,0) -> 0 | Q74: =K74-P74 -> 0.005 | R74: 0.055 | S74: -0.457 | T74: 0.457 | U74: -0.217 | V74: -0.065 | W74: -0.064 | X74: -0.031 | Y74: -0.349 | Z74: 0.043 | AA74: 0.041 | AB74: 0.796 | AC74: 0.582 | AD74: 0.524 | AE74: -0.093 | AF74: 0.848 | AG74: -0.688 | AH74: 0.661 | AI74: -0.272 | AJ74: 0.298 | AK74: -0.028 | AL74: 0.302 | AM74: -0.206 | AN74: 0.704 | AO74: -0.471 | AP74: -1 | AQ74: 0.428 | AR74: -0.017 | AS74: -0.37 | AT74: -0.012 | AU74: -0.098 | AV74: -0.282 | AW74: -0.325 | AX74: 0.053 | AY74: 0.63 | AZ74: 0.254 | BA74: 0.666 | BB74: 0.047 | BC74: -0.106 | BD74: 0.245 | BE74: 1 | BF74: 0.473 | BG74: 0.323 | BH74: -0.382 | BI74: 0.714 | BJ74: 0.797 | BK74: 0.525 | BM74: =10%*AK74+5%*AL74+2.5%*AM74+2.5%*AN74+10%*AO74+10%*AP74+10%*AQ74+5%*AR74+5%*AS74+10%*AT74+5%*AU74+5%*AY74+10%*AV74+10%*AW74 -> -0.1342
A75: CMIG3 | B75: =K75 -> 0.018 | C75: =B75-E75 -> 0.018 | D75: =B75-K75 -> 0 | E75: =K75-L75 -> 0 | F75: 1.228 | G75: 1.286 | H75: bond_proxies | I75: =VLOOKUP(A75,Setores!$A$2:$C$215,2,0) -> utilities | J75: =VLOOKUP(A75,Setores!$A$2:$C$215,3,0) -> very_low_beta | K75: 0.018 | L75: 0.018 | M75: =VLOOKUP(A75,'Mandato Ibov'!$B$1:$C$215,2,0) -> 0.00580521 | N75: =K75-M75 -> 0.01219479 | O75: =B75-M75 -> 0.01219479 | P75: =VLOOKUP(A75,'Mandato Ibov'!$B$2:$D$215,3,0) -> 0.0084555686 | Q75: =K75-P75 -> 0.0095444314 | R75: -0.686 | S75: -0.321 | T75: -0.824 | U75: -0.503 | V75: -0.562 | W75: -0.261 | X75: -0.107 | Y75: 0.217 | Z75: 0.61 | AA75: 0.614 | AB75: 0.653 | AC75: 0.748 | AD75: 0.721 | AE75: -0.83 | AF75: -0.77 | AG75: 0.541 | AH75: -0.911 | AI75: -0.385 | AJ75: -0.962 | AK75: -0.324 | AL75: 0.185 | AM75: -0.522 | AN75: -0.589 | AO75: 0.524 | AP75: 0.992 | AQ75: -0.238 | AR75: 0.187 | AS75: -0.246 | AT75: 0.2 | AU75: -0.331 | AV75: -0.546 | AW75: 0.588 | AX75: -0.597 | AY75: 0.853 | AZ75: 0.566 | BA75: 0.103 | BB75: -0.432 | BC75: -0.665 | BD75: 0.235 | BE75: 0.031 | BF75: -0.134 | BG75: 0.54 | BH75: -0.532 | BI75: -0.409 | BJ75: 0.952 | BK75: -0.378 | BM75: =10%*AK75+5%*AL75+2.5%*AM75+2.5%*AN75+10%*AO75+10%*AP75+10%*AQ75+5%*AR75+5%*AS75+10%*AT75+5%*AU75+5%*AY75+10%*AV75+10%*AW75 -> 0.124225
A76: ITUB3 | B76: 0.025 | C76: =B76-E76 -> 0.025 | D76: =B76-K76 -> 0.002 | E76: =K76-L76 -> 0 | F76: 1.191 | G76: 1.618 | H76: pro_cyclicals | I76: =VLOOKUP(A76,Setores!$A$2:$C$215,2,0) -> banks | J76: =VLOOKUP(A76,Setores!$A$2:$C$215,3,0) -> low_beta | K76: 0.023 | L76: 0.023 | M76: =VLOOKUP(A76,'Mandato Ibov'!$B$1:$C$215,2,0) -> 0.0056328167 | N76: =K76-M76 -> 0.017367183 | O76: =B76-M76 -> 0.019367183 | P76: =VLOOKUP(A76,'Mandato Ibov'!$B$2:$D$215,3,0) -> 0.0077314624 | Q76: =K76-P76 -> 0.015268538 | R76: -0.748 | S76: -0.557 | T76: -0.869 | U76: -0.345 | V76: -0.565 | W76: -0.285 | X76: -0.031 | Y76: 0.207 | Z76: 0.616 | AA76: 0.615 | AB76: 0.763 | AC76: 0.781 | AD76: 0.695 | AE76: -0.584 | AF76: 0.096 | AG76: 0.36 | AH76: -0.948 | AI76: -0.744 | AJ76: -0.961 | AK76: -0.247 | AL76: 0.135 | AM76: -0.557 | AN76: -0.193 | AO76: 0.567 | AP76: 0.074 | AQ76: 0.234 | AR76: 0.269 | AS76: -0.112 | AT76: -0.081 | AU76: -0.222 | AV76: -0.209 | AW76: 0.474 | AX76: -0.453 | AY76: 0.162 | AZ76: 0.612 | BA76: -0.462 | BB76: -0.341 | BC76: -0.317 | BD76: -0.827 | BE76: -0.092 | BF76: -0.036 | BG76: 0.82 | BH76: -0.829 | BI76: -0.229 | BJ76: 0.343 | BK76: -0.939 | BM76: =10%*AK76+5%*AL76+2.5%*AM76+2.5%*AN76+10%*AO76+10%*AP76+10%*AQ76+5%*AR76+5%*AS76+10%*AT76+5%*AU76+5%*AY76+10%*AV76+10%*AW76 -> 0.07405
A77: SAUD3 | B77: 0.01 | C77: =B77-E77 -> 0.01 | D77: =B77-K77 -> -0.002 | E77: =K77-L77 -> 0 | F77: 1.152 | G77: 1.03 | H77: defensives | I77: =VLOOKUP(A77,Setores!$A$2:$C$215,2,0) -> healthcare | J77: =VLOOKUP(A77,Setores!$A$2:$C$215,3,0) -> low_beta | K77: 0.012 | L77: 0.012 | M77: =VLOOKUP(A77,'Mandato Ibov'!$B$1:$C$215,2,0) -> 0.005446653 | N77: =K77-M77 -> 0.006553347 | O77: =B77-M77 -> 0.004553347 | P77: =VLOOKUP(A77,'Mandato Ibov'!$B$2:$D$215,3,0) -> 0.0080269653 | Q77: =K77-P77 -> 0.0039730347 | R77: -0.45 | S77: -0.511 | T77: -0.716 | U77: -0.206 | V77: -0.527 | W77: -0.136 | X77: 0.065 | Y77: 0.038 | Z77: 0.297 | AA77: 0.298 | AB77: 0.591 | AC77: 0.661 | AD77: 0.626 | AE77: -0.033 | AF77: -0.845 | AG77: -0.319 | AH77: -0.987 | AI77: -0.491 | AJ77: -0.441 | AK77: -0.507 | AL77: -0.122 | AM77: -0.946 | AN77: -0.948 | AO77: 0.355 | AP77: 0.986 | AQ77: -0.096 | AR77: 0.187 | AS77: -0.7 | AT77: 0.96 | AU77: -0.039 | AV77: 0.908 | AW77: 0.732 | AX77: 0.666 | AY77: 0.647 | AZ77: 0.414 | BA77: 0.999 | BB77: 0.224 | BC77: 0.094 | BD77: -0.876 | BE77: -0.047 | BF77: -0.386 | BG77: 0.194 | BH77: -0.475 | BI77: -0.199 | BJ77: 0.114 | BK77: -0.737 | BM77: =10%*AK77+5%*AL77+2.5%*AM77+2.5%*AN77+10%*AO77+10%*AP77+10%*AQ77+5%*AR77+5%*AS77+10%*AT77+5%*AU77+5%*AY77+10%*AV77+10%*AW77 -> 0.2851
A78: PAGS34 | B78: 0 | C78: =B78-E78 -> 0 | D78: =B78-K78 -> -0.009 | E78: =K78-L78 -> 0 | F78: 1.151 | G78: 0.861 | H78: pro_cyclicals | I78: =VLOOKUP(A78,Setores!$A$2:$C$215,2,0) -> financial_services | J78: =VLOOKUP(A78,Setores!$A$2:$C$215,3,0) -> neutral_beta | K78: 0.009 | L78: 0.009 | M78: =VLOOKUP(A78,'Mandato Ibov'!$B$1:$C$215,2,0) -> 0.0054418809 | N78: =K78-M78 -> 0.0035581191 | O78: =B78-M78 -> -0.0054418809 | P78: =VLOOKUP(A78,'Mandato Ibov'!$B$2:$D$215,3,0) -> 0 | Q78: =K78-P78 -> 0.009 | R78: -0.117 | S78: -0.142 | T78: -0.176 | U78: -0.165 | V78: -0.178 | W78: -0.344 | X78: -0.32 | Y78: -0.502 | Z78: 0.453 | AA78: 0.45 | AB78: 0.816 | AC78: 1 | AD78: 0.672 | AE78: -0.156 | AF78: 0.702 | AG78: -0.199 | AH78: -0.478 | AI78: -0.826 | AJ78: -0.55 | AK78: 0.429 | AL78: -0.484 | AM78: -0.034 | AN78: 0.953 | AO78: -0.218 | AP78: -0.063 | AQ78: 0.056 | AR78: 0.263 | AS78: -0.073 | AT78: 0.178 | AU78: 0.408 | AV78: -0.392 | AW78: 0.042 | AX78: -0.165 | AY78: 0.089 | AZ78: -0.014 | BA78: -0.02 | BB78: -0.054 | BC78: 0.244 | BD78: 0.336 | BE78: 0.009 | BF78: 0.437 | BG78: -0.24 | BH78: 0.274 | BI78: -0.165 | BJ78: 0.992 | BK78: -0.119 | BM78: =10%*AK78+5%*AL78+2.5%*AM78+2.5%*AN78+10%*AO78+10%*AP78+10%*AQ78+5%*AR78+5%*AS78+10%*AT78+5%*AU78+5%*AY78+10%*AV78+10%*AW78 -> 0.036325
A79: BLAU3 | B79: =K79 -> 0 | C79: =B79-E79 -> 0 | D79: =B79-K79 -> 0 | E79: =K79-L79 -> 0 | F79: 1.143 | G79: 0.974 | H79: defensives | I79: =VLOOKUP(A79,Setores!$A$2:$C$215,2,0) -> healthcare | J79: =VLOOKUP(A79,Setores!$A$2:$C$215,3,0) -> low_beta | K79: 0 | L79: 0 | M79: =VLOOKUP(A79,'Mandato Ibov'!$B$1:$C$215,2,0) -> 0 | N79: =K79-M79 -> 0 | O79: =B79-M79 -> 0 | P79: =VLOOKUP(A79,'Mandato Ibov'!$B$2:$D$215,3,0) -> 0 | Q79: =K79-P79 -> 0 | R79: -0.181 | S79: -0.037 | T79: -0.18 | U79: -0.503 | V79: -0.354 | W79: -0.182 | X79: -0.112 | Y79: -0.283 | Z79: 0.145 | AA79: 0.143 | AB79: 0.698 | AC79: 0.596 | AD79: 0.701 | AE79: -0.399 | AF79: -0.867 | AG79: -0.257 | AH79: -0.327 | AI79: 0.317 | AJ79: -0.175 | AK79: -0.218 | AL79: -0.33 | AM79: -0.469 | AN79: 0.254 | AO79: 0.185 | AP79: 0.329 | AQ79: -0.265 | AR79: -0.328 | AS79: -0.302 | AT79: 0.061 | AU79: -0.143 | AV79: 0.035 | AW79: 0.288 | AX79: 0.254 | AY79: 0.817 | AZ79: 0.78 | BA79: 0.603 | BB79: -0.074 | BC79: -0.171 | BD79: 0.213 | BE79: -0.333 | BF79: 0.5 | BG79: 0.486 | BH79: 0.266 | BI79: -0.153 | BJ79: 0.707 | BK79: 0.35 | BM79: =10%*AK79+5%*AL79+2.5%*AM79+2.5%*AN79+10%*AO79+10%*AP79+10%*AQ79+5%*AR79+5%*AS79+10%*AT79+5%*AU79+5%*AY79+10%*AV79+10%*AW79 -> 0.021825
A80: USIM3 | B80: =K80 -> 0 | C80: =B80-E80 -> 0 | D80: =B80-K80 -> 0 | E80: =K80-L80 -> 0 | F80: 1.128 | G80: 0.851 | H80: commodities | I80: =VLOOKUP(A80,Setores!$A$2:$C$215,2,0) -> basic_materials | J80: =VLOOKUP(A80,Setores!$A$2:$C$215,3,0) -> neutral_beta | K80: 0 | L80: 0 | M80: =VLOOKUP(A80,'Mandato Ibov'!$B$1:$C$215,2,0) -> 0 | N80: =K80-M80 -> 0 | O80: =B80-M80 -> 0 | P80: =VLOOKUP(A80,'Mandato Ibov'!$B$2:$D$215,3,0) -> 0 | Q80: =K80-P80 -> 0 | R80: -0.364 | S80: 0.245 | T80: -0.636 | U80: -0.31 | V80: -0.181 | W80: -0.644 | X80: -0.824 | Y80: -0.138 | Z80: 0.483 | AA80: 0.484 | AB80: 0.611 | AC80: 0.572 | AD80: 0.879 | AE80: -0.205 | AF80: -0.491 | AG80: 0.98 | AH80: -0.731 | AI80: -0.23 | AJ80: -0.921 | AK80: -0.254 | AL80: -0.675 | AM80: 0.224 | AN80: -0.46 | AO80: 0.668 | AP80: 0.626 | AQ80: -0.535 | AR80: 1 | AS80: 0.155 | AT80: -0.118 | AU80: -0.8 | AV80: 0.067 | AW80: -0.134 | AX80: 0.124 | AY80: 0.622 | AZ80: -1 | BA80: 0.743 | BB80: 0.506 | BC80: 0.266 | BD80: 0.773 | BE80: -1 | BF80: 0.62 | BG80: -0.426 | BH80: 0.003 | BI80: -0.324 | BJ80: 0.835 | BK80: -0.009 | BM80: =10%*AK80+5%*AL80+2.5%*AM80+2.5%*AN80+10%*AO80+10%*AP80+10%*AQ80+5%*AR80+5%*AS80+10%*AT80+5%*AU80+5%*AY80+10%*AV80+10%*AW80 -> 0.0412
A81: EVEN3 | B81: =K81 -> 0 | C81: =B81-E81 -> 0 | D81: =B81-K81 -> 0 | E81: =K81-L81 -> 0 | F81: 1.111 | G81: 1.143 | H81: pro_cyclicals | I81: =VLOOKUP(A81,Setores!$A$2:$C$215,2,0) -> homebuilders | J81: =VLOOKUP(A81,Setores!$A$2:$C$215,3,0) -> neutral_beta | K81: 0 | L81: 0 | M81: =VLOOKUP(A81,'Mandato Ibov'!$B$1:$C$215,2,0) -> 0 | N81: =K81-M81 -> 0 | O81: =B81-M81 -> 0 | P81: =VLOOKUP(A81,'Mandato Ibov'!$B$2:$D$215,3,0) -> 0 | Q81: =K81-P81 -> 0 | R81: -0.171 | S81: -0.589 | T81: 0.269 | U81: -0.239 | V81: -0.151 | W81: -0.031 | X81: 0.072 | Y81: -0.368 | Z81: 0.178 | AA81: 0.177 | AB81: 0.531 | AC81: 0.617 | AD81: 0.551 | AE81: 0.326 | AF81: 0.53 | AG81: -0.658 | AH81: 0.604 | AI81: -0.376 | AJ81: 0.159 | AK81: -0.223 | AL81: 0.378 | AM81: 0.091 | AN81: 0.157 | AO81: -0.753 | AP81: -0.845 | AQ81: 0.387 | AR81: -0.063 | AS81: -0.158 | AT81: -0.144 | AU81: -0.458 | AV81: 0.056 | AW81: 0.066 | AX81: -0.002 | AY81: 0.64 | AZ81: 0.325 | BA81: 0.1 | BB81: -0.099 | BC81: -0.442 | BD81: 0.073 | BE81: 0.606 | BF81: 0.3 | BG81: 0.861 | BH81: -0.267 | BI81: 0.187 | BJ81: 0.534 | BK81: 0.493 | BM81: =10%*AK81+5%*AL81+2.5%*AM81+2.5%*AN81+10%*AO81+10%*AP81+10%*AQ81+5%*AR81+5%*AS81+10%*AT81+5%*AU81+5%*AY81+10%*AV81+10%*AW81 -> -0.12245
A82: VVEO3 | B82: =K82 -> 0 | C82: =B82-E82 -> 0 | D82: =B82-K82 -> 0 | E82: =K82-L82 -> 0 | F82: 1.097 | G82: 0.768 | H82: defensives | I82: =VLOOKUP(A82,Setores!$A$2:$C$215,2,0) -> healthcare | J82: =VLOOKUP(A82,Setores!$A$2:$C$215,3,0) -> very_high_beta | K82: 0 | L82: 0 | M82: =VLOOKUP(A82,'Mandato Ibov'!$B$1:$C$215,2,0) -> 0 | N82: =K82-M82 -> 0 | O82: =B82-M82 -> 0 | P82: =VLOOKUP(A82,'Mandato Ibov'!$B$2:$D$215,3,0) -> 0 | Q82: =K82-P82 -> 0 | R82: 0.387 | S82: 0.828 | T82: 0.56 | U82: 0.091 | V82: 0.565 | W82: -0.571 | X82: -0.79 | Y82: -0.503 | Z82: -0.149 | AA82: -0.148 | AB82: 0.324 | AC82: 0.425 | AD82: 0.312 | AE82: 0.437 | AF82: 0.64 | AG82: 0.764 | AH82: 1 | AI82: 0.658 | AJ82: -0.524 | AK82: 0.674 | AL82: -0.891 | AM82: 0.802 | AN82: 0.217 | AO82: -0.228 | AP82: 0.249 | AQ82: -0.304 | AR82: 0.265 | AS82: 0.052 | AT82: 0.007 | AU82: -0.62 | AV82: -0.01 | AW82: -0.558 | AX82: -0.612 | AY82: -0.336 | AZ82: -0.513 | BA82: 0.984 | BB82: 0.104 | BC82: -0.003 | BD82: 0.323 | BE82: 0.547 | BF82: 0.515 | BG82: -0.639 | BH82: 1 | BI82: 0.386 | BJ82: 0.595 | BK82: 0.994 | BM82: =10%*AK82+5%*AL82+2.5%*AM82+2.5%*AN82+10%*AO82+10%*AP82+10%*AQ82+5%*AR82+5%*AS82+10%*AT82+5%*AU82+5%*AY82+10%*AV82+10%*AW82 -> -0.068025
A83: MYPK3 | B83: =K83 -> 0 | C83: =B83-E83 -> 0 | D83: =B83-K83 -> 0 | E83: =K83-L83 -> 0 | F83: 1.093 | G83: 1.172 | H83: industrials | I83: =VLOOKUP(A83,Setores!$A$2:$C$215,2,0) -> capital_goods | J83: =VLOOKUP(A83,Setores!$A$2:$C$215,3,0) -> neutral_beta | K83: 0 | L83: 0 | M83: =VLOOKUP(A83,'Mandato Ibov'!$B$1:$C$215,2,0) -> 0 | N83: =K83-M83 -> 0 | O83: =B83-M83 -> 0 | P83: =VLOOKUP(A83,'Mandato Ibov'!$B$2:$D$215,3,0) -> 0 | Q83: =K83-P83 -> 0 | R83: -0.071 | S83: -0.002 | T83: -0.056 | U83: -0.33 | V83: -0.218 | W83: -0.259 | X83: -0.407 | Y83: -0.605 | Z83: 0.532 | AA83: 0.529 | AB83: 0.62 | AC83: 0.709 | AD83: 0.706 | AE83: -0.228 | AF83: 0.004 | AG83: -0.16 | AH83: 0.548 | AI83: -0.37 | AJ83: -0.531 | AK83: 0.314 | AL83: -0.465 | AM83: 0.717 | AN83: -0.257 | AO83: -0.433 | AP83: -0.175 | AQ83: 0.058 | AR83: 0.314 | AS83: 0.069 | AT83: 0.009 | AU83: -0.543 | AV83: -0.217 | AW83: 0.54 | AX83: -0.211 | AY83: 0.928 | AZ83: 1 | BA83: 0.048 | BB83: 0.224 | BC83: 0.138 | BD83: 0.295 | BE83: -0.288 | BF83: -0.224 | BG83: 0.383 | BH83: -0.043 | BI83: 0.24 | BJ83: 0.061 | BK83: 0.454 | BM83: =10%*AK83+5%*AL83+2.5%*AM83+2.5%*AN83+10%*AO83+10%*AP83+10%*AQ83+5%*AR83+5%*AS83+10%*AT83+5%*AU83+5%*AY83+10%*AV83+10%*AW83 -> 0.03625
A84: FLRY3 | B84: =K84 -> 0 | C84: =B84-E84 -> -0.003 | D84: =B84-K84 -> 0 | E84: =K84-L84 -> 0.003 | F84: 1.08 | G84: 1.333 | H84: defensives | I84: =VLOOKUP(A84,Setores!$A$2:$C$215,2,0) -> healthcare | J84: =VLOOKUP(A84,Setores!$A$2:$C$215,3,0) -> low_beta | K84: 0 | L84: -0.003 | M84: =VLOOKUP(A84,'Mandato Ibov'!$B$1:$C$215,2,0) -> 0 | N84: =K84-M84 -> 0 | O84: =B84-M84 -> 0 | P84: =VLOOKUP(A84,'Mandato Ibov'!$B$2:$D$215,3,0) -> 0.0067214707 | Q84: =K84-P84 -> -0.0067214707 | R84: -0.395 | S84: -0.47 | T84: -0.7 | U84: -0.315 | V84: -0.575 | W84: -0.086 | X84: 0.132 | Y84: -0.22 | Z84: 0.327 | AA84: 0.325 | AB84: 0.817 | AC84: 0.825 | AD84: 0.622 | AE84: -0.264 | AF84: -0.392 | AG84: -0.313 | AH84: -0.652 | AI84: -0.328 | AJ84: -0.788 | AK84: 0.016 | AL84: -0.084 | AM84: -0.64 | AN84: 0.221 | AO84: 0.064 | AP84: -0.102 | AQ84: 0.058 | AR84: 0.332 | AS84: 0.119 | AT84: 0.217 | AU84: -0.292 | AV84: 0.071 | AW84: 0.457 | AX84: -0.158 | AY84: 0.926 | AZ84: 0.508 | BA84: -0.009 | BB84: -0.118 | BC84: -0.026 | BD84: 0.488 | BE84: -0.183 | BF84: 0.096 | BG84: 0.71 | BH84: -0.123 | BI84: -0.183 | BJ84: 0.046 | BK84: -0.145 | BM84: =10%*AK84+5%*AL84+2.5%*AM84+2.5%*AN84+10%*AO84+10%*AP84+10%*AQ84+5%*AR84+5%*AS84+10%*AT84+5%*AU84+5%*AY84+10%*AV84+10%*AW84 -> 0.117675
A85: PGMN3 | B85: =K85 -> 0 | C85: =B85-E85 -> 0 | D85: =B85-K85 -> 0 | E85: =K85-L85 -> 0 | F85: 1.08 | G85: 0.884 | H85: defensives | I85: =VLOOKUP(A85,Setores!$A$2:$C$215,2,0) -> healthcare | J85: =VLOOKUP(A85,Setores!$A$2:$C$215,3,0) -> high_beta | K85: 0 | L85: 0 | M85: =VLOOKUP(A85,'Mandato Ibov'!$B$1:$C$215,2,0) -> 0 | N85: =K85-M85 -> 0 | O85: =B85-M85 -> 0 | P85: =VLOOKUP(A85,'Mandato Ibov'!$B$2:$D$215,3,0) -> 0 | Q85: =K85-P85 -> 0 | R85: -0.275 | S85: -0.478 | T85: -0.474 | U85: -0.259 | V85: -0.465 | W85: -0.134 | X85: -0.01 | Y85: -0.299 | Z85: 0.304 | AA85: 0.298 | AB85: 0.748 | AC85: 0.776 | AD85: 0.634 | AE85: -0.148 | AF85: -0.207 | AG85: -0.458 | AH85: -0.519 | AI85: 0.046 | AJ85: -0.397 | AK85: -0.187 | AL85: -0.057 | AM85: -0.419 | AN85: -0.113 | AO85: -0.016 | AP85: -0.991 | AQ85: 0.239 | AR85: 1 | AS85: 0.384 | AT85: 0.304 | AU85: -0.46 | AV85: 0.364 | AW85: -0.14 | AX85: -0.15 | AY85: 0.88 | AZ85: 0.442 | BA85: 0.739 | BB85: -0.388 | BC85: -0.435 | BD85: 0.507 | BE85: 0.367 | BF85: 0.198 | BG85: 0.717 | BH85: -0.334 | BI85: 0.142 | BJ85: -0.105 | BK85: 0.206 | BM85: =10%*AK85+5%*AL85+2.5%*AM85+2.5%*AN85+10%*AO85+10%*AP85+10%*AQ85+5%*AR85+5%*AS85+10%*AT85+5%*AU85+5%*AY85+10%*AV85+10%*AW85 -> 0.03135
A86: AUAU3 | B86: =K86 -> 0 | C86: =B86-E86 -> 0 | D86: =B86-K86 -> 0 | E86: =K86-L86 -> 0 | F86: 1.072 | G86: 0.812 | H86: pro_cyclicals | I86: =VLOOKUP(A86,Setores!$A$2:$C$215,2,0) -> consumer_durables | J86: =VLOOKUP(A86,Setores!$A$2:$C$215,3,0) -> high_beta | K86: 0 | L86: 0 | M86: =VLOOKUP(A86,'Mandato Ibov'!$B$1:$C$215,2,0) -> 0 | N86: =K86-M86 -> 0 | O86: =B86-M86 -> 0 | P86: =VLOOKUP(A86,'Mandato Ibov'!$B$2:$D$215,3,0) -> 0 | Q86: =K86-P86 -> 0 | R86: 0.032 | S86: 0.45 | T86: -0.041 | U86: -0.27 | V86: -0.048 | W86: -0.403 | X86: -0.602 | Y86: -0.501 | Z86: -0.103 | AA86: -0.102 | AB86: 0.731 | AC86: 0.81 | AD86: 0.699 | AE86: -0.931 | AF86: 0.2 | AG86: 0.842 | AH86: -0.481 | AI86: 1 | AJ86: 0.389 | AK86: -0.175 | AL86: -0.851 | AM86: -0.465 | AN86: 0.201 | AO86: -0.005 | AP86: 0.932 | AQ86: 0.326 | AR86: 0.448 | AS86: 0.286 | AT86: 0.275 | AU86: -0.308 | AV86: -0.157 | AW86: -0.399 | AX86: 0.21 | AY86: -0.344 | AZ86: 0.045 | BA86: -0.028 | BB86: 0.171 | BC86: 0.518 | BD86: -0.883 | BE86: -0.246 | BF86: 0.293 | BG86: 0.293 | BH86: 0.288 | BI86: -0.025 | BJ86: 0.25 | BK86: -0.054 | BM86: =10%*AK86+5%*AL86+2.5%*AM86+2.5%*AN86+10%*AO86+10%*AP86+10%*AQ86+5%*AR86+5%*AS86+10%*AT86+5%*AU86+5%*AY86+10%*AV86+10%*AW86 -> 0.03465
A87: MULT3 | B87: =K87 -> 0 | C87: =B87-E87 -> -0.004 | D87: =B87-K87 -> 0 | E87: =K87-L87 -> 0.004 | F87: 1.052 | G87: 1.633 | H87: bond_proxies | I87: =VLOOKUP(A87,Setores!$A$2:$C$215,2,0) -> real_estate | J87: =VLOOKUP(A87,Setores!$A$2:$C$215,3,0) -> high_beta | K87: 0 | L87: -0.004 | M87: =VLOOKUP(A87,'Mandato Ibov'!$B$1:$C$215,2,0) -> 0 | N87: =K87-M87 -> 0 | O87: =B87-M87 -> 0 | P87: =VLOOKUP(A87,'Mandato Ibov'!$B$2:$D$215,3,0) -> 0 | Q87: =K87-P87 -> 0 | R87: -0.346 | S87: -0.485 | T87: -0.774 | U87: -0.295 | V87: -0.656 | W87: 0.133 | X87: 0.676 | Y87: -0.388 | Z87: 0.298 | AA87: 0.299 | AB87: 0.7 | AC87: 0.722 | AD87: 0.551 | AE87: -0.241 | AF87: -0.559 | AG87: -0.523 | AH87: -0.863 | AI87: -0.564 | AJ87: -0.585 | AK87: -0.289 | AL87: -0.393 | AM87: -0.771 | AN87: 0.213 | AO87: -0.009 | AP87: 0.101 | AQ87: 0.047 | AR87: 0.393 | AS87: 0.333 | AT87: 0.431 | AU87: 0.901 | AV87: 0.351 | AW87: 0.304 | AX87: -0.584 | AY87: 0.807 | AZ87: 0.297 | BA87: -0.099 | BB87: -0.42 | BC87: 0.41 | BD87: 0.352 | BE87: -0.028 | BF87: -0.031 | BG87: 0.704 | BH87: -0.36 | BI87: 0.547 | BJ87: -0.266 | BK87: -0.42 | BM87: =10%*AK87+5%*AL87+2.5%*AM87+2.5%*AN87+10%*AO87+10%*AP87+10%*AQ87+5%*AR87+5%*AS87+10%*AT87+5%*AU87+5%*AY87+10%*AV87+10%*AW87 -> 0.1817
A88: ANIM3 | B88: =K88 -> 0 | C88: =B88-E88 -> 0 | D88: =B88-K88 -> 0 | E88: =K88-L88 -> 0 | F88: 1.046 | G88: 0.762 | H88: pro_cyclicals | I88: =VLOOKUP(A88,Setores!$A$2:$C$215,2,0) -> education | J88: =VLOOKUP(A88,Setores!$A$2:$C$215,3,0) -> very_high_beta | K88: 0 | L88: 0 | M88: =VLOOKUP(A88,'Mandato Ibov'!$B$1:$C$215,2,0) -> 0 | N88: =K88-M88 -> 0 | O88: =B88-M88 -> 0 | P88: =VLOOKUP(A88,'Mandato Ibov'!$B$2:$D$215,3,0) -> 0.0074640141 | Q88: =K88-P88 -> -0.0074640141 | R88: 0.083 | S88: 0.162 | T88: 0.125 | U88: 0.025 | V88: 0.145 | W88: -0.272 | X88: -0.39 | Y88: -0.558 | Z88: -0.054 | AA88: -0.053 | AB88: 0.569 | AC88: 0.556 | AD88: 0.539 | AE88: 0.183 | AF88: 0.939 | AG88: 0.125 | AH88: 0.389 | AI88: -0.113 | AJ88: 0.671 | AK88: 0.143 | AL88: -0.753 | AM88: 0.249 | AN88: 0.147 | AO88: -0.198 | AP88: -0.436 | AQ88: 0.564 | AR88: 0.231 | AS88: 0.188 | AT88: 0.078 | AU88: 0.126 | AV88: 0.234 | AW88: -0.885 | AX88: -0.474 | AY88: 0.643 | AZ88: 0.173 | BA88: 0.533 | BB88: 0.159 | BC88: -0.219 | BD88: 0.204 | BE88: 0.469 | BF88: 0.315 | BG88: 0.276 | BH88: -0.153 | BI88: 0.507 | BJ88: -0.594 | BK88: 0.653 | BM88: =10%*AK88+5%*AL88+2.5%*AM88+2.5%*AN88+10%*AO88+10%*AP88+10%*AQ88+5%*AR88+5%*AS88+10%*AT88+5%*AU88+5%*AY88+10%*AV88+10%*AW88 -> -0.01835
A89: TAEE4 | B89: 0.005 | C89: =B89-E89 -> 0.005 | D89: =B89-K89 -> 0.005 | E89: =K89-L89 -> 0 | F89: 1.043 | G89: 1.408 | H89: bond_proxies | I89: =VLOOKUP(A89,Setores!$A$2:$C$215,2,0) -> utilities | J89: =VLOOKUP(A89,Setores!$A$2:$C$215,3,0) -> low_beta | K89: 0 | L89: 0 | M89: =VLOOKUP(A89,'Mandato Ibov'!$B$1:$C$215,2,0) -> 0 | N89: =K89-M89 -> 0 | O89: =B89-M89 -> 0.005 | P89: =VLOOKUP(A89,'Mandato Ibov'!$B$2:$D$215,3,0) -> 0 | Q89: =K89-P89 -> 0 | R89: -0.55 | S89: -0.739 | T89: -0.716 | U89: -0.421 | V89: -0.692 | W89: 0.092 | X89: 0.719 | Y89: -0.288 | Z89: 0.484 | AA89: 0.482 | AB89: 0.634 | AC89: 0.721 | AD89: 0.592 | AE89: -0.27 | AF89: -0.532 | AG89: -0.668 | AH89: -0.763 | AI89: -0.676 | AJ89: -0.881 | AK89: -0.182 | AL89: 0.187 | AM89: -0.599 | AN89: -0.217 | AO89: -0.27 | AP89: 0.006 | AQ89: -0.136 | AR89: 0.176 | AS89: 0.124 | AT89: 0.113 | AU89: 0.537 | AV89: 0.022 | AW89: 0.893 | AX89: -0.845 | AY89: 0.438 | AZ89: -0.065 | BA89: 0.885 | BB89: -0.164 | BC89: -0.368 | BD89: 0.364 | BE89: -0.166 | BF89: 0.116 | BG89: 0.839 | BH89: -0.379 | BI89: -0.301 | BJ89: 0.931 | BK89: 0.054 | BM89: =10%*AK89+5%*AL89+2.5%*AM89+2.5%*AN89+10%*AO89+10%*AP89+10%*AQ89+5%*AR89+5%*AS89+10%*AT89+5%*AU89+5%*AY89+10%*AV89+10%*AW89 -> 0.0973
A90: TGMA3 | B90: =K90 -> 0 | C90: =B90-E90 -> 0 | D90: =B90-K90 -> 0 | E90: =K90-L90 -> 0 | F90: 1.041 | G90: 1.149 | H90: pro_cyclicals | I90: =VLOOKUP(A90,Setores!$A$2:$C$215,2,0) -> transportation | J90: =VLOOKUP(A90,Setores!$A$2:$C$215,3,0) -> neutral_beta | K90: 0 | L90: 0 | M90: =VLOOKUP(A90,'Mandato Ibov'!$B$1:$C$215,2,0) -> 0 | N90: =K90-M90 -> 0 | O90: =B90-M90 -> 0 | P90: =VLOOKUP(A90,'Mandato Ibov'!$B$2:$D$215,3,0) -> 0 | Q90: =K90-P90 -> 0 | R90: -0.239 | S90: -0.787 | T90: -0.003 | U90: -0.308 | V90: -0.464 | W90: 0.031 | X90: 0.3 | Y90: -0.354 | Z90: 0.214 | AA90: 0.218 | AB90: 0.582 | AC90: 0.543 | AD90: 0.534 | AE90: 0.029 | AF90: -0.278 | AG90: -1 | AH90: -0.113 | AI90: -0.517 | AJ90: 0.816 | AK90: -0.219 | AL90: 0.351 | AM90: -0.862 | AN90: 0.241 | AO90: -0.551 | AP90: -0.677 | AQ90: 0.104 | AR90: 0.194 | AS90: -0.318 | AT90: 0.817 | AU90: -0.28 | AV90: 0.176 | AW90: 0.378 | AX90: 0.214 | AY90: 0.851 | AZ90: 0.318 | BA90: 0.421 | BB90: -0.131 | BC90: -0.362 | BD90: 0.347 | BE90: -0.239 | BF90: -0.274 | BG90: 0.75 | BH90: -0.596 | BI90: 0.243 | BJ90: 0.368 | BK90: 0.588 | BM90: =10%*AK90+5%*AL90+2.5%*AM90+2.5%*AN90+10%*AO90+10%*AP90+10%*AQ90+5%*AR90+5%*AS90+10%*AT90+5%*AU90+5%*AY90+10%*AV90+10%*AW90 -> 0.027175
A91: MDIA3 | B91: =K91 -> 0 | C91: =B91-E91 -> 0 | D91: =B91-K91 -> 0 | E91: =K91-L91 -> 0 | F91: 1 | G91: 0.817 | H91: defensives | I91: =VLOOKUP(A91,Setores!$A$2:$C$215,2,0) -> consumer_staples | J91: =VLOOKUP(A91,Setores!$A$2:$C$215,3,0) -> low_beta | K91: 0 | L91: 0 | M91: =VLOOKUP(A91,'Mandato Ibov'!$B$1:$C$215,2,0) -> 0 | N91: =K91-M91 -> 0 | O91: =B91-M91 -> 0 | P91: =VLOOKUP(A91,'Mandato Ibov'!$B$2:$D$215,3,0) -> 0 | Q91: =K91-P91 -> 0 | R91: 0.031 | S91: -0.484 | T91: -0.096 | U91: -0.123 | V91: -0.384 | W91: -0.046 | X91: -0.115 | Y91: -0.617 | Z91: 0.205 | AA91: 0.203 | AB91: 0.652 | AC91: 0.561 | AD91: 0.591 | AE91: 0.331 | AF91: 0.04 | AG91: -0.855 | AH91: -0.584 | AI91: -0.803 | AJ91: 0.03 | AK91: -0.058 | AL91: -0.508 | AM91: -0.123 | AN91: 0.42 | AO91: -0.538 | AP91: -0.3 | AQ91: 0.385 | AR91: 0.519 | AS91: 0.181 | AT91: 0.132 | AU91: -0.357 | AV91: 0.557 | AW91: 0.544 | AX91: 0.262 | AY91: 0.877 | AZ91: 1 | BA91: 0.644 | BB91: 0.091 | BC91: -0.006 | BD91: 0.515 | BE91: 0.079 | BF91: 1 | BG91: 0.111 | BH91: -0.032 | BI91: -0.247 | BJ91: 0.526 | BK91: 0.073 | BM91: =10%*AK91+5%*AL91+2.5%*AM91+2.5%*AN91+10%*AO91+10%*AP91+10%*AQ91+5%*AR91+5%*AS91+10%*AT91+5%*AU91+5%*AY91+10%*AV91+10%*AW91 -> 0.115225
A92: TAEE3 | B92: =K92 -> 0 | C92: =B92-E92 -> 0 | D92: =B92-K92 -> 0 | E92: =K92-L92 -> 0 | F92: 0.986 | G92: 1.313 | H92: bond_proxies | I92: =VLOOKUP(A92,Setores!$A$2:$C$215,2,0) -> utilities | J92: =VLOOKUP(A92,Setores!$A$2:$C$215,3,0) -> very_low_beta | K92: 0 | L92: 0 | M92: =VLOOKUP(A92,'Mandato Ibov'!$B$1:$C$215,2,0) -> 0 | N92: =K92-M92 -> 0 | O92: =B92-M92 -> 0 | P92: =VLOOKUP(A92,'Mandato Ibov'!$B$2:$D$215,3,0) -> 0 | Q92: =K92-P92 -> 0 | R92: -0.621 | S92: -0.764 | T92: -0.725 | U92: -0.453 | V92: -0.707 | W92: 0.04 | X92: 0.673 | Y92: -0.308 | Z92: 0.571 | AA92: 0.569 | AB92: 0.615 | AC92: 0.72 | AD92: 0.579 | AE92: -0.265 | AF92: -0.528 | AG92: -0.706 | AH92: -0.761 | AI92: -0.709 | AJ92: -0.881 | AK92: -0.182 | AL92: 0.194 | AM92: -0.599 | AN92: -0.213 | AO92: -0.29 | AP92: 0.014 | AQ92: -0.136 | AR92: 0.176 | AS92: 0.124 | AT92: 0.113 | AU92: 0.537 | AV92: 0.022 | AW92: 0.9 | AX92: -0.845 | AY92: 0.438 | AZ92: 0.038 | BA92: 0.229 | BB92: -0.164 | BC92: -0.368 | BD92: 0.359 | BE92: -0.192 | BF92: 0.041 | BG92: 0.866 | BH92: -0.364 | BI92: -0.346 | BJ92: 1 | BK92: 0.054 | BM92: =10%*AK92+5%*AL92+2.5%*AM92+2.5%*AN92+10%*AO92+10%*AP92+10%*AQ92+5%*AR92+5%*AS92+10%*AT92+5%*AU92+5%*AY92+10%*AV92+10%*AW92 -> 0.09725
A93: CPLE3 | B93: 0.007 | C93: =B93-E93 -> -0.011 | D93: =B93-K93 -> 0.007 | E93: =K93-L93 -> 0.018 | F93: 0.973 | G93: 2.06 | H93: bond_proxies | I93: =VLOOKUP(A93,Setores!$A$2:$C$215,2,0) -> utilities | J93: =VLOOKUP(A93,Setores!$A$2:$C$215,3,0) -> neutral_beta | K93: 0 | L93: -0.018 | M93: =VLOOKUP(A93,'Mandato Ibov'!$B$1:$C$215,2,0) -> 0 | N93: =K93-M93 -> 0 | O93: =B93-M93 -> 0.007 | P93: =VLOOKUP(A93,'Mandato Ibov'!$B$2:$D$215,3,0) -> 0.034397875 | Q93: =K93-P93 -> -0.034397875 | R93: -0.606 | S93: -0.515 | T93: -0.922 | U93: -0.451 | V93: -0.759 | W93: -0.071 | X93: 0.089 | Y93: -0.138 | Z93: 0.335 | AA93: 0.337 | AB93: 0.741 | AC93: 0.796 | AD93: 0.672 | AE93: -0.766 | AF93: -0.47 | AG93: 0.065 | AH93: -0.946 | AI93: -0.435 | AJ93: -0.939 | AK93: -0.345 | AL93: -0.23 | AM93: -0.659 | AN93: -0.554 | AO93: 0.403 | AP93: 0.824 | AQ93: 0.254 | AR93: 0.301 | AS93: 0.454 | AT93: 0.004 | AU93: -0.294 | AV93: -0.279 | AW93: 0.662 | AX93: -0.538 | AY93: 0.946 | AZ93: 1 | BA93: 0.565 | BB93: 0.152 | BC93: -0.38 | BD93: 0.383 | BE93: -0.235 | BF93: -0.181 | BG93: 0.8 | BH93: -0.89 | BI93: -0.117 | BJ93: -0.37 | BK93: -0.451 | BM93: =10%*AK93+5%*AL93+2.5%*AM93+2.5%*AN93+10%*AO93+10%*AP93+10%*AQ93+5%*AR93+5%*AS93+10%*AT93+5%*AU93+5%*AY93+10%*AV93+10%*AW93 -> 0.180825
A94: CMIG4 | B94: =K94 -> 0 | C94: =B94-E94 -> -0.009 | D94: =B94-K94 -> 0 | E94: =K94-L94 -> 0.009 | F94: 0.97 | G94: 1.722 | H94: bond_proxies | I94: =VLOOKUP(A94,Setores!$A$2:$C$215,2,0) -> utilities | J94: =VLOOKUP(A94,Setores!$A$2:$C$215,3,0) -> low_beta | K94: 0 | L94: -0.009 | M94: =VLOOKUP(A94,'Mandato Ibov'!$B$1:$C$215,2,0) -> 0 | N94: =K94-M94 -> 0 | O94: =B94-M94 -> 0 | P94: =VLOOKUP(A94,'Mandato Ibov'!$B$2:$D$215,3,0) -> 0.016401025 | Q94: =K94-P94 -> -0.016401025 | R94: -0.82 | S94: -0.673 | T94: -0.93 | U94: -0.627 | V94: -0.75 | W94: -0.24 | X94: 0.124 | Y94: 0.132 | Z94: 0.549 | AA94: 0.552 | AB94: 0.649 | AC94: 0.655 | AD94: 0.586 | AE94: -0.775 | AF94: -0.689 | AG94: 0.202 | AH94: -0.878 | AI94: -0.496 | AJ94: -0.966 | AK94: -0.324 | AL94: 0.565 | AM94: -0.522 | AN94: -0.55 | AO94: 0.277 | AP94: 0.559 | AQ94: -0.238 | AR94: 0.187 | AS94: -0.246 | AT94: 0.2 | AU94: -0.331 | AV94: -0.558 | AW94: 0.553 | AX94: -0.597 | AY94: 0.853 | AZ94: 0.41 | BA94: -0.406 | BB94: -0.432 | BC94: -0.665 | BD94: 0.222 | BE94: 0.086 | BF94: 0.25 | BG94: 0.983 | BH94: -0.654 | BI94: -0.293 | BJ94: -0.114 | BK94: -0.378 | BM94: =10%*AK94+5%*AL94+2.5%*AM94+2.5%*AN94+10%*AO94+10%*AP94+10%*AQ94+5%*AR94+5%*AS94+10%*AT94+5%*AU94+5%*AY94+10%*AV94+10%*AW94 -> 0.0715
A95: LAVV3 | B95: =K95 -> 0 | C95: =B95-E95 -> 0 | D95: =B95-K95 -> 0 | E95: =K95-L95 -> 0 | F95: 0.928 | G95: 1.059 | H95: pro_cyclicals | I95: =VLOOKUP(A95,Setores!$A$2:$C$215,2,0) -> homebuilders | J95: =VLOOKUP(A95,Setores!$A$2:$C$215,3,0) -> high_beta | K95: 0 | L95: 0 | M95: =VLOOKUP(A95,'Mandato Ibov'!$B$1:$C$215,2,0) -> 0 | N95: =K95-M95 -> 0 | O95: =B95-M95 -> 0 | P95: =VLOOKUP(A95,'Mandato Ibov'!$B$2:$D$215,3,0) -> 0 | Q95: =K95-P95 -> 0 | R95: -0.434 | S95: -0.756 | T95: -0.139 | U95: -0.522 | V95: -0.517 | W95: -0.113 | X95: 0.148 | Y95: -0.216 | Z95: 0.121 | AA95: 0.118 | AB95: 0.434 | AC95: 0.666 | AD95: 0.561 | AE95: -0.46 | AF95: 0.246 | AG95: -0.54 | AH95: 0.009 | AI95: 0.202 | AJ95: -0.224 | AK95: -0.246 | AL95: 0.646 | AM95: -0.561 | AN95: 0.295 | AO95: -0.465 | AP95: -0.906 | AQ95: 0.256 | AR95: 0.097 | AS95: -0.482 | AT95: 0.089 | AU95: -0.15 | AV95: -0.541 | AW95: 0.167 | AX95: 0.188 | AY95: 0.434 | AZ95: 0.639 | BA95: 0.413 | BB95: -0.421 | BC95: -0.34 | BD95: -0.531 | BE95: 0.765 | BF95: 0.259 | BG95: 0.733 | BH95: -0.817 | BI95: 0.544 | BJ95: 0.436 | BK95: 0.208 | BM95: =10%*AK95+5%*AL95+2.5%*AM95+2.5%*AN95+10%*AO95+10%*AP95+10%*AQ95+5%*AR95+5%*AS95+10%*AT95+5%*AU95+5%*AY95+10%*AV95+10%*AW95 -> -0.144
A96: HYPE3 | B96: =K96 -> 0 | C96: =B96-E96 -> -0.003 | D96: =B96-K96 -> 0 | E96: =K96-L96 -> 0.003 | F96: 0.908 | G96: 1.075 | H96: defensives | I96: =VLOOKUP(A96,Setores!$A$2:$C$215,2,0) -> healthcare | J96: =VLOOKUP(A96,Setores!$A$2:$C$215,3,0) -> very_low_beta | K96: 0 | L96: -0.003 | M96: =VLOOKUP(A96,'Mandato Ibov'!$B$1:$C$215,2,0) -> 0 | N96: =K96-M96 -> 0 | O96: =B96-M96 -> 0 | P96: =VLOOKUP(A96,'Mandato Ibov'!$B$2:$D$215,3,0) -> 0 | Q96: =K96-P96 -> 0 | R96: -0.221 | S96: -0.453 | T96: -0.721 | U96: -0.25 | V96: -0.635 | W96: 0.002 | X96: 0.299 | Y96: -0.522 | Z96: 0.137 | AA96: 0.138 | AB96: 0.626 | AC96: 0.722 | AD96: 0.564 | AE96: 0.023 | AF96: -0.381 | AG96: -0.649 | AH96: -0.83 | AI96: -0.77 | AJ96: -0.784 | AK96: -0.177 | AL96: -0.351 | AM96: -0.514 | AN96: 0.28 | AO96: -0.379 | AP96: 0.239 | AQ96: -0.001 | AR96: 1 | AS96: 0.755 | AT96: 0.095 | AU96: 0.26 | AV96: 0.46 | AW96: 0.441 | AX96: -0.367 | AY96: 0.815 | AZ96: 0.536 | BA96: 0.925 | BB96: -0.127 | BC96: -0.299 | BD96: 0.397 | BE96: -0.761 | BF96: -0.167 | BG96: 0.459 | BH96: 0.109 | BI96: -0.377 | BJ96: 0.008 | BK96: -0.39 | BM96: =10%*AK96+5%*AL96+2.5%*AM96+2.5%*AN96+10%*AO96+10%*AP96+10%*AQ96+5%*AR96+5%*AS96+10%*AT96+5%*AU96+5%*AY96+10%*AV96+10%*AW96 -> 0.1859
A97: AXIA3 | B97: =K97 -> 0 | C97: =B97-E97 -> -0.042 | D97: =B97-K97 -> 0 | E97: =K97-L97 -> 0.042 | F97: 0.892 | G97: 1.942 | H97: bond_proxies | I97: =VLOOKUP(A97,Setores!$A$2:$C$215,2,0) -> utilities | J97: =VLOOKUP(A97,Setores!$A$2:$C$215,3,0) -> high_beta | K97: 0 | L97: -0.042 | M97: =VLOOKUP(A97,'Mandato Ibov'!$B$1:$C$215,2,0) -> 0 | N97: =K97-M97 -> 0 | O97: =B97-M97 -> 0 | P97: =VLOOKUP(A97,'Mandato Ibov'!$B$2:$D$215,3,0) -> 0.038499621 | Q97: =K97-P97 -> -0.038499621 | R97: -0.523 | S97: -0.475 | T97: -0.906 | U97: -0.342 | V97: -0.722 | W97: -0.119 | X97: 0.109 | Y97: -0.381 | Z97: 0.331 | AA97: 0.333 | AB97: 0.78 | AC97: 0.929 | AD97: 0.636 | AE97: -0.46 | AF97: -0.252 | AG97: 0.014 | AH97: -1 | AI97: -0.692 | AJ97: -0.865 | AK97: -0.378 | AL97: -0.597 | AM97: -0.553 | AN97: -0.234 | AO97: 0.288 | AP97: 0.378 | AQ97: 0.469 | AR97: 1 | AS97: 0.65 | AT97: -0.216 | AU97: 0.002 | AV97: 0.145 | AW97: 0.252 | AX97: -0.582 | AY97: 0.639 | AZ97: 0.329 | BA97: 0.008 | BB97: -0.074 | BC97: -0.295 | BD97: 0.713 | BE97: 0.273 | BF97: 0.714 | BG97: 0.835 | BH97: -0.666 | BI97: 0.071 | BJ97: -0.26 | BK97: -1 | BM97: =10%*AK97+5%*AL97+2.5%*AM97+2.5%*AN97+10%*AO97+10%*AP97+10%*AQ97+5%*AR97+5%*AS97+10%*AT97+5%*AU97+5%*AY97+10%*AV97+10%*AW97 -> 0.158825
A98: CAML3 | B98: =K98 -> 0 | C98: =B98-E98 -> 0 | D98: =B98-K98 -> 0 | E98: =K98-L98 -> 0 | F98: 0.885 | G98: 0.801 | H98: defensives | I98: =VLOOKUP(A98,Setores!$A$2:$C$215,2,0) -> consumer_staples | J98: =VLOOKUP(A98,Setores!$A$2:$C$215,3,0) -> very_high_beta | K98: 0 | L98: 0 | M98: =VLOOKUP(A98,'Mandato Ibov'!$B$1:$C$215,2,0) -> 0 | N98: =K98-M98 -> 0 | O98: =B98-M98 -> 0 | P98: =VLOOKUP(A98,'Mandato Ibov'!$B$2:$D$215,3,0) -> 0 | Q98: =K98-P98 -> 0 | R98: -0.417 | S98: -0.189 | T98: -0.327 | U98: -0.588 | V98: -0.411 | W98: -0.492 | X98: -0.371 | Y98: -0.493 | Z98: 0.379 | AA98: 0.375 | AB98: 0.882 | AC98: 0.783 | AD98: 0.727 | AE98: -0.565 | AF98: -0.531 | AG98: 0.065 | AH98: -0.188 | AI98: 0.602 | AJ98: -0.603 | AK98: -0.144 | AL98: -0.359 | AM98: 0.136 | AN98: -0.169 | AO98: 0.023 | AP98: 0.193 | AQ98: -0.147 | AR98: -0.12 | AS98: -0.454 | AT98: 0.009 | AU98: -0.263 | AV98: -0.226 | AW98: 0.31 | AX98: -0.207 | AY98: 0.557 | AZ98: -0.122 | BA98: -0.241 | BB98: 0.205 | BC98: 0.076 | BD98: 0.437 | BE98: 0.372 | BF98: 0.795 | BG98: 0.439 | BH98: -0.084 | BI98: 0.382 | BJ98: 0.559 | BK98: 0.533 | BM98: =10%*AK98+5%*AL98+2.5%*AM98+2.5%*AN98+10%*AO98+10%*AP98+10%*AQ98+5%*AR98+5%*AS98+10%*AT98+5%*AU98+5%*AY98+10%*AV98+10%*AW98 -> -0.030975
A99: BBDC3 | B99: =K99 -> 0 | C99: =B99-E99 -> -0.009 | D99: =B99-K99 -> 0 | E99: =K99-L99 -> 0.009 | F99: 0.88 | G99: 1.62 | H99: pro_cyclicals | I99: =VLOOKUP(A99,Setores!$A$2:$C$215,2,0) -> banks | J99: =VLOOKUP(A99,Setores!$A$2:$C$215,3,0) -> neutral_beta | K99: 0 | L99: -0.009 | M99: =VLOOKUP(A99,'Mandato Ibov'!$B$1:$C$215,2,0) -> 0 | N99: =K99-M99 -> 0 | O99: =B99-M99 -> 0 | P99: =VLOOKUP(A99,'Mandato Ibov'!$B$2:$D$215,3,0) -> 0 | Q99: =K99-P99 -> 0 | R99: -0.602 | S99: -0.623 | T99: -0.819 | U99: -0.556 | V99: -0.716 | W99: -0.207 | X99: 0.002 | Y99: -0.294 | Z99: 0.492 | AA99: 0.491 | AB99: 0.697 | AC99: 0.79 | AD99: 0.666 | AE99: -0.616 | AF99: -0.243 | AG99: -0.083 | AH99: -0.91 | AI99: -0.909 | AJ99: -1 | AK99: -0.19 | AL99: 0.194 | AM99: -0.041 | AN99: 0.115 | AO99: -0.152 | AP99: -0.203 | AQ99: 0.039 | AR99: 0.135 | AS99: 0.417 | AT99: -0.156 | AU99: -0.53 | AV99: -0.395 | AW99: 0.367 | AX99: -0.266 | AY99: 0.059 | AZ99: 0.236 | BA99: 0.738 | BB99: -0.28 | BC99: -0.154 | BD99: 0.422 | BE99: 0.007 | BF99: 0.152 | BG99: 0.984 | BH99: -0.365 | BI99: -0.102 | BJ99: 0.206 | BK99: -0.765 | BM99: =10%*AK99+5%*AL99+2.5%*AM99+2.5%*AN99+10%*AO99+10%*AP99+10%*AQ99+5%*AR99+5%*AS99+10%*AT99+5%*AU99+5%*AY99+10%*AV99+10%*AW99 -> -0.0534
A100: ORVR3 | B100: =K100 -> 0 | C100: =B100-E100 -> 0 | D100: =B100-K100 -> 0 | E100: =K100-L100 -> 0 | F100: 0.857 | G100: 1.037 | H100: bond_proxies | I100: =VLOOKUP(A100,Setores!$A$2:$C$215,2,0) -> utilities | J100: =VLOOKUP(A100,Setores!$A$2:$C$215,3,0) -> very_high_beta | K100: 0 | L100: 0 | M100: =VLOOKUP(A100,'Mandato Ibov'!$B$1:$C$215,2,0) -> 0 | N100: =K100-M100 -> 0 | O100: =B100-M100 -> 0 | P100: =VLOOKUP(A100,'Mandato Ibov'!$B$2:$D$215,3,0) -> 0.0067615541 | Q100: =K100-P100 -> -0.0067615541 | R100: -0.325 | S100: -0.302 | T100: -0.8 | U100: -0.252 | V100: -0.636 | W100: -0.205 | X100: -0.096 | Y100: -0.453 | Z100: 0.387 | AA100: 0.381 | AB100: 0.523 | AC100: 0.632 | AD100: 0.558 | AE100: -0.511 | AF100: -0.358 | AG100: -0.148 | AH100: -0.863 | AI100: 0.396 | AJ100: -0.555 | AK100: -0.48 | AL100: -1 | AM100: -0.884 | AN100: 0.133 | AO100: 0.566 | AP100: 0.749 | AQ100: 0.648 | AR100: 1 | AS100: 0.663 | AT100: -0.166 | AU100: 0.059 | AV100: 0.415 | AW100: 0.511 | AX100: -0.089 | AY100: 0.52 | AZ100: 0.178 | BA100: -0.239 | BB100: -0.712 | BC100: -0.837 | BD100: 0.387 | BE100: -0.48 | BF100: -0.517 | BG100: 0.375 | BH100: -0.702 | BI100: 0.263 | BJ100: -0.092 | BK100: 0.295 | BM100: =10%*AK100+5%*AL100+2.5%*AM100+2.5%*AN100+10%*AO100+10%*AP100+10%*AQ100+5%*AR100+5%*AS100+10%*AT100+5%*AU100+5%*AY100+10%*AV100+10%*AW100 -> 0.267625
A101: AMER3 | B101: =K101 -> 0 | C101: =B101-E101 -> 0 | D101: =B101-K101 -> 0 | E101: =K101-L101 -> 0 | F101: 0.85 | G101: 0.603 | H101: pro_cyclicals | I101: =VLOOKUP(A101,Setores!$A$2:$C$215,2,0) -> consumer_durables | J101: =VLOOKUP(A101,Setores!$A$2:$C$215,3,0) -> high_beta | K101: 0 | L101: 0 | M101: =VLOOKUP(A101,'Mandato Ibov'!$B$1:$C$215,2,0) -> 0 | N101: =K101-M101 -> 0 | O101: =B101-M101 -> 0 | P101: =VLOOKUP(A101,'Mandato Ibov'!$B$2:$D$215,3,0) -> 0 | Q101: =K101-P101 -> 0 | R101: -0.136 | S101: 0.763 | T101: -0.146 | U101: -0.594 | V101: -0.016 | W101: -0.749 | X101: -0.835 | Y101: -0.742 | Z101: 0.161 | AA101: 0.159 | AB101: 0.299 | AC101: 1 | AD101: 0.793 | AE101: -0.693 | AF101: -0.094 | AG101: 0.906 | AH101: 0.486 | AI101: 1 | AJ101: -0.669 | AK101: 0.138 | AL101: -1 | AM101: 0.997 | AN101: -0.071 | AO101: -0.024 | AP101: 0.634 | AQ101: -0.3 | AR101: 0.487 | AS101: 0.273 | AT101: -0.261 | AU101: -0.655 | AV101: -0.631 | AW101: -0.57 | AX101: -0.208 | AY101: -0.939 | AZ101: -1 | BA101: 0.022 | BB101: 0.318 | BC101: 0.302 | BD101: 0.401 | BE101: 1 | BF101: 0.436 | BG101: 0.156 | BH101: 1 | BI101: 0.248 | BJ101: -0.199 | BK101: 0.5 | BM101: =10%*AK101+5%*AL101+2.5%*AM101+2.5%*AN101+10%*AO101+10%*AP101+10%*AQ101+5%*AR101+5%*AS101+10%*AT101+5%*AU101+5%*AY101+10%*AV101+10%*AW101 -> -0.16995
A102: DIRR3 | B102: =K102 -> 0 | C102: =B102-E102 -> -0.002 | D102: =B102-K102 -> 0 | E102: =K102-L102 -> 0.002 | F102: 0.848 | G102: 0.843 | H102: pro_cyclicals | I102: =VLOOKUP(A102,Setores!$A$2:$C$215,2,0) -> homebuilders | J102: =VLOOKUP(A102,Setores!$A$2:$C$215,3,0) -> very_high_beta | K102: 0 | L102: -0.002 | M102: =VLOOKUP(A102,'Mandato Ibov'!$B$1:$C$215,2,0) -> 0 | N102: =K102-M102 -> 0 | O102: =B102-M102 -> 0 | P102: =VLOOKUP(A102,'Mandato Ibov'!$B$2:$D$215,3,0) -> 0 | Q102: =K102-P102 -> 0 | R102: -0.39 | S102: -0.846 | T102: -0.591 | U102: -0.152 | V102: -0.628 | W102: -0.071 | X102: 0.089 | Y102: -0.183 | Z102: -0.022 | AA102: -0.023 | AB102: 0.62 | AC102: 0.514 | AD102: 0.434 | AE102: 0.323 | AF102: 0.463 | AG102: -0.848 | AH102: -0.449 | AI102: -0.655 | AJ102: -0.509 | AK102: -0.1 | AL102: 0.581 | AM102: -0.733 | AN102: 0.496 | AO102: -0.594 | AP102: -0.393 | AQ102: 0.421 | AR102: 0.36 | AS102: -0.006 | AT102: 0.265 | AU102: 0 | AV102: 0.237 | AW102: 0.006 | AX102: -0.029 | AY102: 0.647 | AZ102: 1 | BA102: 0.089 | BB102: -0.387 | BC102: -0.103 | BD102: 0.074 | BE102: -0.183 | BF102: -0.367 | BG102: 0.108 | BH102: -0.955 | BI102: 0.664 | BJ102: -0.727 | BK102: -0.229 | BM102: =10%*AK102+5%*AL102+2.5%*AM102+2.5%*AN102+10%*AO102+10%*AP102+10%*AQ102+5%*AR102+5%*AS102+10%*AT102+5%*AU102+5%*AY102+10%*AV102+10%*AW102 -> 0.057375
A103: FESA4 | B103: =K103 -> 0 | C103: =B103-E103 -> 0 | D103: =B103-K103 -> 0 | E103: =K103-L103 -> 0 | F103: 0.845 | G103: 0.831 | H103: commodities | I103: =VLOOKUP(A103,Setores!$A$2:$C$215,2,0) -> basic_materials | J103: =VLOOKUP(A103,Setores!$A$2:$C$215,3,0) -> low_beta | K103: 0 | L103: 0 | M103: =VLOOKUP(A103,'Mandato Ibov'!$B$1:$C$215,2,0) -> 0 | N103: =K103-M103 -> 0 | O103: =B103-M103 -> 0 | P103: =VLOOKUP(A103,'Mandato Ibov'!$B$2:$D$215,3,0) -> 0 | Q103: =K103-P103 -> 0 | R103: -0.54 | S103: -0.4 | T103: -0.361 | U103: -0.713 | V103: -0.55 | W103: -0.349 | X103: -0.501 | Y103: -0.312 | Z103: 0.452 | AA103: 0.444 | AB103: 0.508 | AC103: 0.667 | AD103: 0.716 | AE103: -0.487 | AF103: -0.96 | AG103: -0.45 | AH103: -0.11 | AI103: 0.074 | AJ103: -0.365 | AK103: -0.171 | AL103: 0.259 | AM103: -0.086 | AN103: -0.106 | AO103: 0.004 | AP103: 0.049 | AQ103: -0.913 | AR103: -0.231 | AS103: -0.164 | AT103: -0.083 | AU103: -0.501 | AV103: -0.224 | AW103: 0.393 | AX103: 0.498 | AY103: 0.821 | AZ103: -0.019 | BA103: 0.83 | BB103: 0.186 | BC103: 0.172 | BD103: 0.362 | BE103: 0.486 | BF103: 1 | BG103: 0.298 | BH103: -0.035 | BI103: -0.694 | BJ103: 0.65 | BK103: 0.637 | BM103: =10%*AK103+5%*AL103+2.5%*AM103+2.5%*AN103+10%*AO103+10%*AP103+10%*AQ103+5%*AR103+5%*AS103+10%*AT103+5%*AU103+5%*AY103+10%*AV103+10%*AW103 -> -0.0901
...

Sheet 35 - SMLL
B1: =COUNTIF(B9:B222,">0") -> 64 | E1: =COUNTIF(E9:E222,">0") -> 107 | K1: Act Share | L1: Bmk | M1: Mandato | N1: Modelo 2.0 | O1: Meta | S1: Modelos | AF1: Interações | AL1: Clusters
K2: Meta | L2: =SQRT(SUMSQ(L9:L222)^2) -> 0.025911 | M2: =SQRT(SUMSQ(O9:O222)^2) -> 0.0056573174 | N2: =SQRT(SUMSQ(R9:R222)^2) -> 0.016580346
E3: MF - Meta | F3: =SUMPRODUCT($D$9:$D$222,F9:F222) -> 0.01944 | K3: MF | L3: =SQRT(SUMSQ(C9:C222)^2) -> 0.02466625 | M3: =SQRT(SUMSQ(P9:P222)^2) -> 0.003230955 | O3: =SQRT(SUMSQ(D9:D222)^2) -> 0.00280425
E4: Meta - 2.0 | F4: =SUMPRODUCT($R$9:$R$222,F9:F222) -> 0.28664574 | R4: MF - Meta | S4: =SUMPRODUCT($D$9:$D$226,S9:S226) -> 0.0096685 | T4: =SUMPRODUCT($D$9:$D$226,T9:T226) -> 0.029332 | U4: =SUMPRODUCT($D$9:$D$226,U9:U226) -> 0.008372 | V4: =SUMPRODUCT($D$9:$D$226,V9:V226) -> 0.0092695 | W4: =SUMPRODUCT($D$9:$D$226,W9:W226) -> 0.0213305 | X4: =SUMPRODUCT($D$9:$D$226,X9:X226) -> 0.008898 | Y4: =SUMPRODUCT($D$9:$D$226,Y9:Y226) -> 0.000838 | Z4: =SUMPRODUCT($D$9:$D$226,Z9:Z226) -> 0.009817 | ... BL4: =SUMPRODUCT($D$9:$D$226,BL9:BL226) -> 0.0505145
E5: Meta - Mandato | F5: =SUMPRODUCT($O$9:$O$222,F9:F222) -> -0.16852387 | R5: Meta - 2.0 | S5: =SUMPRODUCT($R$9:$R$226,S9:S226) -> 0.22174161 | T5: =SUMPRODUCT($R$9:$R$226,T9:T226) -> 0.10194263 | U5: =SUMPRODUCT($R$9:$R$226,U9:U226) -> 0.29679101 | V5: =SUMPRODUCT($R$9:$R$226,V9:V226) -> 0.1692171 | W5: =SUMPRODUCT($R$9:$R$226,W9:W226) -> 0.19721738 | X5: =SUMPRODUCT($R$9:$R$226,X9:X226) -> 0.16364992 | Y5: =SUMPRODUCT($R$9:$R$226,Y9:Y226) -> 0.13382343 | Z5: =SUMPRODUCT($R$9:$R$226,Z9:Z226) -> 0.072871613 | ... BL5: =SUMPRODUCT($R$9:$R$226,BL9:BL226) -> 0.09172254
E6: Meta - Bmk | F6: =SUMPRODUCT($L$9:$L$222,F9:F222) -> 1.16829 | G6: =SUMPRODUCT($L$9:$L$222,G9:G222) -> 0.985298 | R6: Meta - Mandato | S6: =SUMPRODUCT($O$9:$O$226,S8:S225) -> -0.083684056 | T6: =SUMPRODUCT($O$9:$O$226,T8:T225) -> -0.093971221 | U6: =SUMPRODUCT($O$9:$O$226,U8:U225) -> -0.10467822 | V6: =SUMPRODUCT($O$9:$O$226,V8:V225) -> -0.057609762 | W6: =SUMPRODUCT($O$9:$O$226,W8:W225) -> -0.091990103 | X6: =SUMPRODUCT($O$9:$O$226,X8:X225) -> -0.037293004 | Y6: =SUMPRODUCT($O$9:$O$226,Y8:Y225) -> 0.0036994201 | Z6: =SUMPRODUCT($O$9:$O$226,Z8:Z225) -> -0.03305356 | ... BL6: =SUMPRODUCT($O$9:$O$226,BL8:BL225) -> -0.094285101
B7: =SUM(B9:B222) -> 0.9995 | E7: =SUM(E9:E222) -> 1.005 | K7: =SUM(K9:K222) -> 1 | N7: =SUM(N9:N222) -> 1 | Q7: =SUM(Q9:Q222) -> 1 | R7: Meta - Bmk | S7: =SUMPRODUCT($L$9:$L$226,S9:S226) -> 0.669161 | T7: =SUMPRODUCT($L$9:$L$226,T9:T226) -> 0.611905 | U7: =SUMPRODUCT($L$9:$L$226,U9:U226) -> 0.634624 | V7: =SUMPRODUCT($L$9:$L$226,V9:V226) -> 0.679227 | W7: =SUMPRODUCT($L$9:$L$226,W9:W226) -> 0.670947 | X7: =SUMPRODUCT($L$9:$L$226,X9:X226) -> 0.663008 | Y7: =SUMPRODUCT($L$9:$L$226,Y9:Y226) -> 0.592108 | Z7: =SUMPRODUCT($L$9:$L$226,Z9:Z226) -> 0.682796 | ... BL7: =SUMPRODUCT($L$9:$L$226,BL9:BL226) -> 0.151208
A8: tickers | B8: MF | C8: MF - Smll | D8: MF - META | E8: Bmk | F8: exp_ret_score_raw | G8: exp_ret_score | H8: sectors_c2 | I8: sectors_c1 | J8: sectors_dyn | K8: META | L8: act_weights | M8: ibov_rank | N8: mandato | O8: Meta - Mandato | P8: MF - Mandao | Q8: modelo 2.0 | R8: Meta - 2.0 | S8: ew | T8: sw_mom | U8: sw_val | V8: sw_lt_perf | W8: sw_overall | X8: rp_cc | Y8: hrp_cc | Z8: mvo_overall_cc_con | AA8: ols | AB8: glmnet_bayes | AC8: rf_bayes | AD8: xgb_bayes | AE8: nn1_bayes | AF8: qv | AG8: garp | AH8: vm | AI8: sv | AJ8: sm | AK8: smcj | AL8: fac_inc_cs_value | AM8: fac_payout_yield | AN8: fac_bs_cs_value | AO8: fac_ts_value | AP8: fac_interm_momentum | AQ8: fac_st_momentum | AR8: fac_lt_profit_growth | AS8: fac_st_profit_growth | AT8: fac_surprise | AU8: fac_bs_profitability | AV8: fac_profit_margins | AW8: fac_quality | AX8: fac_mkt_risk | AY8: fac_leverage | AZ8: fac_profit_vol | BA8: fac_seasonality | BB8: fac_short_interest | BC8: fac_acc_growth | BD8: fac_accruals | BE8: fac_issuance | BF8: fac_st_reversal | BG8: fac_skewness | BH8: fac_max | BI8: fac_lt_reversal | BJ8: fac_macro | BK8: fac_liquidity | BL8: fac_size
A9: JHSF3 | B9: 0.026 | C9: =B9-E9 -> 0.018 | D9: =B9-K9 -> 0.01 | E9: =K9-L9 -> 0.008 | F9: 3.612 | G9: 4.683 | H9: pro_cyclicals | I9: =VLOOKUP(A9,Setores!$A$2:$C$215,2,0) -> homebuilders | J9: =VLOOKUP(A9,Setores!$A$2:$C$215,3,0) -> very_high_beta | K9: 0.016 | L9: 0.008 | M9: 80 | N9: =VLOOKUP(A9,'Mandato Smll'!$A$2:$C$215,2,0) -> 0.036202388 | O9: =K9-N9 -> -0.020202388 | P9: =B9-N9 -> -0.010202388 | Q9: =VLOOKUP(A9,'Mandato Smll'!$A$2:$C$215,3,0) -> 0.032680853 | R9: =K9-Q9 -> -0.016680853 | S9: 1 | T9: 1 | U9: 0.606 | V9: 1 | W9: 1 | X9: 1 | Y9: 0.973 | Z9: 1 | AA9: 0.695 | AB9: 0.691 | AC9: 0.929 | AD9: 0.859 | AE9: 1 | AF9: 1 | AG9: 0.938 | AH9: 1 | AI9: -0.415 | AJ9: 0.728 | AK9: 0.253 | AL9: 0.296 | AM9: -0.053 | AN9: -0.411 | AO9: 0.313 | AP9: 0.632 | AQ9: 0.927 | AR9: 0.532 | AS9: 0.182 | AT9: 0.309 | AU9: 0.33 | AV9: 0.414 | AW9: 0.908 | AX9: -0.045 | AY9: 0.136 | AZ9: -0.176 | BA9: 0.537 | BB9: -0.253 | BC9: 0.008 | BD9: 0.541 | BE9: 0.647 | BF9: 0.217 | BG9: 0.151 | BH9: 0.142 | BI9: -0.857 | BJ9: 0.704 | BK9: -0.051 | BL9: -0.258
A10: WIZC3 | B10: 0.015 | C10: =B10-E10 -> 0.015 | D10: =B10-K10 -> 0 | E10: =K10-L10 -> 0 | F10: 3.612 | G10: 3.511 | H10: defensives | I10: =VLOOKUP(A10,Setores!$A$2:$C$215,2,0) -> financial_services | J10: =VLOOKUP(A10,Setores!$A$2:$C$215,3,0) -> very_low_beta | K10: 0.015 | L10: 0.015 | M10: 80 | N10: =VLOOKUP(A10,'Mandato Smll'!$A$2:$C$215,2,0) -> 0.016068234 | O10: =K10-N10 -> -0.0010682341 | P10: =B10-N10 -> -0.0010682341 | Q10: =VLOOKUP(A10,'Mandato Smll'!$A$2:$C$215,3,0) -> 0.0096893833 | R10: =K10-Q10 -> 0.0053106167 | S10: 1 | T10: 0.966 | U10: 1 | V10: 1 | W10: 1 | X10: 1 | Y10: 1 | Z10: 0.631 | AA10: 0.724 | AB10: 0.723 | AC10: 1 | AD10: 1 | AE10: 0.99 | AF10: 1 | AG10: 0.205 | AH10: 0.421 | AI10: 0.546 | AJ10: 0.997 | AK10: 1 | AL10: 0.551 | AM10: -0.187 | AN10: -0.263 | AO10: 0.055 | AP10: 0.036 | AQ10: 0.118 | AR10: 0.271 | AS10: 0.157 | AT10: -0.346 | AU10: 0.724 | AV10: 0.403 | AW10: 1 | AX10: 0.363 | AY10: -0.062 | AZ10: 0.804 | BA10: 0.496 | BB10: -0.043 | BC10: 0.05 | BD10: 0.06 | BE10: 0.535 | BF10: -0.021 | BG10: 1 | BH10: 0.641 | BI10: -0.361 | BJ10: -0.367 | BK10: 0.614 | BL10: 0.693
A11: LOGG3 | B11: 0.018 | C11: =B11-E11 -> 0.014 | D11: =B11-K11 -> 0.003 | E11: =K11-L11 -> 0.004 | F11: 3.612 | G11: 4.551 | H11: bond_proxies | I11: =VLOOKUP(A11,Setores!$A$2:$C$215,2,0) -> real_estate | J11: =VLOOKUP(A11,Setores!$A$2:$C$215,3,0) -> neutral_beta | K11: 0.015 | L11: 0.011 | M11: 80 | N11: =VLOOKUP(A11,'Mandato Smll'!$A$2:$C$215,2,0) -> 0.022252393 | O11: =K11-N11 -> -0.0072523931 | P11: =B11-N11 -> -0.0042523931 | Q11: =VLOOKUP(A11,'Mandato Smll'!$A$2:$C$215,3,0) -> 0.011704847 | R11: =K11-Q11 -> 0.0032951526 | S11: 0.753 | T11: 1 | U11: 0.511 | V11: 0.896 | W11: 0.882 | X11: 0.996 | Y11: 1 | Z11: 1 | AA11: 0.535 | AB11: 0.54 | AC11: 1 | AD11: 0.991 | AE11: 1 | AF11: 1 | AG11: 0.092 | AH11: 0.797 | AI11: 0.298 | AJ11: 0.918 | AK11: -0.122 | AL11: -0.204 | AM11: 0.327 | AN11: -0.17 | AO11: 0.033 | AP11: 0.439 | AQ11: 0.023 | AR11: -0.072 | AS11: 0.527 | AT11: 0.52 | AU11: -0.109 | AV11: 0.759 | AW11: 0.419 | AX11: 0.344 | AY11: -0.735 | AZ11: 0.03 | BA11: -0.262 | BB11: -0.245 | BC11: 0.135 | BD11: 0.593 | BE11: 0.51 | BF11: -0.351 | BG11: -0.122 | BH11: 0.728 | BI11: -0.416 | BJ11: 0.223 | BK11: 0.369 | BL11: 0.297
A12: FIQE3 | B12: 0.015 | C12: =B12-E12 -> 0.015 | D12: =B12-K12 -> 0 | E12: =K12-L12 -> 0 | F12: 3.612 | G12: 3.585 | H12: bond_proxies | I12: =VLOOKUP(A12,Setores!$A$2:$C$215,2,0) -> telecom | J12: =VLOOKUP(A12,Setores!$A$2:$C$215,3,0) -> low_beta | K12: 0.015 | L12: 0.015 | M12: 80 | N12: =VLOOKUP(A12,'Mandato Smll'!$A$2:$C$215,2,0) -> 0.016068234 | O12: =K12-N12 -> -0.0010682341 | P12: =B12-N12 -> -0.0010682341 | Q12: =VLOOKUP(A12,'Mandato Smll'!$A$2:$C$215,3,0) -> 0.014190228 | R12: =K12-Q12 -> 0.00080977182 | S12: 1 | T12: 1 | U12: 0.642 | V12: 1 | W12: 0.938 | X12: 1 | Y12: 1 | Z12: 1 | AA12: 0.687 | AB12: 0.689 | AC12: 1 | AD12: 1 | AE12: 1 | AF12: 0.557 | AG12: 0.002 | AH12: 0.805 | AI12: -0.261 | AJ12: 1 | AK12: 0.752 | AL12: -0.205 | AM12: 0.133 | AN12: -0.805 | AO12: 0.064 | AP12: 0.751 | AQ12: 1 | AR12: 0.293 | AS12: 0.405 | AT12: 0.475 | AU12: 0.417 | AV12: 0.26 | AW12: 0.767 | AX12: 0.426 | AY12: 0.179 | AZ12: 0.885 | BA12: 0.104 | BB12: 0.583 | BC12: -0.299 | BD12: -0.201 | BE12: 0.293 | BF12: -0.371 | BG12: 0.371 | BH12: 0.682 | BI12: -0.527 | BJ12: -0.401 | BK12: 0.717 | BL12: 0.495
A13: BMGB4 | B13: 0.014 | C13: =B13-E13 -> 0.014 | D13: =B13-K13 -> 0 | E13: =K13-L13 -> 0 | F13: 3.612 | G13: 3.556 | H13: pro_cyclicals | I13: =VLOOKUP(A13,Setores!$A$2:$C$215,2,0) -> banks | J13: =VLOOKUP(A13,Setores!$A$2:$C$215,3,0) -> high_beta | K13: 0.014 | L13: 0.014 | M13: 80 | N13: =VLOOKUP(A13,'Mandato Smll'!$A$2:$C$215,2,0) -> 0.016068234 | O13: =K13-N13 -> -0.0020682341 | P13: =B13-N13 -> -0.0020682341 | Q13: =VLOOKUP(A13,'Mandato Smll'!$A$2:$C$215,3,0) -> 0.01450522 | R13: =K13-Q13 -> -0.00050521981 | S13: 0.902 | T13: 1 | U13: 0.817 | V13: 0.911 | W13: 1 | X13: 1 | Y13: 1 | Z13: 1 | AA13: 1 | AB13: 1 | AC13: 1 | AD13: 1 | AE13: 1 | AF13: 0.194 | AG13: 1 | AH13: 1 | AI13: 0.251 | AJ13: 1 | AK13: 0.23 | AL13: 0.073 | AM13: 0.54 | AN13: 0.42 | AO13: 0.223 | AP13: 0.561 | AQ13: 0.813 | AR13: 0.557 | AS13: 0.25 | AT13: -0.139 | AU13: 0.002 | AV13: -0.267 | AW13: -0.131 | AX13: 0.515 | AY13: -0.09 | AZ13: 0.655 | BA13: 0.249 | BB13: -0.003 | BC13: 0.126 | BD13: 0.215 | BE13: -0.732 | BF13: -0.363 | BG13: 0.186 | BH13: 0.936 | BI13: -0.81 | BJ13: 0.082 | BK13: 0.64 | BL13: 0.679
A14: ALLD3 | B14: 0.011 | C14: =B14-E14 -> 0.011 | D14: =B14-K14 -> 0.003 | E14: =K14-L14 -> 0 | F14: 3.612 | G14: 2.69 | H14: pro_cyclicals | I14: =VLOOKUP(A14,Setores!$A$2:$C$215,2,0) -> consumer_durables | J14: =VLOOKUP(A14,Setores!$A$2:$C$215,3,0) -> very_low_beta | K14: 0.008 | L14: 0.008 | M14: 80 | N14: =VLOOKUP(A14,'Mandato Smll'!$A$2:$C$215,2,0) -> 0.016068234 | O14: =K14-N14 -> -0.0080682341 | P14: =B14-N14 -> -0.0050682341 | Q14: =VLOOKUP(A14,'Mandato Smll'!$A$2:$C$215,3,0) -> 0.0092479761 | R14: =K14-Q14 -> -0.0012479761 | S14: 1 | T14: 0.646 | U14: 1 | V14: 1 | W14: 1 | X14: 1 | Y14: 1 | Z14: 0.737 | AA14: 1 | AB14: 1 | AC14: 0.735 | AD14: 0.749 | AE14: 0.928 | AF14: 1 | AG14: 1 | AH14: -0.138 | AI14: 1 | AJ14: -0.315 | AK14: 1 | AL14: 0.882 | AM14: 1 | AN14: 0.451 | AO14: 0.652 | AP14: -0.808 | AQ14: -0.665 | AR14: 0.303 | AS14: 0.594 | AT14: 0.097 | AU14: 0.697 | AV14: -0.548 | AW14: 0.908 | AX14: 0.326 | AY14: 0.054 | AZ14: 0.47 | BA14: 0.604 | BB14: 0.25 | BC14: 0.292 | BD14: 0.303 | BE14: 0.594 | BF14: 0.043 | BG14: 0.097 | BH14: 0.907 | BI14: -0.345 | BJ14: -0.437 | BK14: 0.521 | BL14: 0.802
A15: RIAA3 | B15: 0.015 | C15: =B15-E15 -> 0.013 | D15: =B15-K15 -> 0 | E15: =K15-L15 -> 0.002 | F15: 3.529 | G15: 2.708 | H15: pro_cyclicals | I15: =VLOOKUP(A15,Setores!$A$2:$C$215,2,0) -> apparel | J15: =VLOOKUP(A15,Setores!$A$2:$C$215,3,0) -> very_high_beta | K15: 0.015 | L15: 0.013 | M15: 80 | N15: =VLOOKUP(A15,'Mandato Smll'!$A$2:$C$215,2,0) -> 0.017842949 | O15: =K15-N15 -> -0.0028429486 | P15: =B15-N15 -> -0.0028429486 | Q15: =VLOOKUP(A15,'Mandato Smll'!$A$2:$C$215,3,0) -> 0.010739004 | R15: =K15-Q15 -> 0.0042609957 | S15: 0.993 | T15: 0.849 | U15: 0.797 | V15: 1 | W15: 0.969 | X15: 0.786 | Y15: 0.514 | Z15: 0.755 | AA15: 0.757 | AB15: 0.752 | AC15: 0.778 | AD15: 0.798 | AE15: 0.956 | AF15: 1 | AG15: 1 | AH15: 0.418 | AI15: 0.137 | AJ15: 0.133 | AK15: 0.61 | AL15: 0.556 | AM15: 0.091 | AN15: -0.118 | AO15: 0.478 | AP15: 0.227 | AQ15: -0.081 | AR15: 0.584 | AS15: 0.768 | AT15: 0.384 | AU15: 0.428 | AV15: -0.1 | AW15: 0.958 | AX15: -0.591 | AY15: 0.077 | AZ15: 0.423 | BA15: 0.629 | BB15: -0.314 | BC15: 0.211 | BD15: 0.019 | BE15: 0.625 | BF15: 0.234 | BG15: -0.288 | BH15: 0.204 | BI15: -0.488 | BJ15: 0.292 | BK15: 0.253 | BL15: 0.206
A16: GRND3 | B16: 0.015 | C16: =B16-E16 -> 0.013 | D16: =B16-K16 -> 0 | E16: =K16-L16 -> 0.002 | F16: 3.497 | G16: 4.141 | H16: pro_cyclicals | I16: =VLOOKUP(A16,Setores!$A$2:$C$215,2,0) -> apparel | J16: =VLOOKUP(A16,Setores!$A$2:$C$215,3,0) -> very_low_beta | K16: 0.015 | L16: 0.013 | M16: 80 | N16: =VLOOKUP(A16,'Mandato Smll'!$A$2:$C$215,2,0) -> 0.01888876 | O16: =K16-N16 -> -0.0038887601 | P16: =B16-N16 -> -0.0038887601 | Q16: =VLOOKUP(A16,'Mandato Smll'!$A$2:$C$215,3,0) -> 0.0095426165 | R16: =K16-Q16 -> 0.0054573835 | S16: 0.737 | T16: 0.61 | U16: 0.678 | V16: 0.687 | W16: 0.675 | X16: 1 | Y16: 1 | Z16: 0.978 | AA16: 0.556 | AB16: 0.559 | AC16: 0.894 | AD16: 0.839 | AE16: 0.891 | AF16: 0.847 | AG16: 0.063 | AH16: -0.123 | AI16: 0.027 | AJ16: 0.129 | AK16: 0.847 | AL16: 0.135 | AM16: 0.948 | AN16: -0.477 | AO16: 0.54 | AP16: 0.169 | AQ16: -0.258 | AR16: -0.023 | AS16: 0.299 | AT16: -0.168 | AU16: 0.205 | AV16: 0.159 | AW16: 0.17 | AX16: 0.518 | AY16: 0.774 | AZ16: 0.495 | BA16: -0.049 | BB16: 0.102 | BC16: 0.553 | BD16: 0.507 | BE16: 0.546 | BF16: 0.211 | BG16: 0.048 | BH16: 0.829 | BI16: -0.075 | BJ16: -0.358 | BK16: 0.197 | BL16: 0.347
A17: HBRE3 | B17: 0.014 | C17: =B17-E17 -> 0.014 | D17: =B17-K17 -> 0 | E17: =K17-L17 -> 0 | F17: 3.378 | G17: 2.51 | H17: bond_proxies | I17: =VLOOKUP(A17,Setores!$A$2:$C$215,2,0) -> real_estate | J17: =VLOOKUP(A17,Setores!$A$2:$C$215,3,0) -> very_high_beta | K17: 0.014 | L17: 0.014 | M17: 80 | N17: =VLOOKUP(A17,'Mandato Smll'!$A$2:$C$215,2,0) -> 0.015027458 | O17: =K17-N17 -> -0.0010274581 | P17: =B17-N17 -> -0.0010274581 | Q17: =VLOOKUP(A17,'Mandato Smll'!$A$2:$C$215,3,0) -> 0 | R17: =K17-Q17 -> 0.014 | S17: 1 | T17: 1 | U17: 1 | V17: 0.702 | W17: 1 | X17: 0.86 | Y17: 0.81 | Z17: 0.47 | AA17: 0.557 | AB17: 0.556 | AC17: 0.644 | AD17: 0.81 | AE17: 0.978 | AF17: 0.237 | AG17: 1 | AH17: 1 | AI17: 1 | AJ17: 0.384 | AK17: -0.225 | AL17: 0.75 | AM17: -0.02 | AN17: 1 | AO17: 0.775 | AP17: -0.097 | AQ17: -0.185 | AR17: -0.221 | AS17: 0.343 | AT17: 0.114 | AU17: -0.228 | AV17: 0.47 | AW17: -0.336 | AX17: -0.048 | AY17: -0.714 | AZ17: -0.344 | BA17: 0.126 | BB17: 0.847 | BC17: 0.166 | BD17: 0.739 | BE17: 0.326 | BF17: -0.001 | BG17: 0.315 | BH17: 0.283 | BI17: 0.154 | BJ17: 0.819 | BK17: 0.621 | BL17: 0.974
A18: POMO3 | B18: 0.015 | C18: =B18-E18 -> 0.011 | D18: =B18-K18 -> 0.001 | E18: =K18-L18 -> 0.004 | F18: 3.324 | G18: 3.232 | H18: industrials | I18: =VLOOKUP(A18,Setores!$A$2:$C$215,2,0) -> capital_goods | J18: =VLOOKUP(A18,Setores!$A$2:$C$215,3,0) -> neutral_beta | K18: 0.014 | L18: 0.01 | M18: 80 | N18: =VLOOKUP(A18,'Mandato Smll'!$A$2:$C$215,2,0) -> 0.019521104 | O18: =K18-N18 -> -0.0055211042 | P18: =B18-N18 -> -0.0045211042 | Q18: =VLOOKUP(A18,'Mandato Smll'!$A$2:$C$215,3,0) -> 0.01416419 | R18: =K18-Q18 -> -0.00016419038 | S18: 0.621 | T18: 0.14 | U18: 0.397 | V18: 0.923 | W18: 0.539 | X18: 0.848 | Y18: 0.816 | Z18: 1 | AA18: 0.632 | AB18: 0.633 | AC18: 0.946 | AD18: 0.86 | AE18: 0.854 | AF18: 1 | AG18: 0.59 | AH18: 0.154 | AI18: -0.454 | AJ18: -0.03 | AK18: 0.096 | AL18: -0.035 | AM18: 0.628 | AN18: -0.685 | AO18: 0.375 | AP18: 0.287 | AQ18: 0.448 | AR18: 0.599 | AS18: 0.283 | AT18: -0.498 | AU18: 0.614 | AV18: -0.337 | AW18: 0.644 | AX18: 0.41 | AY18: 0.114 | AZ18: 0.843 | BA18: 0.741 | BB18: 0.226 | BC18: -0.159 | BD18: -0.188 | BE18: 0.438 | BF18: -0.417 | BG18: 0.146 | BH18: 0.346 | BI18: -0.961 | BJ18: 0.172 | BK18: 0.73 | BL18: -0.151
A19: MTRE3 | B19: 0.021 | C19: =B19-E19 -> 0.021 | D19: =B19-K19 -> 0 | E19: =K19-L19 -> 0 | F19: 3.23 | G19: 3.499 | H19: pro_cyclicals | I19: =VLOOKUP(A19,Setores!$A$2:$C$215,2,0) -> homebuilders | J19: =VLOOKUP(A19,Setores!$A$2:$C$215,3,0) -> low_beta | K19: 0.021 | L19: 0.021 | M19: 80 | N19: =VLOOKUP(A19,'Mandato Smll'!$A$2:$C$215,2,0) -> 0.014370629 | O19: =K19-N19 -> 0.0066293713 | P19: =B19-N19 -> 0.0066293713 | Q19: =VLOOKUP(A19,'Mandato Smll'!$A$2:$C$215,3,0) -> 0.0090573424 | R19: =K19-Q19 -> 0.011942658 | S19: 0.688 | T19: 0.794 | U19: 0.801 | V19: 0.52 | W19: 0.767 | X19: 0.688 | Y19: 0.667 | Z19: 0.602 | AA19: 0.676 | AB19: 0.672 | AC19: 1 | AD19: 0.934 | AE19: 0.937 | AF19: -0.026 | AG19: 1 | AH19: 0.535 | AI19: 1 | AJ19: 0.456 | AK19: 0.016 | AL19: 0.147 | AM19: 0.699 | AN19: 0.319 | AO19: 0.416 | AP19: -0.131 | AQ19: -0.245 | AR19: 0.252 | AS19: 0.546 | AT19: 0.171 | AU19: -0.031 | AV19: -0.327 | AW19: -0.239 | AX19: -0.015 | AY19: -0.326 | AZ19: 0.678 | BA19: 0.185 | BB19: 0.058 | BC19: -0.186 | BD19: -0.07 | BE19: 0.244 | BF19: -0.151 | BG19: 0.367 | BH19: 0.853 | BI19: -0.061 | BJ19: 0.12 | BK19: 0.609 | BL19: 0.875
A20: MLAS3 | B20: 0.011 | C20: =B20-E20 -> 0.011 | D20: =B20-K20 -> 0 | E20: =K20-L20 -> 0 | F20: 2.937 | G20: 2.111 | H20: pro_cyclicals | I20: =VLOOKUP(A20,Setores!$A$2:$C$215,2,0) -> tech | J20: =VLOOKUP(A20,Setores!$A$2:$C$215,3,0) -> high_beta | K20: 0.011 | L20: 0.011 | M20: 80 | N20: =VLOOKUP(A20,'Mandato Smll'!$A$2:$C$215,2,0) -> 0.013066612 | O20: =K20-N20 -> -0.0020666124 | P20: =B20-N20 -> -0.0020666124 | Q20: =VLOOKUP(A20,'Mandato Smll'!$A$2:$C$215,3,0) -> 0.009910464 | R20: =K20-Q20 -> 0.001089536 | S20: 1 | T20: 1 | U20: 1 | V20: 1 | W20: 1 | X20: 0.184 | Y20: -0.575 | Z20: 0.389 | AA20: 0.348 | AB20: 0.347 | AC20: 0.766 | AD20: 0.793 | AE20: 1 | AF20: 1 | AG20: 1 | AH20: 1 | AI20: 0.588 | AJ20: 0.898 | AK20: 1 | AL20: 0.424 | AM20: -0.809 | AN20: 0.445 | AO20: 0.341 | AP20: 0.355 | AQ20: 0.382 | AR20: 0.7 | AS20: 0.664 | AT20: 0.366 | AU20: 0.137 | AV20: -0.445 | AW20: 0.858 | AX20: -0.528 | AY20: 0.358 | AZ20: 0.413 | BA20: -0.318 | BB20: 0.932 | BC20: 0.336 | BD20: 0.234 | BE20: 0.799 | BF20: -1 | BG20: -0.382 | BH20: -1 | BI20: 0.533 | BJ20: -0.127 | BK20: 0.917 | BL20: 0.464
... A219: PMAM3 | B219: 0 | C219: =B219-E219 -> 0 | D219: =B219-K219 -> 0 | E219: =K219-L219 -> 0 | F219: 0.477 | G219: 0.326 | H219: commodities | I219: =VLOOKUP(A219,Setores!$A$2:$C$215,2,0) -> basic_materials | J219: =VLOOKUP(A219,Setores!$A$2:$C$215,3,0) -> high_beta | K219: 0 | L219: 0 | M219: 80 | N219: =VLOOKUP(A219,'Mandato Smll'!$A$2:$C$215,2,0) -> 0 | O219: =K219-N219 -> 0 | P219: =B219-N219 -> 0 | Q219: =VLOOKUP(A219,'Mandato Smll'!$A$2:$C$215,3,0) -> 0 | R219: =K219-Q219 -> 0 | S219: -0.996 | T219: -1 | U219: -0.933 | V219: -1 | W219: -1 | X219: -1 | Y219: -1 | Z219: -1 | AA219: -1 | AB219: -1 | AC219: -1 | AD219: -1 | AE219: -1 | AF219: -1 | AG219: -0.823 | AH219: -1 | AI219: -0.48 | AJ219: -0.264 | AK219: -0.397 | AL219: -0.585 | AM219: -1 | AN219: -0.957 | AO219: -0.017 | AP219: -0.585 | AQ219: -0.378 | AR219: 0.171 | AS219: -0.502 | AT219: -0.356 | AU219: -0.783 | AV219: -0.819 | AW219: -0.417 | AX219: -0.492 | AY219: -0.774 | AZ219: -0.87 | BA219: -0.621 | BB219: -0.477 | BC219: 0.853 | BD219: 0.755 | BE219: -0.023 | BF219: 0.62 | BG219: 0.698 | BH219: -0.708 | BI219: 1 | BJ219: -0.02 | BK219: 0.689 | BL219: 0.965
H241: Rótulos de Linha | I241: Soma de MF | J241: Soma de MF - Smll | K241: Soma de META | L241: Soma de act_weights | M241: Soma de mandato | N241: Soma de modelo 2.0
H242: bond_proxies | I242: 0.222 | J242: 0.006 | K242: 0.223 | L242: 0.007 | M242: 0.21768803 | N242: 0.3114017
H243: real_estate | I243: 0.107 | J243: 0.018 | K243: 0.1 | L243: 0.011 | M243: 0.11870265 | N243: 0.047198643
H244: telecom | I244: 0.044 | J244: 0.042 | K244: 0.044 | L244: 0.042 | M244: 0.030239513 | N244: 0.020939009
H245: transportation | I245: 0 | J245: -0.007 | K245: 0 | L245: -0.007 | M245: 0 | N245: 0
H246: utilities | I246: 0.071 | J246: -0.047 | K246: 0.079 | L246: -0.039 | M246: 0.068745871 | N246: 0.24326405
H247: commodities | I247: 0.119 | J247: -0.026 | K247: 0.094 | L247: -0.051 | M247: 0.1540588 | N247: 0.19422644
H248: basic_materials | I248: 0.082 | J248: 0.002 | K248: 0.061 | L248: -0.019 | M248: 0.12051458 | N248: 0.1343302
H249: crude_oil | I249: 0.027 | J249: -0.008 | K249: 0.023 | L249: -0.012 | M249: 0.027137284 | N249: 0.041005554
H250: food | I250: 0.01 | J250: -0.02 | K250: 0.01 | L250: -0.02 | M250: 0.0064069296 | N250: 0.018890684
H251: defensives | I251: 0.1055 | J251: -0.0605 | K251: 0.096 | L251: -0.07 | M251: 0.072013928 | N251: 0.10977325
H252: consumer_staples | I252: 0 | J252: -0.072 | K252: 0 | L252: -0.072 | M252: 0 | N252: 0
H253: financial_services | I253: 0.015 | J253: 0.015 | K253: 0.015 | L253: 0.015 | M253: 0.016068234 | N253: 0.0096893833
... H269: transportation | I269: 0.014 | J269: 0 | K269: 0.014 | L269: 0 | M269: 0.0083272851 | N269: 0
H270: (vazio)
H271: (vazio)
H272: Total Geral | I272: 0.9995 | J272: -0.0055 | K272: 1 | L272: -0.005 | M272: 1 | N272: 1

Sheet 36 - LP
B1: =COUNTIF(B9:B222,">0") -> 71 | E1: =COUNTIF(E9:E222,">0") -> 92 | K1: Act Share | L1: Bmk | M1: Mandato | N1: Modelo 2.0 | O1: Meta | S1: Modelos | AF1: Interações | AL1: Clusters
K2: Meta | L2: =SQRT(SUMSQ(L9:L222)^2) -> 0.020148 | M2: =SQRT(SUMSQ(O9:O222)^2) -> 0.0056373456 | N2: =SQRT(SUMSQ(R9:R222)^2) -> 0.011107266
E3: MF - Meta | F3: =SUMPRODUCT($D$9:$D$222,F9:F222) -> -0.009538 | K3: MF | L3: =SQRT(SUMSQ(C9:C222)^2) -> 0.018691 | M3: =SQRT(SUMSQ(P9:P222)^2) -> 0.0045939468 | O3: =SQRT(SUMSQ(D9:D222)^2) -> 0.002444
E4: Meta - 2.0 | F4: =SUMPRODUCT($R$9:$R$222,F9:F222) -> 0.066554388 | R4: MF - Meta | S4: =SUMPRODUCT($D$9:$D$226,S9:S226) -> -0.0145195 | T4: =SUMPRODUCT($D$9:$D$226,T9:T226) -> -0.001312 | U4: =SUMPRODUCT($D$9:$D$226,U9:U226) -> -0.0268065 | V4: =SUMPRODUCT($D$9:$D$226,V9:V226) -> -0.0011345 | W4: =SUMPRODUCT($D$9:$D$226,W9:W226) -> -0.0091425 | X4: =SUMPRODUCT($D$9:$D$226,X9:X226) -> 0.0006875 | Y4: =SUMPRODUCT($D$9:$D$226,Y9:Y226) -> 0.0027445 | Z4: =SUMPRODUCT($D$9:$D$226,Z9:Z226) -> 0.0088495 | ... BL4: =SUMPRODUCT($D$9:$D$226,BL9:BL226) -> -0.015196
E5: Meta - Mandato | F5: =SUMPRODUCT($O$9:$O$222,F9:F222) -> -0.20507567 | R5: Meta - 2.0 | S5: =SUMPRODUCT($R$9:$R$226,S9:S226) -> 0.084216886 | T5: =SUMPRODUCT($R$9:$R$226,T9:T226) -> 0.0077811873 | U5: =SUMPRODUCT($R$9:$R$226,U9:U226) -> 0.12607791 | V5: =SUMPRODUCT($R$9:$R$226,V9:V226) -> 0.032316257 | W5: =SUMPRODUCT($R$9:$R$226,W9:W226) -> 0.057435402 | X5: =SUMPRODUCT($R$9:$R$226,X9:X226) -> 0.066838134 | Y5: =SUMPRODUCT($R$9:$R$226,Y9:Y226) -> 0.076329166 | Z5: =SUMPRODUCT($R$9:$R$226,Z9:Z226) -> -0.030848923 | ... BL5: =SUMPRODUCT($R$9:$R$226,BL9:BL226) -> 0.13243432
E6: Meta - Bmk | F6: =SUMPRODUCT($L$9:$L$222,F9:F222) -> 0.814114 | G6: =SUMPRODUCT($L$9:$L$222,G9:G222) -> 0.414538 | R6: Meta - Mandato | S6: =SUMPRODUCT($O$9:$O$226,S9:S226) -> -0.1193542 | T6: =SUMPRODUCT($O$9:$O$226,T9:T226) -> -0.095044741 | U6: =SUMPRODUCT($O$9:$O$226,U9:U226) -> -0.086237273 | V6: =SUMPRODUCT($O$9:$O$226,V9:V226) -> -0.13822657 | W6: =SUMPRODUCT($O$9:$O$226,W9:W226) -> -0.11497348 | X6: =SUMPRODUCT($O$9:$O$226,X9:X226) -> -0.10774091 | Y6: =SUMPRODUCT($O$9:$O$226,Y9:Y226) -> -0.088218799 | Z6: =SUMPRODUCT($O$9:$O$226,Z9:Z226) -> -0.092988333 | ... BL6: =SUMPRODUCT($O$9:$O$226,BL9:BL226) -> -0.0047137238
B7: =SUM(B9:B222) -> 1 | E7: =SUM(E9:E222) -> 0.994 | F7: =SUMPRODUCT($L$9:$L$226,F9:F226) -> 0.814114 | G7: =SUMPRODUCT($L$9:$L$226,G9:G226) -> 0.414538 | K7: =SUM(K9:K222) -> 1 | N7: =SUM(N9:N222) -> 1 | Q7: =SUM(Q9:Q222) -> 1 | R7: Meta - Bmk | S7: =SUMPRODUCT($L$9:$L$226,S9:S226) -> 0.528855 | T7: =SUMPRODUCT($L$9:$L$226,T9:T226) -> 0.49426 | U7: =SUMPRODUCT($L$9:$L$226,U9:U226) -> 0.545539 | V7: =SUMPRODUCT($L$9:$L$226,V9:V226) -> 0.463101 | W7: =SUMPRODUCT($L$9:$L$226,W9:W226) -> 0.521598 | X7: =SUMPRODUCT($L$9:$L$226,X9:X226) -> 0.400015 | Y7: =SUMPRODUCT($L$9:$L$226,Y9:Y226) -> 0.280001 | Z7: =SUMPRODUCT($L$9:$L$226,Z9:Z226) -> 0.323373 | ... BL7: =SUMPRODUCT($L$9:$L$226,BL9:BL226) -> 0.469462
A8: tickers | B8: MF | C8: MF - LP | D8: MF - META | E8: Bmk | F8: exp_ret_score_raw | G8: exp_ret_score | H8: sectors_c2 | I8: sectors_c1 | J8: sectors_dyn | K8: META | L8: act_weights | M8: mean_dps_36m | N8: mandato | O8: Meta - Mandato | P8: MF - Mandato | Q8: modelo 2.0 | R8: Meta - 2.0 | S8: ew | T8: sw_mom | U8: sw_val | V8: sw_lt_perf | W8: sw_overall | X8: rp_cc | Y8: hrp_cc | Z8: mvo_overall_cc_con | AA8: ols | AB8: glmnet_bayes | AC8: rf_bayes | AD8: xgb_bayes | AE8: nn1_bayes | AF8: qv | AG8: garp | AH8: vm | AI8: sv | AJ8: sm | AK8: smcj | AL8: fac_inc_cs_value | AM8: fac_payout_yield | AN8: fac_bs_cs_value | AO8: fac_ts_value | AP8: fac_interm_momentum | AQ8: fac_st_momentum | AR8: fac_lt_profit_growth | AS8: fac_st_profit_growth | AT8: fac_surprise | AU8: fac_bs_profitability | AV8: fac_profit_margins | AW8: fac_quality | AX8: fac_mkt_risk | AY8: fac_leverage | AZ8: fac_profit_vol | BA8: fac_seasonality | BB8: fac_short_interest | BC8: fac_acc_growth | BD8: fac_accruals | BE8: fac_issuance | BF8: fac_st_reversal | BG8: fac_skewness | BH8: fac_max | BI8: fac_lt_reversal | BJ8: fac_macro | BK8: fac_liquidity | BL8: fac_size
A9: WIZC3 | B9: 0.012 | C9: =B9-E9 -> 0.012 | D9: =B9-K9 -> 0 | E9: =K9-L9 -> 0 | F9: 3.612 | G9: 3.564 | H9: defensives | I9: =VLOOKUP(A9,Setores!$A$2:$C$215,2,0) -> financial_services | J9: =VLOOKUP(A9,Setores!$A$2:$C$215,3,0) -> very_low_beta | K9: 0.012 | L9: 0.012 | M9: 0.37509688 | N9: =VLOOKUP(A9,'Mandato LP'!$A$2:$B$215,2,0) -> 0.014603918 | O9: =K9-N9 -> -0.002603918 | P9: =B9-N9 -> -0.002603918 | Q9: =VLOOKUP(A9,'Mandato LP'!$A$2:$C$215,3,0) -> 0.011989198 | R9: =K9-Q9 -> 1.080188e-05 | S9: 1 | T9: 0.966 | U9: 1 | V9: 1 | W9: 1 | X9: 1 | Y9: 1 | Z9: 0.631 | AA9: 0.724 | AB9: 0.723 | AC9: 1 | AD9: 1 | AE9: 0.99 | AF9: 1 | AG9: 0.205 | AH9: 0.421 | AI9: 0.546 | AJ9: 0.997 | AK9: 1 | AL9: 0.551 | AM9: -0.187 | AN9: -0.263 | AO9: 0.055 | AP9: 0.036 | AQ9: 0.118 | AR9: 0.271 | AS9: 0.157 | AT9: -0.346 | AU9: 0.724 | AV9: 0.403 | AW9: 1 | AX9: 0.363 | AY9: -0.062 | AZ9: 0.804 | BA9: 0.496 | BB9: -0.043 | BC9: 0.05 | BD9: 0.06 | BE9: 0.535 | BF9: -0.021 | BG9: 1 | BH9: 0.641 | BI9: -0.361 | BJ9: -0.367 | BK9: 0.614 | BL9: 0.693
A10: BMGB4 | B10: 0.012 | C10: =B10-E10 -> 0.012 | D10: =B10-K10 -> 0 | E10: =K10-L10 -> 0 | F10: 3.612 | G10: 3.605 | H10: pro_cyclicals | I10: =VLOOKUP(A10,Setores!$A$2:$C$215,2,0) -> banks | J10: =VLOOKUP(A10,Setores!$A$2:$C$215,3,0) -> high_beta | K10: 0.012 | L10: 0.012 | M10: 0.45753333 | N10: =VLOOKUP(A10,'Mandato LP'!$A$2:$B$215,2,0) -> 0.014603918 | O10: =K10-N10 -> -0.002603918 | P10: =B10-N10 -> -0.002603918 | Q10: =VLOOKUP(A10,'Mandato LP'!$A$2:$C$215,3,0) -> 0.011989198 | R10: =K10-Q10 -> 1.080188e-05 | S10: 0.902 | T10: 1 | U10: 0.817 | V10: 0.911 | W10: 1 | X10: 1 | Y10: 1 | Z10: 1 | AA10: 1 | AB10: 1 | AC10: 1 | AD10: 1 | AE10: 1 | AF10: 0.194 | AG10: 1 | AH10: 1 | AI10: 0.251 | AJ10: 1 | AK10: 0.23 | AL10: 0.073 | AM10: 0.54 | AN10: 0.42 | AO10: 0.223 | AP10: 0.561 | AQ10: 0.813 | AR10: 0.557 | AS10: 0.25 | AT10: -0.139 | AU10: 0.002 | AV10: -0.267 | AW10: -0.131 | AX10: 0.515 | AY10: -0.09 | AZ10: 0.655 | BA10: 0.249 | BB10: -0.003 | BC10: 0.126 | BD10: 0.215 | BE10: -0.732 | BF10: -0.363 | BG10: 0.186 | BH10: 0.936 | BI10: -0.81 | BJ10: 0.082 | BK10: 0.64 | BL10: 0.679
A11: LOGG3 | B11: 0.01 | C11: =B11-E11 -> 0.008 | D11: =B11-K11 -> 0.001 | E11: =K11-L11 -> 0.002 | F11: 3.612 | G11: 4.113 | H11: bond_proxies | I11: =VLOOKUP(A11,Setores!$A$2:$C$215,2,0) -> real_estate | J11: =VLOOKUP(A11,Setores!$A$2:$C$215,3,0) -> neutral_beta | K11: 0.009 | L11: 0.007 | M11: 2.2479335 | N11: =VLOOKUP(A11,'Mandato LP'!$A$2:$B$215,2,0) -> 0.016604721 | O11: =K11-N11 -> -0.0076047206 | P11: =B11-N11 -> -0.0066047206 | Q11: =VLOOKUP(A11,'Mandato LP'!$A$2:$C$215,3,0) -> 0.011182919 | R11: =K11-Q11 -> -0.0021829191 | S11: 0.753 | T11: 1 | U11: 0.511 | V11: 0.896 | W11: 0.882 | X11: 0.996 | Y11: 1 | Z11: 1 | AA11: 0.535 | AB11: 0.54 | AC11: 1 | AD11: 0.991 | AE11: 1 | AF11: 1 | AG11: 0.092 | AH11: 0.797 | AI11: 0.298 | AJ11: 0.918 | AK11: -0.122 | AL11: -0.204 | AM11: 0.327 | AN11: -0.17 | AO11: 0.033 | AP11: 0.439 | AQ11: 0.023 | AR11: -0.072 | AS11: 0.527 | AT11: 0.52 | AU11: -0.109 | AV11: 0.759 | AW11: 0.419 | AX11: 0.344 | AY11: -0.735 | AZ11: 0.03 | BA11: -0.262 | BB11: -0.245 | BC11: 0.135 | BD11: 0.593 | BE11: 0.51 | BF11: -0.351 | BG11: -0.122 | BH11: 0.728 | BI11: -0.416 | BJ11: 0.223 | BK11: 0.369 | BL11: 0.297
A12: FIQE3 | B12: 0.009 | C12: =B12-E12 -> 0.009 | D12: =B12-K12 -> 0 | E12: =K12-L12 -> 0 | F12: 3.612 | G12: 3.629 | H12: bond_proxies | I12: =VLOOKUP(A12,Setores!$A$2:$C$215,2,0) -> telecom | J12: =VLOOKUP(A12,Setores!$A$2:$C$215,3,0) -> low_beta | K12: 0.009 | L12: 0.009 | M12: 0.36297066 | N12: =VLOOKUP(A12,'Mandato LP'!$A$2:$B$215,2,0) -> 0.014603918 | O12: =K12-N12 -> -0.005603918 | P12: =B12-N12 -> -0.005603918 | Q12: =VLOOKUP(A12,'Mandato LP'!$A$2:$C$215,3,0) -> 0.011989198 | R12: =K12-Q12 -> -0.0029891981 | S12: 1 | T12: 1 | U12: 0.642 | V12: 1 | W12: 0.938 | X12: 1 | Y12: 1 | Z12: 1 | AA12: 0.687 | AB12: 0.689 | AC12: 1 | AD12: 1 | AE12: 1 | AF12: 0.557 | AG12: 0.002 | AH12: 0.805 | AI12: -0.261 | AJ12: 1 | AK12: 0.752 | AL12: -0.205 | AM12: 0.133 | AN12: -0.805 | AO12: 0.064 | AP12: 0.751 | AQ12: 1 | AR12: 0.293 | AS12: 0.405 | AT12: 0.475 | AU12: 0.417 | AV12: 0.26 | AW12: 0.767 | AX12: 0.426 | AY12: 0.179 | AZ12: 0.885 | BA12: 0.104 | BB12: 0.583 | BC12: -0.299 | BD12: -0.201 | BE12: 0.293 | BF12: -0.371 | BG12: 0.371 | BH12: 0.682 | BI12: -0.527 | BJ12: -0.401 | BK12: 0.717 | BL12: 0.495
A13: JHSF3 | B13: 0.0125 | C13: =B13-E13 -> 0.0085 | D13: =B13-K13 -> 0.0045 | E13: =K13-L13 -> 0.004 | F13: 3.612 | G13: 3.895 | H13: pro_cyclicals | I13: =VLOOKUP(A13,Setores!$A$2:$C$215,2,0) -> homebuilders | J13: =VLOOKUP(A13,Setores!$A$2:$C$215,3,0) -> very_high_beta | K13: 0.008 | L13: 0.004 | M13: 0.44893281 | N13: =VLOOKUP(A13,'Mandato LP'!$A$2:$B$215,2,0) -> 0.020861103 | O13: =K13-N13 -> -0.012861103 | P13: =B13-N13 -> -0.008361103 | Q13: =VLOOKUP(A13,'Mandato LP'!$A$2:$C$215,3,0) -> 0.017126082 | R13: =K13-Q13 -> -0.0091260819 | S13: 1 | T13: 1 | U13: 0.606 | V13: 1 | W13: 1 | X13: 1 | Y13: 0.973 | Z13: 1 | AA13: 0.695 | AB13: 0.691 | AC13: 0.929 | AD13: 0.859 | AE13: 1 | AF13: 1 | AG13: 0.938 | AH13: 1 | AI13: -0.415 | AJ13: 0.728 | AK13: 0.253 | AL13: 0.296 | AM13: -0.053 | AN13: -0.411 | AO13: 0.313 | AP13: 0.632 | AQ13: 0.927 | AR13: 0.532 | AS13: 0.182 | AT13: 0.309 | AU13: 0.33 | AV13: 0.414 | AW13: 0.908 | AX13: -0.045 | AY13: 0.136 | AZ13: -0.176 | BA13: 0.537 | BB13: -0.253 | BC13: 0.008 | BD13: 0.541 | BE13: 0.647 | BF13: 0.217 | BG13: 0.151 | BH13: 0.142 | BI13: -0.857 | BJ13: 0.704 | BK13: -0.051 | BL13: -0.258
A14: ALLD3 | B14: 0.01 | C14: =B14-E14 -> 0.01 | D14: =B14-K14 -> 0.004 | E14: =K14-L14 -> 0 | F14: 3.612 | G14: 2.778 | H14: pro_cyclicals | I14: =VLOOKUP(A14,Setores!$A$2:$C$215,2,0) -> consumer_durables | J14: =VLOOKUP(A14,Setores!$A$2:$C$215,3,0) -> very_low_beta | K14: 0.006 | L14: 0.006 | M14: 2.1306249 | N14: =VLOOKUP(A14,'Mandato LP'!$A$2:$B$215,2,0) -> 0.014603918 | O14: =K14-N14 -> -0.008603918 | P14: =B14-N14 -> -0.004603918 | Q14: =VLOOKUP(A14,'Mandato LP'!$A$2:$C$215,3,0) -> 0.0093931854 | R14: =K14-Q14 -> -0.0033931854 | S14: 1 | T14: 0.646 | U14: 1 | V14: 1 | W14: 1 | X14: 1 | Y14: 1 | Z14: 0.737 | AA14: 1 | AB14: 1 | AC14: 0.735 | AD14: 0.749 | AE14: 0.928 | AF14: 1 | AG14: 1 | AH14: -0.138 | AI14: 1 | AJ14: -0.315 | AK14: 1 | AL14: 0.882 | AM14: 1 | AN14: 0.451 | AO14: 0.652 | AP14: -0.808 | AQ14: -0.665 | AR14: 0.303 | AS14: 0.594 | AT14: 0.097 | AU14: 0.697 | AV14: -0.548 | AW14: 0.908 | AX14: 0.326 | AY14: 0.054 | AZ14: 0.47 | BA14: 0.604 | BB14: 0.25 | BC14: 0.292 | BD14: 0.303 | BE14: 0.594 | BF14: 0.043 | BG14: 0.097 | BH14: 0.907 | BI14: -0.345 | BJ14: -0.437 | BK14: 0.521 | BL14: 0.802
A15: RIAA3 | B15: 0.008 | C15: =B15-E15 -> 0.008 | D15: =B15-K15 -> 0 | E15: =K15-L15 -> 0 | F15: 3.529 | G15: 2.738 | H15: pro_cyclicals | I15: =VLOOKUP(A15,Setores!$A$2:$C$215,2,0) -> apparel | J15: =VLOOKUP(A15,Setores!$A$2:$C$215,3,0) -> very_high_beta | K15: 0.008 | L15: 0.008 | M15: 1.1310544 | N15: =VLOOKUP(A15,'Mandato LP'!$A$2:$B$215,2,0) -> 0.014269527 | O15: =K15-N15 -> -0.0062695275 | P15: =B15-N15 -> -0.0062695275 | Q15: =VLOOKUP(A15,'Mandato LP'!$A$2:$C$215,3,0) -> 0.0093190118 | R15: =K15-Q15 -> -0.0013190118 | S15: 0.993 | T15: 0.849 | U15: 0.797 | V15: 1 | W15: 0.969 | X15: 0.786 | Y15: 0.514 | Z15: 0.755 | AA15: 0.757 | AB15: 0.752 | AC15: 0.778 | AD15: 0.798 | AE15: 0.956 | AF15: 1 | AG15: 1 | AH15: 0.418 | AI15: 0.137 | AJ15: 0.133 | AK15: 0.61 | AL15: 0.556 | AM15: 0.091 | AN15: -0.118 | AO15: 0.478 | AP15: 0.227 | AQ15: -0.081 | AR15: 0.584 | AS15: 0.768 | AT15: 0.384 | AU15: 0.428 | AV15: -0.1 | AW15: 0.958 | AX15: -0.591 | AY15: 0.077 | AZ15: 0.423 | BA15: 0.629 | BB15: -0.314 | BC15: 0.211 | BD15: 0.019 | BE15: 0.625 | BF15: 0.234 | BG15: -0.288 | BH15: 0.204 | BI15: -0.488 | BJ15: 0.292 | BK15: 0.253 | BL15: 0.206
A16: GRND3 | B16: 0.012 | C16: =B16-E16 -> 0.01 | D16: =B16-K16 -> 0 | E16: =K16-L16 -> 0.002 | F16: 3.497 | G16: 3.883 | H16: pro_cyclicals | I16: =VLOOKUP(A16,Setores!$A$2:$C$215,2,0) -> apparel | J16: =VLOOKUP(A16,Setores!$A$2:$C$215,3,0) -> very_low_beta | K16: 0.012 | L16: 0.01 | M16: 0.75574802 | N16: =VLOOKUP(A16,'Mandato LP'!$A$2:$B$215,2,0) -> 0.015304377 | O16: =K16-N16 -> -0.0033043767 | P16: =B16-N16 -> -0.0033043767 | Q16: =VLOOKUP(A16,'Mandato LP'!$A$2:$C$215,3,0) -> 0.009244726 | R16: =K16-Q16 -> 0.002755274 | S16: 0.737 | T16: 0.61 | U16: 0.678 | V16: 0.687 | W16: 0.675 | X16: 1 | Y16: 1 | Z16: 0.978 | AA16: 0.556 | AB16: 0.559 | AC16: 0.894 | AD16: 0.839 | AE16: 0.891 | AF16: 0.847 | AG16: 0.063 | AH16: -0.123 | AI16: 0.027 | AJ16: 0.129 | AK16: 0.847 | AL16: 0.135 | AM16: 0.948 | AN16: -0.477 | AO16: 0.54 | AP16: 0.169 | AQ16: -0.258 | AR16: -0.023 | AS16: 0.299 | AT16: -0.168 | AU16: 0.205 | AV16: 0.159 | AW16: 0.17 | AX16: 0.518 | AY16: 0.774 | AZ16: 0.495 | BA16: -0.049 | BB16: 0.102 | BC16: 0.553 | BD16: 0.507 | BE16: 0.546 | BF16: 0.211 | BG16: 0.048 | BH16: 0.829 | BI16: -0.075 | BJ16: -0.358 | BK16: 0.197 | BL16: 0.347
A17: HBRE3 | B17: 0.007 | C17: =B17-E17 -> 0.007 | D17: =B17-K17 -> 0 | E17: =K17-L17 -> 0 | F17: 3.378 | G17: 2.591 | H17: bond_proxies | I17: =VLOOKUP(A17,Setores!$A$2:$C$215,2,0) -> real_estate | J17: =VLOOKUP(A17,Setores!$A$2:$C$215,3,0) -> very_high_beta | K17: 0.007 | L17: 0.007 | M17: 0.38847621 | N17: =VLOOKUP(A17,'Mandato LP'!$A$2:$B$215,2,0) -> 0.013657989 | O17: =K17-N17 -> -0.0066579891 | P17: =B17-N17 -> -0.0066579891 | Q17: =VLOOKUP(A17,'Mandato LP'!$A$2:$C$215,3,0) -> 0.0070157204 | R17: =K17-Q17 -> -1.5720448e-05 | S17: 1 | T17: 1 | U17: 1 | V17: 0.702 | W17: 1 | X17: 0.86 | Y17: 0.81 | Z17: 0.47 | AA17: 0.557 | AB17: 0.556 | AC17: 0.644 | AD17: 0.81 | AE17: 0.978 | AF17: 0.237 | AG17: 1 | AH17: 1 | AI17: 1 | AJ17: 0.384 | AK17: -0.225 | AL17: 0.75 | AM17: -0.02 | AN17: 1 | AO17: 0.775 | AP17: -0.097 | AQ17: -0.185 | AR17: -0.221 | AS17: 0.343 | AT17: 0.114 | AU17: -0.228 | AV17: 0.47 | AW17: -0.336 | AX17: -0.048 | AY17: -0.714 | AZ17: -0.344 | BA17: 0.126 | BB17: 0.847 | BC17: 0.166 | BD17: 0.739 | BE17: 0.326 | BF17: -0.001 | BG17: 0.315 | BH17: 0.283 | BI17: 0.154 | BJ17: 0.819 | BK17: 0.621 | BL17: 0.974
A18: POMO3 | B18: 0.01 | C18: =B18-E18 -> 0.008 | D18: =B18-K18 -> 0 | E18: =K18-L18 -> 0.002 | F18: 3.324 | G18: 3.092 | H18: industrials | I18: =VLOOKUP(A18,Setores!$A$2:$C$215,2,0) -> capital_goods | J18: =VLOOKUP(A18,Setores!$A$2:$C$215,3,0) -> neutral_beta | K18: 0.01 | L18: 0.008 | M18: 0.65941919 | N18: =VLOOKUP(A18,'Mandato LP'!$A$2:$B$215,2,0) -> 0.015002818 | O18: =K18-N18 -> -0.0050028175 | P18: =B18-N18 -> -0.0050028175 | Q18: =VLOOKUP(A18,'Mandato LP'!$A$2:$C$215,3,0) -> 0.010481845 | R18: =K18-Q18 -> -0.0004818445 | S18: 0.621 | T18: 0.14 | U18: 0.397 | V18: 0.923 | W18: 0.539 | X18: 0.848 | Y18: 0.816 | Z18: 1 | AA18: 0.632 | AB18: 0.633 | AC18: 0.946 | AD18: 0.86 | AE18: 0.854 | AF18: 1 | AG18: 0.59 | AH18: 0.154 | AI18: -0.454 | AJ18: -0.03 | AK18: 0.096 | AL18: -0.035 | AM18: 0.628 | AN18: -0.685 | AO18: 0.375 | AP18: 0.287 | AQ18: 0.448 | AR18: 0.599 | AS18: 0.283 | AT18: -0.498 | AU18: 0.614 | AV18: -0.337 | AW18: 0.644 | AX18: 0.41 | AY18: 0.114 | AZ18: 0.843 | BA18: 0.741 | BB18: 0.226 | BC18: -0.159 | BD18: -0.188 | BE18: 0.438 | BF18: -0.417 | BG18: 0.146 | BH18: 0.346 | BI18: -0.961 | BJ18: 0.172 | BK18: 0.73 | BL18: -0.151
A19: MTRE3 | B19: 0.015 | C19: =B19-E19 -> 0.015 | D19: =B19-K19 -> 0 | E19: =K19-L19 -> 0 | F19: 3.23 | G19: 3.494 | H19: pro_cyclicals | I19: =VLOOKUP(A19,Setores!$A$2:$C$215,2,0) -> homebuilders | J19: =VLOOKUP(A19,Setores!$A$2:$C$215,3,0) -> low_beta | K19: 0.015 | L19: 0.015 | M19: 0.52897669 | N19: =VLOOKUP(A19,'Mandato LP'!$A$2:$B$215,2,0) -> 0.013061017 | O19: =K19-N19 -> 0.0019389826 | P19: =B19-N19 -> 0.0019389826 | Q19: =VLOOKUP(A19,'Mandato LP'!$A$2:$C$215,3,0) -> 0.0098796697 | R19: =K19-Q19 -> 0.0051203303 | S19: 0.688 | T19: 0.794 | U19: 0.801 | V19: 0.52 | W19: 0.767 | X19: 0.688 | Y19: 0.667 | Z19: 0.602 | AA19: 0.676 | AB19: 0.672 | AC19: 1 | AD19: 0.934 | AE19: 0.937 | AF19: -0.026 | AG19: 1 | AH19: 0.535 | AI19: 1 | AJ19: 0.456 | AK19: 0.016 | AL19: 0.147 | AM19: 0.699 | AN19: 0.319 | AO19: 0.416 | AP19: -0.131 | AQ19: -0.245 | AR19: 0.252 | AS19: 0.546 | AT19: 0.171 | AU19: -0.031 | AV19: -0.327 | AW19: -0.239 | AX19: -0.015 | AY19: -0.326 | AZ19: 0.678 | BA19: 0.185 | BB19: 0.058 | BC19: -0.186 | BD19: -0.07 | BE19: 0.244 | BF19: -0.151 | BG19: 0.367 | BH19: 0.853 | BI19: -0.061 | BJ19: 0.12 | BK19: 0.609 | BL19: 0.875
A20: MLAS3 | B20: 0.005 | C20: =B20-E20 -> 0.005 | D20: =B20-K20 -> 0 | E20: =K20-L20 -> 0 | F20: 2.937 | G20: 2.18 | H20: pro_cyclicals | I20: =VLOOKUP(A20,Setores!$A$2:$C$215,2,0) -> tech | J20: =VLOOKUP(A20,Setores!$A$2:$C$215,3,0) -> high_beta | K20: 0.005 | L20: 0.005 | M20: 0.016823221 | N20: =VLOOKUP(A20,'Mandato LP'!$A$2:$B$215,2,0) -> 0.011875837 | O20: =K20-N20 -> -0.0068758375 | P20: =B20-N20 -> -0.0068758375 | Q20: =VLOOKUP(A20,'Mandato LP'!$A$2:$C$215,3,0) -> 0.011989198 | R20: =K20-Q20 -> -0.0069891981 | S20: 1 | T20: 1 | U20: 1 | V20: 1 | W20: 1 | X20: 0.184 | Y20: -0.575 | Z20: 0.389 | AA20: 0.348 | AB20: 0.347 | AC20: 0.766 | AD20: 0.793 | AE20: 1 | AF20: 1 | AG20: 1 | AH20: 1 | AI20: 0.588 | AJ20: 0.898 | AK20: 1 | AL20: 0.424 | AM20: -0.809 | AN20: 0.445 | AO20: 0.341 | AP20: 0.355 | AQ20: 0.382 | AR20: 0.7 | AS20: 0.664 | AT20: 0.366 | AU20: 0.137 | AV20: -0.445 | AW20: 0.858 | AX20: -0.528 | AY20: 0.358 | AZ20: 0.413 | BA20: -0.318 | BB20: 0.932 | BC20: 0.336 | BD20: 0.234 | BE20: 0.799 | BF20: -1 | BG20: -0.382 | BH20: -1 | BI20: 0.533 | BJ20: -0.127 | BK20: 0.917 | BL20: 0.464
... A219: PMAM3 | B219: 0 | C219: =B219-E219 -> 0 | D219: =B219-K219 -> 0 | E219: =K219-L219 -> 0 | F219: 0.477 | G219: 0.336 | H219: commodities | I219: =VLOOKUP(A219,Setores!$A$2:$C$215,2,0) -> basic_materials | J219: =VLOOKUP(A219,Setores!$A$2:$C$215,3,0) -> high_beta | K219: 0 | L219: 0 | M219: 0 | N219: =VLOOKUP(A219,'Mandato LP'!$A$2:$B$215,2,0) -> 0 | O219: =K219-N219 -> 0 | P219: =B219-N219 -> 0 | Q219: =VLOOKUP(A219,'Mandato LP'!$A$2:$C$215,3,0) -> 0 | R219: =K219-Q219 -> 0 | S219: -0.996 | T219: -1 | U219: -0.933 | V219: -1 | W219: -1 | X219: -1 | Y219: -1 | Z219: -1 | AA219: -1 | AB219: -1 | AC219: -1 | AD219: -1 | AE219: -1 | AF219: -1 | AG219: -0.823 | AH219: -1 | AI219: -0.48 | AJ219: -0.264 | AK219: -0.397 | AL219: -0.585 | AM219: -1 | AN219: -0.957 | AO219: -0.017 | AP219: -0.585 | AQ219: -0.378 | AR219: 0.171 | AS219: -0.502 | AT219: -0.356 | AU219: -0.783 | AV219: -0.819 | AW219: -0.417 | AX219: -0.492 | AY219: -0.774 | AZ219: -0.87 | BA219: -0.621 | BB219: -0.477 | BC219: 0.853 | BD219: 0.755 | BE219: -0.023 | BF219: 0.62 | BG219: 0.698 | BH219: -0.708 | BI219: 1 | BJ219: -0.02 | BK219: 0.689 | BL219: 0.965
I244: Rótulos de Linha | J244: Soma de MF | K244: Soma de MF - LP | L244: Soma de META | M244: Soma de act_weights | N244: Soma de mandato | O244: Soma de modelo 2.0
I245: bond_proxies | J245: 0.1935 | K245: -0.0625 | L245: 0.183 | M245: -0.073 | N245: 0.19616391 | O245: 0.1736052
I246: real_estate | J246: 0.052 | K246: 0.024 | L246: 0.051 | M246: 0.023 | N246: 0.076829933 | O246: 0.031544688
I247: telecom | J247: 0.054 | K247: 0.024 | L247: 0.058 | M247: 0.028 | N247: 0.060668786 | O247: 0.011989198
I248: transportation | J248: 0 | K248: -0.002 | L248: 0 | M248: -0.002 | N248: 0 | O248: 0
I249: utilities | J249: 0.0875 | K249: -0.1085 | L249: 0.074 | M249: -0.122 | N249: 0.058665188 | O249: 0.13007131
I250: commodities | J250: 0.232 | K250: -0.026 | L250: 0.222 | M250: -0.036 | N250: 0.19212425 | O250: 0.26194675
I251: basic_materials | J251: 0.096 | K251: -0.009 | L251: 0.11 | M251: 0.005 | N251: 0.055036797 | O251: 0.081390469
I252: crude_oil | J252: 0.123 | K252: -0.001 | L252: 0.099 | M252: -0.025 | N252: 0.13126439 | O252: 0.16769456
I253: food | J253: 0.013 | K253: -0.016 | L253: 0.013 | M253: -0.016 | N253: 0.005823059 | O253: 0.012861723
I254: defensives | J254: 0.11 | K254: 0.013 | L254: 0.112 | M254: 0.015 | N254: 0.10658917 | O254: 0.13550587
I255: consumer_staples | J255: 0 | K255: -0.013 | L255: 0 | M255: -0.013 | N255: 0 | O255: 0.012211113
I256: financial_services | J256: 0.012 | K256: 0.012 | L256: 0.012 | M256: 0.012 | N256: 0.014603918 | O256: 0.011989198
... I272: transportation | J272: 0.004 | K272: 0 | L272: 0.004 | M272: 0 | N272: 0.0069135825 | O272: 0.0067950064
I273: (vazio)
I274: (vazio)
I275: Total Geral | J275: 1 | K275: 0.006 | L275: 1 | M275: 0.006 | N275: 1 | O275: 1
H294: tickers | J294: legacy_ticker | K294: large_payers_bench_weights
H295: h102_ON | J295: BBAS3 | K295: 0.03643361
H296: h1045_PN | J296: ALPA4 | K296: 0
H297: h1159_PNB | J297: UNIP6 | K297: 0.00436304
H298: h1176_ON | J298: VULC3 | K298: 0.00260697
H299: h1193_ON | J299: MYPK3 | K299: 0
H300: h1197_PN | J300: AZEV4 | K300: 0
H301: h121_PNB | J301: BRSR6 | K301: 0.00461228
H302: h1257_ON | J302: RCSL3 | K302: 0
H303: h1257_PN | J303: RCSL4 | K303: 0
H304: h1265_ON | J304: KLBN3 | K304: 0
H305: h1265_PN | J305: KLBN4 | K305: 0
H306: h1265_UNT | J306: KLBN11 | K306: 0.02172066
... H508: hUS0001848309_BDR_N1_NP | J508: S2GM34 | K508: 0

Sheet 37 - ISEE
B1: =COUNTIF(B9:B222,">0") -> 38 | E1: =COUNTIF(E9:E222,">0") -> 67 | K1: Act Share | L1: Bmk | M1: Mandato | N1: Modelo 2.0 | O1: Meta | R1: Modelos | AE1: Interações | AK1: Clusters
K2: Meta | L2: =SQRT(SUMSQ(L9:L222)^2) -> 0.022827 | M2: =SQRT(SUMSQ(N9:N222)^2) -> 0.073015388 | N2: =SQRT(SUMSQ(Q9:Q222)^2) -> 0.041852868
E3: MF - Meta | F3: =SUMPRODUCT($D$9:$D$222,F9:F222) -> 0.062452 | K3: MF | L3: =SQRT(SUMSQ(C9:C222)^2) -> 0.021455 | M3: =SQRT(SUMSQ(O9:O222)^2) -> 0.040534391 | O3: =SQRT(SUMSQ(D9:D222)^2) -> 0.000383
E4: Meta - 2.0 | F4: =SUMPRODUCT($Q$9:$Q$222,F9:F222) -> 0.034543138 | Q4: MF - Meta | R4: =SUMPRODUCT($D$9:$D$226,R9:R226) -> 0.037585 | S4: =SUMPRODUCT($D$9:$D$226,S9:S226) -> 0.034379 | T4: =SUMPRODUCT($D$9:$D$226,T9:T226) -> 0.037804 | U4: =SUMPRODUCT($D$9:$D$226,U9:U226) -> 0.034273 | V4: =SUMPRODUCT($D$9:$D$226,V9:V226) -> 0.039319 | W4: =SUMPRODUCT($D$9:$D$226,W9:W226) -> 0.027454 | X4: =SUMPRODUCT($D$9:$D$226,X9:X226) -> 0.01877 | Y4: =SUMPRODUCT($D$9:$D$226,Y9:Y226) -> 0.029156 | ... BK4: =SUMPRODUCT($D$9:$D$226,BK9:BK226) -> 0.022976
E5: Meta - Mandato | F5: =SUMPRODUCT($O$9:$O$222,F9:F222) -> -0.43261611 | Q5: Meta - 2.0 | R5: =SUMPRODUCT($Q$9:$Q$226,R9:R226) -> 0.05308614 | S5: =SUMPRODUCT($Q$9:$Q$226,S9:S226) -> -0.024449984 | T5: =SUMPRODUCT($Q$9:$Q$226,T9:T226) -> 0.13445274 | U5: =SUMPRODUCT($Q$9:$Q$226,U9:U226) -> 0.024543499 | V5: =SUMPRODUCT($Q$9:$Q$226,V9:V226) -> 0.074111708 | W5: =SUMPRODUCT($Q$9:$Q$226,W9:W226) -> 0.044055233 | X5: =SUMPRODUCT($Q$9:$Q$226,X9:X226) -> 0.081397496 | Y5: =SUMPRODUCT($Q$9:$Q$226,Y9:Y226) -> 0.022847824 | ... BK5: =SUMPRODUCT($Q$9:$Q$226,BK9:BK226) -> 0.15393458
E6: Meta - Bmk | F6: =SUMPRODUCT($L$9:$L$222,F9:F222) -> 0.468367 | G6: =SUMPRODUCT($L$9:$L$222,G9:G222) -> 0.649737 | Q6: Meta - Mandato | R6: =SUMPRODUCT($O$9:$O$226,R9:R226) -> -0.21597169 | S6: =SUMPRODUCT($O$9:$O$226,S9:S226) -> -0.18287059 | T6: =SUMPRODUCT($O$9:$O$226,T9:T226) -> -0.092801236 | U6: =SUMPRODUCT($O$9:$O$226,U9:U226) -> -0.26911445 | V6: =SUMPRODUCT($O$9:$O$226,V9:V226) -> -0.18396119 | W6: =SUMPRODUCT($O$9:$O$226,W9:W226) -> -0.23063888 | X6: =SUMPRODUCT($O$9:$O$226,X9:X226) -> -0.22061254 | Y6: =SUMPRODUCT($O$9:$O$226,Y9:Y226) -> -0.19591368 | ... BK6: =SUMPRODUCT($O$9:$O$226,BK9:BK226) -> 0.037309358
B7: =SUM(B9:B222) -> 1 | E7: =SUM(E9:E222) -> 1.003 | F7: =SUMPRODUCT($L$9:$L$226,F9:F226) -> 0.468367 | G7: =SUMPRODUCT($L$9:$L$226,G9:G226) -> 0.649737 | K7: =SUM(K9:K222) -> 1.003 | N7: =SUM(N9:N222) -> 1 | P7: =SUM(P9:P222) -> 1 | Q7: Meta - Bmk | R7: =SUMPRODUCT($L$9:$L$226,R9:R226) -> 0.318006 | S7: =SUMPRODUCT($L$9:$L$226,S9:S226) -> 0.304338 | T7: =SUMPRODUCT($L$9:$L$226,T9:T226) -> 0.249244 | U7: =SUMPRODUCT($L$9:$L$226,U9:U226) -> 0.331126 | V7: =SUMPRODUCT($L$9:$L$226,V9:V226) -> 0.282441 | W7: =SUMPRODUCT($L$9:$L$226,W9:W226) -> 0.348156 | X7: =SUMPRODUCT($L$9:$L$226,X9:X226) -> 0.336476 | Y7: =SUMPRODUCT($L$9:$L$226,Y9:Y226) -> 0.32992 | ... BK7: =SUMPRODUCT($L$9:$L$226,BK9:BK226) -> 0.169073
A8: tickers | B8: MF | C8: MF - ISEE | D8: MF - META | E8: Bmk | F8: exp_ret_score_raw | G8: exp_ret_score | H8: sectors_c2 | I8: sectors_c1 | J8: sectors_dyn | K8: META | L8: act_weights | M8: isee_bench_weights | N8: mandato | O8: Meta - Mandato | P8: modelo 2.0 | Q8: Meta - 2.0 | R8: ew | S8: sw_mom | T8: sw_val | U8: sw_lt_perf | V8: sw_overall | W8: rp_cc | X8: hrp_cc | Y8: mvo_overall_cc_con | Z8: ols | AA8: glmnet_bayes | AB8: rf_bayes | AC8: xgb_bayes | AD8: nn1_bayes | AE8: qv | AF8: garp | AG8: vm | AH8: sv | AI8: sm | AJ8: smcj | AK8: fac_inc_cs_value | AL8: fac_payout_yield | AM8: fac_bs_cs_value | AN8: fac_ts_value | AO8: fac_interm_momentum | AP8: fac_st_momentum | AQ8: fac_lt_profit_growth | AR8: fac_st_profit_growth | AS8: fac_surprise | AT8: fac_bs_profitability | AU8: fac_profit_margins | AV8: fac_quality | AW8: fac_mkt_risk | AX8: fac_leverage | AY8: fac_profit_vol | AZ8: fac_seasonality | BA8: fac_short_interest | BB8: fac_acc_growth | BC8: fac_accruals | BD8: fac_issuance | BE8: fac_st_reversal | BF8: fac_skewness | BG8: fac_max | BH8: fac_lt_reversal | BI8: fac_macro | BJ8: fac_liquidity | BK8: fac_size
A9: JHSF3 | B9: 0.005 | C9: =B9-E9 -> 0.005 | D9: =B9-K9 -> 0.005 | E9: =M9 -> 0 | F9: 3.612 | G9: 3.376 | H9: pro_cyclicals | I9: =VLOOKUP(A9,Setores!$A$2:$C$215,2,0) -> homebuilders | J9: =VLOOKUP(A9,Setores!$A$2:$C$215,3,0) -> very_high_beta | K9: 0 | L9: 0 | M9: 0 | N9: =VLOOKUP(A9,'Mandato ISEE'!$A$1:$C$215,2,0) -> 0 | O9: =K9-N9 -> 0 | P9: =VLOOKUP(A9,'Mandato ISEE'!$A$1:$C$215,3,0) -> 0 | Q9: =K9-P9 -> 0 | R9: 1 | S9: 1 | T9: 0.606 | U9: 1 | V9: 1 | W9: 1 | X9: 0.973 | Y9: 1 | Z9: 0.695 | AA9: 0.691 | AB9: 0.929 | AC9: 0.859 | AD9: 1 | AE9: 1 | AF9: 0.938 | AG9: 1 | AH9: -0.415 | AI9: 0.728 | AJ9: 0.253 | AK9: 0.296 | AL9: -0.053 | AM9: -0.411 | AN9: 0.313 | AO9: 0.632 | AP9: 0.927 | AQ9: 0.532 | AR9: 0.182 | AS9: 0.309 | AT9: 0.33 | AU9: 0.414 | AV9: 0.908 | AW9: -0.045 | AX9: 0.136 | AY9: -0.176 | AZ9: 0.537 | BA9: -0.253 | BB9: 0.008 | BC9: 0.541 | BD9: 0.647 | BE9: 0.217 | BF9: 0.151 | BG9: 0.142 | BH9: -0.857 | BI9: 0.704 | BJ9: -0.051 | BK9: -0.258
A10: LOGG3 | B10: 0 | C10: =B10-E10 -> 0 | D10: =B10-K10 -> 0 | E10: =M10 -> 0 | F10: 3.612 | G10: 3.865 | H10: bond_proxies | I10: =VLOOKUP(A10,Setores!$A$2:$C$215,2,0) -> real_estate | J10: =VLOOKUP(A10,Setores!$A$2:$C$215,3,0) -> neutral_beta | K10: 0 | L10: 0 | M10: 0 | N10: =VLOOKUP(A10,'Mandato ISEE'!$A$1:$C$215,2,0) -> 0 | O10: =K10-N10 -> 0 | P10: =VLOOKUP(A10,'Mandato ISEE'!$A$1:$C$215,3,0) -> 0 | Q10: =K10-P10 -> 0 | R10: 0.753 | S10: 1 | T10: 0.511 | U10: 0.896 | V10: 0.882 | W10: 0.996 | X10: 1 | Y10: 1 | Z10: 0.535 | AA10: 0.54 | AB10: 1 | AC10: 0.991 | AD10: 1 | AE10: 1 | AF10: 0.092 | AG10: 0.797 | AH10: 0.298 | AI10: 0.918 | AJ10: -0.122 | AK10: -0.204 | AL10: 0.327 | AM10: -0.17 | AN10: 0.033 | AO10: 0.439 | AP10: 0.023 | AQ10: -0.072 | AR10: 0.527 | AS10: 0.52 | AT10: -0.109 | AU10: 0.759 | AV10: 0.419 | AW10: 0.344 | AX10: -0.735 | AY10: 0.03 | AZ10: -0.262 | BA10: -0.245 | BB10: 0.135 | BC10: 0.593 | BD10: 0.51 | BE10: -0.351 | BF10: -0.122 | BG10: 0.728 | BH10: -0.416 | BI10: 0.223 | BJ10: 0.369 | BK10: 0.297
A11: WIZC3 | B11: 0 | C11: =B11-E11 -> 0 | D11: =B11-K11 -> 0 | E11: =M11 -> 0 | F11: 3.612 | G11: 3.555 | H11: defensives | I11: =VLOOKUP(A11,Setores!$A$2:$C$215,2,0) -> financial_services | J11: =VLOOKUP(A11,Setores!$A$2:$C$215,3,0) -> very_low_beta | K11: 0 | L11: 0 | M11: 0 | N11: =VLOOKUP(A11,'Mandato ISEE'!$A$1:$C$215,2,0) -> 0 | O11: =K11-N11 -> 0 | P11: =VLOOKUP(A11,'Mandato ISEE'!$A$1:$C$215,3,0) -> 0 | Q11: =K11-P11 -> 0 | R11: 1 | S11: 0.966 | T11: 1 | U11: 1 | V11: 1 | W11: 1 | X11: 1 | Y11: 0.631 | Z11: 0.724 | AA11: 0.723 | AB11: 1 | AC11: 1 | AD11: 0.99 | AE11: 1 | AF11: 0.205 | AG11: 0.421 | AH11: 0.546 | AI11: 0.997 | AJ11: 1 | AK11: 0.551 | AL11: -0.187 | AM11: -0.263 | AN11: 0.055 | AO11: 0.036 | AP11: 0.118 | AQ11: 0.271 | AR11: 0.157 | AS11: -0.346 | AT11: 0.724 | AU11: 0.403 | AV11: 1 | AW11: 0.363 | AX11: -0.062 | AY11: 0.804 | AZ11: 0.496 | BA11: -0.043 | BB11: 0.05 | BC11: 0.06 | BD11: 0.535 | BE11: -0.021 | BF11: 1 | BG11: 0.641 | BH11: -0.361 | BI11: -0.367 | BJ11: 0.614 | BK11: 0.693
A12: BMGB4 | B12: =K12 -> 0 | C12: =B12-E12 -> 0 | D12: =B12-K12 -> 0 | E12: =M12 -> 0 | F12: 3.612 | G12: 3.597 | H12: pro_cyclicals | I12: =VLOOKUP(A12,Setores!$A$2:$C$215,2,0) -> banks | J12: =VLOOKUP(A12,Setores!$A$2:$C$215,3,0) -> high_beta | K12: 0 | L12: 0 | M12: 0 | N12: =VLOOKUP(A12,'Mandato ISEE'!$A$1:$C$215,2,0) -> 0 | O12: =K12-N12 -> 0 | P12: =VLOOKUP(A12,'Mandato ISEE'!$A$1:$C$215,3,0) -> 0 | Q12: =K12-P12 -> 0 | R12: 0.902 | S12: 1 | T12: 0.817 | U12: 0.911 | V12: 1 | W12: 1 | X12: 1 | Y12: 1 | Z12: 1 | AA12: 1 | AB12: 1 | AC12: 1 | AD12: 1 | AE12: 0.194 | AF12: 1 | AG12: 1 | AH12: 0.251 | AI12: 1 | AJ12: 0.23 | AK12: 0.073 | AL12: 0.54 | AM12: 0.42 | AN12: 0.223 | AO12: 0.561 | AP12: 0.813 | AQ12: 0.557 | AR12: 0.25 | AS12: -0.139 | AT12: 0.002 | AU12: -0.267 | AV12: -0.131 | AW12: 0.515 | AX12: -0.09 | AY12: 0.655 | AZ12: 0.249 | BA12: -0.003 | BB12: 0.126 | BC12: 0.215 | BD12: -0.732 | BE12: -0.363 | BF12: 0.186 | BG12: 0.936 | BH12: -0.81 | BI12: 0.082 | BJ12: 0.64 | BK12: 0.679
A13: ALLD3 | B13: =K13 -> 0 | C13: =B13-E13 -> 0 | D13: =B13-K13 -> 0 | E13: =M13 -> 0 | F13: 3.612 | G13: 2.763 | H13: pro_cyclicals | I13: =VLOOKUP(A13,Setores!$A$2:$C$215,2,0) -> consumer_durables | J13: =VLOOKUP(A13,Setores!$A$2:$C$215,3,0) -> very_low_beta | K13: 0 | L13: 0 | M13: 0 | N13: =VLOOKUP(A13,'Mandato ISEE'!$A$1:$C$215,2,0) -> 0 | O13: =K13-N13 -> 0 | P13: =VLOOKUP(A13,'Mandato ISEE'!$A$1:$C$215,3,0) -> 0 | Q13: =K13-P13 -> 0 | R13: 1 | S13: 0.646 | T13: 1 | U13: 1 | V13: 1 | W13: 1 | X13: 1 | Y13: 0.737 | Z13: 1 | AA13: 1 | AB13: 0.735 | AC13: 0.749 | AD13: 0.928 | AE13: 1 | AF13: 1 | AG13: -0.138 | AH13: 1 | AI13: -0.315 | AJ13: 1 | AK13: 0.882 | AL13: 1 | AM13: 0.451 | AN13: 0.652 | AO13: -0.808 | AP13: -0.665 | AQ13: 0.303 | AR13: 0.594 | AS13: 0.097 | AT13: 0.697 | AU13: -0.548 | AV13: 0.908 | AW13: 0.326 | AX13: 0.054 | AY13: 0.47 | AZ13: 0.604 | BA13: 0.25 | BB13: 0.292 | BC13: 0.303 | BD13: 0.594 | BE13: 0.043 | BF13: 0.097 | BG13: 0.907 | BH13: -0.345 | BI13: -0.437 | BJ13: 0.521 | BK13: 0.802
A14: FIQE3 | B14: =K14 -> 0 | C14: =B14-E14 -> 0 | D14: =B14-K14 -> 0 | E14: =M14 -> 0 | F14: 3.612 | G14: 3.622 | H14: bond_proxies | I14: =VLOOKUP(A14,Setores!$A$2:$C$215,2,0) -> telecom | J14: =VLOOKUP(A14,Setores!$A$2:$C$215,3,0) -> low_beta | K14: 0 | L14: 0 | M14: 0 | N14: =VLOOKUP(A14,'Mandato ISEE'!$A$1:$C$215,2,0) -> 0 | O14: =K14-N14 -> 0 | P14: =VLOOKUP(A14,'Mandato ISEE'!$A$1:$C$215,3,0) -> 0 | Q14: =K14-P14 -> 0 | R14: 1 | S14: 1 | T14: 0.642 | U14: 1 | V14: 0.938 | W14: 1 | X14: 1 | Y14: 1 | Z14: 0.687 | AA14: 0.689 | AB14: 1 | AC14: 1 | AD14: 1 | AE14: 0.557 | AF14: 0.002 | AG14: 0.805 | AH14: -0.261 | AI14: 1 | AJ14: 0.752 | AK14: -0.205 | AL14: 0.133 | AM14: -0.805 | AN14: 0.064 | AO14: 0.751 | AP14: 1 | AQ14: 0.293 | AR14: 0.405 | AS14: 0.475 | AT14: 0.417 | AU14: 0.26 | AV14: 0.767 | AW14: 0.426 | AX14: 0.179 | AY14: 0.885 | AZ14: 0.104 | BA14: 0.583 | BB14: -0.299 | BC14: -0.201 | BD14: 0.293 | BE14: -0.371 | BF14: 0.371 | BG14: 0.682 | BH14: -0.527 | BI14: -0.401 | BJ14: 0.717 | BK14: 0.495
A15: RIAA3 | B15: =K15 -> 0.016 | C15: =B15-E15 -> 0.015 | D15: =B15-K15 -> 0 | E15: =M15 -> 0.001 | F15: 3.529 | G15: 2.754 | H15: pro_cyclicals | I15: =VLOOKUP(A15,Setores!$A$2:$C$215,2,0) -> apparel | J15: =VLOOKUP(A15,Setores!$A$2:$C$215,3,0) -> very_high_beta | K15: 0.016 | L15: 0.014 | M15: 0.001 | N15: =VLOOKUP(A15,'Mandato ISEE'!$A$1:$C$215,2,0) -> 0.046826126 | O15: =K15-N15 -> -0.030826126 | P15: =VLOOKUP(A15,'Mandato ISEE'!$A$1:$C$215,3,0) -> 0.025488817 | Q15: =K15-P15 -> -0.0094888173 | R15: 0.993 | S15: 0.849 | T15: 0.797 | U15: 1 | V15: 0.969 | W15: 0.786 | X15: 0.514 | Y15: 0.755 | Z15: 0.757 | AA15: 0.752 | AB15: 0.778 | AC15: 0.798 | AD15: 0.956 | AE15: 1 | AF15: 1 | AG15: 0.418 | AH15: 0.137 | AI15: 0.133 | AJ15: 0.61 | AK15: 0.556 | AL15: 0.091 | AM15: -0.118 | AN15: 0.478 | AO15: 0.227 | AP15: -0.081 | AQ15: 0.584 | AR15: 0.768 | AS15: 0.384 | AT15: 0.428 | AU15: -0.1 | AV15: 0.958 | AW15: -0.591 | AX15: 0.077 | AY15: 0.423 | AZ15: 0.629 | BA15: -0.314 | BB15: 0.211 | BC15: 0.019 | BD15: 0.625 | BE15: 0.234 | BF15: -0.288 | BG15: 0.204 | BH15: -0.488 | BI15: 0.292 | BJ15: 0.253 | BK15: 0.206
A16: GRND3 | B16: 0.005 | C16: =B16-E16 -> 0.005 | D16: =B16-K16 -> 0.005 | E16: =M16 -> 0 | F16: 3.497 | G16: 3.72 | H16: pro_cyclicals | I16: =VLOOKUP(A16,Setores!$A$2:$C$215,2,0) -> apparel | J16: =VLOOKUP(A16,Setores!$A$2:$C$215,3,0) -> very_low_beta | K16: 0 | L16: 0 | M16: 0 | N16: =VLOOKUP(A16,'Mandato ISEE'!$A$1:$C$215,2,0) -> 0 | O16: =K16-N16 -> 0 | P16: =VLOOKUP(A16,'Mandato ISEE'!$A$1:$C$215,3,0) -> 0 | Q16: =K16-P16 -> 0 | R16: 0.737 | S16: 0.61 | T16: 0.678 | U16: 0.687 | V16: 0.675 | W16: 1 | X16: 1 | Y16: 0.978 | Z16: 0.556 | AA16: 0.559 | AB16: 0.894 | AC16: 0.839 | AD16: 0.891 | AE16: 0.847 | AF16: 0.063 | AG16: -0.123 | AH16: 0.027 | AI16: 0.129 | AJ16: 0.847 | AK16: 0.135 | AL16: 0.948 | AM16: -0.477 | AN16: 0.54 | AO16: 0.169 | AP16: -0.258 | AQ16: -0.023 | AR16: 0.299 | AS16: -0.168 | AT16: 0.205 | AU16: 0.159 | AV16: 0.17 | AW16: 0.518 | AX16: 0.774 | AY16: 0.495 | AZ16: -0.049 | BA16: 0.102 | BB16: 0.553 | BC16: 0.507 | BD16: 0.546 | BE16: 0.211 | BF16: 0.048 | BG16: 0.829 | BH16: -0.075 | BI16: -0.358 | BJ16: 0.197 | BK16: 0.347
A17: HBRE3 | B17: =K17 -> 0 | C17: =B17-E17 -> 0 | D17: =B17-K17 -> 0 | E17: =M17 -> 0 | F17: 3.378 | G17: 2.577 | H17: bond_proxies | I17: =VLOOKUP(A17,Setores!$A$2:$C$215,2,0) -> real_estate | J17: =VLOOKUP(A17,Setores!$A$2:$C$215,3,0) -> very_high_beta | K17: 0 | L17: 0 | M17: 0 | N17: =VLOOKUP(A17,'Mandato ISEE'!$A$1:$C$215,2,0) -> 0 | O17: =K17-N17 -> 0 | P17: =VLOOKUP(A17,'Mandato ISEE'!$A$1:$C$215,3,0) -> 0 | Q17: =K17-P17 -> 0 | R17: 1 | S17: 1 | T17: 1 | U17: 0.702 | V17: 1 | W17: 0.86 | X17: 0.81 | Y17: 0.47 | Z17: 0.557 | AA17: 0.556 | AB17: 0.644 | AC17: 0.81 | AD17: 0.978 | AE17: 0.237 | AF17: 1 | AG17: 1 | AH17: 1 | AI17: 0.384 | AJ17: -0.225 | AK17: 0.75 | AL17: -0.02 | AM17: 1 | AN17: 0.775 | AO17: -0.097 | AP17: -0.185 | AQ17: -0.221 | AR17: 0.343 | AS17: 0.114 | AT17: -0.228 | AU17: 0.47 | AV17: -0.336 | AW17: -0.048 | AX17: -0.714 | AY17: -0.344 | AZ17: 0.126 | BA17: 0.847 | BB17: 0.166 | BC17: 0.739 | BD17: 0.326 | BE17: -0.001 | BF17: 0.315 | BG17: 0.283 | BH17: 0.154 | BI17: 0.819 | BJ17: 0.621 | BK17: 0.974
A18: POMO3 | B18: =K18 -> 0 | C18: =B18-E18 -> 0 | D18: =B18-K18 -> 0 | E18: =M18 -> 0 | F18: 3.324 | G18: 2.963 | H18: industrials | I18: =VLOOKUP(A18,Setores!$A$2:$C$215,2,0) -> capital_goods | J18: =VLOOKUP(A18,Setores!$A$2:$C$215,3,0) -> neutral_beta | K18: 0 | L18: 0 | M18: 0 | N18: =VLOOKUP(A18,'Mandato ISEE'!$A$1:$C$215,2,0) -> 0 | O18: =K18-N18 -> 0 | P18: =VLOOKUP(A18,'Mandato ISEE'!$A$1:$C$215,3,0) -> 0 | Q18: =K18-P18 -> 0 | R18: 0.621 | S18: 0.14 | T18: 0.397 | U18: 0.923 | V18: 0.539 | W18: 0.848 | X18: 0.816 | Y18: 1 | Z18: 0.632 | AA18: 0.633 | AB18: 0.946 | AC18: 0.86 | AD18: 0.854 | AE18: 1 | AF18: 0.59 | AG18: 0.154 | AH18: -0.454 | AI18: -0.03 | AJ18: 0.096 | AK18: -0.035 | AL18: 0.628 | AM18: -0.685 | AN18: 0.375 | AO18: 0.287 | AP18: 0.448 | AQ18: 0.599 | AR18: 0.283 | AS18: -0.498 | AT18: 0.614 | AU18: -0.337 | AV18: 0.644 | AW18: 0.41 | AX18: 0.114 | AY18: 0.843 | AZ18: 0.741 | BA18: 0.226 | BB18: -0.159 | BC18: -0.188 | BD18: 0.438 | BE18: -0.417 | BF18: 0.146 | BG18: 0.346 | BH18: -0.961 | BI18: 0.172 | BJ18: 0.73 | BK18: -0.151
A19: MTRE3 | B19: =K19 -> 0.034 | C19: =B19-E19 -> 0.034 | D19: =B19-K19 -> 0 | E19: =M19 -> 0 | F19: 3.23 | G19: 3.534 | H19: pro_cyclicals | I19: =VLOOKUP(A19,Setores!$A$2:$C$215,2,0) -> homebuilders | J19: =VLOOKUP(A19,Setores!$A$2:$C$215,3,0) -> low_beta | K19: 0.034 | L19: 0.033 | M19: 0 | N19: =VLOOKUP(A19,'Mandato ISEE'!$A$1:$C$215,2,0) -> 0.040785259 | O19: =K19-N19 -> -0.0067852591 | P19: =VLOOKUP(A19,'Mandato ISEE'!$A$1:$C$215,3,0) -> 0.018467466 | Q19: =K19-P19 -> 0.015532534 | R19: 0.688 | S19: 0.794 | T19: 0.801 | U19: 0.52 | V19: 0.767 | W19: 0.688 | X19: 0.667 | Y19: 0.602 | Z19: 0.676 | AA19: 0.672 | AB19: 1 | AC19: 0.934 | AD19: 0.937 | AE19: -0.026 | AF19: 1 | AG19: 0.535 | AH19: 1 | AI19: 0.456 | AJ19: 0.016 | AK19: 0.147 | AL19: 0.699 | AM19: 0.319 | AN19: 0.416 | AO19: -0.131 | AP19: -0.245 | AQ19: 0.252 | AR19: 0.546 | AS19: 0.171 | AT19: -0.031 | AU19: -0.327 | AV19: -0.239 | AW19: -0.015 | AX19: -0.326 | AY19: 0.678 | AZ19: 0.185 | BA19: 0.058 | BB19: -0.186 | BC19: -0.07 | BD19: 0.244 | BE19: -0.151 | BF19: 0.367 | BG19: 0.853 | BH19: -0.061 | BI19: 0.12 | BJ19: 0.609 | BK19: 0.875
A20: MLAS3 | B20: =K20 -> 0 | C20: =B20-E20 -> 0 | D20: =B20-K20 -> 0 | E20: =M20 -> 0 | F20: 2.937 | G20: 2.169 | H20: pro_cyclicals | I20: =VLOOKUP(A20,Setores!$A$2:$C$215,2,0) -> tech | J20: =VLOOKUP(A20,Setores!$A$2:$C$215,3,0) -> high_beta | K20: 0 | L20: 0 | M20: 0 | N20: =VLOOKUP(A20,'Mandato ISEE'!$A$1:$C$215,2,0) -> 0 | O20: =K20-N20 -> 0 | P20: =VLOOKUP(A20,'Mandato ISEE'!$A$1:$C$215,3,0) -> 0 | Q20: =K20-P20 -> 0 | R20: 1 | S20: 1 | T20: 1 | U20: 1 | V20: 1 | W20: 0.184 | X20: -0.575 | Y20: 0.389 | Z20: 0.348 | AA20: 0.347 | AB20: 0.766 | AC20: 0.793 | AD20: 1 | AE20: 1 | AF20: 1 | AG20: 1 | AH20: 0.588 | AI20: 0.898 | AJ20: 1 | AK20: 0.424 | AL20: -0.809 | AM20: 0.445 | AN20: 0.341 | AO20: 0.355 | AP20: 0.382 | AQ20: 0.7 | AR20: 0.664 | AS20: 0.366 | AT20: 0.137 | AU20: -0.445 | AV20: 0.858 | AW20: -0.528 | AX20: 0.358 | AY20: 0.413 | AZ20: -0.318 | BA20: 0.932 | BB20: 0.336 | BC20: 0.234 | BD20: 0.799 | BE20: -1 | BF20: -0.382 | BG20: -1 | BH20: 0.533 | BI20: -0.127 | BJ20: 0.917 | BK20: 0.464
A21: BRAP3 | B21: =K21 -> 0 | C21: =B21-E21 -> 0 | D21: =B21-K21 -> 0 | E21: =M21 -> 0 | F21: 2.92 | G21: 3.671 | H21: commodities | I21: =VLOOKUP(A21,Setores!$A$2:$C$215,2,0) -> basic_materials | J21: =VLOOKUP(A21,Setores!$A$2:$C$215,3,0) -> low_beta | K21: 0 | L21: 0 | M21: 0 | N21: =VLOOKUP(A21,'Mandato ISEE'!$A$1:$C$215,2,0) -> 0 | O21: =K21-N21 -> 0 | P21: =VLOOKUP(A21,'Mandato ISEE'!$A$1:$C$215,3,0) -> 0 | Q21: =K21-P21 -> 0 | R21: 0.087 | S21: 0.432 | T21: -0.19 | U21: 0.2 | V21: 0.191 | W21: 0.582 | X21: 0.73 | Y21: 0.879 | Z21: 0.973 | AA21: 0.968 | AB21: 0.789 | AC21: 0.787 | AD21: 1 | AE21: -0.129 | AF21: -0.587 | AG21: 0.444 | AH21: -0.638 | AI21: 0.171 | AJ21: -0.491 | AK21: -0.306 | AL21: 0.66 | AM21: -0.439 | AN21: -0.489 | AO21: 0.799 | AP21: 0.125 | AQ21: -0.776 | AR21: 0.686 | AS21: 0.407 | AT21: 0.044 | AU21: 0.072 | AV21: 0.119 | AW21: 0.676 | AX21: 0.086 | AY21: 0.614 | AZ21: -0.941 | BA21: 0.867 | BB21: -0.091 | BC21: 0.377 | BD21: 0.583 | BE21: -0.457 | BF21: -0.004 | BG21: 0.718 | BH21: -0.349 | BI21: -0.532 | BJ21: 1 | BK21: 0.096
A22: SYNE3 | B22: =K22 -> 0 | C22: =B22-E22 -> 0 | D22: =B22-K22 -> 0 | E22: =M22 -> 0 | F22: 2.901 | G22: 2.256 | H22: bond_proxies | I22: =VLOOKUP(A22,Setores!$A$2:$C$215,2,0) -> real_estate | J22: =VLOOKUP(A22,Setores!$A$2:$C$215,3,0) -> low_beta | K22: 0 | L22: 0 | M22: 0 | N22: =VLOOKUP(A22,'Mandato ISEE'!$A$1:$C$215,2,0) -> 0 | O22: =K22-N22 -> 0 | P22: =VLOOKUP(A22,'Mandato ISEE'!$A$1:$C$215,3,0) -> 0 | Q22: =K22-P22 -> 0 | R22: 0.611 | S22: -0.004 | T22: 1 | U22: 0.671 | V22: 0.658 | W22: 0.82 | X22: 0.983 | Y22: 0.424 | Z22: 0.42 | AA22: 0.419 | AB22: 0.894 | AC22: 0.815 | AD22: 0.751 | AE22: 1 | AF22: 1 | AG22: -0.635 | AH22: 1 | AI22: -0.185 | AJ22: 1 | AK22: 0.377 | AL22: 1 | AM22: 0.215 | AN22: -0.282 | AO22: -0.565 | AP22: -0.497 | AQ22: 0.695 | AR22: -0.375 | AS22: -0.027 | AT22: -0.119 | AU22: 0.146 | AV22: 0.379 | AW22: 0.238 | AX22: -0.358 | AY22: 0.053 | AZ22: -0.182 | BA22: 0.007 | BB22: 0.602 | BC22: 0.73 | BD22: 0.622 | BE22: -0.114 | BF22: -0.537 | BG22: 0.542 | BH22: -0.852 | BI22: 0.099 | BJ22: 0.669 | BK22: 0.822
A23: BRSR6 | B23: 0.005 | C23: =B23-E23 -> 0.005 | D23: =B23-K23 -> 0.005 | E23: =M23 -> 0 | F23: 2.834 | G23: 2.975 | H23: pro_cyclicals | I23: =VLOOKUP(A23,Setores!$A$2:$C$215,2,0) -> banks | J23: =VLOOKUP(A23,Setores!$A$2:$C$215,3,0) -> neutral_beta | K23: 0 | L23: 0 | M23: 0 | N23: =VLOOKUP(A23,'Mandato ISEE'!$A$1:$C$215,2,0) -> 0 | O23: =K23-N23 -> 0 | P23: =VLOOKUP(A23,'Mandato ISEE'!$A$1:$C$215,3,0) -> 0 | Q23: =K23-P23 -> 0 | R23: 0.249 | S23: 0.528 | T23: -0.031 | U23: 0.371 | V23: 0.361 | W23: 0.534 | X23: 0.672 | Y23: 0.571 | Z23: 0.912 | AA23: 0.911 | AB23: 0.863 | AC23: 0.914 | AD23: 0.945 | AE23: -0.077 | AF23: 0.651 | AG23: 0.924 | AH23: -0.038 | AI23: -0.273 | AJ23: -0.625 | AK23: -0.058 | AL23: 0.32 | AM23: 0.583 | AN23: 0.342 | AO23: 0.114 | AP23: -0.514 | AQ23: 0.138 | AR23: 0.321 | AS23: 0.241 | AT23: -0.162 | AU23: -0.238 | AV23: -0.212 | AW23: 0.442 | AX23: -0.393 | AY23: 0.67 | AZ23: 0.393 | BA23: 0.657 | BB23: -0.409 | BC23: -0.234 | BD23: 0.34 | BE23: -0.044 | BF23: 0.291 | BG23: 0.958 | BH23: -0.478 | BI23: -0.089 | BJ23: 0.203 | BK23: 0.426
A24: MILS3 | B24: =K24 -> 0.027 | C24: =B24-E24 -> 0.024 | D24: =B24-K24 -> 0 | E24: =M24 -> 0.003 | F24: 2.64 | G24: 3.544 | H24: industrials | I24: =VLOOKUP(A24,Setores!$A$2:$C$215,2,0) -> building_materials | J24: =VLOOKUP(A24,Setores!$A$2:$C$215,3,0) -> neutral_beta | K24: 0.027 | L24: 0.024 | M24: 0.003 | N24: =VLOOKUP(A24,'Mandato ISEE'!$A$1:$C$215,2,0) -> 0.038757149 | O24: =K24-N24 -> -0.011757149 | P24: =VLOOKUP(A24,'Mandato ISEE'!$A$1:$C$215,3,0) -> 0.017070738 | Q24: =K24-P24 -> 0.0099292621 | R24: 0.499 | S24: 0.281 | T24: 0.11 | U24: 0.375 | V24: 0.126 | W24: 0.673 | X24: 0.953 | Y24: 0.191 | Z24: 0.702 | AA24: 0.697 | AB24: 0.904 | AC24: 0.888 | AD24: 0.845 | AE24: 0.022 | AF24: 0.116 | AG24: -0.165 | AH24: -0.341 | AI24: 0.346 | AJ24: 0.006 | AK24: -0.056 | AL24: -0.236 | AM24: -0.617 | AN24: 0.825 | AO24: 0.209 | AP24: -0.249 | AQ24: 0.34 | AR24: 0.864 | AS24: 0.258 | AT24: 0.436 | AU24: 0.442 | AV24: 0.325 | AW24: 0.397 | AX24: 0.044 | AY24: 0.384 | AZ24: 0.607 | BA24: 0.466 | BB24: -0.293 | BC24: -0.375 | BD24: 0.399 | BE24: -0.373 | BF24: -0.309 | BG24: 0.808 | BH24: -0.483 | BI24: 0.215 | BJ24: 0.295 | BK24: 0.047
A25: AURA33 | B25: =K25 -> 0 | C25: =B25-E25 -> 0 | D25: =B25-K25 -> 0 | E25: =M25 -> 0 | F25: 2.624 | G25: 1.87 | H25: commodities | I25: =VLOOKUP(A25,Setores!$A$2:$C$215,2,0) -> basic_materials | J25: =VLOOKUP(A25,Setores!$A$2:$C$215,3,0) -> very_high_beta | K25: 0 | L25: 0 | M25: 0 | N25: =VLOOKUP(A25,'Mandato ISEE'!$A$1:$C$215,2,0) -> 0 | O25: =K25-N25 -> 0 | P25: =VLOOKUP(A25,'Mandato ISEE'!$A$1:$C$215,3,0) -> 0 | Q25: =K25-P25 -> 0 | R25: 0.33 | S25: 0.658 | T25: -0.467 | U25: 0.589 | V25: 0.203 | W25: 0.227 | X25: -0.08 | Y25: 0.47 | Z25: 1 | AA25: 1 | AB25: 0.871 | AC25: 0.996 | AD25: 0.966 | AE25: -0.265 | AF25: -0.508 | AG25: 1 | AH25: -0.754 | AI25: 0.041 | AJ25: -0.678 | AK25: 0.101 | AL25: -0.546 | AM25: -0.202 | AN25: -0.543 | AO25: 0.834 | AP25: 0.811 | AQ25: 0.495 | AR25: 0.922 | AS25: 0.363 | AT25: 0.956 | AU25: 0.373 | AV25: 0.835 | AW25: 0.046 | AX25: 0.167 | AY25: -0.353 | AZ25: 0.141 | BA25: 0.657 | BB25: -0.282 | BC25: 0.33 | BD25: 0.646 | BE25: 1 | BF25: -0.364 | BG25: -0.786 | BH25: -1 | BI25: 0.361 | BJ25: -0.019 | BK25: -0.455
A26: BRAP4 | B26: =K26 -> 0 | C26: =B26-E26 -> 0 | D26: =B26-K26 -> 0 | E26: =M26 -> 0 | F26: 2.61 | G26: 3.212 | H26: commodities | I26: =VLOOKUP(A26,Setores!$A$2:$C$215,2,0) -> basic_materials | J26: =VLOOKUP(A26,Setores!$A$2:$C$215,3,0) -> neutral_beta | K26: 0 | L26: 0 | M26: 0 | N26: =VLOOKUP(A26,'Mandato ISEE'!$A$1:$C$215,2,0) -> 0 | O26: =K26-N26 -> 0 | P26: =VLOOKUP(A26,'Mandato ISEE'!$A$1:$C$215,3,0) -> 0 | Q26: =K26-P26 -> 0 | R26: -0.117 | S26: 0.408 | T26: -0.566 | U26: 0.127 | V26: 0.055 | W26: 0.433 | X26: 0.593 | Y26: 0.848 | Z26: 0.813 | AA26: 0.809 | AB26: 0.865 | AC26: 0.767 | AD26: 0.939 | AE26: -0.158 | AF26: -0.605 | AG26: 0.574 | AH26: -0.65 | AI26: 0.298 | AJ26: -0.491 | AK26: -0.306 | AL26: 0.621 | AM26: -0.439 | AN26: -0.491 | AO26: 0.871 | AP26: 0.225 | AQ26: -0.772 | AR26: 0.686 | AS26: 0.403 | AT26: 0.044 | AU26: 0.12 | AV26: 0.119 | AW26: 0.563 | AX26: 0.02 | AY26: 0.553 | AZ26: -0.787 | BA26: 0.341 | BB26: -0.091 | BC26: 0.377 | BD26: 0.602 | BE26: -0.327 | BF26: 0.335 | BG26: 0.673 | BH26: -0.403 | BI26: -0.36 | BJ26: -0.277 | BK26: 0.096
A27: INTB3 | B27: 0.005 | C27: =B27-E27 -> 0.005 | D27: =B27-K27 -> 0.005 | E27: =M27 -> 0 | F27: 2.602 | G27: 2.246 | H27: pro_cyclicals | I27: =VLOOKUP(A27,Setores!$A$2:$C$215,2,0) -> tech | J27: =VLOOKUP(A27,Setores!$A$2:$C$215,3,0) -> high_beta | K27: 0 | L27: 0 | M27: 0 | N27: =VLOOKUP(A27,'Mandato ISEE'!$A$1:$C$215,2,0) -> 0 | O27: =K27-N27 -> 0 | P27: =VLOOKUP(A27,'Mandato ISEE'!$A$1:$C$215,3,0) -> 0 | Q27: =K27-P27 -> 0 | R27: 0.713 | S27: 0.611 | T27: 0.232 | U27: 0.683 | V27: 0.433 | W27: 0.275 | X27: -0.007 | Y27: 0.343 | Z27: 0.233 | AA27: 0.236 | AB27: 0.994 | AC27: 0.89 | AD27: 0.877 | AE27: 0.834 | AF27: -0.139 | AG27: 0.116 | AH27: -0.401 | AI27: 0.139 | AJ27: 0.278 | AK27: 0.113 | AL27: -0.288 | AM27: -0.698 | AN27: 0.721 | AO27: 0.292 | AP27: 0.791 | AQ27: 0.076 | AR27: 0.815 | AS27: 0.804 | AT27: 0.594 | AU27: -0.229 | AV27: 0.842 | AW27: 0.182 | AX27: 0.495 | AY27: 0.755 | AZ27: -0.271 | BA27: 0.618 | BB27: 0.087 | BC27: 0.413 | BD27: 0.444 | BE27: -0.994 | BF27: -1 | BG27: -0.447 | BH27: 0.165 | BI27: 0.038 | BJ27: 0.025 | BK27: -0.151
A28: SEER3 | B28: =K28 -> 0 | C28: =B28-E28 -> 0 | D28: =B28-K28 -> 0 | E28: =M28 -> 0 | F28: 2.593 | G28: 1.862 | H28: pro_cyclicals | I28: =VLOOKUP(A28,Setores!$A$2:$C$215,2,0) -> education | J28: =VLOOKUP(A28,Setores!$A$2:$C$215,3,0) -> high_beta | K28: 0 | L28: 0 | M28: 0 | N28: =VLOOKUP(A28,'Mandato ISEE'!$A$1:$C$215,2,0) -> 0 | O28: =K28-N28 -> 0 | P28: =VLOOKUP(A28,'Mandato ISEE'!$A$1:$C$215,3,0) -> 0 | Q28: =K28-P28 -> 0 | R28: 0.799 | S28: 0.628 | T28: 0.588 | U28: 0.725 | V28: 0.601 | W28: 0.413 | X28: 0.161 | Y28: 0.164 | Z28: 0.2 | AA28: 0.2 | AB28: 0.822 | AC28: 0.583 | AD28: 0.888 | AE28: 0.877 | AF28: 0.457 | AG28: 0.337 | AH28: -0.034 | AI28: 1 | AJ28: 1 | AK28: 0.184 | AL28: -0.76 | AM28: -0.528 | AN28: 0.457 | AO28: 0.25 | AP28: 0.472 | AQ28: 0.472 | AR28: 0.559 | AS28: 0.038 | AT28: 0.459 | AU28: 0.08 | AV28: 0.998 | AW28: -0.629 | AX28: 0.002 | AY28: 0.747 | AZ28: 0.525 | BA28: 0.273 | BB28: -0.008 | BC28: 0.049 | BD28: 0.526 | BE28: -0.135 | BF28: 0.544 | BG28: 0.223 | BH28: -0.623 | BI28: 0.273 | BJ28: -0.049 | BK28: 0.547
A29: PETR4 | B29: =K29 -> 0 | C29: =B29-E29 -> 0 | D29: =B29-K29 -> 0 | E29: =M29 -> 0 | F29: 2.559 | G29: 2.825 | H29: commodities | I29: =VLOOKUP(A29,Setores!$A$2:$C$215,2,0) -> crude_oil | J29: =VLOOKUP(A29,Setores!$A$2:$C$215,3,0) -> very_low_beta | K29: 0 | L29: 0 | M29: 0 | N29: =VLOOKUP(A29,'Mandato ISEE'!$A$1:$C$215,2,0) -> 0 | O29: =K29-N29 -> 0 | P29: =VLOOKUP(A29,'Mandato ISEE'!$A$1:$C$215,3,0) -> 0 | Q29: =K29-P29 -> 0 | R29: -0.294 | S29: 0.28 | T29: -0.853 | U29: 0.315 | V29: -0.04 | W29: 0.447 | X29: 0.531 | Y29: 1 | Z29: 1 | AA29: 1 | AB29: 0.561 | AC29: 0.73 | AD29: 0.889 | AE29: -0.018 | AF29: -0.745 | AG29: 1 | AH29: -0.935 | AI29: -0.544 | AJ29: -0.922 | AK29: 0.151 | AL29: 0.432 | AM29: -0.542 | AN29: -0.647 | AO29: 0.944 | AP29: 1 | AQ29: -0.335 | AR29: 0.145 | AS29: 0.035 | AT29: 0.412 | AU29: 0.269 | AV29: 0.23 | AW29: 0.503 | AX29: -0.212 | AY29: 0.743 | AZ29: 0.389 | BA29: 0.391 | BB29: -0.151 | BC29: -0.213 | BD29: 0.601 | BE29: -0.679 | BF29: 0.293 | BG29: 0.392 | BH29: -0.907 | BI29: -1 | BJ29: -0.247 | BK29: -0.898
A30: PINE4 | B30: =K30 -> 0 | C30: =B30-E30 -> 0 | D30: =B30-K30 -> 0 | E30: =M30 -> 0 | F30: 2.523 | G30: 1.932 | H30: pro_cyclicals | I30: =VLOOKUP(A30,Setores!$A$2:$C$215,2,0) -> banks | J30: =VLOOKUP(A30,Setores!$A$2:$C$215,3,0) -> neutral_beta | K30: 0 | L30: 0 | M30: 0 | N30: =VLOOKUP(A30,'Mandato ISEE'!$A$1:$C$215,2,0) -> 0 | O30: =K30-N30 -> 0 | P30: =VLOOKUP(A30,'Mandato ISEE'!$A$1:$C$215,3,0) -> 0 | Q30: =K30-P30 -> 0 | R30: 0.326 | S30: 0.392 | T30: 0.235 | U30: 0.476 | V30: 0.399 | W30: 0.138 | X30: -0.048 | Y30: 0.493 | Z30: 0.473 | AA30: 0.47 | AB30: 0.884 | AC30: 0.924 | AD30: 0.946 | AE30: -0.175 | AF30: 0.657 | AG30: 0.655 | AH30: -0.403 | AI30: 1 | AJ30: 0.653 | AK30: -0.112 | AL30: -0.07 | AM30: -0.407 | AN30: 0.058 | AO30: 0.543 | AP30: 0.466 | AQ30: 0.992 | AR30: 0.512 | AS30: -0.163 | AT30: 0.192 | AU30: -0.232 | AV30: 0.085 | AW30: 0.364 | AX30: -0.141 | AY30: 0.476 | AZ30: 0.444 | BA30: 0.333 | BB30: -0.502 | BC30: -0.023 | BD30: -0.603 | BE30: -0.496 | BF30: 0.188 | BG30: -0.108 | BH30: -1 | BI30: -0.204 | BJ30: 0.437 | BK30: 0.638
A31: POMO4 | B31: 0.005 | C31: =B31-E31 -> 0.005 | D31: =B31-K31 -> 0.005 | E31: =M31 -> 0 | F31: 2.518 | G31: 2.327 | H31: industrials | I31: =VLOOKUP(A31,Setores!$A$2:$C$215,2,0) -> capital_goods | J31: =VLOOKUP(A31,Setores!$A$2:$C$215,3,0) -> high_beta | K31: 0 | L31: 0 | M31: 0 | N31: =VLOOKUP(A31,'Mandato ISEE'!$A$1:$C$215,2,0) -> 0 | O31: =K31-N31 -> 0 | P31: =VLOOKUP(A31,'Mandato ISEE'!$A$1:$C$215,3,0) -> 0 | Q31: =K31-P31 -> 0 | R31: 0.34 | S31: -0.216 | T31: -0.007 | U31: 0.643 | V31: 0.168 | W31: 0.679 | X31: 0.757 | Y31: 0.581 | Z31: 0.311 | AA31: 0.313 | AB31: 0.798 | AC31: 0.779 | AD31: 0.693 | AE31: 1 | AF31: 0.575 | AG31: -0.214 | AH31: -0.459 | AI31: -0.306 | AJ31: 0.088 | AK31: -0.035 | AL31: 0.433 | AM31: -0.685 | AN31: 0.428 | AO31: 0.057 | AP31: 0.312 | AQ31: 0.599 | AR31: 0.283 | AS31: -0.498 | AT31: 0.614 | AU31: -0.337 | AV31: 0.639 | AW31: 0.414 | AX31: 0.114 | AY31: 0.843 | AZ31: 0.561 | BA31: 0.448 | BB31: -0.159 | BC31: -0.188 | BD31: 0.3 | BE31: -0.187 | BF31: 0.027 | BG31: 0.588 | BH31: -0.854 | BI31: 0.346 | BJ31: -0.382 | BK31: -0.151
A32: PETR3 | B32: =K32 -> 0 | C32: =B32-E32 -> 0 | D32: =B32-K32 -> 0 | E32: =M32 -> 0 | F32: 2.471 | G32: 2.472 | H32: commodities | I32: =VLOOKUP(A32,Setores!$A$2:$C$215,2,0) -> crude_oil | J32: =VLOOKUP(A32,Setores!$A$2:$C$215,3,0) -> very_low_beta | K32: 0 | L32: 0 | M32: 0 | N32: =VLOOKUP(A32,'Mandato ISEE'!$A$1:$C$215,2,0) -> 0 | O32: =K32-N32 -> 0 | P32: =VLOOKUP(A32,'Mandato ISEE'!$A$1:$C$215,3,0) -> 0 | Q32: =K32-P32 -> 0 | R32: -0.308 | S32: 0.263 | T32: -0.848 | U32: 0.265 | V32: -0.067 | W32: 0.358 | X32: 0.396 | Y32: 0.946 | Z32: 1 | AA32: 1 | AB32: 0.596 | AC32: 0.756 | AD32: 0.885 | AE32: -0.089 | AF32: -0.771 | AG32: 1 | AH32: -0.944 | AI32: -0.568 | AJ32: -0.926 | AK32: 0.151 | AL32: 0.357 | AM32: -0.542 | AN32: -0.658 | AO32: 0.935 | AP32: 1 | AQ32: -0.335 | AR32: 0.145 | AS32: 0.035 | AT32: 0.412 | AU32: 0.269 | AV32: 0.223 | AW32: 0.409 | AX32: -0.212 | AY32: 0.743 | AZ32: 0.438 | BA32: 0.498 | BB32: -0.151 | BC32: -0.213 | BD32: 0.624 | BE32: -0.705 | BF32: 0.311 | BG32: 0.27 | BH32: -0.893 | BI32: -1 | BJ32: -0.085 | BK32: -0.898
A33: CSED3 | B33: =K33 -> 0 | C33: =B33-E33 -> 0 | D33: =B33-K33 -> 0 | E33: =M33 -> 0 | F33: 2.425 | G33: 1.841 | H33: pro_cyclicals | I33: =VLOOKUP(A33,Setores!$A$2:$C$215,2,0) -> education | J33: =VLOOKUP(A33,Setores!$A$2:$C$215,3,0) -> very_high_beta | K33: 0 | L33: 0 | M33: 0 | N33: =VLOOKUP(A33,'Mandato ISEE'!$A$1:$C$215,2,0) -> 0 | O33: =K33-N33 -> 0 | P33: =VLOOKUP(A33,'Mandato ISEE'!$A$1:$C$215,3,0) -> 0 | Q33: =K33-P33 -> 0 | R33: 0.691 | S33: -0.014 | T33: 0.99 | U33: 0.688 | V33: 0.603 | W33: 0.487 | X33: 0.433 | Y33: 0.112 | Z33: 0.149 | AA33: 0.148 | AB33: 0.905 | AC33: 0.701 | AD33: 0.643 | AE33: 1 | AF33: 1 | AG33: -0.461 | AH33: 0.728 | AI33: -0.228 | AJ33: 1 | AK33: 0.633 | AL33: 0.309 | AM33: -0.392 | AN33: 0.609 | AO33: -0.624 | AP33: -0.604 | AQ33: 0.734 | AR33: 0.021 | AS33: -0.567 | AT33: 0.41 | AU33: 0.08 | AV33: 0.897 | AW33: -0.286 | AX33: 0.03 | AY33: 0.744 | AZ33: 0.218 | BA33: 0.45 | BB33: 0.098 | BC33: 0.171 | BD33: 0.268 | BE33: 1 | BF33: 1 | BG33: 0.056 | BH33: -0.295 | BI33: 0.285 | BJ33: 0.734 | BK33: 0.557
A34: OPCT3 | B34: =K34 -> 0.025 | C34: =B34-E34 -> 0.022 | D34: =B34-K34 -> 0 | E34: =M34 -> 0.003 | F34: 2.366 | G34: 2.74 | H34: commodities | I34: =VLOOKUP(A34,Setores!$A$2:$C$215,2,0) -> crude_oil | J34: =VLOOKUP(A34,Setores!$A$2:$C$215,3,0) -> very_low_beta | K34: 0.025 | L34: 0.022 | M34: 0.003 | N34: =VLOOKUP(A34,'Mandato ISEE'!$A$1:$C$215,2,0) -> 0.03394016 | O34: =K34-N34 -> -0.0089401597 | P34: =VLOOKUP(A34,'Mandato ISEE'!$A$1:$C$215,3,0) -> 0.031143675 | Q34: =K34-P34 -> -0.0061436752 | R34: 0.331 | S34: 0.409 | T34: -0.131 | U34: 0.324 | V34: 0.119 | W34: 0.484 | X34: 0.35 | Y34: 0.062 | Z34: 0.723 | AA34: 0.718 | AB34: 0.75 | AC34: 0.86 | AD34: 0.991 | AE34: -0.318 | AF34: -0.084 | AG34: 0.574 | AH34: -0.499 | AI34: 1 | AJ34: 0.29 | AK34: -0.305 | AL34: -0.943 | AM34: -0.722 | AN34: 0.556 | AO34: 0.765 | AP34: 0.74 | AQ34: 0.813 | AR34: 0.696 | AS34: 0.12 | AT34: 0.191 | AU34: -0.289 | AV34: 0.546 | AW34: 0.503 | AX34: -0.163 | AY34: 0.671 | AZ34: -0.49 | BA34: 0.966 | BB34: -0.371 | BC34: -0.73 | BD34: 0.546 | BE34: -0.593 | BF34: 0.241 | BG34: 0.809 | BH34: -0.615 | BI34: -0.838 | BJ34: 0.66 | BK34: 0.645
A35: ESPA3 | B35: =K35 -> 0 | C35: =B35-E35 -> 0 | D35: =B35-K35 -> 0 | E35: =M35 -> 0 | F35: 2.359 | G35: 1.746 | H35: pro_cyclicals | I35: =VLOOKUP(A35,Setores!$A$2:$C$215,2,0) -> consumer_services | J35: =VLOOKUP(A35,Setores!$A$2:$C$215,3,0) -> very_low_beta | K35: 0 | L35: 0 | M35: 0 | N35: =VLOOKUP(A35,'Mandato ISEE'!$A$1:$C$215,2,0) -> 0 | O35: =K35-N35 -> 0 | P35: =VLOOKUP(A35,'Mandato ISEE'!$A$1:$C$215,3,0) -> 0 | Q35: =K35-P35 -> 0 | R35: 0.847 | S35: 0.872 | T35: 1 | U35: 0.537 | V35: 0.863 | W35: 0.231 | X35: -0.08 | Y35: -0.224 | Z35: 0.215 | AA35: 0.214 | AB35: 0.807 | AC35: 0.766 | AD35: 0.792 | AE35: 0.964 | AF35: 1 | AG35: 0.189 | AH35: 1 | AI35: 0.649 | AJ35: 0.617 | AK35: 0.176 | AL35: -0.723 | AM35: 0.641 | AN35: 0.601 | AO35: -0.322 | AP35: 0.136 | AQ35: 0.471 | AR35: 0.252 | AS35: -0.143 | AT35: -0.041 | AU35: -0.282 | AV35: 0.462 | AW35: -0.194 | AX35: -0.33 | AY35: 0.943 | AZ35: -0.359 | BA35: 0.985 | BB35: 0.148 | BC35: 0.035 | BD35: 0.35 | BE35: 1 | BF35: 0.468 | BG35: 0.3 | BH35: 0.645 | BI35: -0.68 | BJ35: 0.815 | BK35: 1
A36: VTRU3 | B36: =K36 -> 0 | C36: =B36-E36 -> 0 | D36: =B36-K36 -> 0 | E36: =M36 -> 0 | F36: 2.358 | G36: 1.834 | H36: pro_cyclicals | I36: =VLOOKUP(A36,Setores!$A$2:$C$215,2,0) -> education | J36: =VLOOKUP(A36,Setores!$A$2:$C$215,3,0) -> neutral_beta | K36: 0 | L36: 0 | M36: 0 | N36: =VLOOKUP(A36,'Mandato ISEE'!$A$1:$C$215,2,0) -> 0 | O36: =K36-N36 -> 0 | P36: =VLOOKUP(A36,'Mandato ISEE'!$A$1:$C$215,3,0) -> 0 | Q36: =K36-P36 -> 0 | R36: 0.55 | S36: 0.588 | T36: 0.402 | U36: 0.602 | V36: 0.547 | W36: 0.17 | X36: 0.128 | Y36: -0.117 | Z36: 0.564 | AA36: 0.565 | AB36: 0.926 | AC36: 0.911 | AD36: 0.882 | AE36: 0.504 | AF36: 1 | AG36: 0.472 | AH36: 0.102 | AI36: 0.195 | AJ36: 0.479 | AK36: -0.04 | AL36: -0.912 | AM36: 0.172 | AN36: 0.367 | AO36: -0.056 | AP36: -0.225 | AQ36: 0.617 | AR36: 1 | AS36: 0.251 | AT36: 0.432 | AU36: 0.659 | AV36: 0.518 | AW36: -0.34 | AX36: -0.298 | AY36: 0.583 | AZ36: 0.238 | BA36: 0.65 | BB36: -0.21 | BC36: -0.646 | BD36: 0.424 | BE36: -0.813 | BF36: 0.372 | BG36: -0.075 | BH36: -0.44 | BI36: -0.157 | BJ36: 0.347 | BK36: 0.387
A37: ITSA3 | B37: =K37 -> 0 | C37: =B37-E37 -> 0 | D37: =B37-K37 -> 0 | E37: =M37 -> 0 | F37: 2.34 | G37: 3.138 | H37: pro_cyclicals | I37: =VLOOKUP(A37,Setores!$A$2:$C$215,2,0) -> banks | J37: =VLOOKUP(A37,Setores!$A$2:$C$215,3,0) -> neutral_beta | K37: 0 | L37: 0 | M37: 0 | N37: =VLOOKUP(A37,'Mandato ISEE'!$A$1:$C$215,2,0) -> 0 | O37: =K37-N37 -> 0 | P37: =VLOOKUP(A37,'Mandato ISEE'!$A$1:$C$215,3,0) -> 0 | Q37: =K37-P37 -> 0 | R37: -0.02 | S37: -0.124 | T37: -0.477 | U37: 0.216 | V37: -0.156 | W37: 0.425 | X37: 0.67 | Y37: 0.54 | Z37: 0.676 | AA37: 0.675 | AB37: 0.872 | AC37: 0.845 | AD37: 0.864 | AE37: 0.147 | AF37: -0.222 | AG37: 0.09 | AH37: -0.964 | AI37: -0.758 | AJ37: -0.816 | AK37: -0.174 | AL37: 0.211 | AM37: -0.679 | AN37: -0.208 | AO37: 0.498 | AP37: -0.056 | AQ37: 0.009 | AR37: 0.306 | AS37: 0.413 | AT37: -0.001 | AU37: -0.002 | AV37: 0.403 | AW37: 0.499 | AX37: -0.401 | AY37: 0.91 | AZ37: 0.668 | BA37: 0.967 | BB37: -0.207 | BC37: 0.014 | BD37: 0.557 | BE37: -0.215 | BF37: -0.339 | BG37: 0.841 | BH37: -0.656 | BI37: -0.146 | BJ37: 0.903 | BK37: -0.709
