Workbook

Sheet 29 - FIA
B1: =COUNTIF(B9:B222,">0") -> 70 | E1: =COUNTIF(E9:E222,">0") -> 82 | K1: Act Share | L1: Bmk | M1: Mandato | N1: Modelo 2.0 | O1: Meta | R1: Modelos | AE1: Interações | AK1: Clusters
K2: Meta | L2: =SQRT(SUMSQ(L9:L222)^2) -> 0.028648 | M2: =SQRT(SUMSQ(N9:N222)^2) -> 0.011613963 | N2: =SQRT(SUMSQ(Q9:Q222)^2) -> 0.016104689
E3: MF - Meta | F3: =SUMPRODUCT($D$9:$D$222,F9:F222) -> 0.0453245 | K3: MF | L3: =SQRT(SUMSQ(C9:C222)^2) -> 0.025881 | M3: =SQRT(SUMSQ(O9:O222)^2) -> 0.0077695005 | O3: =SQRT(SUMSQ(D9:D222)^2) -> 0.001755
E4: Meta - 2.0 | F4: =SUMPRODUCT($Q$9:$Q$222,F9:F222) -> 0.14824029 | Q4: MF - Meta | R4: =SUMPRODUCT($D$9:$D$222,R9:R222) -> 0.002224 | S4: =SUMPRODUCT($D$9:$D$222,S9:S222) -> 0.036637 | T4: =SUMPRODUCT($D$9:$D$222,T9:T222) -> -0.0214555 | U4: =SUMPRODUCT($D$9:$D$222,U9:U222) -> 0.027442 | V4: =SUMPRODUCT($D$9:$D$222,V9:V222) -> 0.024823 | W4: =SUMPRODUCT($D$9:$D$222,W9:W222) -> 0.0323545 | X4: =SUMPRODUCT($D$9:$D$222,X9:X222) -> 0.0320335 | Y4: =SUMPRODUCT($D$9:$D$222,Y9:Y222) -> 0.039434 | ... BK4: =SUMPRODUCT($D$9:$D$222,BK9:BK222) -> -0.0395335
E5: Meta - Mandato | F5: =SUMPRODUCT($N$9:$N$222,F9:F222) -> -0.29501619 | Q5: Meta - 2.0 | R5: =SUMPRODUCT($Q$9:$Q$222,R8:R221) -> 0.069992677 | S5: =SUMPRODUCT($Q$9:$Q$222,S8:S221) -> 0.059022074 | T5: =SUMPRODUCT($Q$9:$Q$222,T8:T221) -> 0.049883926 | U5: =SUMPRODUCT($Q$9:$Q$222,U8:U221) -> 0.092977471 | V5: =SUMPRODUCT($Q$9:$Q$222,V8:V221) -> 0.081574548 | W5: =SUMPRODUCT($Q$9:$Q$222,W8:W221) -> 0.067072081 | X5: =SUMPRODUCT($Q$9:$Q$222,X8:X221) -> 0.029411808 | Y5: =SUMPRODUCT($Q$9:$Q$222,Y8:Y221) -> 0.060329438 | ... BK5: =SUMPRODUCT($Q$9:$Q$222,BK8:BK221) -> 0.0021132287
E6: Meta - Bmk | F6: =SUMPRODUCT($L$9:$L$222,F9:F222) -> 0.945976 | G6: =SUMPRODUCT($L$9:$L$222,G9:G222) -> 0.491052 | Q6: Meta - Mandato | R6: =SUMPRODUCT($N$9:$N$222,R9:R222) -> -0.16380101 | S6: =SUMPRODUCT($N$9:$N$222,S9:S222) -> -0.16830965 | T6: =SUMPRODUCT($N$9:$N$222,T9:T222) -> -0.10476061 | U6: =SUMPRODUCT($N$9:$N$222,U9:U222) -> -0.20004875 | V6: =SUMPRODUCT($N$9:$N$222,V9:V222) -> -0.18217704 | W6: =SUMPRODUCT($N$9:$N$222,W9:W222) -> -0.17646254 | X6: =SUMPRODUCT($N$9:$N$222,X9:X222) -> -0.14720546 | Y6: =SUMPRODUCT($N$9:$N$222,Y9:Y222) -> -0.14473658 | ... BK6: =SUMPRODUCT($N$9:$N$222,BK9:BK222) -> -0.017758614
B7: =SUM(B9:B222) -> 1 | E7: =SUM(E9:E222) -> 1 | K7: =SUM(K9:K222) -> 1.002 | M7: =SUM(M9:M222) -> 1 | P7: =SUM(P9:P222) -> 1 | Q7: Meta - Bmk | R7: =SUMPRODUCT($L$9:$L$226,R9:R226) -> 0.645657 | S7: =SUMPRODUCT($L$9:$L$226,S9:S226) -> 0.450684 | T7: =SUMPRODUCT($L$9:$L$226,T9:T226) -> 0.715184 | U7: =SUMPRODUCT($L$9:$L$226,U9:U226) -> 0.532446 | V7: =SUMPRODUCT($L$9:$L$226,V9:V226) -> 0.608712 | W7: =SUMPRODUCT($L$9:$L$226,W9:W226) -> 0.527245 | X7: =SUMPRODUCT($L$9:$L$226,X9:X226) -> 0.437461 | Y7: =SUMPRODUCT($L$9:$L$226,Y9:Y226) -> 0.474667 | ... BK7: =SUMPRODUCT($L$9:$L$226,BK9:BK226) -> 0.589495
A8: tickers | B8: MF | C8: MF - Ibov | D8: MF - META | E8: Bmk | F8: exp_ret_score_raw | G8: exp_ret_score | H8: sectors_c2 | I8: sectors_c1 | J8: sectors_dyn | K8: META | L8: act_weights | M8: mandato | N8: META - Mandato | O8: MF - Mandao | P8: modelo 2.0 | Q8: Meta - 2.0 | R8: ew | S8: sw_mom | T8: sw_val | U8: sw_lt_perf | V8: sw_overall | W8: rp_cc | X8: hrp_cc | Y8: mvo_overall_cc_con | Z8: ols | AA8: glmnet_bayes | AB8: rf_bayes | AC8: xgb_bayes | AD8: nn1_bayes | AE8: qv | AF8: garp | AG8: vm | AH8: sv | AI8: sm | AJ8: smcj | AK8: fac_inc_cs_value | AL8: fac_payout_yield | AM8: fac_bs_cs_value | AN8: fac_ts_value | AO8: fac_interm_momentum | AP8: fac_st_momentum | AQ8: fac_lt_profit_growth | AR8: fac_st_profit_growth | AS8: fac_surprise | AT8: fac_bs_profitability | AU8: fac_profit_margins | AV8: fac_quality | AW8: fac_mkt_risk | AX8: fac_leverage | AY8: fac_profit_vol | AZ8: fac_seasonality | BA8: fac_short_interest | BB8: fac_acc_growth | BC8: fac_accruals | BD8: fac_issuance | BE8: fac_st_reversal | BF8: fac_skewness | BG8: fac_max | BH8: fac_lt_reversal | BI8: fac_macro | BJ8: fac_liquidity | BK8: fac_size
A9: WIZC3 | B9: =K9 -> 0.014 | C9: =B9-E9 -> 0.014 | D9: =B9-K9 -> 0 | E9: =K9-L9 -> 0 | F9: 3.261 | G9: 3.444 | H9: defensives | I9: =VLOOKUP(A9,Planilha6!$BL$9:$BN$222,2,0) -> financial_services | J9: =VLOOKUP(A9,Planilha6!$BL$9:$BN$222,3,0) -> low_beta | K9: 0.014 | L9: 0.014 | M9: =VLOOKUP(A9,'Mandato Ibov'!$B$1:$C$215,2,0) -> 0.014696516 | N9: =K9-M9 -> -0.00069651617 | O9: =B9-M9 -> -0.00069651617 | P9: =VLOOKUP(A9,'Mandato Ibov'!$B$2:$D$215,3,0) -> 0.010528639 | Q9: =K9-P9 -> 0.0034713605 | R9: 1 | S9: 1 | T9: 1 | U9: 1 | V9: 1 | W9: 1 | X9: 1 | Y9: 0.903 | Z9: 0.817 | AA9: 0.826 | AB9: 1 | AC9: 1 | AD9: 1 | AE9: 1 | AF9: 0.241 | AG9: 0.49 | AH9: 0.447 | AI9: 0.841 | AJ9: 1 | AK9: 0.477 | AL9: -0.271 | AM9: -0.236 | AN9: -0.056 | AO9: 0.114 | AP9: 0.015 | AQ9: 0.304 | AR9: 0.173 | AS9: 0.233 | AT9: 0.847 | AU9: 0.517 | AV9: 0.759 | AW9: 0.418 | AX9: -0.066 | AY9: 0.636 | AZ9: 1 | BA9: 0.851 | BB9: -0.177 | BC9: 0.006 | BD9: 0.393 | BE9: 0.134 | BF9: 0.783 | BG9: 0.809 | BH9: -0.469 | BI9: -0.202 | BJ9: 0.615 | BK9: 0.798 | BM9: =SUMPRODUCT(R9:AD9,$R$225:$AD$225) -> 0.9637631
A10: JHSF3 | B10: =K10 -> 0.011 | C10: =B10-E10 -> 0.011 | D10: =B10-K10 -> 0 | E10: =K10-L10 -> 0 | F10: 3.261 | G10: 3.158 | H10: pro_cyclicals | I10: =VLOOKUP(A10,Planilha6!$BL$9:$BN$222,2,0) -> homebuilders | J10: =VLOOKUP(A10,Planilha6!$BL$9:$BN$222,3,0) -> very_high_beta | K10: 0.011 | L10: 0.011 | M10: =VLOOKUP(A10,'Mandato Ibov'!$B$1:$C$215,2,0) -> 0.014696516 | N10: =K10-M10 -> -0.0036965162 | O10: =B10-M10 -> -0.0036965162 | P10: =VLOOKUP(A10,'Mandato Ibov'!$B$2:$D$215,3,0) -> 0.011222419 | Q10: =K10-P10 -> -0.00022241857 | R10: 1 | S10: 1 | T10: 0.907 | U10: 1 | V10: 1 | W10: 1 | X10: 1 | Y10: 0.989 | Z10: 0.919 | AA10: 0.922 | AB10: 0.908 | AC10: 0.952 | AD10: 1 | AE10: 1 | AF10: 1 | AG10: 1 | AH10: -0.45 | AI10: 0.31 | AJ10: 0.34 | AK10: 0.287 | AL10: -0.104 | AM10: -0.455 | AN10: 0.136 | AO10: 0.8 | AP10: 0.769 | AQ10: 0.615 | AR10: 0.414 | AS10: 0.976 | AT10: 0.525 | AU10: 0.913 | AV10: 0.997 | AW10: -0.029 | AX10: 0.216 | AY10: 0.188 | AZ10: 0.763 | BA10: 0.149 | BB10: -0.1 | BC10: 0.573 | BD10: 0.306 | BE10: -1 | BF10: 0.248 | BG10: -0.132 | BH10: -0.672 | BI10: 0.631 | BJ10: 0.025 | BK10: -0.268 | BM10: =SUMPRODUCT(R10:AD10,$R$225:$AD$225) -> 0.9805947
A11: BMGB4 | B11: =K11 -> 0.01 | C11: =B11-E11 -> 0.01 | D11: =B11-K11 -> 0 | E11: =K11-L11 -> 0 | F11: 3.261 | G11: 3.335 | H11: pro_cyclicals | I11: =VLOOKUP(A11,Planilha6!$BL$9:$BN$222,2,0) -> banks | J11: =VLOOKUP(A11,Planilha6!$BL$9:$BN$222,3,0) -> high_beta | K11: 0.01 | L11: 0.01 | M11: =VLOOKUP(A11,'Mandato Ibov'!$B$1:$C$215,2,0) -> 0.014696516 | N11: =K11-M11 -> -0.0046965162 | O11: =B11-M11 -> -0.0046965162 | P11: =VLOOKUP(A11,'Mandato Ibov'!$B$2:$D$215,3,0) -> 0.011222419 | Q11: =K11-P11 -> -0.0012224186 | R11: 0.916 | S11: 0.882 | T11: 0.789 | U11: 0.877 | V11: 0.975 | W11: 0.701 | X11: 0.542 | Y11: 0.732 | Z11: 1 | AA11: 1 | AB11: 1 | AC11: 0.973 | AD11: 1 | AE11: 0.053 | AF11: 1 | AG11: 1 | AH11: 0.061 | AI11: 0.609 | AJ11: 0.345 | AK11: 0.076 | AL11: 0.43 | AM11: 0.453 | AN11: 0.057 | AO11: 0.652 | AP11: 0.106 | AQ11: 0.544 | AR11: 1 | AS11: -0.031 | AT11: 0.056 | AU11: -0.204 | AV11: -0.217 | AW11: 0.525 | AX11: -0.14 | AY11: 0.812 | AZ11: 0.15 | BA11: -0.238 | BB11: 0.064 | BC11: 0.001 | BD11: 0.647 | BE11: -0.457 | BF11: -0.309 | BG11: 0.337 | BH11: -0.754 | BI11: 0.07 | BJ11: 0.654 | BK11: 0.642 | BM11: =SUMPRODUCT(R11:AD11,$R$225:$AD$225) -> 0.8631715
A12: RIAA3 | B12: =K12 -> 0.009 | C12: =B12-E12 -> 0.009 | D12: =B12-K12 -> 0 | E12: =K12-L12 -> 0 | F12: 3.261 | G12: 2.528 | H12: pro_cyclicals | I12: =VLOOKUP(A12,Planilha6!$BL$9:$BN$222,2,0) -> apparel | J12: =VLOOKUP(A12,Planilha6!$BL$9:$BN$222,3,0) -> very_high_beta | K12: 0.009 | L12: 0.009 | M12: =VLOOKUP(A12,'Mandato Ibov'!$B$1:$C$215,2,0) -> 0.014696516 | N12: =K12-M12 -> -0.0056965162 | O12: =B12-M12 -> -0.0056965162 | P12: =VLOOKUP(A12,'Mandato Ibov'!$B$2:$D$215,3,0) -> 0.010796721 | Q12: =K12-P12 -> -0.0017967207 | R12: 1 | S12: 1 | T12: 1 | U12: 1 | V12: 1 | W12: 0.975 | X12: 0.688 | Y12: 0.586 | Z12: 0.955 | AA12: 0.959 | AB12: 0.804 | AC12: 0.855 | AD12: 0.968 | AE12: 1 | AF12: 1 | AG12: 0.652 | AH12: 0.03 | AI12: 0.265 | AJ12: 0.681 | AK12: 0.459 | AL12: 0.101 | AM12: -0.148 | AN12: 0.505 | AO12: 0.282 | AP12: 0.441 | AQ12: 0.612 | AR12: 0.999 | AS12: 0.662 | AT12: 0.657 | AU12: 0.118 | AV12: 0.782 | AW12: -0.567 | AX12: 0.214 | AY12: 0.626 | AZ12: 0.553 | BA12: -0.497 | BB12: 0.179 | BC12: 0.057 | BD12: 0.609 | BE12: -0.773 | BF12: -0.537 | BG12: 0.242 | BH12: -0.523 | BI12: 0.428 | BJ12: 0.235 | BK12: 0.131 | BM12: =SUMPRODUCT(R12:AD12,$R$225:$AD$225) -> 0.8715232
A13: CSED3 | B13: =K13 -> 0.009 | C13: =B13-E13 -> 0.009 | D13: =B13-K13 -> 0 | E13: =K13-L13 -> 0 | F13: 3.261 | G13: 2.574 | H13: pro_cyclicals | I13: =VLOOKUP(A13,Planilha6!$BL$9:$BN$222,2,0) -> education | J13: =VLOOKUP(A13,Planilha6!$BL$9:$BN$222,3,0) -> high_beta | K13: 0.009 | L13: 0.009 | M13: =VLOOKUP(A13,'Mandato Ibov'!$B$1:$C$215,2,0) -> 0.014696516 | N13: =K13-M13 -> -0.0056965162 | O13: =B13-M13 -> -0.0056965162 | P13: =VLOOKUP(A13,'Mandato Ibov'!$B$2:$D$215,3,0) -> 0.010573984 | Q13: =K13-P13 -> -0.0015739839 | R13: 1 | S13: 1 | T13: 1 | U13: 1 | V13: 1 | W13: 1 | X13: 0.941 | Y13: 0.768 | Z13: 0.614 | AA13: 0.616 | AB13: 1 | AC13: 0.951 | AD13: 0.935 | AE13: 1 | AF13: 1 | AG13: 0.124 | AH13: 0.206 | AI13: 0.403 | AJ13: 1 | AK13: 0.371 | AL13: 0.099 | AM13: -0.603 | AN13: 0.331 | AO13: 0.06 | AP13: -0.193 | AQ13: 0.8 | AR13: 1 | AS13: 0.849 | AT13: 0.506 | AU13: 0.042 | AV13: 0.926 | AW13: -0.17 | AX13: -0.052 | AY13: 0.81 | AZ13: 0.998 | BA13: 0.872 | BB13: -0.051 | BC13: -0.103 | BD13: 0.232 | BE13: 0.298 | BF13: 1 | BG13: 0.517 | BH13: -0.445 | BI13: 0.139 | BJ13: 0.715 | BK13: 0.318 | BM13: =SUMPRODUCT(R13:AD13,$R$225:$AD$225) -> 0.9005612
A14: ALLD3 | B14: 0.009 | C14: =B14-E14 -> 0.009 | D14: =B14-K14 -> 0.001 | E14: =K14-L14 -> 0 | F14: 3.261 | G14: 2.528 | H14: pro_cyclicals | I14: =VLOOKUP(A14,Planilha6!$BL$9:$BN$222,2,0) -> consumer_durables | J14: =VLOOKUP(A14,Planilha6!$BL$9:$BN$222,3,0) -> very_low_beta | K14: 0.008 | L14: 0.008 | M14: =VLOOKUP(A14,'Mandato Ibov'!$B$1:$C$215,2,0) -> 0.014696516 | N14: =K14-M14 -> -0.0066965162 | O14: =B14-M14 -> -0.0056965162 | P14: =VLOOKUP(A14,'Mandato Ibov'!$B$2:$D$215,3,0) -> 0.011222419 | Q14: =K14-P14 -> -0.0032224186 | R14: 1 | S14: 0.906 | T14: 1 | U14: 1 | V14: 1 | W14: 1 | X14: 1 | Y14: 1 | Z14: 1 | AA14: 1 | AB14: 0.847 | AC14: 0.809 | AD14: 0.966 | AE14: 1 | AF14: 1 | AG14: 0.174 | AH14: 1 | AI14: -0.036 | AJ14: 1 | AK14: 0.893 | AL14: 1 | AM14: 0.503 | AN14: 0.722 | AO14: -0.354 | AP14: -0.493 | AQ14: 0.369 | AR14: -0.124 | AS14: -0.006 | AT14: 0.808 | AU14: -0.377 | AV14: 0.637 | AW14: 0.361 | AX14: 0.097 | AY14: 0.674 | AZ14: 0.223 | BA14: 0.655 | BB14: 0.318 | BC14: 0.317 | BD14: 0.509 | BE14: 0.864 | BF14: 1 | BG14: 0.732 | BH14: -0.456 | BI14: -0.442 | BJ14: 0.471 | BK14: 0.792 | BM14: =SUMPRODUCT(R14:AD14,$R$225:$AD$225) -> 0.9766646
A15: SYNE3 | B15: =K15 -> 0.008 | C15: =B15-E15 -> 0.008 | D15: =B15-K15 -> 0 | E15: =K15-L15 -> 0 | F15: 3.257 | G15: 2.537 | H15: bond_proxies | I15: =VLOOKUP(A15,Planilha6!$BL$9:$BN$222,2,0) -> real_estate | J15: =VLOOKUP(A15,Planilha6!$BL$9:$BN$222,3,0) -> neutral_beta | K15: 0.008 | L15: 0.008 | M15: =VLOOKUP(A15,'Mandato Ibov'!$B$1:$C$215,2,0) -> 0.014680455 | N15: =K15-M15 -> -0.0066804553 | O15: =B15-M15 -> -0.0066804553 | P15: =VLOOKUP(A15,'Mandato Ibov'!$B$2:$D$215,3,0) -> 0.0074194024 | Q15: =K15-P15 -> 0.0005805976 | R15: 0.977 | S15: 0.59 | T15: 1 | U15: 0.907 | V15: 0.966 | W15: 0.964 | X15: 0.959 | Y15: 0.973 | Z15: 0.642 | AA15: 0.642 | AB15: 0.626 | AC15: 0.457 | AD15: 0.799 | AE15: 1 | AF15: 1 | AG15: -0.379 | AH15: 1 | AI15: 0.193 | AJ15: 1 | AK15: 0.334 | AL15: 1 | AM15: 0.199 | AN15: -0.225 | AO15: -0.224 | AP15: -0.278 | AQ15: 0.719 | AR15: -0.751 | AS15: 0.011 | AT15: 0.004 | AU15: 0.18 | AV15: 0.533 | AW15: 0.247 | AX15: -0.371 | AY15: 0.352 | AZ15: 0.256 | BA15: 0.145 | BB15: 0.686 | BC15: 1 | BD15: 0.72 | BE15: 0.834 | BF15: 1 | BG15: 0.335 | BH15: -0.906 | BI15: 0.26 | BJ15: 0.618 | BK15: 0.771 | BM15: =SUMPRODUCT(R15:AD15,$R$225:$AD$225) -> 0.8603519
A16: POMO3 | B16: =K16 -> 0.009 | C16: =B16-E16 -> 0.009 | D16: =B16-K16 -> 0 | E16: =K16-L16 -> 0 | F16: 3.228 | G16: 2.949 | H16: industrials | I16: =VLOOKUP(A16,Planilha6!$BL$9:$BN$222,2,0) -> capital_goods | J16: =VLOOKUP(A16,Planilha6!$BL$9:$BN$222,3,0) -> neutral_beta | K16: 0.009 | L16: 0.009 | M16: =VLOOKUP(A16,'Mandato Ibov'!$B$1:$C$215,2,0) -> 0.014549271 | N16: =K16-M16 -> -0.0055492711 | O16: =B16-M16 -> -0.0055492711 | P16: =VLOOKUP(A16,'Mandato Ibov'!$B$2:$D$215,3,0) -> 0.0068122102 | Q16: =K16-P16 -> 0.0021877898 | R16: 0.839 | S16: 0.877 | T16: 0.672 | U16: 0.932 | V16: 1 | W16: 1 | X16: 1 | Y16: 1 | Z16: 0.642 | AA16: 0.647 | AB16: 0.808 | AC16: 0.756 | AD16: 0.704 | AE16: 1 | AF16: 1 | AG16: -0.197 | AH16: -0.419 | AI16: -0.261 | AJ16: 0.405 | AK16: -0.003 | AL16: 0.601 | AM16: -0.614 | AN16: 0.429 | AO16: -0.103 | AP16: 0.286 | AQ16: 0.941 | AR16: 0.126 | AS16: -0.527 | AT16: 0.719 | AU16: -0.029 | AV16: 0.539 | AW16: 0.42 | AX16: 0.163 | AY16: 0.91 | AZ16: 1 | BA16: 0.581 | BB16: -0.046 | BC16: -0.167 | BD16: 0.22 | BE16: -0.345 | BF16: -0.617 | BG16: 0.563 | BH16: -0.989 | BI16: 0.355 | BJ16: 0.72 | BK16: -0.209 | BM16: =SUMPRODUCT(R16:AD16,$R$225:$AD$225) -> 0.8499682
A17: SHUL4 | B17: =K17 -> 0.012 | C17: =B17-E17 -> 0.012 | D17: =B17-K17 -> 0 | E17: =K17-L17 -> 0 | F17: 3.132 | G17: 3.876 | H17: industrials | I17: =VLOOKUP(A17,Planilha6!$BL$9:$BN$222,2,0) -> capital_goods | J17: =VLOOKUP(A17,Planilha6!$BL$9:$BN$222,3,0) -> low_beta | K17: 0.012 | L17: 0.012 | M17: =VLOOKUP(A17,'Mandato Ibov'!$B$1:$C$215,2,0) -> 0.014117597 | N17: =K17-M17 -> -0.0021175971 | O17: =B17-M17 -> -0.0021175971 | P17: =VLOOKUP(A17,'Mandato Ibov'!$B$2:$D$215,3,0) -> 0.0077194535 | Q17: =K17-P17 -> 0.0042805465 | R17: 0.721 | S17: 0.878 | T17: 0.708 | U17: 0.282 | V17: 0.706 | W17: 0.778 | X17: 0.84 | Y17: 0.77 | Z17: 0.982 | AA17: 0.982 | AB17: 0.921 | AC17: 0.974 | AD17: 0.976 | AE17: -0.334 | AF17: -0.296 | AG17: 0.308 | AH17: 0.127 | AI17: 0.947 | AJ17: -0.135 | AK17: -0.046 | AL17: 0.33 | AM17: -0.426 | AN17: 0.436 | AO17: 0.439 | AP17: 0.294 | AQ17: -0.044 | AR17: 0.28 | AS17: 0.169 | AT17: 0.36 | AU17: -0.143 | AV17: -0.152 | AW17: 0.733 | AX17: 0.494 | AY17: 0.905 | AZ17: 0.706 | BA17: 0.814 | BB17: -0.144 | BC17: -0.183 | BD17: -0.045 | BE17: 0.269 | BF17: 0.31 | BG17: 1 | BH17: -0.443 | BI17: -0.023 | BJ17: 0.858 | BK17: 0.286 | BM17: =SUMPRODUCT(R17:AD17,$R$225:$AD$225) -> 0.8160552
A18: FIQE3 | B18: =K18 -> 0.012 | C18: =B18-E18 -> 0.012 | D18: =B18-K18 -> 0 | E18: =K18-L18 -> 0 | F18: 3.082 | G18: 3.174 | H18: bond_proxies | I18: =VLOOKUP(A18,Planilha6!$BL$9:$BN$222,2,0) -> telecom | J18: =VLOOKUP(A18,Planilha6!$BL$9:$BN$222,3,0) -> low_beta | K18: 0.012 | L18: 0.012 | M18: =VLOOKUP(A18,'Mandato Ibov'!$B$1:$C$215,2,0) -> 0.013891662 | N18: =K18-M18 -> -0.0018916623 | O18: =B18-M18 -> -0.0018916623 | P18: =VLOOKUP(A18,'Mandato Ibov'!$B$2:$D$215,3,0) -> 0.011222419 | Q18: =K18-P18 -> 0.00077758143 | R18: 0.886 | S18: 0.823 | T18: 0.713 | U18: 0.994 | V18: 0.952 | W18: 0.642 | X18: 0.616 | Y18: 0.585 | Z18: 0.668 | AA18: 0.676 | AB18: 1 | AC18: 1 | AD18: 1 | AE18: 0.629 | AF18: -0.012 | AG18: 0.847 | AH18: -0.234 | AI18: 1 | AJ18: 1 | AK18: -0.23 | AL18: 0.091 | AM18: -0.768 | AN18: 0.009 | AO18: 0.871 | AP18: 0.813 | AQ18: 0.298 | AR18: 0.199 | AS18: 0.439 | AT18: 0.523 | AU18: 0.36 | AV18: 0.722 | AW18: 0.446 | AX18: -0.068 | AY18: 0.93 | AZ18: -0.661 | BA18: 0.851 | BB18: -0.161 | BC18: -0.297 | BD18: 0.597 | BE18: -1 | BF18: -0.32 | BG18: -0.17 | BH18: -0.541 | BI18: -0.361 | BJ18: 0.7 | BK18: 0.468 | BM18: =SUMPRODUCT(R18:AD18,$R$225:$AD$225) -> 0.7981371
A19: MTRE3 | B19: 0.014 | C19: =B19-E19 -> 0.014 | D19: =B19-K19 -> -0.001 | E19: =K19-L19 -> 0 | F19: 3.077 | G19: 3.096 | H19: pro_cyclicals | I19: =VLOOKUP(A19,Planilha6!$BL$9:$BN$222,2,0) -> homebuilders | J19: =VLOOKUP(A19,Planilha6!$BL$9:$BN$222,3,0) -> neutral_beta | K19: 0.015 | L19: 0.015 | M19: =VLOOKUP(A19,'Mandato Ibov'!$B$1:$C$215,2,0) -> 0.013869747 | N19: =K19-M19 -> 0.0011302531 | O19: =B19-M19 -> 0.00013025315 | P19: =VLOOKUP(A19,'Mandato Ibov'!$B$2:$D$215,3,0) -> 0.010241009 | Q19: =K19-P19 -> 0.0047589907 | R19: 0.879 | S19: 0.604 | T19: 0.947 | U19: 0.578 | V19: 0.76 | W19: 0.77 | X19: 0.732 | Y19: 0.685 | Z19: 0.685 | AA19: 0.687 | AB19: 1 | AC19: 0.953 | AD19: 0.917 | AE19: 0.527 | AF19: 0.465 | AG19: 0.502 | AH19: 1 | AI19: 0.966 | AJ19: 0.018 | AK19: -0.107 | AL19: 0.714 | AM19: 0.319 | AN19: 0.349 | AO19: 0.011 | AP19: 0.21 | AQ19: 0.263 | AR19: 0.136 | AS19: -0.081 | AT19: 0.013 | AU19: -0.221 | AV19: 0.077 | AW19: -0.064 | AX19: -0.285 | AY19: 0.765 | AZ19: 0.183 | BA19: 0.558 | BB19: 0.048 | BC19: -0.275 | BD19: 0.131 | BE19: 0.064 | BF19: 0.003 | BG19: 0.917 | BH19: -0.142 | BI19: 0.233 | BJ19: 0.595 | BK19: 0.837 | BM19: =SUMPRODUCT(R19:AD19,$R$225:$AD$225) -> 0.7963066
A20: BRSR6 | B20: =K20 -> 0.012 | C20: =B20-E20 -> 0.012 | D20: =B20-K20 -> 0 | E20: =K20-L20 -> 0 | F20: 3.053 | G20: 3.259 | H20: pro_cyclicals | I20: =VLOOKUP(A20,Planilha6!$BL$9:$BN$222,2,0) -> banks | J20: =VLOOKUP(A20,Planilha6!$BL$9:$BN$222,3,0) -> high_beta | K20: 0.012 | L20: 0.012 | M20: =VLOOKUP(A20,'Mandato Ibov'!$B$1:$C$215,2,0) -> 0.013762926 | N20: =K20-M20 -> -0.0017629263 | O20: =B20-M20 -> -0.0017629263 | P20: =VLOOKUP(A20,'Mandato Ibov'!$B$2:$D$215,3,0) -> 0.011060179 | Q20: =K20-P20 -> 0.00093982079 | R20: 0.722 | S20: 0.822 | T20: 0.383 | U20: 0.77 | V20: 0.835 | W20: 0.662 | X20: 0.569 | Y20: 0.682 | Z20: 1 | AA20: 1 | AB20: 0.957 | AC20: 0.985 | AD20: 1 | AE20: 0.002 | AF20: 0.92 | AG20: 1 | AH20: -0.092 | AI20: 0.3 | AJ20: -0.516 | AK20: 0.067 | AL20: 0.284 | AM20: 0.456 | AN20: 0.401 | AO20: 0.626 | AP20: 0.129 | AQ20: 0.239 | AR20: 0.566 | AS20: 0.683 | AT20: 0.074 | AU20: -0.176 | AV20: -0.128 | AW20: 0.455 | AX20: -0.563 | AY20: 0.714 | AZ20: 0.397 | BA20: 0.39 | BB20: -0.151 | BC20: -0.066 | BD20: 0.454 | BE20: 0.494 | BF20: 1 | BG20: 0.466 | BH20: -0.58 | BI20: 0.035 | BJ20: 0.207 | BK20: 0.403 | BM20: =SUMPRODUCT(R20:AD20,$R$225:$AD$225) -> 0.7880018
A21: GRND3 | B21: =K21 -> 0.009 | C21: =B21-E21 -> 0.009 | D21: =B21-K21 -> 0 | E21: =K21-L21 -> 0 | F21: 3.007 | G21: 3.076 | H21: pro_cyclicals | I21: =VLOOKUP(A21,Planilha6!$BL$9:$BN$222,2,0) -> apparel | J21: =VLOOKUP(A21,Planilha6!$BL$9:$BN$222,3,0) -> very_low_beta | K21: 0.009 | L21: 0.009 | M21: =VLOOKUP(A21,'Mandato Ibov'!$B$1:$C$215,2,0) -> 0.013552612 | N21: =K21-M21 -> -0.0045526118 | O21: =B21-M21 -> -0.0045526118 | P21: =VLOOKUP(A21,'Mandato Ibov'!$B$2:$D$215,3,0) -> 0.0088452433 | Q21: =K21-P21 -> 0.00015475669 | R21: 0.69 | S21: 0.625 | T21: 0.448 | U21: 0.532 | V21: 0.623 | W21: 0.907 | X21: 1 | Y21: 1 | Z21: 0.59 | AA21: 0.597 | AB21: 0.791 | AC21: 0.77 | AD21: 0.747 | AE21: 0.934 | AF21: -0.051 | AG21: -0.365 | AH21: -0.082 | AI21: -0.23 | AJ21: 1 | AK21: -0.094 | AL21: 0.948 | AM21: -0.506 | AN21: 0.657 | AO21: 0.14 | AP21: 0.013 | AQ21: 0.081 | AR21: -0.001 | AS21: -0.467 | AT21: 0.308 | AU21: -0.007 | AV21: 0.386 | AW21: 0.495 | AX21: 0.835 | AY21: 0.66 | AZ21: -0.102 | BA21: 0.446 | BB21: 0.826 | BC21: 0.453 | BD21: 0.583 | BE21: 0.176 | BF21: 0.005 | BG21: 0.93 | BH21: -0.235 | BI21: -0.371 | BJ21: 0.129 | BK21: 0.293 | BM21: =SUMPRODUCT(R21:AD21,$R$225:$AD$225) -> 0.7714426
A22: TIMS3 | B22: =K22 -> 0.019 | C22: =B22-E22 -> 0.011 | D22: =B22-K22 -> 0 | E22: =K22-L22 -> 0.008 | F22: 2.998 | G22: 4.584 | H22: bond_proxies | I22: =VLOOKUP(A22,Planilha6!$BL$9:$BN$222,2,0) -> telecom | J22: =VLOOKUP(A22,Planilha6!$BL$9:$BN$222,3,0) -> very_low_beta | K22: 0.019 | L22: 0.011 | M22: =VLOOKUP(A22,'Mandato Ibov'!$B$1:$C$215,2,0) -> 0.029194607 | N22: =K22-M22 -> -0.010194607 | O22: =B22-M22 -> -0.010194607 | P22: =VLOOKUP(A22,'Mandato Ibov'!$B$2:$D$215,3,0) -> 0.018920006 | Q22: =K22-P22 -> 7.9994089e-05 | R22: 0.542 | S22: 1 | T22: -0.201 | U22: 0.855 | V22: 0.795 | W22: 1 | X22: 1 | Y22: 0.898 | Z22: 0.802 | AA22: 0.81 | AB22: 0.85 | AC22: 0.845 | AD22: 0.79 | AE22: 0.838 | AF22: 0.034 | AG22: 0.287 | AH22: -0.92 | AI22: -0.582 | AJ22: -0.423 | AK22: 0.231 | AL22: -0.068 | AM22: -0.848 | AN22: -0.478 | AO22: 0.382 | AP22: 0.671 | AQ22: 0.579 | AR22: 0.237 | AS22: 0.149 | AT22: 0.552 | AU22: 0.407 | AV22: 1 | AW22: 0.766 | AX22: 0.163 | AY22: 0.846 | AZ22: 0.277 | BA22: 0.813 | BB22: 0.36 | BC22: 0.37 | BD22: 0.67 | BE22: 0.271 | BF22: 0.39 | BG22: 0.946 | BH22: -0.771 | BI22: -0.359 | BJ22: -0.017 | BK22: -0.547 | BM22: =SUMPRODUCT(R22:AD22,$R$225:$AD$225) -> 0.7684141
A23: SAPR4 | B23: =K23 -> 0.011 | C23: =B23-E23 -> 0.011 | D23: =B23-K23 -> 0 | E23: =K23-L23 -> 0 | F23: 2.933 | G23: 3.163 | H23: bond_proxies | I23: =VLOOKUP(A23,Planilha6!$BL$9:$BN$222,2,0) -> utilities | J23: =VLOOKUP(A23,Planilha6!$BL$9:$BN$222,3,0) -> low_beta | K23: 0.011 | L23: 0.011 | M23: =VLOOKUP(A23,'Mandato Ibov'!$B$1:$C$215,2,0) -> 0.013222209 | N23: =K23-M23 -> -0.0022222087 | O23: =B23-M23 -> -0.0022222087 | P23: =VLOOKUP(A23,'Mandato Ibov'!$B$2:$D$215,3,0) -> 0.0078670833 | Q23: =K23-P23 -> 0.0031329167 | R23: 0.575 | S23: 0.876 | T23: 0.247 | U23: 0.806 | V23: 0.885 | W23: 0.812 | X23: 0.899 | Y23: 0.776 | Z23: 0.753 | AA23: 0.763 | AB23: 0.863 | AC23: 0.846 | AD23: 0.795 | AE23: 0.875 | AF23: 0.438 | AG23: 0.582 | AH23: -0.452 | AI23: -0.556 | AJ23: -0.145 | AK23: 0.484 | AL23: -0.202 | AM23: -0.316 | AN23: -0.052 | AO23: 0.212 | AP23: -0.205 | AQ23: 0.276 | AR23: -0.09 | AS23: -0.061 | AT23: 0.395 | AU23: 0.424 | AV23: 0.532 | AW23: 0.756 | AX23: -0.08 | AY23: 0.149 | AZ23: 0.837 | BA23: 0.898 | BB23: -0.133 | BC23: 0.179 | BD23: 0.183 | BE23: 0.246 | BF23: 1 | BG23: 0.439 | BH23: -0.752 | BI23: -0.085 | BJ23: 0.6 | BK23: 0.118 | BM23: =SUMPRODUCT(R23:AD23,$R$225:$AD$225) -> 0.7451919
A24: PFRM3 | B24: =K24 -> 0.008 | C24: =B24-E24 -> 0.008 | D24: =B24-K24 -> 0 | E24: =K24-L24 -> 0 | F24: 2.887 | G24: 2.303 | H24: defensives | I24: =VLOOKUP(A24,Planilha6!$BL$9:$BN$222,2,0) -> healthcare | J24: =VLOOKUP(A24,Planilha6!$BL$9:$BN$222,3,0) -> high_beta | K24: 0.008 | L24: 0.008 | M24: =VLOOKUP(A24,'Mandato Ibov'!$B$1:$C$215,2,0) -> 0.013012017 | N24: =K24-M24 -> -0.0050120171 | O24: =B24-M24 -> -0.0050120171 | P24: =VLOOKUP(A24,'Mandato Ibov'!$B$2:$D$215,3,0) -> 0.0089002949 | Q24: =K24-P24 -> -0.00090029494 | R24: 1 | S24: 0.464 | T24: 1 | U24: 1 | V24: 0.93 | W24: 0.613 | X24: 0.377 | Y24: 0.37 | Z24: 0.624 | AA24: 0.63 | AB24: 0.947 | AC24: 0.819 | AD24: 0.926 | AE24: 1 | AF24: 0.977 | AG24: 0.581 | AH24: 1 | AI24: 0.694 | AJ24: 0.719 | AK24: 0.655 | AL24: 0.1 | AM24: 0.107 | AN24: 0.075 | AO24: 0.138 | AP24: -0.038 | AQ24: 0.417 | AR24: 0.118 | AS24: -0.218 | AT24: 0.475 | AU24: -0.481 | AV24: 0.457 | AW24: 0.291 | AX24: -0.128 | AY24: 0.919 | AZ24: -0.172 | BA24: 0.741 | BB24: -0.122 | BC24: -0.038 | BD24: 0.101 | BE24: 0.463 | BF24: -0.099 | BG24: 0.161 | BH24: -0.688 | BI24: 0.081 | BJ24: 0.815 | BK24: 0.715 | BM24: =SUMPRODUCT(R24:AD24,$R$225:$AD$225) -> 0.7290081
A25: SAPR3 | B25: 0 | C25: =B25-E25 -> 0 | D25: =B25-K25 -> -0.009 | E25: =K25-L25 -> 0 | F25: 2.85 | G25: 2.454 | H25: bond_proxies | I25: =VLOOKUP(A25,Planilha6!$BL$9:$BN$222,2,0) -> utilities | J25: =VLOOKUP(A25,Planilha6!$BL$9:$BN$222,3,0) -> high_beta | K25: 0.009 | L25: 0.009 | M25: =VLOOKUP(A25,'Mandato Ibov'!$B$1:$C$215,2,0) -> 0.012847823 | N25: =K25-M25 -> -0.0038478228 | O25: =B25-M25 -> -0.012847823 | P25: =VLOOKUP(A25,'Mandato Ibov'!$B$2:$D$215,3,0) -> 0.0079549626 | Q25: =K25-P25 -> 0.0010450374 | R25: 0.558 | S25: 0.864 | T25: 0.327 | U25: 0.802 | V25: 0.903 | W25: 0.689 | X25: 0.706 | Y25: 0.667 | Z25: 0.835 | AA25: 0.845 | AB25: 0.874 | AC25: 0.814 | AD25: 0.827 | AE25: 0.811 | AF25: 0.4 | AG25: 0.739 | AH25: -0.467 | AI25: -0.518 | AJ25: -0.145 | AK25: 0.484 | AL25: -0.333 | AM25: -0.316 | AN25: -0.103 | AO25: 0.304 | AP25: -0.214 | AQ25: 0.276 | AR25: -0.09 | AS25: -0.061 | AT25: 0.395 | AU25: 0.424 | AV25: 0.532 | AW25: 0.648 | AX25: -0.08 | AY25: 0.149 | AZ25: 0.954 | BA25: 0.456 | BB25: -0.133 | BC25: 0.179 | BD25: 0.293 | BE25: 0.008 | BF25: 0.449 | BG25: 0.239 | BH25: -0.872 | BI25: 0.109 | BJ25: 0.962 | BK25: 0.118 | BM25: =SUMPRODUCT(R25:AD25,$R$225:$AD$225) -> 0.7159515
A26: DEXP3 | B26: =K26 -> 0.011 | C26: =B26-E26 -> 0.011 | D26: =B26-K26 -> 0 | E26: =K26-L26 -> 0 | F26: 2.829 | G26: 2.69 | H26: industrials | I26: =VLOOKUP(A26,Planilha6!$BL$9:$BN$222,2,0) -> chemicals | J26: =VLOOKUP(A26,Planilha6!$BL$9:$BN$222,3,0) -> very_low_beta | K26: 0.011 | L26: 0.011 | M26: =VLOOKUP(A26,'Mandato Ibov'!$B$1:$C$215,2,0) -> 0.012750222 | N26: =K26-M26 -> -0.0017502219 | O26: =B26-M26 -> -0.0017502219 | P26: =VLOOKUP(A26,'Mandato Ibov'!$B$2:$D$215,3,0) -> 0 | Q26: =K26-P26 -> 0.011 | R26: 0.69 | S26: 0.584 | T26: 0.855 | U26: 0.288 | V26: 0.627 | W26: 0.639 | X26: 0.652 | Y26: 0.613 | Z26: 0.885 | AA26: 0.89 | AB26: 0.865 | AC26: 0.777 | AD26: 0.838 | AE26: 0.547 | AF26: -0.463 | AG26: -0.245 | AH26: 0.75 | AI26: 0.262 | AJ26: 0.52 | AK26: 0.352 | AL26: 0.183 | AM26: -0.093 | AN26: 0.36 | AO26: 0.096 | AP26: -0.436 | AQ26: -0.057 | AR26: -0.17 | AS26: -0.479 | AT26: 0.551 | AU26: -0.246 | AV26: 0.248 | AW26: 0.583 | AX26: 0.479 | AY26: 0.869 | AZ26: 0.773 | BA26: 0.881 | BB26: -0.037 | BC26: -0.094 | BD26: 0.248 | BE26: 0.272 | BF26: -0.091 | BG26: 0.918 | BH26: -0.312 | BI26: -0.254 | BJ26: 0.927 | BK26: 0.883 | BM26: =SUMPRODUCT(R26:AD26,$R$225:$AD$225) -> 0.7084624
A27: PETR4 | B27: 0.055 | C27: =B27-E27 -> -0.018 | D27: =B27-K27 -> 0.028 | E27: =K27-L27 -> 0.073 | F27: 2.806 | G27: 5.734 | H27: commodities | I27: =VLOOKUP(A27,Planilha6!$BL$9:$BN$222,2,0) -> crude_oil | J27: =VLOOKUP(A27,Planilha6!$BL$9:$BN$222,3,0) -> very_low_beta | K27: 0.027 | L27: -0.046 | M27: =VLOOKUP(A27,'Mandato Ibov'!$B$1:$C$215,2,0) -> 0.07042607 | N27: =K27-M27 -> -0.04342607 | O27: =B27-M27 -> -0.01542607 | P27: =VLOOKUP(A27,'Mandato Ibov'!$B$2:$D$215,3,0) -> 0.062482534 | Q27: =K27-P27 -> -0.035482534 | R27: 0.112 | S27: 1 | T27: -0.544 | U27: 0.651 | V27: 0.729 | W27: 0.842 | X27: 0.869 | Y27: 1 | Z27: 1 | AA27: 1 | AB27: 0.644 | AC27: 0.867 | AD27: 0.912 | AE27: 0.399 | AF27: -0.306 | AG27: 1 | AH27: -0.912 | AI27: -0.555 | AJ27: -0.906 | AK27: 0.218 | AL27: 0.453 | AM27: -0.514 | AN27: -0.652 | AO27: 0.985 | AP27: 1 | AQ27: -0.241 | AR27: 0.669 | AS27: 0.465 | AT27: 0.465 | AU27: 0.344 | AV27: 0.372 | AW27: 0.496 | AX27: -0.231 | AY27: 0.814 | AZ27: 0.629 | BA27: 0.479 | BB27: -0.148 | BC27: -0.273 | BD27: 0.338 | BE27: 0.191 | BF27: 0.744 | BG27: 0.708 | BH27: -0.954 | BI27: -0.997 | BJ27: -0.259 | BK27: -0.89 | BM27: =SUMPRODUCT(R27:AD27,$R$225:$AD$225) -> 0.7003428
A28: LEVE3 | B28: =K28 -> 0.011 | C28: =B28-E28 -> 0.011 | D28: =B28-K28 -> 0 | E28: =K28-L28 -> 0 | F28: 2.696 | G28: 3.196 | H28: industrials | I28: =VLOOKUP(A28,Planilha6!$BL$9:$BN$222,2,0) -> capital_goods | J28: =VLOOKUP(A28,Planilha6!$BL$9:$BN$222,3,0) -> very_low_beta | K28: 0.011 | L28: 0.011 | M28: =VLOOKUP(A28,'Mandato Ibov'!$B$1:$C$215,2,0) -> 0.012150787 | N28: =K28-M28 -> -0.001150787 | O28: =B28-M28 -> -0.001150787 | P28: =VLOOKUP(A28,'Mandato Ibov'!$B$2:$D$215,3,0) -> 0.010928911 | Q28: =K28-P28 -> 7.1089482e-05 | R28: 0.303 | S28: 0.75 | T28: 0.358 | U28: 0.359 | V28: 0.72 | W28: 0.556 | X28: 0.698 | Y28: 0.825 | Z28: 0.883 | AA28: 0.888 | AB28: 0.781 | AC28: 0.804 | AD28: 0.788 | AE28: 0.036 | AF28: -0.326 | AG28: 0.117 | AH28: -0.488 | AI28: 0.317 | AJ28: 0.437 | AK28: -0.13 | AL28: 0.264 | AM28: -0.795 | AN28: -0.089 | AO28: 0.503 | AP28: 0.221 | AQ28: 0.323 | AR28: 0.151 | AS28: -0.072 | AT28: 0.989 | AU28: -0.065 | AV28: 0.357 | AW28: 0.664 | AX28: -0.057 | AY28: 0.804 | AZ28: 1 | BA28: 0.4 | BB28: -0.203 | BC28: -0.465 | BD28: -0.421 | BE28: 0.114 | BF28: -0.403 | BG28: 0.802 | BH28: -0.604 | BI28: -0.108 | BJ28: 0.451 | BK28: -0.034 | BM28: =SUMPRODUCT(R28:AD28,$R$225:$AD$225) -> 0.6610803
A29: PETR3 | B29: 0.05 | C29: =B29-E29 -> -0.004 | D29: =B29-K29 -> 0.023 | E29: =K29-L29 -> 0.054 | F29: 2.686 | G29: 5.132 | H29: commodities | I29: =VLOOKUP(A29,Planilha6!$BL$9:$BN$222,2,0) -> crude_oil | J29: =VLOOKUP(A29,Planilha6!$BL$9:$BN$222,3,0) -> very_low_beta | K29: 0.027 | L29: -0.027 | M29: =VLOOKUP(A29,'Mandato Ibov'!$B$1:$C$215,2,0) -> 0.067399922 | N29: =K29-M29 -> -0.040399922 | O29: =B29-M29 -> -0.017399922 | P29: =VLOOKUP(A29,'Mandato Ibov'!$B$2:$D$215,3,0) -> 0.062192443 | Q29: =K29-P29 -> -0.035192443 | R29: 0.005 | S29: 0.981 | T29: -0.562 | U29: 0.586 | V29: 0.679 | W29: 0.731 | X29: 0.753 | Y29: 1 | Z29: 1 | AA29: 1 | AB29: 0.679 | AC29: 0.79 | AD29: 0.899 | AE29: 0.348 | AF29: -0.325 | AG29: 1 | AH29: -0.916 | AI29: -0.569 | AJ29: -0.911 | AK29: 0.218 | AL29: 0.413 | AM29: -0.514 | AN29: -0.658 | AO29: 0.985 | AP29: 1 | AQ29: -0.241 | AR29: 0.669 | AS29: 0.465 | AT29: 0.465 | AU29: 0.344 | AV29: 0.365 | AW29: 0.411 | AX29: -0.231 | AY29: 0.814 | AZ29: 0.654 | BA29: -0.157 | BB29: -0.148 | BC29: -0.273 | BD29: 0.354 | BE29: 0.225 | BF29: 0.997 | BG29: 0.696 | BH29: -0.93 | BI29: -0.997 | BJ29: -0.111 | BK29: -0.89 | BM29: =SUMPRODUCT(R29:AD29,$R$225:$AD$225) -> 0.6573897
A30: ABCB4 | B30: =K30 -> 0.015 | C30: =B30-E30 -> 0.015 | D30: =B30-K30 -> 0 | E30: =K30-L30 -> 0 | F30: 2.667 | G30: 3.453 | H30: pro_cyclicals | I30: =VLOOKUP(A30,Planilha6!$BL$9:$BN$222,2,0) -> banks | J30: =VLOOKUP(A30,Planilha6!$BL$9:$BN$222,3,0) -> neutral_beta | K30: 0.015 | L30: 0.015 | M30: =VLOOKUP(A30,'Mandato Ibov'!$B$1:$C$215,2,0) -> 0.012021468 | N30: =K30-M30 -> 0.0029785315 | O30: =B30-M30 -> 0.0029785315 | P30: =VLOOKUP(A30,'Mandato Ibov'!$B$2:$D$215,3,0) -> 0.0074109281 | Q30: =K30-P30 -> 0.0075890719 | R30: 0.364 | S30: 0.748 | T30: 0.063 | U30: 0.314 | V30: 0.534 | W30: 0.517 | X30: 0.561 | Y30: 0.61 | Z30: 1 | AA30: 1 | AB30: 0.908 | AC30: 0.93 | AD30: 0.994 | AE30: -0.446 | AF30: 0.492 | AG30: 1 | AH30: -0.262 | AI30: 0.597 | AJ30: -0.727 | AK30: -0.052 | AL30: 0.23 | AM30: -0.009 | AN30: 0.214 | AO30: 0.585 | AP30: 0.458 | AQ30: 0.102 | AR30: 0.169 | AS30: -0.314 | AT30: -0.006 | AU30: -0.224 | AV30: -0.281 | AW30: 0.654 | AX30: -0.396 | AY30: 0.818 | AZ30: 0.432 | BA30: 0.576 | BB30: 0.065 | BC30: 0.038 | BD30: 0.392 | BE30: 0.122 | BF30: -0.167 | BG30: 0.875 | BH30: -0.641 | BI30: -0.095 | BJ30: 0.431 | BK30: 0.43 | BM30: =SUMPRODUCT(R30:AD30,$R$225:$AD$225) -> 0.6509591
A31: ALPA4 | B31: =K31 -> 0.009 | C31: =B31-E31 -> 0.009 | D31: =B31-K31 -> 0 | E31: =K31-L31 -> 0 | F31: 2.612 | G31: 2.176 | H31: pro_cyclicals | I31: =VLOOKUP(A31,Planilha6!$BL$9:$BN$222,2,0) -> apparel | J31: =VLOOKUP(A31,Planilha6!$BL$9:$BN$222,3,0) -> high_beta | K31: 0.009 | L31: 0.009 | M31: =VLOOKUP(A31,'Mandato Ibov'!$B$1:$C$215,2,0) -> 0.011772324 | N31: =K31-M31 -> -0.002772324 | O31: =B31-M31 -> -0.002772324 | P31: =VLOOKUP(A31,'Mandato Ibov'!$B$2:$D$215,3,0) -> 0.0066143629 | Q31: =K31-P31 -> 0.0023856371 | R31: 0.769 | S31: 0.503 | T31: 0.539 | U31: 0.854 | V31: 0.765 | W31: 0.622 | X31: 0.521 | Y31: 0.392 | Z31: 0.46 | AA31: 0.462 | AB31: 0.846 | AC31: 0.818 | AD31: 0.794 | AE31: 1 | AF31: 0.947 | AG31: -0.199 | AH31: -0.518 | AI31: -0.122 | AJ31: 0.311 | AK31: -0.406 | AL31: -0.083 | AM31: -0.771 | AN31: 0.575 | AO31: 0.373 | AP31: -0.366 | AQ31: 0.714 | AR31: 1 | AS31: 0.997 | AT31: 0.325 | AU31: -0.056 | AV31: 0.778 | AW31: 0.015 | AX31: -0.052 | AY31: 0.261 | AZ31: 0.362 | BA31: 0.471 | BB31: 0.457 | BC31: -0.16 | BD31: 0.703 | BE31: 0.062 | BF31: -0.297 | BG31: 0.377 | BH31: -0.188 | BI31: 0.093 | BJ31: 0.201 | BK31: -0.211 | BM31: =SUMPRODUCT(R31:AD31,$R$225:$AD$225) -> 0.6312346
A32: SAPR11 | B32: =K32 -> 0.011 | C32: =B32-E32 -> 0.011 | D32: =B32-K32 -> 0 | E32: =K32-L32 -> 0 | F32: 2.581 | G32: 2.765 | H32: bond_proxies | I32: =VLOOKUP(A32,Planilha6!$BL$9:$BN$222,2,0) -> utilities | J32: =VLOOKUP(A32,Planilha6!$BL$9:$BN$222,3,0) -> neutral_beta | K32: 0.011 | L32: 0.011 | M32: =VLOOKUP(A32,'Mandato Ibov'!$B$1:$C$215,2,0) -> 0.011634276 | N32: =K32-M32 -> -0.00063427556 | O32: =B32-M32 -> -0.00063427556 | P32: =VLOOKUP(A32,'Mandato Ibov'!$B$2:$D$215,3,0) -> 0.0079996634 | Q32: =K32-P32 -> 0.0030003366 | R32: 0.34 | S32: 0.749 | T32: -0.043 | U32: 0.709 | V32: 0.738 | W32: 0.64 | X32: 0.76 | Y32: 0.676 | Z32: 0.724 | AA32: 0.733 | AB32: 0.793 | AC32: 0.823 | AD32: 0.73 | AE32: 0.853 | AF32: 0.427 | AG32: 0.612 | AH32: -0.457 | AI32: -0.553 | AJ32: -0.148 | AK32: 0.484 | AL32: -0.228 | AM32: -0.316 | AN32: -0.075 | AO32: 0.21 | AP32: -0.219 | AQ32: 0.276 | AR32: -0.09 | AS32: -0.061 | AT32: 0.395 | AU32: 0.424 | AV32: 0.53 | AW32: 0.726 | AX32: -0.08 | AY32: 0.149 | AZ32: 0.78 | BA32: 0.212 | BB32: -0.133 | BC32: 0.179 | BD32: 0.209 | BE32: 0.131 | BF32: 1 | BG32: 0.423 | BH32: -0.833 | BI32: -0.006 | BJ32: -0.032 | BK32: 0.118 | BM32: =SUMPRODUCT(R32:AD32,$R$225:$AD$225) -> 0.6203108
A33: POMO4 | B33: =K33 -> 0.01 | C33: =B33-E33 -> 0.008 | D33: =B33-K33 -> 0 | E33: =K33-L33 -> 0.002 | F33: 2.564 | G33: 2.46 | H33: industrials | I33: =VLOOKUP(A33,Planilha6!$BL$9:$BN$222,2,0) -> capital_goods | J33: =VLOOKUP(A33,Planilha6!$BL$9:$BN$222,3,0) -> high_beta | K33: 0.01 | L33: 0.008 | M33: =VLOOKUP(A33,'Mandato Ibov'!$B$1:$C$215,2,0) -> 0.013098457 | N33: =K33-M33 -> -0.0030984567 | O33: =B33-M33 -> -0.0030984567 | P33: =VLOOKUP(A33,'Mandato Ibov'!$B$2:$D$215,3,0) -> 0 | Q33: =K33-P33 -> 0.01 | R33: 0.558 | S33: 0.607 | T33: 0.207 | U33: 0.686 | V33: 0.684 | W33: 0.801 | X33: 0.852 | Y33: 0.796 | Z33: 0.269 | AA33: 0.275 | AB33: 0.698 | AC33: 0.645 | AD33: 0.536 | AE33: 0.977 | AF33: 1 | AG33: -0.373 | AH33: -0.438 | AI33: -0.404 | AJ33: 0.405 | AK33: -0.003 | AL33: 0.384 | AM33: -0.614 | AN33: 0.468 | AO33: -0.364 | AP33: 0.378 | AQ33: 0.941 | AR33: 0.126 | AS33: -0.527 | AT33: 0.719 | AU33: -0.029 | AV33: 0.539 | AW33: 0.409 | AX33: 0.163 | AY33: 0.91 | AZ33: 1 | BA33: 0.837 | BB33: -0.046 | BC33: -0.167 | BD33: 0.084 | BE33: -0.345 | BF33: -0.598 | BG33: 0.554 | BH33: -0.923 | BI33: 0.354 | BJ33: -0.494 | BK33: -0.209 | BM33: =SUMPRODUCT(R33:AD33,$R$225:$AD$225) -> 0.6142674
A34: LOGG3 | B34: =K34 -> 0.01 | C34: =B34-E34 -> 0.01 | D34: =B34-K34 -> 0 | E34: =K34-L34 -> 0 | F34: 2.512 | G34: 2.724 | H34: bond_proxies | I34: =VLOOKUP(A34,Planilha6!$BL$9:$BN$222,2,0) -> real_estate | J34: =VLOOKUP(A34,Planilha6!$BL$9:$BN$222,3,0) -> low_beta | K34: 0.01 | L34: 0.01 | M34: =VLOOKUP(A34,'Mandato Ibov'!$B$1:$C$215,2,0) -> 0.011321078 | N34: =K34-M34 -> -0.0013210781 | O34: =B34-M34 -> -0.0013210781 | P34: =VLOOKUP(A34,'Mandato Ibov'!$B$2:$D$215,3,0) -> 0.0060706506 | Q34: =K34-P34 -> 0.0039293494 | R34: 0.234 | S34: 0.711 | T34: 0.135 | U34: 0.235 | V34: 0.525 | W34: 0.44 | X34: 0.755 | Y34: 0.617 | Z34: 0.758 | AA34: 0.764 | AB34: 0.928 | AC34: 0.849 | AD34: 0.899 | AE34: -0.115 | AF34: -0.275 | AG34: 1 | AH34: 0.248 | AI34: 1 | AJ34: -0.239 | AK34: -0.305 | AL34: 0.283 | AM34: -0.155 | AN34: -0.081 | AO34: 0.747 | AP34: 0.064 | AQ34: -0.126 | AR34: -0.043 | AS34: -0.039 | AT34: -0.077 | AU34: 0.688 | AV34: -0.158 | AW34: 0.345 | AX34: -0.782 | AY34: 0.314 | AZ34: -0.012 | BA34: -0.189 | BB34: 0.181 | BC34: 0.235 | BD34: 0.356 | BE34: 0.084 | BF34: -0.185 | BG34: 0.721 | BH34: -0.512 | BI34: 0.063 | BJ34: 0.333 | BK34: 0.283 | BM34: =SUMPRODUCT(R34:AD34,$R$225:$AD$225) -> 0.5958134
A35: ODPV3 | B35: =K35 -> 0.01 | C35: =B35-E35 -> 0.01 | D35: =B35-K35 -> 0 | E35: =K35-L35 -> 0 | F35: 2.474 | G35: 2.261 | H35: defensives | I35: =VLOOKUP(A35,Planilha6!$BL$9:$BN$222,2,0) -> healthcare | J35: =VLOOKUP(A35,Planilha6!$BL$9:$BN$222,3,0) -> very_low_beta | K35: 0.01 | L35: 0.01 | M35: =VLOOKUP(A35,'Mandato Ibov'!$B$1:$C$215,2,0) -> 0.011152737 | N35: =K35-M35 -> -0.0011527375 | O35: =B35-M35 -> -0.0011527375 | P35: =VLOOKUP(A35,'Mandato Ibov'!$B$2:$D$215,3,0) -> 0.0063914334 | Q35: =K35-P35 -> 0.0036085666 | R35: 0.341 | S35: 0.755 | T35: 0.043 | U35: 0.326 | V35: 0.516 | W35: 0.642 | X35: 0.921 | Y35: 0.699 | Z35: 0.543 | AA35: 0.549 | AB35: 0.69 | AC35: 0.702 | AD35: 0.679 | AE35: 0.549 | AF35: -0.607 | AG35: -0.312 | AH35: -0.751 | AI35: -0.03 | AJ35: 0.378 | AK35: -0.315 | AL35: -0.045 | AM35: -0.93 | AN35: -0.345 | AO35: 0.12 | AP35: 1 | AQ35: 0.004 | AR35: 0.134 | AS35: -0.309 | AT35: 0.969 | AU35: 0.426 | AV35: 1 | AW35: 0.764 | AX35: 0.427 | AY35: 0.745 | AZ35: 0.646 | BA35: 0.948 | BB35: 0.186 | BC35: -0.13 | BD35: 0.31 | BE35: -0.506 | BF35: -0.221 | BG35: 0.687 | BH35: -0.484 | BI35: -0.431 | BJ35: -0.028 | BK35: -0.122 | BM35: =SUMPRODUCT(R35:AD35,$R$225:$AD$225) -> 0.5826759
A36: EVEN3 | B36: 0.011 | C36: =B36-E36 -> 0.011 | D36: =B36-K36 -> -0.001 | E36: =K36-L36 -> 0 | F36: 2.352 | G36: 2.419 | H36: pro_cyclicals | I36: =VLOOKUP(A36,Planilha6!$BL$9:$BN$222,2,0) -> homebuilders | J36: =VLOOKUP(A36,Planilha6!$BL$9:$BN$222,3,0) -> high_beta | K36: 0.012 | L36: 0.012 | M36: =VLOOKUP(A36,'Mandato Ibov'!$B$1:$C$215,2,0) -> 0.010599059 | N36: =K36-M36 -> 0.0014009414 | O36: =B36-M36 -> 0.00040094137 | P36: =VLOOKUP(A36,'Mandato Ibov'!$B$2:$D$215,3,0) -> 0 | Q36: =K36-P36 -> 0.012 | R36: 0.59 | S36: 0.187 | T36: 0.708 | U36: 0.431 | V36: 0.506 | W36: 0.459 | X36: 0.34 | Y36: 0.301 | Z36: 0.554 | AA36: 0.556 | AB36: 0.841 | AC36: 0.924 | AD36: 0.776 | AE36: 0.691 | AF36: 0.635 | AG36: -0.165 | AH36: 0.395 | AI36: 0.196 | AJ36: -0.015 | AK36: -0.202 | AL36: 0.257 | AM36: -0.034 | AN36: 0.219 | AO36: -0.191 | AP36: -0.15 | AQ36: 0.405 | AR36: 0.92 | AS36: 0.84 | AT36: 0.016 | AU36: -0.342 | AV36: 0.313 | AW36: 0.061 | AX36: 0.027 | AY36: 0.757 | AZ36: 0.448 | BA36: 0.166 | BB36: -0.021 | BC36: -0.289 | BD36: -0.073 | BE36: 0.466 | BF36: -0.125 | BG36: 0.625 | BH36: -0.393 | BI36: 0.359 | BJ36: 0.485 | BK36: 0.411 | BM36: =SUMPRODUCT(R36:AD36,$R$225:$AD$225) -> 0.5388127
A37: CURY3 | B37: =K37 -> 0.011 | C37: =B37-E37 -> 0.009 | D37: =B37-K37 -> 0 | E37: =K37-L37 -> 0.002 | F37: 2.352 | G37: 2.494 | H37: pro_cyclicals | I37: =VLOOKUP(A37,Planilha6!$BL$9:$BN$222,2,0) -> homebuilders | J37: =VLOOKUP(A37,Planilha6!$BL$9:$BN$222,3,0) -> low_beta | K37: 0.011 | L37: 0.009 | M37: =VLOOKUP(A37,'Mandato Ibov'!$B$1:$C$215,2,0) -> 0.012374801 | N37: =K37-M37 -> -0.0013748005 | O37: =B37-M37 -> -0.0013748005 | P37: =VLOOKUP(A37,'Mandato Ibov'!$B$2:$D$215,3,0) -> 0.0074086906 | Q37: =K37-P37 -> 0.0035913094 | R37: 0.231 | S37: 0.503 | T37: -0.049 | U37: 0.509 | V37: 0.564 | W37: 0.494 | X37: 0.537 | Y37: 0.721 | Z37: 0.622 | AA37: 0.627 | AB37: 0.794 | AC37: 0.796 | AD37: 0.656 | AE37: 0.712 | AF37: 0.257 | AG37: -0.238 | AH37: -0.628 | AI37: -0.21 | AJ37: -0.034 | AK37: -0.137 | AL37: 0.385 | AM37: -0.856 | AN37: 0.119 | AO37: 0.177 | AP37: 0.465 | AQ37: 0.449 | AR37: 0.193 | AS37: 0.385 | AT37: 1 | AU37: 0.102 | AV37: 0.546 | AW37: 0.144 | AX37: 0.31 | AY37: 0.841 | AZ37: 0.963 | BA37: 0.326 | BB37: -0.759 | BC37: -0.295 | BD37: -0.274 | BE37: 0.573 | BF37: -0.043 | BG37: 0.335 | BH37: -0.981 | BI37: 0.172 | BJ37: -0.427 | BK37: -0.336 | BM37: =SUMPRODUCT(R37:AD37,$R$225:$AD$225) -> 0.5391686
A38: ALOS3 | B38: =K38 -> 0.016 | C38: =B38-E38 -> 0.01 | D38: =B38-K38 -> 0 | E38: =K38-L38 -> 0.006 | F38: 2.348 | G38: 3.874 | H38: bond_proxies | I38: =VLOOKUP(A38,Planilha6!$BL$9:$BN$222,2,0) -> real_estate | J38: =VLOOKUP(A38,Planilha6!$BL$9:$BN$222,3,0) -> high_beta | K38: 0.016 | L38: 0.01 | M38: =VLOOKUP(A38,'Mandato Ibov'!$B$1:$C$215,2,0) -> 0.018441014 | N38: =K38-M38 -> -0.0024410138 | O38: =B38-M38 -> -0.0024410138 | P38: =VLOOKUP(A38,'Mandato Ibov'!$B$2:$D$215,3,0) -> 0.013361495 | Q38: =K38-P38 -> 0.0026385051 | R38: 0.19 | S38: 0.836 | T38: -0.35 | U38: 0.447 | V38: 0.505 | W38: 0.613 | X38: 0.906 | Y38: 0.58 | Z38: 0.67 | AA38: 0.675 | AB38: 0.757 | AC38: 0.723 | AD38: 0.693 | AE38: 0.628 | AF38: -0.127 | AG38: 0.518 | AH38: -0.772 | AI38: -0.114 | AJ38: -0.293 | AK38: -0.079 | AL38: -0.193 | AM38: -0.513 | AN38: 0.018 | AO38: 0.598 | AP38: 0.472 | AQ38: 0.265 | AR38: 0.286 | AS38: -0.136 | AT38: 0.015 | AU38: 0.87 | AV38: 0.656 | AW38: 0.319 | AX38: 0.293 | AY38: 0.577 | AZ38: 0.419 | BA38: -0.7 | BB38: -0.048 | BC38: -0.143 | BD38: 0.363 | BE38: -0.388 | BF38: 0.155 | BG38: 0.749 | BH38: -0.489 | BI38: 0.381 | BJ38: -0.587 | BK38: -0.416 | BM38: =SUMPRODUCT(R38:AD38,$R$225:$AD$225) -> 0.5377946
A39: ITSA3 | B39: =K39 -> 0.021 | C39: =B39-E39 -> 0.021 | D39: =B39-K39 -> 0 | E39: =K39-L39 -> 0 | F39: 2.334 | G39: 3.14 | H39: pro_cyclicals | I39: =VLOOKUP(A39,Planilha6!$BL$9:$BN$222,2,0) -> banks | J39: =VLOOKUP(A39,Planilha6!$BL$9:$BN$222,3,0) -> neutral_beta | K39: 0.021 | L39: 0.021 | M39: =VLOOKUP(A39,'Mandato Ibov'!$B$1:$C$215,2,0) -> 0.010521458 | N39: =K39-M39 -> 0.010478542 | O39: =B39-M39 -> 0.010478542 | P39: =VLOOKUP(A39,'Mandato Ibov'!$B$2:$D$215,3,0) -> 0.0075607711 | Q39: =K39-P39 -> 0.013439229 | R39: 0.126 | S39: 0.664 | T39: -0.309 | U39: 0.276 | V39: 0.389 | W39: 0.442 | X39: 0.616 | Y39: 0.61 | Z39: 0.752 | AA39: 0.76 | AB39: 0.8 | AC39: 0.886 | AD39: 0.873 | AE39: 0.106 | AF39: -0.297 | AG39: 0.557 | AH39: -0.966 | AI39: -0.636 | AJ39: -0.845 | AK39: -0.149 | AL39: 0.186 | AM39: -0.665 | AN39: -0.399 | AO39: 0.671 | AP39: 0.685 | AQ39: -0.01 | AR39: 0.171 | AS39: 0.41 | AT39: 0.058 | AU39: 0.051 | AV39: 0.294 | AW39: 0.502 | AX39: -0.451 | AY39: 0.936 | AZ39: 0.252 | BA39: 0.911 | BB39: -0.023 | BC39: 0.321 | BD39: 0.521 | BE39: -0.231 | BF39: -0.275 | BG39: 0.832 | BH39: -0.668 | BI39: -0.017 | BJ39: 0.885 | BK39: -0.689 | BM39: =SUMPRODUCT(R39:AD39,$R$225:$AD$225) -> 0.5327716
A40: MELK3 | B40: 0.0115 | C40: =B40-E40 -> 0.0115 | D40: =B40-K40 -> -0.0015 | E40: =K40-L40 -> 0 | F40: 2.315 | G40: 2.539 | H40: pro_cyclicals | I40: =VLOOKUP(A40,Planilha6!$BL$9:$BN$222,2,0) -> homebuilders | J40: =VLOOKUP(A40,Planilha6!$BL$9:$BN$222,3,0) -> neutral_beta | K40: 0.013 | L40: 0.013 | M40: =VLOOKUP(A40,'Mandato Ibov'!$B$1:$C$215,2,0) -> 0.010436295 | N40: =K40-M40 -> 0.0025637045 | O40: =B40-M40 -> 0.0010637045 | P40: =VLOOKUP(A40,'Mandato Ibov'!$B$2:$D$215,3,0) -> 0.0071146122 | Q40: =K40-P40 -> 0.0058853878 | R40: 0.201 | S40: 0.158 | T40: 0.57 | U40: 0.021 | V40: 0.365 | W40: 0.364 | X40: 0.486 | Y40: 0.733 | Z40: 0.636 | AA40: 0.637 | AB40: 0.825 | AC40: 0.699 | AD40: 0.749 | AE40: 0.156 | AF40: -0.116 | AG40: -0.124 | AH40: 0.978 | AI40: 0.649 | AJ40: -0.077 | AK40: -0.165 | AL40: 0.986 | AM40: -0.031 | AN40: -0.049 | AO40: -0.128 | AP40: -0.022 | AQ40: 0.021 | AR40: -0.13 | AS40: -0.125 | AT40: 0.016 | AU40: -0.412 | AV40: -0.064 | AW40: 0.598 | AX40: -0.367 | AY40: 0.678 | AZ40: 0.411 | BA40: 0.231 | BB40: -0.029 | BC40: -0.434 | BD40: -0.499 | BE40: 0.43 | BF40: 0.671 | BG40: 0.881 | BH40: -0.404 | BI40: 0.265 | BJ40: 0.729 | BK40: 0.638 | BM40: =SUMPRODUCT(R40:AD40,$R$225:$AD$225) -> 0.5260785
A41: VLID3 | B41: 0.0125 | C41: =B41-E41 -> 0.0125 | D41: =B41-K41 -> -0.0015 | E41: =K41-L41 -> 0 | F41: 2.277 | G41: 2.293 | H41: pro_cyclicals | I41: =VLOOKUP(A41,Planilha6!$BL$9:$BN$222,2,0) -> tech | J41: =VLOOKUP(A41,Planilha6!$BL$9:$BN$222,3,0) -> low_beta | K41: 0.014 | L41: 0.014 | M41: =VLOOKUP(A41,'Mandato Ibov'!$B$1:$C$215,2,0) -> 0.010264782 | N41: =K41-M41 -> 0.0037352181 | O41: =B41-M41 -> 0.0022352181 | P41: =VLOOKUP(A41,'Mandato Ibov'!$B$2:$D$215,3,0) -> 0.0097176257 | Q41: =K41-P41 -> 0.0042823743 | R41: 0.459 | S41: 0.329 | T41: 0.609 | U41: 0.231 | V41: 0.442 | W41: 0.459 | X41: 0.496 | Y41: 0.317 | Z41: 0.585 | AA41: 0.592 | AB41: 0.824 | AC41: 0.795 | AD41: 0.742 | AE41: 0.208 | AF41: 0.34 | AG41: -0.365 | AH41: 0.246 | AI41: -0.139 | AJ41: 1 | AK41: 0.245 | AL41: 0.089 | AM41: -0.326 | AN41: -0.038 | AO41: -0.137 | AP41: -0.088 | AQ41: 0.47 | AR41: 0.275 | AS41: 0.1 | AT41: 0.428 | AU41: -0.036 | AV41: -0.041 | AW41: 0.442 | AX41: 0.223 | AY41: 0.733 | AZ41: 0.469 | BA41: 0.797 | BB41: -0.083 | BC41: -0.056 | BD41: -0.021 | BE41: 0.3 | BF41: -0.092 | BG41: 0.75 | BH41: -0.785 | BI41: -0.164 | BJ41: 0.5 | BK41: 0.349 | BM41: =SUMPRODUCT(R41:AD41,$R$225:$AD$225) -> 0.5126405
A42: TRIS3 | B42: =K42 -> 0.005 | C42: =B42-E42 -> 0.005 | D42: =B42-K42 -> 0 | E42: =K42-L42 -> 0 | F42: 2.228 | G42: 1.644 | H42: pro_cyclicals | I42: =VLOOKUP(A42,Planilha6!$BL$9:$BN$222,2,0) -> homebuilders | J42: =VLOOKUP(A42,Planilha6!$BL$9:$BN$222,3,0) -> high_beta | K42: 0.005 | L42: 0.005 | M42: =VLOOKUP(A42,'Mandato Ibov'!$B$1:$C$215,2,0) -> 0.010041029 | N42: =K42-M42 -> -0.0050410286 | O42: =B42-M42 -> -0.0050410286 | P42: =VLOOKUP(A42,'Mandato Ibov'!$B$2:$D$215,3,0) -> 0 | Q42: =K42-P42 -> 0.005 | R42: 0.576 | S42: 0.225 | T42: 0.71 | U42: 0.357 | V42: 0.483 | W42: 0.404 | X42: 0.292 | Y42: 0.304 | Z42: 0.369 | AA42: 0.367 | AB42: 0.876 | AC42: 0.737 | AD42: 0.718 | AE42: 0.579 | AF42: 0.806 | AG42: -0.356 | AH42: 0.406 | AI42: 0.338 | AJ42: 0.348 | AK42: -0.186 | AL42: 0.315 | AM42: -0.306 | AN42: 0.588 | AO42: 0.137 | AP42: -0.187 | AQ42: 0.604 | AR42: -0.009 | AS42: -0.339 | AT42: 0.092 | AU42: -0.106 | AV42: 0.251 | AW42: -0.26 | AX42: 0.034 | AY42: 0.671 | AZ42: 0.612 | BA42: 0.804 | BB42: -0.004 | BC42: -0.325 | BD42: 0.099 | BE42: 0.641 | BF42: -0.541 | BG42: 0.375 | BH42: -0.559 | BI42: 0.603 | BJ42: 0.757 | BK42: 0.413 | BM42: =SUMPRODUCT(R42:AD42,$R$225:$AD$225) -> 0.4950593
A43: VULC3 | B43: =K43 -> 0.012 | C43: =B43-E43 -> 0.012 | D43: =B43-K43 -> 0 | E43: =K43-L43 -> 0 | F43: 2.224 | G43: 2.463 | H43: pro_cyclicals | I43: =VLOOKUP(A43,Planilha6!$BL$9:$BN$222,2,0) -> apparel | J43: =VLOOKUP(A43,Planilha6!$BL$9:$BN$222,3,0) -> low_beta | K43: 0.012 | L43: 0.012 | M43: =VLOOKUP(A43,'Mandato Ibov'!$B$1:$C$215,2,0) -> 0.010026176 | N43: =K43-M43 -> 0.0019738238 | O43: =B43-M43 -> 0.0019738238 | P43: =VLOOKUP(A43,'Mandato Ibov'!$B$2:$D$215,3,0) -> 0.006223723 | Q43: =K43-P43 -> 0.005776277 | R43: -0.101 | S43: 0.229 | T43: 0.038 | U43: 0.215 | V43: 0.454 | W43: 0.487 | X43: 0.823 | Y43: 1 | Z43: 0.613 | AA43: 0.619 | AB43: 0.748 | AC43: 0.643 | AD43: 0.474 | AE43: 0.758 | AF43: 0.219 | AG43: -0.642 | AH43: -0.236 | AI43: -0.575 | AJ43: 0.381 | AK43: -0.273 | AL43: 1 | AM43: -0.745 | AN43: 0.552 | AO43: -0.275 | AP43: -0.514 | AQ43: 0.288 | AR43: -0.057 | AS43: -0.397 | AT43: 0.831 | AU43: 0.138 | AV43: 0.366 | AW43: 0.373 | AX43: -0.058 | AY43: 0.724 | AZ43: 1 | BA43: 0.073 | BB43: -0.709 | BC43: -0.767 | BD43: -0.525 | BE43: 0.109 | BF43: -0.056 | BG43: 0.797 | BH43: -0.746 | BI43: -0.25 | BJ43: 0.171 | BK43: 0.089 | BM43: =SUMPRODUCT(R43:AD43,$R$225:$AD$225) -> 0.4938117
A44: INTB3 | B44: =K44 -> 0.011 | C44: =B44-E44 -> 0.011 | D44: =B44-K44 -> 0 | E44: =K44-L44 -> 0 | F44: 2.221 | G44: 2.116 | H44: pro_cyclicals | I44: =VLOOKUP(A44,Planilha6!$BL$9:$BN$222,2,0) -> tech | J44: =VLOOKUP(A44,Planilha6!$BL$9:$BN$222,3,0) -> high_beta | K44: 0.011 | L44: 0.011 | M44: =VLOOKUP(A44,'Mandato Ibov'!$B$1:$C$215,2,0) -> 0.010012074 | N44: =K44-M44 -> 0.000987926 | O44: =B44-M44 -> 0.000987926 | P44: =VLOOKUP(A44,'Mandato Ibov'!$B$2:$D$215,3,0) -> 0.0063078922 | Q44: =K44-P44 -> 0.0046921078 | R44: 0.563 | S44: 0.544 | T44: 0.256 | U44: 0.334 | V44: 0.404 | W44: 0.393 | X44: 0.308 | Y44: 0.174 | Z44: 0.533 | AA44: 0.537 | AB44: 0.833 | AC44: 0.852 | AD44: 0.821 | AE44: 0.285 | AF44: -0.339 | AG44: 0.348 | AH44: -0.327 | AI44: 0.589 | AJ44: 0.078 | AK44: 0.095 | AL44: -0.242 | AM44: -0.645 | AN44: 0.766 | AO44: 0.359 | AP44: 0.789 | AQ44: 0.075 | AR44: 0.135 | AS44: 0.173 | AT44: 0.532 | AU44: -0.093 | AV44: 0.353 | AW44: 0.208 | AX44: 0.38 | AY44: 0.817 | AZ44: 0.293 | BA44: 0.164 | BB44: 0.12 | BC44: 0.09 | BD44: 0.386 | BE44: 0.304 | BF44: 0.443 | BG44: 0.464 | BH44: 0.03 | BI44: 0.09 | BJ44: 0.002 | BK44: -0.111 | BM44: =SUMPRODUCT(R44:AD44,$R$225:$AD$225) -> 0.4924735
A45: BMEB4 | B45: =K45 -> 0.008 | C45: =B45-E45 -> 0.008 | D45: =B45-K45 -> 0 | E45: =K45-L45 -> 0 | F45: 2.182 | G45: 1.618 | H45: pro_cyclicals | I45: =VLOOKUP(A45,Planilha6!$BL$9:$BN$222,2,0) -> banks | J45: =VLOOKUP(A45,Planilha6!$BL$9:$BN$222,3,0) -> high_beta | K45: 0.008 | L45: 0.008 | M45: =VLOOKUP(A45,'Mandato Ibov'!$B$1:$C$215,2,0) -> 0.0098346791 | N45: =K45-M45 -> -0.0018346791 | O45: =B45-M45 -> -0.0018346791 | P45: =VLOOKUP(A45,'Mandato Ibov'!$B$2:$D$215,3,0) -> 0.0072699069 | Q45: =K45-P45 -> 0.00073009314 | R45: 0.311 | S45: 0.549 | T45: 0.414 | U45: 0.177 | V45: 0.504 | W45: 0.172 | X45: 0.007 | Y45: 0.139 | Z45: 0.888 | AA45: 0.889 | AB45: 0.962 | AC45: 0.932 | AD45: 0.968 | AE45: -0.517 | AF45: 0.051 | AG45: 0.466 | AH45: -0.718 | AI45: 0.615 | AJ45: -0.055 | AK45: -0.097 | AL45: -0.406 | AM45: -0.587 | AN45: -0.613 | AO45: 0.713 | AP45: 0.805 | AQ45: 0.324 | AR45: 1 | AS45: 0.681 | AT45: 0.363 | AU45: -0.084 | AV45: -0.053 | AW45: 0.382 | AX45: 0.089 | AY45: 0.62 | AZ45: 1 | BA45: 0.233 | BB45: -0.535 | BC45: -0.208 | BD45: -0.461 | BE45: 0.477 | BF45: 0.174 | BG45: 0.328 | BH45: -1 | BI45: 0.306 | BJ45: 0.906 | BK45: 0.399 | BM45: =SUMPRODUCT(R45:AD45,$R$225:$AD$225) -> 0.4786288
A46: MLAS3 | B46: =K46 -> 0.007 | C46: =B46-E46 -> 0.007 | D46: =B46-K46 -> 0 | E46: =K46-L46 -> 0 | F46: 2.15 | G46: 1.622 | H46: pro_cyclicals | I46: =VLOOKUP(A46,Planilha6!$BL$9:$BN$222,2,0) -> tech | J46: =VLOOKUP(A46,Planilha6!$BL$9:$BN$222,3,0) -> neutral_beta | K46: 0.007 | L46: 0.007 | M46: =VLOOKUP(A46,'Mandato Ibov'!$B$1:$C$215,2,0) -> 0.0096885847 | N46: =K46-M46 -> -0.0026885847 | O46: =B46-M46 -> -0.0026885847 | P46: =VLOOKUP(A46,'Mandato Ibov'!$B$2:$D$215,3,0) -> 0 | Q46: =K46-P46 -> 0.007 | R46: 0.946 | S46: 0.209 | T46: 0.956 | U46: 0.491 | V46: 0.448 | W46: 0.177 | X46: -0.253 | Y46: -0.459 | Z46: 0.719 | AA46: 0.721 | AB46: 0.983 | AC46: 1 | AD46: 1 | AE46: 0.592 | AF46: 0.402 | AG46: 0.474 | AH46: 0.266 | AI46: 0.381 | AJ46: 0.307 | AK46: -0.221 | AL46: -0.791 | AM46: 0.558 | AN46: 0.31 | AO46: 0.412 | AP46: -0.161 | AQ46: 0.285 | AR46: 1 | AS46: 0.803 | AT46: 0.001 | AU46: -0.315 | AV46: 0.383 | AW46: -0.457 | AX46: 0.371 | AY46: 0.614 | AZ46: -0.004 | BA46: 0.885 | BB46: 0.308 | BC46: -0.192 | BD46: 0.664 | BE46: -0.495 | BF46: 0.131 | BG46: 0.217 | BH46: 0.498 | BI46: -0.127 | BJ46: 0.887 | BK46: 0.482 | BM46: =SUMPRODUCT(R46:AD46,$R$225:$AD$225) -> 0.4670848
A47: ALUP11 | B47: =K47 -> 0.02 | C47: =B47-E47 -> 0.02 | D47: =B47-K47 -> 0 | E47: =K47-L47 -> 0 | F47: 2.081 | G47: 2.799 | H47: bond_proxies | I47: =VLOOKUP(A47,Planilha6!$BL$9:$BN$222,2,0) -> utilities | J47: =VLOOKUP(A47,Planilha6!$BL$9:$BN$222,3,0) -> very_low_beta | K47: 0.02 | L47: 0.02 | M47: =VLOOKUP(A47,'Mandato Ibov'!$B$1:$C$215,2,0) -> 0.0093783751 | N47: =K47-M47 -> 0.010621625 | O47: =B47-M47 -> 0.010621625 | P47: =VLOOKUP(A47,'Mandato Ibov'!$B$2:$D$215,3,0) -> 0.0064669249 | Q47: =K47-P47 -> 0.013533075 | R47: -0.121 | S47: 0.68 | T47: -0.33 | U47: 0.019 | V47: 0.337 | W47: 0.383 | X47: 0.725 | Y47: 0.479 | Z47: 0.88 | AA47: 0.886 | AB47: 0.704 | AC47: 0.902 | AD47: 0.744 | AE47: 0.101 | AF47: -0.581 | AG47: 0.371 | AH47: -0.705 | AI47: -0.306 | AJ47: -0.756 | AK47: -0.049 | AL47: -0.428 | AM47: -0.287 | AN47: -0.368 | AO47: 0.347 | AP47: 0.403 | AQ47: -0.109 | AR47: 0.07 | AS47: 0.307 | AT47: 0.06 | AU47: 0.708 | AV47: 0.278 | AW47: 0.791 | AX47: -0.504 | AY47: 0.818 | AZ47: 1 | BA47: 0.021 | BB47: 0.03 | BC47: -0.223 | BD47: 0.284 | BE47: 0.147 | BF47: -0.233 | BG47: 0.937 | BH47: -0.494 | BI47: -0.403 | BJ47: 0.298 | BK47: 0.118 | BM47: =SUMPRODUCT(R47:AD47,$R$225:$AD$225) -> 0.4427937
A48: PNVL3 | B48: =K48 -> 0.012 | C48: =B48-E48 -> 0.012 | D48: =B48-K48 -> 0 | E48: =K48-L48 -> 0 | F48: 2.065 | G48: 2.254 | H48: defensives | I48: =VLOOKUP(A48,Planilha6!$BL$9:$BN$222,2,0) -> healthcare | J48: =VLOOKUP(A48,Planilha6!$BL$9:$BN$222,3,0) -> neutral_beta | K48: 0.012 | L48: 0.012 | M48: =VLOOKUP(A48,'Mandato Ibov'!$B$1:$C$215,2,0) -> 0.0093097023 | N48: =K48-M48 -> 0.0026902977 | O48: =B48-M48 -> 0.0026902977 | P48: =VLOOKUP(A48,'Mandato Ibov'!$B$2:$D$215,3,0) -> 0.0092720699 | Q48: =K48-P48 -> 0.0027279301 | R48: 0.451 | S48: 0.491 | T48: 0.285 | U48: 0.336 | V48: 0.41 | W48: 0.276 | X48: 0.274 | Y48: -0.087 | Z48: 0.556 | AA48: 0.56 | AB48: 0.898 | AC48: 1 | AD48: 0.915 | AE48: -0.145 | AF48: -0.352 | AG48: 0.782 | AH48: -0.374 | AI48: 1 | AJ48: 0.352 | AK48: -0.173 | AL48: -0.6 | AM48: -0.581 | AN48: 0.095 | AO48: 0.719 | AP48: 0.665 | AQ48: 0.332 | AR48: 0.214 | AS48: 0.475 | AT48: 0.526 | AU48: -0.321 | AV48: 0.467 | AW48: 0.398 | AX48: -0.129 | AY48: 0.999 | AZ48: -0.28 | BA48: 0.779 | BB48: -0.285 | BC48: -0.276 | BD48: 0.166 | BE48: 0.299 | BF48: -0.692 | BG48: 0.672 | BH48: -0.306 | BI48: -0.034 | BJ48: 0.269 | BK48: 0.402 | BM48: =SUMPRODUCT(R48:AD48,$R$225:$AD$225) -> 0.4373148
A49: RECV3 | B49: =K49 -> 0.015 | C49: =B49-E49 -> 0.014 | D49: =B49-K49 -> 0 | E49: =K49-L49 -> 0.001 | F49: 2.021 | G49: 2.02 | H49: commodities | I49: =VLOOKUP(A49,Planilha6!$BL$9:$BN$222,2,0) -> crude_oil | J49: =VLOOKUP(A49,Planilha6!$BL$9:$BN$222,3,0) -> very_low_beta | K49: 0.015 | L49: 0.014 | M49: =VLOOKUP(A49,'Mandato Ibov'!$B$1:$C$215,2,0) -> 0.0098997659 | N49: =K49-M49 -> 0.0051002341 | O49: =B49-M49 -> 0.0051002341 | P49: =VLOOKUP(A49,'Mandato Ibov'!$B$2:$D$215,3,0) -> 0.0083775133 | Q49: =K49-P49 -> 0.0066224867 | R49: -0.176 | S49: 0.311 | T49: -0.404 | U49: 0.002 | V49: 0.171 | W49: 0.361 | X49: 0.406 | Y49: 0.657 | Z49: 0.905 | AA49: 0.907 | AB49: 0.778 | AC49: 0.828 | AD49: 0.736 | AE49: -0.256 | AF49: -0.341 | AG49: 0.955 | AH49: 0.051 | AI49: 0.522 | AJ49: -0.666 | AK49: -0.243 | AL49: 0.77 | AM49: -0.06 | AN49: 0.331 | AO49: 0.367 | AP49: 0.896 | AQ49: -0.427 | AR49: 0.28 | AS49: 0.045 | AT49: 0.163 | AU49: 0.17 | AV49: -0.175 | AW49: 0.312 | AX49: 0.166 | AY49: 0.822 | AZ49: 0.111 | BA49: -0.317 | BB49: -0.422 | BC49: -0.656 | BD49: -0.674 | BE49: 0.179 | BF49: 0.787 | BG49: 0.624 | BH49: -0.202 | BI49: -0.785 | BJ49: -0.543 | BK49: 0.437 | BM49: =SUMPRODUCT(R49:AD49,$R$225:$AD$225) -> 0.4212812
A50: OPCT3 | B50: =K50 -> 0.014 | C50: =B50-E50 -> 0.014 | D50: =B50-K50 -> 0 | E50: =K50-L50 -> 0 | F50: 1.992 | G50: 2.149 | H50: commodities | I50: =VLOOKUP(A50,Planilha6!$BL$9:$BN$222,2,0) -> crude_oil | J50: =VLOOKUP(A50,Planilha6!$BL$9:$BN$222,3,0) -> very_low_beta | K50: 0.014 | L50: 0.014 | M50: =VLOOKUP(A50,'Mandato Ibov'!$B$1:$C$215,2,0) -> 0.0089807713 | N50: =K50-M50 -> 0.0050192287 | O50: =B50-M50 -> 0.0050192287 | P50: =VLOOKUP(A50,'Mandato Ibov'!$B$2:$D$215,3,0) -> 0.0072310179 | Q50: =K50-P50 -> 0.0067689821 | R50: 0.465 | S50: 0.361 | T50: 0.457 | U50: 0.258 | V50: 0.377 | W50: 0.424 | X50: 0.193 | Y50: -0.241 | Z50: 0.734 | AA50: 0.731 | AB50: 0.839 | AC50: 0.868 | AD50: 0.871 | AE50: -0.243 | AF50: 0.145 | AG50: 0.139 | AH50: -0.431 | AI50: 1 | AJ50: 0.469 | AK50: -0.297 | AL50: -0.94 | AM50: -0.671 | AN50: 0.637 | AO50: 0.482 | AP50: 0.309 | AQ50: 0.917 | AR50: 0.705 | AS50: 0.388 | AT50: 0.259 | AU50: -0.139 | AV50: 0.487 | AW50: 0.484 | AX50: -0.067 | AY50: 0.777 | AZ50: 0.28 | BA50: 0.93 | BB50: -0.272 | BC50: -0.547 | BD50: 0.254 | BE50: -0.215 | BF50: -0.048 | BG50: 0.554 | BH50: -0.565 | BI50: -0.743 | BJ50: 0.626 | BK50: 0.635 | BM50: =SUMPRODUCT(R50:AD50,$R$225:$AD$225) -> 0.4114514
A51: LAVV3 | B51: 0.011 | C51: =B51-E51 -> 0.011 | D51: =B51-K51 -> -0.003 | E51: =K51-L51 -> 0 | F51: 1.983 | G51: 2.289 | H51: pro_cyclicals | I51: =VLOOKUP(A51,Planilha6!$BL$9:$BN$222,2,0) -> homebuilders | J51: =VLOOKUP(A51,Planilha6!$BL$9:$BN$222,3,0) -> high_beta | K51: 0.014 | L51: 0.014 | M51: =VLOOKUP(A51,'Mandato Ibov'!$B$1:$C$215,2,0) -> 0.0089362388 | N51: =K51-M51 -> 0.0050637612 | O51: =B51-M51 -> 0.0020637612 | P51: =VLOOKUP(A51,'Mandato Ibov'!$B$2:$D$215,3,0) -> 0.0082533799 | Q51: =K51-P51 -> 0.0057466201 | R51: 0.034 | S51: 0.271 | T51: 0.195 | U51: -0.062 | V51: 0.305 | W51: 0.235 | X51: 0.307 | Y51: 0.584 | Z51: 0.495 | AA51: 0.492 | AB51: 0.708 | AC51: 0.797 | AD51: 0.7 | AE51: -0.332 | AF51: 0.32 | AG51: 0.09 | AH51: -0.074 | AI51: 0.885 | AJ51: -0.178 | AK51: -0.291 | AL51: 0.661 | AM51: -0.572 | AN51: 0.118 | AO51: 0.261 | AP51: -0.223 | AQ51: 0.406 | AR51: -0.122 | AS51: -0.752 | AT51: 0.217 | AU51: -0.14 | AV51: -0.273 | AW51: 0.199 | AX51: 0.178 | AY51: 0.538 | AZ51: 1 | BA51: 0.695 | BB51: -0.382 | BC51: -0.548 | BD51: -0.546 | BE51: 0.441 | BF51: 0.037 | BG51: 0.604 | BH51: -0.892 | BI51: 0.614 | BJ51: 0.425 | BK51: 0.132 | BM51: =SUMPRODUCT(R51:AD51,$R$225:$AD$225) -> 0.40787
A52: VIVT3 | B52: =K52 -> 0.016 | C52: =B52-E52 -> 0.006 | D52: =B52-K52 -> 0 | E52: =K52-L52 -> 0.01 | F52: 1.978 | G52: 3.475 | H52: bond_proxies | I52: =VLOOKUP(A52,Planilha6!$BL$9:$BN$222,2,0) -> telecom | J52: =VLOOKUP(A52,Planilha6!$BL$9:$BN$222,3,0) -> very_low_beta | K52: 0.016 | L52: 0.006 | M52: =VLOOKUP(A52,'Mandato Ibov'!$B$1:$C$215,2,0) -> 0.024317677 | N52: =K52-M52 -> -0.0083176772 | O52: =B52-M52 -> -0.0083176772 | P52: =VLOOKUP(A52,'Mandato Ibov'!$B$2:$D$215,3,0) -> 0.02197856 | Q52: =K52-P52 -> -0.0059785602 | R52: -0.064 | S52: 0.59 | T52: -0.589 | U52: 0.265 | V52: 0.273 | W52: 0.41 | X52: 0.61 | Y52: 0.34 | Z52: 0.796 | AA52: 0.803 | AB52: 0.754 | AC52: 0.847 | AD52: 0.766 | AE52: 0.162 | AF52: -0.286 | AG52: 0.489 | AH52: -1 | AI52: -0.545 | AJ52: -0.723 | AK52: -0.241 | AL52: -0.413 | AM52: -0.549 | AN52: -0.794 | AO52: 0.494 | AP52: 0.996 | AQ52: 0.389 | AR52: 0.12 | AS52: 0.35 | AT52: 0.248 | AU52: 0.067 | AV52: 0.748 | AW52: 0.862 | AX52: -0.166 | AY52: 0.797 | AZ52: 0.13 | BA52: 0.48 | BB52: 0.142 | BC52: -0.087 | BD52: 0.453 | BE52: 0.291 | BF52: 0.09 | BG52: 0.92 | BH52: -0.69 | BI52: -0.332 | BJ52: 0.039 | BK52: -0.781 | BM52: =SUMPRODUCT(R52:AD52,$R$225:$AD$225) -> 0.4063367
A53: PINE4 | B53: =K53 -> 0.009 | C53: =B53-E53 -> 0.009 | D53: =B53-K53 -> 0 | E53: =K53-L53 -> 0 | F53: 1.963 | G53: 1.523 | H53: pro_cyclicals | I53: =VLOOKUP(A53,Planilha6!$BL$9:$BN$222,2,0) -> banks | J53: =VLOOKUP(A53,Planilha6!$BL$9:$BN$222,3,0) -> neutral_beta | K53: 0.009 | L53: 0.009 | M53: =VLOOKUP(A53,'Mandato Ibov'!$B$1:$C$215,2,0) -> 0.0088460816 | N53: =K53-M53 -> 0.00015391843 | O53: =B53-M53 -> 0.00015391843 | P53: =VLOOKUP(A53,'Mandato Ibov'!$B$2:$D$215,3,0) -> 0.011222419 | Q53: =K53-P53 -> -0.0022224186 | R53: 0.19 | S53: 0.268 | T53: 0.326 | U53: 0.308 | V53: 0.47 | W53: 0.056 | X53: -0.033 | Y53: 0.159 | Z53: 0.711 | AA53: 0.71 | AB53: 0.868 | AC53: 0.868 | AD53: 0.87 | AE53: -0.181 | AF53: 0.431 | AG53: 0.446 | AH53: -0.426 | AI53: 0.679 | AJ53: 0.793 | AK53: -0.049 | AL53: -0.159 | AM53: -0.403 | AN53: -0.097 | AO53: 0.736 | AP53: -0.171 | AQ53: 0.868 | AR53: -0.044 | AS53: -0.317 | AT53: 0.236 | AU53: -0.21 | AV53: 0.237 | AW53: 0.4 | AX53: -0.166 | AY53: -0.135 | AZ53: 0.458 | BA53: 0.48 | BB53: -0.189 | BC53: -0.113 | BD53: -0.461 | BE53: -1 | BF53: -0.728 | BG53: 0.214 | BH53: -1 | BI53: -0.01 | BJ53: 0.533 | BK53: 0.656 | BM53: =SUMPRODUCT(R53:AD53,$R$225:$AD$225) -> 0.4009728
A54: BMOB3 | B54: 0.01 | C54: =B54-E54 -> 0.01 | D54: =B54-K54 -> -0.002 | E54: =K54-L54 -> 0 | F54: 1.913 | G54: 1.879 | H54: pro_cyclicals | I54: =VLOOKUP(A54,Planilha6!$BL$9:$BN$222,2,0) -> tech | J54: =VLOOKUP(A54,Planilha6!$BL$9:$BN$222,3,0) -> high_beta | K54: 0.012 | L54: 0.012 | M54: =VLOOKUP(A54,'Mandato Ibov'!$B$1:$C$215,2,0) -> 0.0086222545 | N54: =K54-M54 -> 0.0033777455 | O54: =B54-M54 -> 0.0013777455 | P54: =VLOOKUP(A54,'Mandato Ibov'!$B$2:$D$215,3,0) -> 0.0079462234 | Q54: =K54-P54 -> 0.0040537766 | R54: 0.43 | S54: 0.138 | T54: 0.574 | U54: 0.186 | V54: 0.339 | W54: 0.209 | X54: 0.072 | Y54: 0.088 | Z54: 0.273 | AA54: 0.274 | AB54: 0.722 | AC54: 0.934 | AD54: 0.788 | AE54: 0.298 | AF54: -0.212 | AG54: -0.185 | AH54: -0.252 | AI54: 0.928 | AJ54: 0.87 | AK54: -0.286 | AL54: -0.06 | AM54: -0.86 | AN54: 0.071 | AO54: 0.207 | AP54: 0.535 | AQ54: 0.284 | AR54: 0.221 | AS54: 0.386 | AT54: 0.517 | AU54: -0.276 | AV54: 0.479 | AW54: 0.235 | AX54: 0.751 | AY54: 0.962 | AZ54: 0.233 | BA54: 0.861 | BB54: 0.084 | BC54: -0.048 | BD54: -0.638 | BE54: -0.726 | BF54: -0.675 | BG54: 0.327 | BH54: -0.591 | BI54: 0.098 | BJ54: 0.316 | BK54: 0.191 | BM54: =SUMPRODUCT(R54:AD54,$R$225:$AD$225) -> 0.3831133
A55: POSI3 | B55: 0.01 | C55: =B55-E55 -> 0.01 | D55: =B55-K55 -> -0.004 | E55: =K55-L55 -> 0 | F55: 1.847 | G55: 1.568 | H55: pro_cyclicals | I55: =VLOOKUP(A55,Planilha6!$BL$9:$BN$222,2,0) -> tech | J55: =VLOOKUP(A55,Planilha6!$BL$9:$BN$222,3,0) -> low_beta | K55: 0.014 | L55: 0.014 | M55: =VLOOKUP(A55,'Mandato Ibov'!$B$1:$C$215,2,0) -> 0.0083264803 | N55: =K55-M55 -> 0.0056735197 | O55: =B55-M55 -> 0.0016735197 | P55: =VLOOKUP(A55,'Mandato Ibov'!$B$2:$D$215,3,0) -> 0 | Q55: =K55-P55 -> 0.014 | R55: 0.321 | S55: 0 | T55: 0.343 | U55: 0.048 | V55: 0.097 | W55: -0.008 | X55: -0.168 | Y55: -0.125 | Z55: 0.925 | AA55: 0.924 | AB55: 0.943 | AC55: 1 | AD55: 0.932 | AE55: -0.139 | AF55: 0.19 | AG55: 0.803 | AH55: 1 | AI55: 0.998 | AJ55: -0.469 | AK55: 0.449 | AL55: 0.191 | AM55: 0.682 | AN55: 0.066 | AO55: -0.039 | AP55: 0.403 | AQ55: -0.502 | AR55: 0.326 | AS55: 0.136 | AT55: 0.1 | AU55: -0.434 | AV55: -0.29 | AW55: -0.111 | AX55: -0.139 | AY55: 0.694 | AZ55: -0.369 | BA55: -0.555 | BB55: 0.211 | BC55: 0.223 | BD55: 0.239 | BE55: 0.444 | BF55: 0.314 | BG55: 0.592 | BH55: 0.135 | BI55: -0.174 | BJ55: 0.21 | BK55: 0.78 | BM55: =SUMPRODUCT(R55:AD55,$R$225:$AD$225) -> 0.3599822
A56: ITSA4 | B56: =K56 -> 0.025 | C56: =B56-E56 -> -0.006 | D56: =B56-K56 -> 0 | E56: =K56-L56 -> 0.031 | F56: 1.845 | G56: 4.036 | H56: pro_cyclicals | I56: =VLOOKUP(A56,Planilha6!$BL$9:$BN$222,2,0) -> banks | J56: =VLOOKUP(A56,Planilha6!$BL$9:$BN$222,3,0) -> neutral_beta | K56: 0.025 | L56: -0.006 | M56: =VLOOKUP(A56,'Mandato Ibov'!$B$1:$C$215,2,0) -> 0.046306273 | N56: =K56-M56 -> -0.021306273 | O56: =B56-M56 -> -0.021306273 | P56: =VLOOKUP(A56,'Mandato Ibov'!$B$2:$D$215,3,0) -> 0.041624557 | Q56: =K56-P56 -> -0.016624557 | R56: -0.153 | S56: 0.496 | T56: -0.695 | U56: 0.131 | V56: 0.169 | W56: 0.234 | X56: 0.43 | Y56: 0.491 | Z56: 0.588 | AA56: 0.596 | AB56: 0.724 | AC56: 0.839 | AD56: 0.76 | AE56: 0.07 | AF56: -0.3 | AG56: 0.534 | AH56: -0.967 | AI56: -0.645 | AJ56: -0.86 | AK56: -0.149 | AL56: 0.177 | AM56: -0.665 | AN56: -0.406 | AO56: 0.618 | AP56: 0.689 | AQ56: -0.01 | AR56: 0.171 | AS56: 0.41 | AT56: 0.058 | AU56: 0.051 | AV56: 0.273 | AW56: 0.44 | AX56: -0.451 | AY56: 0.936 | AZ56: 0.292 | BA56: 0.474 | BB56: -0.023 | BC56: 0.321 | BD56: 0.532 | BE56: -0.285 | BF56: -0.428 | BG56: 0.763 | BH56: -0.693 | BI56: 0.039 | BJ56: -0.2 | BK56: -0.689 | BM56: =SUMPRODUCT(R56:AD56,$R$225:$AD$225) -> 0.358869
A57: ABEV3 | B57: 0.017 | C57: =B57-E57 -> -0.006 | D57: =B57-K57 -> 0.002 | E57: =K57-L57 -> 0.023 | F57: 1.842 | G57: 4.029 | H57: defensives | I57: =VLOOKUP(A57,Planilha6!$BL$9:$BN$222,2,0) -> consumer_staples | J57: =VLOOKUP(A57,Planilha6!$BL$9:$BN$222,3,0) -> very_low_beta | K57: 0.015 | L57: -0.008 | M57: =VLOOKUP(A57,'Mandato Ibov'!$B$1:$C$215,2,0) -> 0.042916866 | N57: =K57-M57 -> -0.027916866 | O57: =B57-M57 -> -0.025916866 | P57: =VLOOKUP(A57,'Mandato Ibov'!$B$2:$D$215,3,0) -> 0.034187506 | Q57: =K57-P57 -> -0.019187506 | R57: -0.228 | S57: 0.508 | T57: -0.769 | U57: 0.147 | V57: 0.136 | W57: 0.341 | X57: 0.802 | Y57: 0.479 | Z57: 0.707 | AA57: 0.716 | AB57: 0.731 | AC57: 0.78 | AD57: 0.621 | AE57: 0.342 | AF57: -0.533 | AG57: 0.185 | AH57: -0.999 | AI57: -0.787 | AJ57: -0.584 | AK57: -0.302 | AL57: -0.121 | AM57: -0.912 | AN57: -0.083 | AO57: 0.63 | AP57: 0.404 | AQ57: 0.209 | AR57: 0.09 | AS57: -0.418 | AT57: 0.498 | AU57: 0.374 | AV57: 0.693 | AW57: 0.818 | AX57: 0.482 | AY57: 0.744 | AZ57: -0.195 | BA57: -0.196 | BB57: 0.263 | BC57: -0.007 | BD57: 0.323 | BE57: 0.163 | BF57: 0.009 | BG57: 1 | BH57: -0.301 | BI57: -0.362 | BJ57: -0.15 | BK57: -1 | BM57: =SUMPRODUCT(R57:AD57,$R$225:$AD$225) -> 0.3577998
A58: VVEO3 | B58: 0.004 | C58: =B58-E58 -> 0.004 | D58: =B58-K58 -> 0 | E58: =K58-L58 -> 0 | F58: 1.84 | G58: 1.292 | H58: defensives | I58: =VLOOKUP(A58,Planilha6!$BL$9:$BN$222,2,0) -> healthcare | J58: =VLOOKUP(A58,Planilha6!$BL$9:$BN$222,3,0) -> high_beta | K58: 0.004 | L58: 0.004 | M58: =VLOOKUP(A58,'Mandato Ibov'!$B$1:$C$215,2,0) -> 0.0082949666 | N58: =K58-M58 -> -0.0042949666 | O58: =B58-M58 -> -0.0042949666 | P58: =VLOOKUP(A58,'Mandato Ibov'!$B$2:$D$215,3,0) -> 0 | Q58: =K58-P58 -> 0.004 | R58: 0.96 | S58: 0.049 | T58: 0.859 | U58: 0.615 | V58: 0.391 | W58: 0.05 | X58: -0.404 | Y58: -0.609 | Z58: 0.468 | AA58: 0.471 | AB58: 0.321 | AC58: 0.879 | AD58: 0.995 | AE58: 1 | AF58: 0.676 | AG58: 1 | AH58: 1 | AI58: 1 | AJ58: -0.538 | AK58: 0.86 | AL58: -0.878 | AM58: 0.796 | AN58: 0.231 | AO58: 0.427 | AP58: 0.224 | AQ58: -0.588 | AR58: 1 | AS58: 0.445 | AT58: 0.184 | AU58: -0.466 | AV58: 0.075 | AW58: -0.546 | AX58: -0.579 | AY58: 0.083 | AZ58: -0.707 | BA58: 0.942 | BB58: 0.256 | BC58: -0.238 | BD58: 0.361 | BE58: -0.47 | BF58: 0.741 | BG58: 0.06 | BH58: 1 | BI58: 0.164 | BJ58: 0.606 | BK58: 0.966 | BM58: =SUMPRODUCT(R58:AD58,$R$225:$AD$225) -> 0.3575425
A59: BRAP3 | B59: =K59 -> 0 | C59: =B59-E59 -> 0 | D59: =B59-K59 -> 0 | E59: =K59-L59 -> 0 | F59: 1.794 | G59: 2.288 | H59: commodities | I59: =VLOOKUP(A59,Planilha6!$BL$9:$BN$222,2,0) -> basic_materials | J59: =VLOOKUP(A59,Planilha6!$BL$9:$BN$222,3,0) -> low_beta | K59: 0 | L59: 0 | M59: =VLOOKUP(A59,'Mandato Ibov'!$B$1:$C$215,2,0) -> 0.008086223 | N59: =K59-M59 -> -0.008086223 | O59: =B59-M59 -> -0.008086223 | P59: =VLOOKUP(A59,'Mandato Ibov'!$B$2:$D$215,3,0) -> 0 | Q59: =K59-P59 -> 0 | R59: -0.402 | S59: 0.165 | T59: -0.579 | U59: -0.348 | V59: -0.116 | W59: 0.283 | X59: 0.611 | Y59: 0.663 | Z59: 0.773 | AA59: 0.774 | AB59: 0.626 | AC59: 0.657 | AD59: 0.81 | AE59: -0.223 | AF59: -0.92 | AG59: 0.36 | AH59: -0.553 | AI59: 0.085 | AJ59: -0.518 | AK59: -0.34 | AL59: 0.899 | AM59: -0.427 | AN59: -0.526 | AO59: 0.767 | AP59: 0.14 | AQ59: -0.936 | AR59: -1 | AS59: -0.671 | AT59: -0.269 | AU59: 0.309 | AV59: -0.082 | AW59: 0.678 | AX59: 0.04 | AY59: 0.701 | AZ59: -0.907 | BA59: 0.983 | BB59: -0.148 | BC59: 0.468 | BD59: 0.351 | BE59: 0.007 | BF59: 0.058 | BG59: 0.998 | BH59: -0.352 | BI59: -0.347 | BJ59: 1 | BK59: 0.085 | BM59: =SUMPRODUCT(R59:AD59,$R$225:$AD$225) -> 0.341007
A60: MDNE3 | B60: 0.007 | C60: =B60-E60 -> 0.007 | D60: =B60-K60 -> -0.002 | E60: =K60-L60 -> 0 | F60: 1.792 | G60: 1.406 | H60: pro_cyclicals | I60: =VLOOKUP(A60,Planilha6!$BL$9:$BN$222,2,0) -> homebuilders | J60: =VLOOKUP(A60,Planilha6!$BL$9:$BN$222,3,0) -> very_high_beta | K60: 0.009 | L60: 0.009 | M60: =VLOOKUP(A60,'Mandato Ibov'!$B$1:$C$215,2,0) -> 0.0080792796 | N60: =K60-M60 -> 0.00092072039 | O60: =B60-M60 -> -0.0010792796 | P60: =VLOOKUP(A60,'Mandato Ibov'!$B$2:$D$215,3,0) -> 0.0064597299 | Q60: =K60-P60 -> 0.0025402701 | R60: 0.346 | S60: 0.23 | T60: 0.228 | U60: 0.289 | V60: 0.337 | W60: 0.143 | X60: -0.03 | Y60: 0.017 | Z60: 0.266 | AA60: 0.264 | AB60: 0.859 | AC60: 0.927 | AD60: 0.788 | AE60: -0.018 | AF60: 0.702 | AG60: 0.268 | AH60: -0.06 | AI60: 1 | AJ60: -0.125 | AK60: -0.309 | AL60: -0.011 | AM60: -0.58 | AN60: 0.259 | AO60: 0.341 | AP60: 0.761 | AQ60: 0.515 | AR60: 0.511 | AS60: 0.97 | AT60: 0.16 | AU60: -0.101 | AV60: 0.043 | AW60: -0.251 | AX60: -0.123 | AY60: 0.857 | AZ60: 0.53 | BA60: 0.375 | BB60: -0.564 | BC60: -0.354 | BD60: -0.273 | BE60: -0.05 | BF60: -0.018 | BG60: 0.122 | BH60: -0.999 | BI60: 0.843 | BJ60: -0.515 | BK60: 0.16 | BM60: =SUMPRODUCT(R60:AD60,$R$225:$AD$225) -> 0.340409
A61: PSSA3 | B61: =K61 -> 0.013 | C61: =B61-E61 -> 0.009 | D61: =B61-K61 -> 0 | E61: =K61-L61 -> 0.004 | F61: 1.789 | G61: 2.301 | H61: defensives | I61: =VLOOKUP(A61,Planilha6!$BL$9:$BN$222,2,0) -> float_financials | J61: =VLOOKUP(A61,Planilha6!$BL$9:$BN$222,3,0) -> very_low_beta | K61: 0.013 | L61: 0.009 | M61: =VLOOKUP(A61,'Mandato Ibov'!$B$1:$C$215,2,0) -> 0.010884828 | N61: =K61-M61 -> 0.0021151715 | O61: =B61-M61 -> 0.0021151715 | P61: =VLOOKUP(A61,'Mandato Ibov'!$B$2:$D$215,3,0) -> 0.0095923516 | Q61: =K61-P61 -> 0.0034076484 | R61: -0.082 | S61: 0.312 | T61: -0.34 | U61: 0.123 | V61: 0.246 | W61: 0.333 | X61: 0.568 | Y61: 0.328 | Z61: 0.596 | AA61: 0.6 | AB61: 0.696 | AC61: 0.822 | AD61: 0.613 | AE61: 0.066 | AF61: 0.186 | AG61: -0.175 | AH61: -0.881 | AI61: -0.728 | AJ61: -0.282 | AK61: -0.23 | AL61: -0.276 | AM61: -0.717 | AN61: 0.03 | AO61: 0.155 | AP61: 0.375 | AQ61: 0.558 | AR61: 0.127 | AS61: 0.495 | AT61: 0.457 | AU61: 0.242 | AV61: 0.386 | AW61: 0.784 | AX61: 0.668 | AY61: 0.913 | AZ61: 0.709 | BA61: 0.359 | BB61: -0.098 | BC61: -0.065 | BD61: -0.82 | BE61: -0.159 | BF61: 0.617 | BG61: 0.732 | BH61: -0.717 | BI61: -0.489 | BJ61: 0.055 | BK61: -0.267 | BM61: =SUMPRODUCT(R61:AD61,$R$225:$AD$225) -> 0.3392613
A62: NEOE3 | B62: 0 | C62: =B62-E62 -> 0 | D62: =B62-K62 -> -0.014 | E62: =K62-L62 -> 0 | F62: 1.753 | G62: 2.126 | H62: bond_proxies | I62: =VLOOKUP(A62,Planilha6!$BL$9:$BN$222,2,0) -> utilities | J62: =VLOOKUP(A62,Planilha6!$BL$9:$BN$222,3,0) -> very_low_beta | K62: 0.014 | L62: 0.014 | M62: =VLOOKUP(A62,'Mandato Ibov'!$B$1:$C$215,2,0) -> 0.0079013385 | N62: =K62-M62 -> 0.0060986615 | O62: =B62-M62 -> -0.0079013385 | P62: =VLOOKUP(A62,'Mandato Ibov'!$B$2:$D$215,3,0) -> 0.0067361009 | Q62: =K62-P62 -> 0.0072638991 | R62: -0.311 | S62: 0.572 | T62: -0.626 | U62: -0.107 | V62: 0.178 | W62: 0.183 | X62: 0.339 | Y62: 0.35 | Z62: 0.876 | AA62: 0.885 | AB62: 0.676 | AC62: 0.74 | AD62: 0.845 | AE62: -0.458 | AF62: -0.63 | AG62: 1 | AH62: -0.928 | AI62: -0.139 | AJ62: -0.986 | AK62: -0.429 | AL62: -0.359 | AM62: -0.308 | AN62: -0.45 | AO62: 0.863 | AP62: 0.641 | AQ62: -0.128 | AR62: 0.347 | AS62: 0.385 | AT62: 0.118 | AU62: -0.171 | AV62: -0.079 | AW62: 0.827 | AX62: -0.713 | AY62: 0.989 | AZ62: 0.763 | BA62: 1 | BB62: -0.233 | BC62: -0.532 | BD62: 0.312 | BE62: 0.366 | BF62: -0.298 | BG62: 1 | BH62: -0.752 | BI62: -0.701 | BJ62: 0.087 | BK62: -0.351 | BM62: =SUMPRODUCT(R62:AD62,$R$225:$AD$225) -> 0.3263644
A63: SEER3 | B63: 0.006 | C63: =B63-E63 -> 0.006 | D63: =B63-K63 -> -0.001 | E63: =K63-L63 -> 0 | F63: 1.725 | G63: 1.248 | H63: pro_cyclicals | I63: =VLOOKUP(A63,Planilha6!$BL$9:$BN$222,2,0) -> education | J63: =VLOOKUP(A63,Planilha6!$BL$9:$BN$222,3,0) -> neutral_beta | K63: 0.007 | L63: 0.007 | M63: =VLOOKUP(A63,'Mandato Ibov'!$B$1:$C$215,2,0) -> 0.0077744706 | N63: =K63-M63 -> -0.00077447059 | O63: =B63-M63 -> -0.0017744706 | P63: =VLOOKUP(A63,'Mandato Ibov'!$B$2:$D$215,3,0) -> 0 | Q63: =K63-P63 -> 0.007 | R63: 0.727 | S63: 0.111 | T63: 0.683 | U63: 0.614 | V63: 0.448 | W63: -0.026 | X63: -0.402 | Y63: -0.397 | Z63: 0.243 | AA63: 0.244 | AB63: 0.931 | AC63: 0.777 | AD63: 0.787 | AE63: 0.865 | AF63: 0.572 | AG63: 0.007 | AH63: -0.028 | AI63: 0.758 | AJ63: 1 | AK63: 0.108 | AL63: -0.699 | AM63: -0.542 | AN63: 0.53 | AO63: 0.125 | AP63: 0.122 | AQ63: 0.49 | AR63: 0.934 | AS63: 0.441 | AT63: 0.509 | AU63: 0.079 | AV63: 0.887 | AW63: -0.571 | AX63: -0.164 | AY63: 0.781 | AZ63: 0.445 | BA63: 0.611 | BB63: 0.086 | BC63: -0.094 | BD63: 0.934 | BE63: -1 | BF63: -1 | BG63: -0.61 | BH63: -0.642 | BI63: -0.01 | BJ63: -0.001 | BK63: 0.554 | BM63: =SUMPRODUCT(R63:AD63,$R$225:$AD$225) -> 0.3164346
A64: CAML3 | B64: =K64 -> 0.01 | C64: =B64-E64 -> 0.01 | D64: =B64-K64 -> 0 | E64: =K64-L64 -> 0 | F64: 1.641 | G64: 1.557 | H64: defensives | I64: =VLOOKUP(A64,Planilha6!$BL$9:$BN$222,2,0) -> consumer_staples | J64: =VLOOKUP(A64,Planilha6!$BL$9:$BN$222,3,0) -> very_high_beta | K64: 0.01 | L64: 0.01 | M64: =VLOOKUP(A64,'Mandato Ibov'!$B$1:$C$215,2,0) -> 0.0073960677 | N64: =K64-M64 -> 0.0026039323 | O64: =B64-M64 -> 0.0026039323 | P64: =VLOOKUP(A64,'Mandato Ibov'!$B$2:$D$215,3,0) -> 0 | Q64: =K64-P64 -> 0.01 | R64: 0.306 | S64: 0.201 | T64: 0.233 | U64: 0.14 | V64: 0.223 | W64: -0.069 | X64: -0.262 | Y64: -0.154 | Z64: 0.473 | AA64: 0.477 | AB64: 0.882 | AC64: 0.915 | AD64: 0.823 | AE64: -0.089 | AF64: 0.024 | AG64: 1 | AH64: 0.19 | AI64: 0.747 | AJ64: -0.513 | AK64: 0.162 | AL64: -0.397 | AM64: 0.09 | AN64: -0.061 | AO64: 0.311 | AP64: 0.312 | AQ64: -0.026 | AR64: 0.079 | AS64: -0.337 | AT64: 0.242 | AU64: -0.458 | AV64: 0.022 | AW64: 0.346 | AX64: -0.265 | AY64: 0.722 | AZ64: 0.308 | BA64: 0.245 | BB64: 0.007 | BC64: 0.095 | BD64: 0.286 | BE64: -0.468 | BF64: -0.239 | BG64: 0.053 | BH64: -0.053 | BI64: 0.55 | BJ64: 0.565 | BK64: 0.476 | BM64: =SUMPRODUCT(R64:AD64,$R$225:$AD$225) -> 0.2867466
A65: HBRE3 | B65: =K65 -> 0.008 | C65: =B65-E65 -> 0.008 | D65: =B65-K65 -> 0 | E65: =K65-L65 -> 0 | F65: 1.618 | G65: 1.25 | H65: bond_proxies | I65: =VLOOKUP(A65,Planilha6!$BL$9:$BN$222,2,0) -> real_estate | J65: =VLOOKUP(A65,Planilha6!$BL$9:$BN$222,3,0) -> very_high_beta | K65: 0.008 | L65: 0.008 | M65: =VLOOKUP(A65,'Mandato Ibov'!$B$1:$C$215,2,0) -> 0.0072909246 | N65: =K65-M65 -> 0.00070907541 | O65: =B65-M65 -> 0.00070907541 | P65: =VLOOKUP(A65,'Mandato Ibov'!$B$2:$D$215,3,0) -> 0 | Q65: =K65-P65 -> 0.008 | R65: 0.375 | S65: -0.26 | T65: 0.44 | U65: 0.035 | V65: 0.015 | W65: 0.063 | X65: 0.042 | Y65: -0.229 | Z65: 0.594 | AA65: 0.594 | AB65: 0.709 | AC65: 0.954 | AD65: 0.71 | AE65: 0.333 | AF65: 0.593 | AG65: -0.008 | AH65: 1 | AI65: -0.043 | AJ65: -0.325 | AK65: 0.231 | AL65: -0.011 | AM65: 1 | AN65: 0.497 | AO65: -0.194 | AP65: -0.726 | AQ65: -0.399 | AR65: 0.121 | AS65: 0.382 | AT65: -0.065 | AU65: 0.082 | AV65: -0.229 | AW65: 0.002 | AX65: -0.794 | AY65: -0.117 | AZ65: -0.381 | BA65: 0.855 | BB65: -0.084 | BC65: 0.122 | BD65: 0.099 | BE65: -0.367 | BF65: 0.288 | BG65: 0.142 | BH65: 0.164 | BI65: 0.8 | BJ65: 0.613 | BK65: 0.96 | BM65: =SUMPRODUCT(R65:AD65,$R$225:$AD$225) -> 0.2783464
A66: ITUB3 | B66: =K66 -> 0.023 | C66: =B66-E66 -> 0.023 | D66: =B66-K66 -> 0 | E66: =K66-L66 -> 0 | F66: 1.584 | G66: 2.13 | H66: pro_cyclicals | I66: =VLOOKUP(A66,Planilha6!$BL$9:$BN$222,2,0) -> banks | J66: =VLOOKUP(A66,Planilha6!$BL$9:$BN$222,3,0) -> neutral_beta | K66: 0.023 | L66: 0.023 | M66: =VLOOKUP(A66,'Mandato Ibov'!$B$1:$C$215,2,0) -> 0.00713852 | N66: =K66-M66 -> 0.01586148 | O66: =B66-M66 -> 0.01586148 | P66: =VLOOKUP(A66,'Mandato Ibov'!$B$2:$D$215,3,0) -> 0.0087436517 | Q66: =K66-P66 -> 0.014256348 | R66: -0.405 | S66: 0.424 | T66: -0.734 | U66: -0.034 | V66: 0.09 | W66: 0.027 | X66: 0.19 | Y66: 0.335 | Z66: 0.867 | AA66: 0.875 | AB66: 0.682 | AC66: 0.775 | AD66: 0.777 | AE66: -0.583 | AF66: 0.042 | AG66: 0.944 | AH66: -0.963 | AI66: -0.603 | AJ66: -0.967 | AK66: -0.194 | AL66: 0.098 | AM66: -0.548 | AN66: -0.309 | AO66: 0.753 | AP66: 0.807 | AQ66: 0.274 | AR66: 0.119 | AS66: -0.063 | AT66: 0.052 | AU66: -0.185 | AV66: -0.181 | AW66: 0.481 | AX66: -0.535 | AY66: 0.893 | AZ66: 0.36 | BA66: -0.267 | BB66: -0.242 | BC66: -0.242 | BD66: 0.397 | BE66: -0.284 | BF66: 0.131 | BG66: 0.834 | BH66: -0.824 | BI66: -0.057 | BJ66: 0.351 | BK66: -0.923 | BM66: =SUMPRODUCT(R66:AD66,$R$225:$AD$225) -> 0.2660918
A67: BBSE3 | B67: =K67 -> 0.02 | C67: =B67-E67 -> 0.013 | D67: =B67-K67 -> 0 | E67: =K67-L67 -> 0.007 | F67: 1.541 | G67: 2.604 | H67: defensives | I67: =VLOOKUP(A67,Planilha6!$BL$9:$BN$222,2,0) -> float_financials | J67: =VLOOKUP(A67,Planilha6!$BL$9:$BN$222,3,0) -> very_low_beta | K67: 0.02 | L67: 0.013 | M67: =VLOOKUP(A67,'Mandato Ibov'!$B$1:$C$215,2,0) -> 0.015053042 | N67: =K67-M67 -> 0.0049469579 | O67: =B67-M67 -> 0.0049469579 | P67: =VLOOKUP(A67,'Mandato Ibov'!$B$2:$D$215,3,0) -> 0.015198091 | Q67: =K67-P67 -> 0.0048019092 | R67: -0.54 | S67: -0.013 | T67: -0.818 | U67: 0.042 | V67: -0.03 | W67: 0.256 | X67: 0.854 | Y67: 0.58 | Z67: 0.573 | AA67: 0.582 | AB67: 0.711 | AC67: 0.767 | AD67: 0.48 | AE67: 0.155 | AF67: 0.75 | AG67: -0.141 | AH67: -0.806 | AI67: -0.847 | AJ67: -0.612 | AK67: -0.277 | AL67: 0.616 | AM67: -0.948 | AN67: 0.374 | AO67: 0.229 | AP67: 0.356 | AQ67: 0.172 | AR67: 0.052 | AS67: -0.331 | AT67: 0.669 | AU67: 0.365 | AV67: -0.279 | AW67: 0.93 | AX67: 0.371 | AY67: 0.834 | AZ67: -0.927 | BA67: -0.532 | BB67: -0.066 | BC67: -0.066 | BD67: -0.993 | BE67: 0.444 | BF67: 0.208 | BG67: 1 | BH67: -0.459 | BI67: -0.592 | BJ67: -0.097 | BK67: -0.575 | BM67: =SUMPRODUCT(R67:AD67,$R$225:$AD$225) -> 0.2508524
A68: TAEE3 | B68: =K68 -> 0.018 | C68: =B68-E68 -> 0.018 | D68: =B68-K68 -> 0 | E68: =K68-L68 -> 0 | F68: 1.478 | G68: 1.969 | H68: bond_proxies | I68: =VLOOKUP(A68,Planilha6!$BL$9:$BN$222,2,0) -> utilities | J68: =VLOOKUP(A68,Planilha6!$BL$9:$BN$222,3,0) -> low_beta | K68: 0.018 | L68: 0.018 | M68: =VLOOKUP(A68,'Mandato Ibov'!$B$1:$C$215,2,0) -> 0.0066627779 | N68: =K68-M68 -> 0.011337222 | O68: =B68-M68 -> 0.011337222 | P68: =VLOOKUP(A68,'Mandato Ibov'!$B$2:$D$215,3,0) -> 0.0079140862 | Q68: =K68-P68 -> 0.010085914 | R68: -0.584 | S68: 0.211 | T68: -0.62 | U68: -0.391 | V68: -0.088 | W68: 0.056 | X68: 0.582 | Y68: 0.391 | Z68: 0.904 | AA68: 0.908 | AB68: 0.651 | AC68: 0.711 | AD68: 0.649 | AE68: -0.543 | AF68: -0.675 | AG68: 0.002 | AH68: -0.79 | AI68: -0.342 | AJ68: -0.888 | AK68: -0.269 | AL68: 0.155 | AM68: -0.593 | AN68: -0.435 | AO68: 0.373 | AP68: 0.452 | AQ68: -0.166 | AR68: -0.142 | AS68: 0.175 | AT68: 0.191 | AU68: 0.503 | AV68: -0.157 | AW68: 0.925 | AX68: -0.928 | AY68: 0.495 | AZ68: 0.073 | BA68: -0.002 | BB68: -0.416 | BC68: -0.521 | BD68: 0.18 | BE68: 0.07 | BF68: -0.189 | BG68: 0.931 | BH68: -0.435 | BI68: -0.274 | BJ68: 1 | BK68: 0.044 | BM68: =SUMPRODUCT(R68:AD68,$R$225:$AD$225) -> 0.2287568
A69: TAEE4 | B69: =K69 -> 0.017 | C69: =B69-E69 -> 0.017 | D69: =B69-K69 -> 0 | E69: =K69-L69 -> 0 | F69: 1.459 | G69: 1.963 | H69: bond_proxies | I69: =VLOOKUP(A69,Planilha6!$BL$9:$BN$222,2,0) -> utilities | J69: =VLOOKUP(A69,Planilha6!$BL$9:$BN$222,3,0) -> low_beta | K69: 0.017 | L69: 0.017 | M69: =VLOOKUP(A69,'Mandato Ibov'!$B$1:$C$215,2,0) -> 0.0065779815 | N69: =K69-M69 -> 0.010422019 | O69: =B69-M69 -> 0.010422019 | P69: =VLOOKUP(A69,'Mandato Ibov'!$B$2:$D$215,3,0) -> 0.0082604486 | Q69: =K69-P69 -> 0.0087395514 | R69: -0.556 | S69: 0.219 | T69: -0.636 | U69: -0.36 | V69: -0.088 | W69: 0.043 | X69: 0.545 | Y69: 0.374 | Z69: 0.852 | AA69: 0.856 | AB69: 0.642 | AC69: 0.652 | AD69: 0.661 | AE69: -0.548 | AF69: -0.68 | AG69: 0.095 | AH69: -0.793 | AI69: -0.282 | AJ69: -0.888 | AK69: -0.269 | AL69: 0.145 | AM69: -0.593 | AN69: -0.44 | AO69: 0.417 | AP69: 0.492 | AQ69: -0.166 | AR69: -0.142 | AS69: 0.175 | AT69: 0.191 | AU69: 0.503 | AV69: -0.157 | AW69: 0.917 | AX69: -0.928 | AY69: 0.495 | AZ69: 0.004 | BA69: 0.261 | BB69: -0.416 | BC69: -0.521 | BD69: 0.188 | BE69: 0.075 | BF69: -0.588 | BG69: 0.823 | BH69: -0.444 | BI69: -0.247 | BJ69: 0.903 | BK69: 0.044 | BM69: =SUMPRODUCT(R69:AD69,$R$225:$AD$225) -> 0.2221226
A70: AZZA3 | B70: 0.006 | C70: =B70-E70 -> 0.005 | D70: =B70-K70 -> -0.003 | E70: =K70-L70 -> 0.001 | F70: 1.438 | G70: 1.117 | H70: pro_cyclicals | I70: =VLOOKUP(A70,Planilha6!$BL$9:$BN$222,2,0) -> apparel | J70: =VLOOKUP(A70,Planilha6!$BL$9:$BN$222,3,0) -> neutral_beta | K70: 0.009 | L70: 0.008 | M70: =VLOOKUP(A70,'Mandato Ibov'!$B$1:$C$215,2,0) -> 0.0068908392 | N70: =K70-M70 -> 0.0021091608 | O70: =B70-M70 -> -0.00089083921 | P70: =VLOOKUP(A70,'Mandato Ibov'!$B$2:$D$215,3,0) -> 0 | Q70: =K70-P70 -> 0.009 | R70: 0.091 | S70: -0.068 | T70: -0.069 | U70: 0.077 | V70: 0.058 | W70: 0.015 | X70: -0.022 | Y70: -0.081 | Z70: 0.52 | AA70: 0.522 | AB70: 0.783 | AC70: 0.911 | AD70: 0.595 | AE70: 0.296 | AF70: 0.434 | AG70: 0.382 | AH70: 0.009 | AI70: 0.003 | AJ70: -0.255 | AK70: 0.178 | AL70: -0.045 | AM70: 0.335 | AN70: 1 | AO70: -0.265 | AP70: 0.172 | AQ70: -0.005 | AR70: 0.761 | AS70: 0.312 | AT70: 0.212 | AU70: 0.031 | AV70: 0.068 | AW70: -0.276 | AX70: -0.186 | AY70: 0.866 | AZ70: 0.492 | BA70: -0.667 | BB70: -0.474 | BC70: -0.305 | BD70: -0.587 | BE70: 1 | BF70: 1 | BG70: 0.43 | BH70: 0.336 | BI70: -0.033 | BJ70: -0.743 | BK70: 0.225 | BM70: =SUMPRODUCT(R70:AD70,$R$225:$AD$225) -> 0.2147568
A71: AXIA6 | B71: =K71 -> 0.023 | C71: =B71-E71 -> 0.017 | D71: =B71-K71 -> 0 | E71: =K71-L71 -> 0.006 | F71: 1.434 | G71: 2.324 | H71: bond_proxies | I71: =VLOOKUP(A71,Planilha6!$BL$9:$BN$222,2,0) -> utilities | J71: =VLOOKUP(A71,Planilha6!$BL$9:$BN$222,3,0) -> high_beta | K71: 0.023 | L71: 0.017 | M71: =VLOOKUP(A71,'Mandato Ibov'!$B$1:$C$215,2,0) -> 0.013107266 | N71: =K71-M71 -> 0.0098927344 | O71: =B71-M71 -> 0.0098927344 | P71: =VLOOKUP(A71,'Mandato Ibov'!$B$2:$D$215,3,0) -> 0.017684943 | Q71: =K71-P71 -> 0.0053150568 | R71: -0.264 | S71: 0.48 | T71: -0.649 | U71: -0.228 | V71: -0.007 | W71: 0.084 | X71: 0.158 | Y71: 0.112 | Z71: 0.63 | AA71: 0.638 | AB71: 0.72 | AC71: 0.823 | AD71: 0.71 | AE71: -0.657 | AF71: -0.442 | AG71: 0.557 | AH71: -1 | AI71: -0.58 | AJ71: -0.998 | AK71: -0.371 | AL71: -0.364 | AM71: -0.564 | AN71: -0.527 | AO71: 0.826 | AP71: 0.909 | AQ71: 0.139 | AR71: 1 | AS71: 0.31 | AT71: -0.048 | AU71: -0.003 | AV71: -0.098 | AW71: 0.358 | AX71: -0.684 | AY71: 0.744 | AZ71: 0.926 | BA71: 0.616 | BB71: 0.12 | BC71: -0.261 | BD71: 0.63 | BE71: -0.321 | BF71: 0.051 | BG71: 0.695 | BH71: -0.739 | BI71: 0.065 | BJ71: 0.182 | BK71: -1 | BM71: =SUMPRODUCT(R71:AD71,$R$225:$AD$225) -> 0.2128559
A72: BBDC3 | B72: =K72 -> 0.023 | C72: =B72-E72 -> 0.013 | D72: =B72-K72 -> 0 | E72: =K72-L72 -> 0.01 | F72: 1.429 | G72: 2.543 | H72: pro_cyclicals | I72: =VLOOKUP(A72,Planilha6!$BL$9:$BN$222,2,0) -> banks | J72: =VLOOKUP(A72,Planilha6!$BL$9:$BN$222,3,0) -> neutral_beta | K72: 0.023 | L72: 0.013 | M72: =VLOOKUP(A72,'Mandato Ibov'!$B$1:$C$215,2,0) -> 0.015828249 | N72: =K72-M72 -> 0.0071717512 | O72: =B72-M72 -> 0.0071717512 | P72: =VLOOKUP(A72,'Mandato Ibov'!$B$2:$D$215,3,0) -> 0.018028235 | Q72: =K72-P72 -> 0.0049717647 | R72: -0.348 | S72: 0.169 | T72: -0.675 | U72: -0.225 | V72: -0.117 | W72: -0.007 | X72: 0.156 | Y72: 0.154 | Z72: 0.848 | AA72: 0.854 | AB72: 0.734 | AC72: 0.969 | AD72: 0.715 | AE72: -0.597 | AF72: -0.151 | AG72: 0.537 | AH72: -0.927 | AI72: -0.844 | AJ72: -1 | AK72: -0.118 | AL72: 0.155 | AM72: -0.079 | AN72: -0.003 | AO72: 0.227 | AP72: 0.384 | AQ72: 0.057 | AR72: 0.276 | AS72: 0.775 | AT72: -0.042 | AU72: -0.115 | AV72: -0.317 | AW72: 0.316 | AX72: -0.374 | AY72: 0.84 | AZ72: 0.398 | BA72: 0.001 | BB72: -0.207 | BC72: -0.08 | BD72: 0.346 | BE72: -0.122 | BF72: -0.454 | BG72: 0.817 | BH72: -0.422 | BI72: -0.03 | BJ72: 0.162 | BK72: -0.754 | BM72: =SUMPRODUCT(R72:AD72,$R$225:$AD$225) -> 0.2113422
A73: BRBI11 | B73: =K73 -> 0.011 | C73: =B73-E73 -> 0.011 | D73: =B73-K73 -> 0 | E73: =K73-L73 -> 0 | F73: 1.37 | G73: 1.343 | H73: pro_cyclicals | I73: =VLOOKUP(A73,Planilha6!$BL$9:$BN$222,2,0) -> banks | J73: =VLOOKUP(A73,Planilha6!$BL$9:$BN$222,3,0) -> very_low_beta | K73: 0.011 | L73: 0.011 | M73: =VLOOKUP(A73,'Mandato Ibov'!$B$1:$C$215,2,0) -> 0.0061754168 | N73: =K73-M73 -> 0.0048245832 | O73: =B73-M73 -> 0.0048245832 | P73: =VLOOKUP(A73,'Mandato Ibov'!$B$2:$D$215,3,0) -> 0 | Q73: =K73-P73 -> 0.011 | R73: -0.142 | S73: -0.08 | T73: 0.141 | U73: -0.565 | V73: -0.155 | W73: -0.076 | X73: 0.081 | Y73: 0.182 | Z73: 0.362 | AA73: 0.363 | AB73: 0.645 | AC73: 0.622 | AD73: 0.709 | AE73: -0.431 | AF73: -0.74 | AG73: -0.668 | AH73: -0.356 | AI73: 0.262 | AJ73: 0.681 | AK73: -0.799 | AL73: 0.338 | AM73: -0.648 | AN73: -0.096 | AO73: 0.112 | AP73: 0.069 | AQ73: -0.238 | AR73: 0.08 | AS73: 0.347 | AT73: -0.235 | AU73: 0.213 | AV73: -0.217 | AW73: 0.557 | AX73: 1 | AY73: 0.028 | AZ73: 0.464 | BA73: 0.614 | BB73: 0.205 | BC73: 0.253 | BD73: 0.004 | BE73: 0.156 | BF73: -0.202 | BG73: 0.519 | BH73: -0.652 | BI73: -0.381 | BJ73: 0.586 | BK73: 0.746 | BM73: =SUMPRODUCT(R73:AD73,$R$225:$AD$225) -> 0.1903315
A74: CPLE3 | B74: =K74 -> 0.022 | C74: =B74-E74 -> 0.011 | D74: =B74-K74 -> 0 | E74: =K74-L74 -> 0.011 | F74: 1.355 | G74: 2.495 | H74: bond_proxies | I74: =VLOOKUP(A74,Planilha6!$BL$9:$BN$222,2,0) -> utilities | J74: =VLOOKUP(A74,Planilha6!$BL$9:$BN$222,3,0) -> neutral_beta | K74: 0.022 | L74: 0.011 | M74: =VLOOKUP(A74,'Mandato Ibov'!$B$1:$C$215,2,0) -> 0.016007324 | N74: =K74-M74 -> 0.0059926759 | O74: =B74-M74 -> 0.0059926759 | P74: =VLOOKUP(A74,'Mandato Ibov'!$B$2:$D$215,3,0) -> 0.024686323 | Q74: =K74-P74 -> -0.0026863227 | R74: -0.365 | S74: 0.29 | T74: -0.713 | U74: -0.138 | V74: -0.022 | W74: 0.029 | X74: 0.109 | Y74: 0.149 | Z74: 0.602 | AA74: 0.608 | AB74: 0.709 | AC74: 0.871 | AD74: 0.7 | AE74: -0.546 | AF74: -0.329 | AG74: 0.391 | AH74: -0.938 | AI74: -0.397 | AJ74: -0.925 | AK74: -0.342 | AL74: -0.188 | AM74: -0.645 | AN74: -0.567 | AO74: 0.696 | AP74: 0.869 | AQ74: 0.344 | AR74: 0.439 | AS74: 0.923 | AT74: 0.121 | AU74: -0.22 | AV74: -0.063 | AW74: 0.663 | AX74: -0.593 | AY74: 0.967 | AZ74: 0.563 | BA74: 0.6 | BB74: 0.173 | BC74: -0.298 | BD74: 0.287 | BE74: -0.485 | BF74: 0.166 | BG74: 0.573 | BH74: -0.826 | BI74: -0.083 | BJ74: -0.266 | BK74: -0.436 | BM74: =SUMPRODUCT(R74:AD74,$R$225:$AD$225) -> 0.1853162
A75: BRAP4 | B75: 0.005 | C75: =B75-E75 -> 0.003 | D75: =B75-K75 -> 0.005 | E75: =K75-L75 -> 0.002 | F75: 1.349 | G75: 1.832 | H75: commodities | I75: =VLOOKUP(A75,Planilha6!$BL$9:$BN$222,2,0) -> basic_materials | J75: =VLOOKUP(A75,Planilha6!$BL$9:$BN$222,3,0) -> high_beta | K75: 0 | L75: -0.002 | M75: =VLOOKUP(A75,'Mandato Ibov'!$B$1:$C$215,2,0) -> 0.0072319136 | N75: =K75-M75 -> -0.0072319136 | O75: =B75-M75 -> -0.0022319136 | P75: =VLOOKUP(A75,'Mandato Ibov'!$B$2:$D$215,3,0) -> 0 | Q75: =K75-P75 -> 0 | R75: -0.655 | S75: 0.021 | T75: -0.843 | U75: -0.449 | V75: -0.302 | W75: 0.013 | X75: 0.269 | Y75: 0.496 | Z75: 0.628 | AA75: 0.628 | AB75: 0.756 | AC75: 0.843 | AD75: 0.734 | AE75: -0.263 | AF75: -0.935 | AG75: 0.601 | AH75: -0.576 | AI75: 0.327 | AJ75: -0.518 | AK75: -0.34 | AL75: 0.827 | AM75: -0.427 | AN75: -0.529 | AO75: 0.89 | AP75: 0.257 | AQ75: -0.936 | AR75: -1 | AS75: -0.66 | AT75: -0.269 | AU75: 0.063 | AV75: -0.082 | AW75: 0.569 | AX75: 0.041 | AY75: 0.708 | AZ75: -0.826 | BA75: 0.02 | BB75: -0.148 | BC75: 0.468 | BD75: 0.433 | BE75: -0.262 | BF75: 0.2 | BG75: 0.921 | BH75: -0.359 | BI75: -0.182 | BJ75: -0.353 | BK75: 0.085 | BM75: =SUMPRODUCT(R75:AD75,$R$225:$AD$225) -> 0.1827919
A76: DIRR3 | B76: 0.0075 | C76: =B76-E76 -> 0.0055 | D76: =B76-K76 -> -0.0035 | E76: =K76-L76 -> 0.002 | F76: 1.334 | G76: 1.377 | H76: pro_cyclicals | I76: =VLOOKUP(A76,Planilha6!$BL$9:$BN$222,2,0) -> homebuilders | J76: =VLOOKUP(A76,Planilha6!$BL$9:$BN$222,3,0) -> high_beta | K76: 0.011 | L76: 0.009 | M76: =VLOOKUP(A76,'Mandato Ibov'!$B$1:$C$215,2,0) -> 0.0067526103 | N76: =K76-M76 -> 0.0042473897 | O76: =B76-M76 -> 0.00074738968 | P76: =VLOOKUP(A76,'Mandato Ibov'!$B$2:$D$215,3,0) -> 0 | Q76: =K76-P76 -> 0.011 | R76: -0.243 | S76: -0.046 | T76: -0.507 | U76: -0.066 | V76: -0.033 | W76: 0.089 | X76: 0.21 | Y76: 0.39 | Z76: 0.251 | AA76: 0.25 | AB76: 0.688 | AC76: 0.702 | AD76: 0.431 | AE76: 0.213 | AF76: 0.421 | AG76: -0.599 | AH76: -0.449 | AI76: -0.461 | AJ76: -0.558 | AK76: -0.16 | AL76: 0.577 | AM76: -0.712 | AN76: 0.515 | AO76: -0.202 | AP76: 0.158 | AQ76: 0.494 | AR76: 0.178 | AS76: 0.111 | AT76: 0.29 | AU76: 0.039 | AV76: 0.164 | AW76: 0.043 | AX76: -0.072 | AY76: 0.763 | AZ76: 1 | BA76: 0.26 | BB76: -0.447 | BC76: -0.248 | BD76: -0.247 | BE76: 0.122 | BF76: -0.146 | BG76: 0.287 | BH76: -0.926 | BI76: 0.543 | BJ76: -0.661 | BK76: -0.202 | BM76: =SUMPRODUCT(R76:AD76,$R$225:$AD$225) -> 0.1775548
A77: CMIG4 | B77: 0.0175 | C77: =B77-E77 -> 0.0085 | D77: =B77-K77 -> -0.0035 | E77: =K77-L77 -> 0.009 | F77: 1.313 | G77: 2.359 | H77: bond_proxies | I77: =VLOOKUP(A77,Planilha6!$BL$9:$BN$222,2,0) -> utilities | J77: =VLOOKUP(A77,Planilha6!$BL$9:$BN$222,3,0) -> low_beta | K77: 0.021 | L77: 0.012 | M77: =VLOOKUP(A77,'Mandato Ibov'!$B$1:$C$215,2,0) -> 0.014365501 | N77: =K77-M77 -> 0.0066344988 | O77: =B77-M77 -> 0.0031344988 | P77: =VLOOKUP(A77,'Mandato Ibov'!$B$2:$D$215,3,0) -> 0.019662426 | Q77: =K77-P77 -> 0.0013375739 | R77: -0.717 | S77: 0.121 | T77: -0.813 | U77: -0.41 | V77: -0.142 | W77: -0.043 | X77: 0.207 | Y77: 0.582 | Z77: 0.807 | AA77: 0.813 | AB77: 0.648 | AC77: 0.71 | AD77: 0.541 | AE77: -0.6 | AF77: -0.428 | AG77: 0.335 | AH77: -0.864 | AI77: -0.556 | AJ77: -0.958 | AK77: -0.384 | AL77: 0.705 | AM77: -0.519 | AN77: -0.591 | AO77: 0.439 | AP77: 0.79 | AQ77: -0.106 | AR77: 0.388 | AS77: -0.15 | AT77: 0.336 | AU77: -0.273 | AV77: -0.297 | AW77: 0.559 | AX77: -0.558 | AY77: 0.908 | AZ77: 0.745 | BA77: -0.578 | BB77: -0.469 | BC77: -0.661 | BD77: -0.127 | BE77: -0.447 | BF77: -0.136 | BG77: 0.85 | BH77: -0.686 | BI77: -0.247 | BJ77: -0.097 | BK77: -0.386 | BM77: =SUMPRODUCT(R77:AD77,$R$225:$AD$225) -> 0.1702354
A78: FESA4 | B78: =K78 -> 0.008 | C78: =B78-E78 -> 0.008 | D78: =B78-K78 -> 0 | E78: =K78-L78 -> 0 | F78: 1.292 | G78: 1.332 | H78: commodities | I78: =VLOOKUP(A78,Planilha6!$BL$9:$BN$222,2,0) -> basic_materials | J78: =VLOOKUP(A78,Planilha6!$BL$9:$BN$222,3,0) -> low_beta | K78: 0.008 | L78: 0.008 | M78: =VLOOKUP(A78,'Mandato Ibov'!$B$1:$C$215,2,0) -> 0.0058248436 | N78: =K78-M78 -> 0.0021751564 | O78: =B78-M78 -> 0.0021751564 | P78: =VLOOKUP(A78,'Mandato Ibov'!$B$2:$D$215,3,0) -> 0 | Q78: =K78-P78 -> 0.008 | R78: -0.225 | S78: -0.142 | T78: -0.197 | U78: -0.505 | V78: -0.268 | W78: 0.002 | X78: -0.127 | Y78: 0.031 | Z78: 0.73 | AA78: 0.727 | AB78: 0.68 | AC78: 0.666 | AD78: 0.759 | AE78: -0.334 | AF78: -0.907 | AG78: -0.16 | AH78: -0.283 | AI78: 0.184 | AJ78: -0.351 | AK78: -0.225 | AL78: 0.177 | AM78: -0.308 | AN78: -0.227 | AO78: 0.355 | AP78: 0.313 | AQ78: -0.928 | AR78: -0.042 | AS78: 0.145 | AT78: 0.138 | AU78: -0.327 | AV78: -0.012 | AW78: 0.487 | AX78: 0.459 | AY78: 0.853 | AZ78: 0.028 | BA78: 0.832 | BB78: 0.149 | BC78: 0.083 | BD78: 0.361 | BE78: -0.059 | BF78: -0.049 | BG78: 0.535 | BH78: -0.108 | BI78: -0.396 | BJ78: 0.625 | BK78: 0.505 | BM78: =SUMPRODUCT(R78:AD78,$R$225:$AD$225) -> 0.1626831
A79: LREN3 | B79: 0.01 | C79: =B79-E79 -> 0.004 | D79: =B79-K79 -> -0.005 | E79: =K79-L79 -> 0.006 | F79: 1.278 | G79: 1.579 | H79: pro_cyclicals | I79: =VLOOKUP(A79,Planilha6!$BL$9:$BN$222,2,0) -> apparel | J79: =VLOOKUP(A79,Planilha6!$BL$9:$BN$222,3,0) -> neutral_beta | K79: 0.015 | L79: 0.009 | M79: =VLOOKUP(A79,'Mandato Ibov'!$B$1:$C$215,2,0) -> 0.0099878157 | N79: =K79-M79 -> 0.0050121843 | O79: =B79-M79 -> 1.2184325e-05 | P79: =VLOOKUP(A79,'Mandato Ibov'!$B$2:$D$215,3,0) -> 0 | Q79: =K79-P79 -> 0.015 | R79: 0.015 | S79: 0.023 | T79: -0.495 | U79: 0.149 | V79: -0.056 | W79: 0.116 | X79: 0.149 | Y79: -0.068 | Z79: 0.299 | AA79: 0.302 | AB79: 0.734 | AC79: 0.696 | AD79: 0.501 | AE79: 0.941 | AF79: -0.11 | AG79: -0.415 | AH79: -0.769 | AI79: -0.673 | AJ79: 0.001 | AK79: 0.051 | AL79: -0.244 | AM79: -0.546 | AN79: 0.492 | AO79: -0.228 | AP79: 0.489 | AQ79: 0.251 | AR79: 0.171 | AS79: 0.16 | AT79: 0.452 | AU79: 0.04 | AV79: 1 | AW79: -0.192 | AX79: 0.486 | AY79: 0.917 | AZ79: 0.285 | BA79: -0.099 | BB79: 0.189 | BC79: 0.008 | BD79: 0.667 | BE79: 0.186 | BF79: -0.533 | BG79: 0.516 | BH79: -0.101 | BI79: -0.06 | BJ79: -0.954 | BK79: -0.581 | BM79: =SUMPRODUCT(R79:AD79,$R$225:$AD$225) -> 0.1578412
A80: RANI3 | B80: =K80 -> 0 | C80: =B80-E80 -> 0 | D80: =B80-K80 -> 0 | E80: =K80-L80 -> 0 | F80: 1.268 | G80: 1.495 | H80: defensives | I80: =VLOOKUP(A80,Planilha6!$BL$9:$BN$222,2,0) -> consumer_staples | J80: =VLOOKUP(A80,Planilha6!$BL$9:$BN$222,3,0) -> low_beta | K80: 0 | L80: 0 | M80: =VLOOKUP(A80,'Mandato Ibov'!$B$1:$C$215,2,0) -> 0 | N80: =K80-M80 -> 0 | O80: =B80-M80 -> 0 | P80: =VLOOKUP(A80,'Mandato Ibov'!$B$2:$D$215,3,0) -> 0 | Q80: =K80-P80 -> 0 | R80: -0.325 | S80: 0.068 | T80: -0.259 | U80: -0.495 | V80: -0.148 | W80: -0.025 | X80: 0.291 | Y80: 0.207 | Z80: 0.41 | AA80: 0.411 | AB80: 0.625 | AC80: 0.598 | AD80: 0.585 | AE80: -0.28 | AF80: -0.777 | AG80: -0.311 | AH80: -0.1 | AI80: 0.271 | AJ80: -0.495 | AK80: -0.109 | AL80: 0.072 | AM80: -0.542 | AN80: -0.12 | AO80: -0.132 | AP80: 0.19 | AQ80: -0.159 | AR80: -0.752 | AS80: -0.495 | AT80: 0.257 | AU80: 0.153 | AV80: 0.014 | AW80: 0.664 | AX80: 0.021 | AY80: 0.671 | AZ80: 0.73 | BA80: 0.819 | BB80: -0.146 | BC80: -0.223 | BD80: 0.245 | BE80: 0.292 | BF80: -0.602 | BG80: 0.727 | BH80: -0.518 | BI80: -0.212 | BJ80: 0.555 | BK80: 0.525 | BM80: =SUMPRODUCT(R80:AD80,$R$225:$AD$225) -> 0.1541315
A81: CSMG3 | B81: =K81 -> 0 | C81: =B81-E81 -> -0.004 | D81: =B81-K81 -> 0 | E81: =K81-L81 -> 0.004 | F81: 1.231 | G81: 1.555 | H81: bond_proxies | I81: =VLOOKUP(A81,Planilha6!$BL$9:$BN$222,2,0) -> utilities | J81: =VLOOKUP(A81,Planilha6!$BL$9:$BN$222,3,0) -> low_beta | K81: 0 | L81: -0.004 | M81: =VLOOKUP(A81,'Mandato Ibov'!$B$1:$C$215,2,0) -> 0 | N81: =K81-M81 -> 0 | O81: =B81-M81 -> 0 | P81: =VLOOKUP(A81,'Mandato Ibov'!$B$2:$D$215,3,0) -> 0.013473572 | Q81: =K81-P81 -> -0.013473572 | R81: -0.683 | S81: 0.352 | T81: -0.829 | U81: -0.246 | V81: -0.036 | W81: -0.169 | X81: 0.098 | Y81: 0.258 | Z81: 0.875 | AA81: 0.882 | AB81: 0.589 | AC81: 0.62 | AD81: 0.691 | AE81: -0.733 | AF81: -0.481 | AG81: 0.809 | AH81: -0.911 | AI81: 0.13 | AJ81: -0.731 | AK81: -0.38 | AL81: -0.032 | AM81: -0.704 | AN81: -0.885 | AO81: 0.914 | AP81: 0.934 | AQ81: 0.37 | AR81: 0.146 | AS81: -0.082 | AT81: 0.352 | AU81: 0.102 | AV81: -0.252 | AW81: 0.616 | AX81: -0.619 | AY81: 1 | AZ81: 0.379 | BA81: -0.901 | BB81: -0.262 | BC81: -0.641 | BD81: 0.357 | BE81: -0.133 | BF81: 0.442 | BG81: 0.678 | BH81: -1 | BI81: -0.247 | BJ81: -0.316 | BK81: -0.098 | BM81: =SUMPRODUCT(R81:AD81,$R$225:$AD$225) -> 0.1408337
A82: IGTI11 | B82: =K82 -> 0 | C82: =B82-E82 -> -0.002 | D82: =B82-K82 -> 0 | E82: =K82-L82 -> 0.002 | F82: 1.15 | G82: 1.619 | H82: bond_proxies | I82: =VLOOKUP(A82,Planilha6!$BL$9:$BN$222,2,0) -> real_estate | J82: =VLOOKUP(A82,Planilha6!$BL$9:$BN$222,3,0) -> high_beta | K82: 0 | L82: -0.002 | M82: =VLOOKUP(A82,'Mandato Ibov'!$B$1:$C$215,2,0) -> 0 | N82: =K82-M82 -> 0 | O82: =B82-M82 -> 0 | P82: =VLOOKUP(A82,'Mandato Ibov'!$B$2:$D$215,3,0) -> 0.0096211158 | Q82: =K82-P82 -> -0.0096211158 | R82: -0.198 | S82: 0.213 | T82: -0.472 | U82: -0.126 | V82: -0.05 | W82: 0.004 | X82: 0.224 | Y82: -0.166 | Z82: 0.35 | AA82: 0.352 | AB82: 0.707 | AC82: 0.733 | AD82: 0.557 | AE82: -0.194 | AF82: -0.237 | AG82: 0.005 | AH82: -0.788 | AI82: 0.077 | AJ82: -0.079 | AK82: -0.439 | AL82: -0.593 | AM82: -0.643 | AN82: -0.128 | AO82: 0.396 | AP82: 0.459 | AQ82: 0.827 | AR82: 0.048 | AS82: -0.028 | AT82: 0.162 | AU82: 0.534 | AV82: 0.438 | AW82: 0.226 | AX82: -0.284 | AY82: 0.658 | AZ82: 0.338 | BA82: -0.263 | BB82: -0.515 | BC82: -0.032 | BD82: 0.278 | BE82: -0.303 | BF82: 0.113 | BG82: 0.48 | BH82: -0.432 | BI82: 0.471 | BJ82: -0.314 | BK82: -0.16 | BM82: =SUMPRODUCT(R82:AD82,$R$225:$AD$225) -> 0.1122213
A83: CMIG3 | B83: =K83 -> 0 | C83: =B83-E83 -> 0 | D83: =B83-K83 -> 0 | E83: =K83-L83 -> 0 | F83: 1.105 | G83: 1.194 | H83: bond_proxies | I83: =VLOOKUP(A83,Planilha6!$BL$9:$BN$222,2,0) -> utilities | J83: =VLOOKUP(A83,Planilha6!$BL$9:$BN$222,3,0) -> very_low_beta | K83: 0 | L83: 0 | M83: =VLOOKUP(A83,'Mandato Ibov'!$B$1:$C$215,2,0) -> 0 | N83: =K83-M83 -> 0 | O83: =B83-M83 -> 0 | P83: =VLOOKUP(A83,'Mandato Ibov'!$B$2:$D$215,3,0) -> 0.0076416264 | Q83: =K83-P83 -> -0.0076416264 | R83: -0.674 | S83: -0.02 | T83: -0.7 | U83: -0.47 | V83: -0.209 | W83: -0.226 | X83: -0.078 | Y83: 0.266 | Z83: 0.828 | AA83: 0.834 | AB83: 0.691 | AC83: 0.773 | AD83: 0.606 | AE83: -0.676 | AF83: -0.538 | AG83: 0.277 | AH83: -0.901 | AI83: -0.648 | AJ83: -0.954 | AK83: -0.384 | AL83: 0.299 | AM83: -0.519 | AN83: -0.621 | AO83: 0.542 | AP83: 0.784 | AQ83: -0.106 | AR83: 0.388 | AS83: -0.15 | AT83: 0.336 | AU83: -0.273 | AV83: -0.285 | AW83: 0.619 | AX83: -0.558 | AY83: 0.908 | AZ83: 0.583 | BA83: 0.098 | BB83: -0.469 | BC83: -0.661 | BD83: -0.148 | BE83: -0.751 | BF83: -0.582 | BG83: 0.502 | BH83: -0.598 | BI83: -0.357 | BJ83: 0.915 | BK83: -0.386 | BM83: =SUMPRODUCT(R83:AD83,$R$225:$AD$225) -> 0.0965253
A84: TAEE11 | B84: =K84 -> 0 | C84: =B84-E84 -> -0.003 | D84: =B84-K84 -> 0 | E84: =K84-L84 -> 0.003 | F84: 1.101 | G84: 1.684 | H84: bond_proxies | I84: =VLOOKUP(A84,Planilha6!$BL$9:$BN$222,2,0) -> utilities | J84: =VLOOKUP(A84,Planilha6!$BL$9:$BN$222,3,0) -> low_beta | K84: 0 | L84: -0.003 | M84: =VLOOKUP(A84,'Mandato Ibov'!$B$1:$C$215,2,0) -> 0 | N84: =K84-M84 -> 0 | O84: =B84-M84 -> 0 | P84: =VLOOKUP(A84,'Mandato Ibov'!$B$2:$D$215,3,0) -> 0.011237761 | Q84: =K84-P84 -> -0.011237761 | R84: -0.738 | S84: 0.076 | T84: -0.851 | U84: -0.495 | V84: -0.275 | W84: -0.135 | X84: 0.408 | Y84: 0.296 | Z84: 0.737 | AA84: 0.741 | AB84: 0.604 | AC84: 0.6 | AD84: 0.549 | AE84: -0.548 | AF84: -0.679 | AG84: 0.058 | AH84: -0.793 | AI84: -0.317 | AJ84: -0.888 | AK84: -0.269 | AL84: 0.145 | AM84: -0.593 | AN84: -0.44 | AO84: 0.369 | AP84: 0.443 | AQ84: -0.166 | AR84: -0.142 | AS84: 0.175 | AT84: 0.191 | AU84: 0.503 | AV84: -0.157 | AW84: 0.857 | AX84: -0.928 | AY84: 0.495 | AZ84: 0.1 | BA84: -0.413 | BB84: -0.416 | BC84: -0.521 | BD84: 0.186 | BE84: 0.043 | BF84: -0.074 | BG84: 0.861 | BH84: -0.437 | BI84: -0.253 | BJ84: -0.155 | BK84: 0.044 | BM84: =SUMPRODUCT(R84:AD84,$R$225:$AD$225) -> 0.0948172
A85: MILS3 | B85: =K85 -> 0 | C85: =B85-E85 -> 0 | D85: =B85-K85 -> 0 | E85: =K85-L85 -> 0 | F85: 1.09 | G85: 1.368 | H85: industrials | I85: =VLOOKUP(A85,Planilha6!$BL$9:$BN$222,2,0) -> building_materials | J85: =VLOOKUP(A85,Planilha6!$BL$9:$BN$222,3,0) -> neutral_beta | K85: 0 | L85: 0 | M85: =VLOOKUP(A85,'Mandato Ibov'!$B$1:$C$215,2,0) -> 0 | N85: =K85-M85 -> 0 | O85: =B85-M85 -> 0 | P85: =VLOOKUP(A85,'Mandato Ibov'!$B$2:$D$215,3,0) -> 0 | Q85: =K85-P85 -> 0 | R85: -0.296 | S85: 0.157 | T85: -0.4 | U85: -0.52 | V85: -0.235 | W85: -0.125 | X85: 0.258 | Y85: -0.228 | Z85: 0.61 | AA85: 0.609 | AB85: 0.69 | AC85: 0.634 | AD85: 0.646 | AE85: -0.772 | AF85: -0.572 | AG85: -0.119 | AH85: -0.529 | AI85: 0.634 | AJ85: -0.525 | AK85: -0.149 | AL85: -0.549 | AM85: -0.656 | AN85: 0.176 | AO85: 0.178 | AP85: -0.015 | AQ85: 0.256 | AR85: 0.065 | AS85: -0.241 | AT85: 0.379 | AU85: 0.544 | AV85: -0.247 | AW85: 0.406 | AX85: -0.047 | AY85: 0.649 | AZ85: 0.332 | BA85: 0.442 | BB85: -0.231 | BC85: -0.467 | BD85: 0.226 | BE85: 0.257 | BF85: -0.058 | BG85: 0.871 | BH85: -0.528 | BI85: 0.33 | BJ85: 0.249 | BK85: -0.064 | BM85: =SUMPRODUCT(R85:AD85,$R$225:$AD$225) -> 0.0910875
A86: ITUB4 | B86: =K86 -> 0.031 | C86: =B86-E86 -> -0.05 | D86: =B86-K86 -> 0 | E86: =K86-L86 -> 0.081 | F86: 1.046 | G86: 2.289 | H86: pro_cyclicals | I86: =VLOOKUP(A86,Planilha6!$BL$9:$BN$222,2,0) -> banks | J86: =VLOOKUP(A86,Planilha6!$BL$9:$BN$222,3,0) -> neutral_beta | K86: 0.031 | L86: -0.05 | M86: =VLOOKUP(A86,'Mandato Ibov'!$B$1:$C$215,2,0) -> 0 | N86: =K86-M86 -> 0.031 | O86: =B86-M86 -> 0.031 | P86: =VLOOKUP(A86,'Mandato Ibov'!$B$2:$D$215,3,0) -> 0.035143369 | Q86: =K86-P86 -> -0.0041433695 | R86: -0.561 | S86: 0.085 | T86: -0.848 | U86: -0.301 | V86: -0.255 | W86: -0.138 | X86: 0.07 | Y86: 0.078 | Z86: 0.562 | AA86: 0.567 | AB86: 0.695 | AC86: 0.792 | AD86: 0.627 | AE86: -0.61 | AF86: 0.039 | AG86: 0.449 | AH86: -0.964 | AI86: -0.751 | AJ86: -0.979 | AK86: -0.183 | AL86: 0.028 | AM86: -0.536 | AN86: -0.165 | AO86: 0.407 | AP86: 0.537 | AQ86: 0.279 | AR86: 0.119 | AS86: -0.063 | AT86: 0.041 | AU86: -0.169 | AV86: -0.206 | AW86: 0.444 | AX86: -0.471 | AY86: 0.856 | AZ86: 0.251 | BA86: 0.342 | BB86: -0.159 | BC86: -0.052 | BD86: 0.303 | BE86: -0.143 | BF86: -0.265 | BG86: 0.801 | BH86: -0.725 | BI86: 0.008 | BJ86: -0.199 | BK86: -0.923 | BM86: =SUMPRODUCT(R86:AD86,$R$225:$AD$225) -> 0.0757224
A87: FLRY3 | B87: =K87 -> 0 | C87: =B87-E87 -> -0.003 | D87: =B87-K87 -> 0 | E87: =K87-L87 -> 0.003 | F87: 1.029 | G87: 1.262 | H87: defensives | I87: =VLOOKUP(A87,Planilha6!$BL$9:$BN$222,2,0) -> healthcare | J87: =VLOOKUP(A87,Planilha6!$BL$9:$BN$222,3,0) -> low_beta | K87: 0 | L87: -0.003 | M87: =VLOOKUP(A87,'Mandato Ibov'!$B$1:$C$215,2,0) -> 0 | N87: =K87-M87 -> 0 | O87: =B87-M87 -> 0 | P87: =VLOOKUP(A87,'Mandato Ibov'!$B$2:$D$215,3,0) -> 0 | Q87: =K87-P87 -> 0 | R87: -0.363 | S87: -0.057 | T87: -0.605 | U87: -0.353 | V87: -0.254 | W87: -0.061 | X87: 0.171 | Y87: -0.02 | Z87: 0.385 | AA87: 0.388 | AB87: 0.715 | AC87: 0.776 | AD87: 0.509 | AE87: -0.206 | AF87: -0.378 | AG87: -0.294 | AH87: -0.609 | AI87: -0.43 | AJ87: -0.74 | AK87: -0.016 | AL87: -0.101 | AM87: -0.617 | AN87: 0.208 | AO87: -0.023 | AP87: 0.172 | AQ87: 0.094 | AR87: 0.207 | AS87: 0.204 | AT87: 0.28 | AU87: -0.106 | AV87: 0.085 | AW87: 0.456 | AX87: -0.178 | AY87: 0.959 | AZ87: 0.478 | BA87: 0.138 | BB87: -0.023 | BC87: 0.007 | BD87: 0.279 | BE87: -0.09 | BF87: 0.169 | BG87: 0.738 | BH87: -0.212 | BI87: -0.134 | BJ87: -0.047 | BK87: -0.152 | BM87: =SUMPRODUCT(R87:AD87,$R$225:$AD$225) -> 0.0695624
A88: EZTC3 | B88: =K88 -> 0 | C88: =B88-E88 -> 0 | D88: =B88-K88 -> 0 | E88: =K88-L88 -> 0 | F88: 1.018 | G88: 0.989 | H88: pro_cyclicals | I88: =VLOOKUP(A88,Planilha6!$BL$9:$BN$222,2,0) -> homebuilders | J88: =VLOOKUP(A88,Planilha6!$BL$9:$BN$222,3,0) -> high_beta | K88: 0 | L88: 0 | M88: =VLOOKUP(A88,'Mandato Ibov'!$B$1:$C$215,2,0) -> 0 | N88: =K88-M88 -> 0 | O88: =B88-M88 -> 0 | P88: =VLOOKUP(A88,'Mandato Ibov'!$B$2:$D$215,3,0) -> 0 | Q88: =K88-P88 -> 0 | R88: -0.211 | S88: -0.089 | T88: -0.394 | U88: -0.232 | V88: -0.189 | W88: -0.165 | X88: 0.04 | Y88: -0.244 | Z88: 0.412 | AA88: 0.413 | AB88: 0.727 | AC88: 0.764 | AD88: 0.576 | AE88: -0.02 | AF88: -0.06 | AG88: -0.052 | AH88: -0.383 | AI88: -0.158 | AJ88: -0.302 | AK88: -0.269 | AL88: -0.339 | AM88: -0.284 | AN88: 0.563 | AO88: 0.207 | AP88: 0.011 | AQ88: 0.393 | AR88: -0.005 | AS88: -0.066 | AT88: 0.002 | AU88: 0.516 | AV88: 0.195 | AW88: -0.09 | AX88: 0.099 | AY88: 0.603 | AZ88: 0.15 | BA88: 0.055 | BB88: -0.209 | BC88: -0.306 | BD88: -0.3 | BE88: -0.376 | BF88: 0.273 | BG88: 0.44 | BH88: -0.18 | BI88: 0.413 | BJ88: -0.028 | BK88: -0.011 | BM88: =SUMPRODUCT(R88:AD88,$R$225:$AD$225) -> 0.0653445
A89: MULT3 | B89: =K89 -> 0 | C89: =B89-E89 -> -0.004 | D89: =B89-K89 -> 0 | E89: =K89-L89 -> 0.004 | F89: 1.015 | G89: 1.577 | H89: bond_proxies | I89: =VLOOKUP(A89,Planilha6!$BL$9:$BN$222,2,0) -> real_estate | J89: =VLOOKUP(A89,Planilha6!$BL$9:$BN$222,3,0) -> high_beta | K89: 0 | L89: -0.004 | M89: =VLOOKUP(A89,'Mandato Ibov'!$B$1:$C$215,2,0) -> 0 | N89: =K89-M89 -> 0 | O89: =B89-M89 -> 0 | P89: =VLOOKUP(A89,'Mandato Ibov'!$B$2:$D$215,3,0) -> 0 | Q89: =K89-P89 -> 0 | R89: -0.474 | S89: 0.206 | T89: -0.781 | U89: -0.36 | V89: -0.231 | W89: 0.005 | X89: 0.499 | Y89: 0.005 | Z89: 0.402 | AA89: 0.407 | AB89: 0.598 | AC89: 0.637 | AD89: 0.44 | AE89: -0.202 | AF89: -0.572 | AG89: -0.204 | AH89: -0.874 | AI89: -0.45 | AJ89: -0.518 | AK89: -0.3 | AL89: -0.421 | AM89: -0.762 | AN89: 0.015 | AO89: 0.214 | AP89: 0.54 | AQ89: 0.162 | AR89: -0.062 | AS89: -0.423 | AT89: 0.5 | AU89: 0.986 | AV89: 0.344 | AW89: 0.315 | AX89: -0.631 | AY89: 0.874 | AZ89: 0.318 | BA89: -0.368 | BB89: -0.284 | BC89: 0.284 | BD89: 0.184 | BE89: -0.366 | BF89: -0.175 | BG89: 0.648 | BH89: -0.398 | BI89: 0.525 | BJ89: -0.29 | BK89: -0.434 | BM89: =SUMPRODUCT(R89:AD89,$R$225:$AD$225) -> 0.0645559
A90: KLBN3 | B90: =K90 -> 0 | C90: =B90-E90 -> 0 | D90: =B90-K90 -> 0 | E90: =K90-L90 -> 0 | F90: 1.007 | G90: 1.229 | H90: commodities | I90: =VLOOKUP(A90,Planilha6!$BL$9:$BN$222,2,0) -> basic_materials | J90: =VLOOKUP(A90,Planilha6!$BL$9:$BN$222,3,0) -> very_low_beta | K90: 0 | L90: 0 | M90: =VLOOKUP(A90,'Mandato Ibov'!$B$1:$C$215,2,0) -> 0 | N90: =K90-M90 -> 0 | O90: =B90-M90 -> 0 | P90: =VLOOKUP(A90,'Mandato Ibov'!$B$2:$D$215,3,0) -> 0 | Q90: =K90-P90 -> 0 | R90: -0.704 | S90: -0.227 | T90: -0.813 | U90: -0.516 | V90: -0.415 | W90: -0.057 | X90: 0.195 | Y90: 0.113 | Z90: 0.88 | AA90: 0.882 | AB90: 0.614 | AC90: 0.683 | AD90: 0.59 | AE90: -0.001 | AF90: -0.829 | AG90: -0.186 | AH90: -0.754 | AI90: -0.741 | AJ90: -0.975 | AK90: 0.122 | AL90: 0.028 | AM90: -0.423 | AN90: -0.054 | AO90: 0.282 | AP90: -0.002 | AQ90: -0.387 | AR90: -0.653 | AS90: -0.49 | AT90: 0.184 | AU90: -0.071 | AV90: 0.017 | AW90: 0.979 | AX90: -0.346 | AY90: 0.758 | AZ90: -0.336 | BA90: 0.234 | BB90: 0.093 | BC90: -0.07 | BD90: 0.205 | BE90: 0.458 | BF90: 0.451 | BG90: 0.948 | BH90: -0.296 | BI90: -0.62 | BJ90: 0.854 | BK90: -0.296 | BM90: =SUMPRODUCT(R90:AD90,$R$225:$AD$225) -> 0.0615595
A91: KLBN4 | B91: =K91 -> 0 | C91: =B91-E91 -> 0 | D91: =B91-K91 -> 0 | E91: =K91-L91 -> 0 | F91: 1.005 | G91: 1.263 | H91: commodities | I91: =VLOOKUP(A91,Planilha6!$BL$9:$BN$222,2,0) -> basic_materials | J91: =VLOOKUP(A91,Planilha6!$BL$9:$BN$222,3,0) -> low_beta | K91: 0 | L91: 0 | M91: =VLOOKUP(A91,'Mandato Ibov'!$B$1:$C$215,2,0) -> 0 | N91: =K91-M91 -> 0 | O91: =B91-M91 -> 0 | P91: =VLOOKUP(A91,'Mandato Ibov'!$B$2:$D$215,3,0) -> 0 | Q91: =K91-P91 -> 0 | R91: -0.686 | S91: -0.201 | T91: -0.842 | U91: -0.495 | V91: -0.428 | W91: -0.034 | X91: 0.213 | Y91: 0.122 | Z91: 0.791 | AA91: 0.794 | AB91: 0.633 | AC91: 0.68 | AD91: 0.587 | AE91: -0.003 | AF91: -0.83 | AG91: -0.13 | AH91: -0.754 | AI91: -0.719 | AJ91: -0.975 | AK91: 0.122 | AL91: 0.043 | AM91: -0.423 | AN91: -0.06 | AO91: 0.308 | AP91: 0.057 | AQ91: -0.387 | AR91: -0.653 | AS91: -0.49 | AT91: 0.184 | AU91: -0.071 | AV91: 0.017 | AW91: 0.976 | AX91: -0.346 | AY91: 0.758 | AZ91: -0.398 | BA91: 0.627 | BB91: 0.093 | BC91: -0.07 | BD91: 0.222 | BE91: 0.417 | BF91: 0.15 | BG91: 0.91 | BH91: -0.303 | BI91: -0.589 | BJ91: 0.563 | BK91: -0.296 | BM91: =SUMPRODUCT(R91:AD91,$R$225:$AD$225) -> 0.0609174
... A132: MYPK3 | B132: =K132 -> 0 | C132: =B132-E132 -> 0 | D132: =B132-K132 -> 0 | E132: =K132-L132 -> 0 | F132: 0.636 | G132: 0.686 | H132: industrials | I132: =VLOOKUP(A132,Planilha6!$BL$9:$BN$222,2,0) -> capital_goods | J132: =VLOOKUP(A132,Planilha6!$BL$9:$BN$222,3,0) -> low_beta | K132: 0 | L132: 0 | M132: =VLOOKUP(A132,'Mandato Ibov'!$B$1:$C$215,2,0) -> 0 | N132: =K132-M132 -> 0 | O132: =B132-M132 -> 0 | P132: =VLOOKUP(A132,'Mandato Ibov'!$B$2:$D$215,3,0) -> 0 | Q132: =K132-P132 -> 0 | R132: -0.558 | S132: -0.514 | T132: -0.388 | U132: -0.706 | V132: -0.573 | W132: -0.58 | X132: -0.55 | Y132: -0.528 | Z132: 0.614 | AA132: 0.616 | AB132: 0.486 | AC132: 0.585 | AD132: 0.496 | AE132: -0.282 | AF132: -0.526 | AG132: -0.338 | AH132: 0.361 | AI132: -0.452 | AJ132: -0.558 | AK132: 0.073 | AL132: -0.459 | AM132: 0.74 | AN132: -0.305 | AO132: -0.543 | AP132: -0.169 | AQ132: -0.15 | AR132: -0.307 | AS132: -0.252 | AT132: 0.098 | AU132: -0.45 | AV132: -0.234 | AW132: 0.549 | AX132: -0.261 | AY132: 0.9 | AZ132: 0.77 | BA132: -0.168 | BB132: 0.242 | BC132: -0.082 | BD132: 0.285 | BE132: -0.145 | BF132: -0.169 | BG132: 0.554 | BH132: -0.077 | BI132: 0.183 | BJ132: 0.004 | BK132: 0.35 | BM132: =SUMPRODUCT(R132:AD132,$R$225:$AD$225) -> -0.1767391
A133: VALE3 | B133: 0.057 | C133: =B133-E133 -> -0.056 | D133: =B133-K133 -> -0.006 | E133: =K133-L133 -> 0.113 | F133: 0.627 | G133: 1.355 | H133: commodities | I133: =VLOOKUP(A133,Planilha6!$BL$9:$BN$222,2,0) -> basic_materials | J133: =VLOOKUP(A133,Planilha6!$BL$9:$BN$222,3,0) -> neutral_beta | K133: 0.063 | L133: -0.05 | M133: =VLOOKUP(A133,'Mandato Ibov'!$B$1:$C$215,2,0) -> 0 | N133: =K133-M133 -> 0.063 | O133: =B133-M133 -> 0.057 | P133: =VLOOKUP(A133,'Mandato Ibov'!$B$2:$D$215,3,0) -> 0 | Q133: =K133-P133 -> 0.063 | R133: -0.914 | S133: -0.531 | T133: -1 | U133: -0.779 | V133: -0.752 | W133: -0.597 | X133: -0.358 | Y133: -0.224 | Z133: 0.593 | AA133: 0.595 | AB133: 0.634 | AC133: 0.643 | AD133: 0.534 | AE133: -0.662 | AF133: -1 | AG133: 0.308 | AH133: -1 | AI133: -0.718 | AJ133: -1 | AK133: -0.278 | AL133: 0.116 | AM133: -0.597 | AN133: -0.777 | AO133: 0.815 | AP133: 0.205 | AQ133: -0.939 | AR133: -0.762 | AS133: -0.565 | AT133: -0.043 | AU133: -0.092 | AV133: -0.167 | AW133: 0.604 | AX133: -0.134 | AY133: 0.678 | AZ133: -0.887 | BA133: -0.249 | BB133: 0.311 | BC133: 0.201 | BD133: 0.322 | BE133: -0.192 | BF133: 0.006 | BG133: 0.864 | BH133: -0.333 | BI133: -0.301 | BJ133: -0.403 | BK133: -1 | BM133: =SUMPRODUCT(R133:AD133,$R$225:$AD$225) -> -0.1911876
A134: BRAV3 | B134: =K134 -> 0 | C134: =B134-E134 -> -0.003 | D134: =B134-K134 -> 0 | E134: =K134-L134 -> 0.003 | F134: 0.62 | G134: 0.523 | H134: commodities | I134: =VLOOKUP(A134,Planilha6!$BL$9:$BN$222,2,0) -> crude_oil | J134: =VLOOKUP(A134,Planilha6!$BL$9:$BN$222,3,0) -> very_low_beta | K134: 0 | L134: -0.003 | M134: =VLOOKUP(A134,'Mandato Ibov'!$B$1:$C$215,2,0) -> 0 | N134: =K134-M134 -> 0 | O134: =B134-M134 -> 0 | P134: =VLOOKUP(A134,'Mandato Ibov'!$B$2:$D$215,3,0) -> 0 | Q134: =K134-P134 -> 0 | R134: -0.55 | S134: -0.513 | T134: -0.892 | U134: -0.232 | V134: -0.577 | W134: -0.449 | X134: -0.509 | Y134: -0.729 | Z134: 0.438 | AA134: 0.438 | AB134: 0.549 | AC134: 0.81 | AD134: 0.57 | AE134: -0.224 | AF134: 0.505 | AG134: 0.627 | AH134: -0.554 | AI134: -0.54 | AJ134: -0.612 | AK134: 0.077 | AL134: -1 | AM134: 0.103 | AN134: 0.495 | AO134: 0.444 | AP134: 0.317 | AQ134: 0.303 | AR134: 0.396 | AS134: 0.035 | AT134: -0.105 | AU134: 0.129 | AV134: 0.181 | AW134: 0.094 | AX134: -0.327 | AY134: 0.518 | AZ134: -0.951 | BA134: 0.359 | BB134: -0.376 | BC134: -0.033 | BD134: -0.251 | BE134: -0.445 | BF134: 0.39 | BG134: 0.198 | BH134: 0.165 | BI134: -0.779 | BJ134: -0.99 | BK134: 0.165 | BM134: =SUMPRODUCT(R134:AD134,$R$225:$AD$225) -> -0.2022927
A135: XPBR31 | B135: =K135 -> 0 | C135: =B135-E135 -> 0 | D135: =B135-K135 -> 0 | E135: =K135-L135 -> 0 | F135: 0.62 | G135: 0.601 | H135: pro_cyclicals | I135: =VLOOKUP(A135,Planilha6!$BL$9:$BN$222,2,0) -> financial_services | J135: =VLOOKUP(A135,Planilha6!$BL$9:$BN$222,3,0) -> very_high_beta | K135: 0 | L135: 0 | M135: =VLOOKUP(A135,'Mandato Ibov'!$B$1:$C$215,2,0) -> 0 | N135: =K135-M135 -> 0 | O135: =B135-M135 -> 0 | P135: =VLOOKUP(A135,'Mandato Ibov'!$B$2:$D$215,3,0) -> 0 | Q135: =K135-P135 -> 0 | R135: -0.512 | S135: -0.491 | T135: -0.747 | U135: -0.523 | V135: -0.583 | W135: -0.481 | X135: -0.42 | Y135: -0.628 | Z135: 0.264 | AA135: 0.263 | AB135: 0.665 | AC135: 0.707 | AD135: 0.505 | AE135: -0.439 | AF135: 0.266 | AG135: -0.228 | AH135: -0.851 | AI135: -0.915 | AJ135: -0.936 | AK135: 0.109 | AL135: -0.607 | AM135: -0.418 | AN135: 0.353 | AO135: -0.133 | AP135: 0.287 | AQ135: 0.097 | AR135: 0.056 | AS135: 0.5 | AT135: 0.015 | AU135: -0.022 | AV135: -0.074 | AW135: 0.064 | AX135: -0.102 | AY135: 0.039 | AZ135: 0.06 | BA135: 0.542 | BB135: -0.308 | BC135: 0.023 | BD135: -0.069 | BE135: 0.001 | BF135: 0.155 | BG135: 0.348 | BH135: -0.13 | BI135: 0.346 | BJ135: 0.18 | BK135: -0.5 | BM135: =SUMPRODUCT(R135:AD135,$R$225:$AD$225) -> -0.2016476
A136: AURA33 | B136: =K136 -> 0 | C136: =B136-E136 -> 0 | D136: =B136-K136 -> 0 | E136: =K136-L136 -> 0 | F136: 0.618 | G136: 0.443 | H136: commodities | I136: =VLOOKUP(A136,Planilha6!$BL$9:$BN$222,2,0) -> basic_materials | J136: =VLOOKUP(A136,Planilha6!$BL$9:$BN$222,3,0) -> very_high_beta | K136: 0 | L136: 0 | M136: =VLOOKUP(A136,'Mandato Ibov'!$B$1:$C$215,2,0) -> 0 | N136: =K136-M136 -> 0 | O136: =B136-M136 -> 0 | P136: =VLOOKUP(A136,'Mandato Ibov'!$B$2:$D$215,3,0) -> 0 | Q136: =K136-P136 -> 0 | R136: -0.675 | S136: -0.375 | T136: -0.903 | U136: -0.549 | V136: -0.622 | W136: -0.627 | X136: -0.691 | Y136: -0.582 | Z136: 0.602 | AA136: 0.601 | AB136: 0.528 | AC136: 0.757 | AD136: 0.614 | AE136: -0.665 | AF136: -0.807 | AG136: 0.145 | AH136: -0.845 | AI136: -0.406 | AJ136: -0.968 | AK136: -0.07 | AL136: -0.54 | AM136: -0.496 | AN136: -0.482 | AO136: 0.799 | AP136: 0.865 | AQ136: 0.164 | AR136: -0.522 | AS136: -0.016 | AT136: 0.257 | AU136: 0.207 | AV136: 0.14 | AW136: 0.164 | AX136: 0.158 | AY136: 0.173 | AZ136: 0.008 | BA136: 0.462 | BB136: -0.098 | BC136: 0.426 | BD136: 0.326 | BE136: -0.946 | BF136: 0.352 | BG136: -0.702 | BH136: -1 | BI136: 0.393 | BJ136: -0.046 | BK136: -0.565 | BM136: =SUMPRODUCT(R136:AD136,$R$225:$AD$225) -> -0.2064671
A137: CBAV3 | B137: =K137 -> 0 | C137: =B137-E137 -> 0 | D137: =B137-K137 -> 0 | E137: =K137-L137 -> 0 | F137: 0.617 | G137: 0.453 | H137: commodities | I137: =VLOOKUP(A137,Planilha6!$BL$9:$BN$222,2,0) -> basic_materials | J137: =VLOOKUP(A137,Planilha6!$BL$9:$BN$222,3,0) -> very_low_beta | K137: 0 | L137: 0 | M137: =VLOOKUP(A137,'Mandato Ibov'!$B$1:$C$215,2,0) -> 0 | N137: =K137-M137 -> 0 | O137: =B137-M137 -> 0 | P137: =VLOOKUP(A137,'Mandato Ibov'!$B$2:$D$215,3,0) -> 0 | Q137: =K137-P137 -> 0 | R137: -0.717 | S137: -0.31 | T137: -0.849 | U137: -0.677 | V137: -0.617 | W137: -0.528 | X137: -0.59 | Y137: -0.71 | Z137: 0.577 | AA137: 0.576 | AB137: 0.461 | AC137: 0.627 | AD137: 0.799 | AE137: -0.472 | AF137: -0.992 | AG137: 0.719 | AH137: -0.727 | AI137: 1 | AJ137: -0.877 | AK137: -0.186 | AL137: -1 | AM137: -0.446 | AN137: -0.137 | AO137: 1 | AP137: 0.894 | AQ137: -0.535 | AR137: -0.487 | AS137: -0.276 | AT137: 0.055 | AU137: -0.376 | AV137: -0.046 | AW137: -0.229 | AX137: -0.247 | AY137: 0.679 | AZ137: -0.386 | BA137: 0.483 | BB137: 0.046 | BC137: -0.256 | BD137: 0.622 | BE137: 0.345 | BF137: -0.011 | BG137: 1 | BH137: -0.391 | BI137: -1 | BJ137: -0.245 | BK137: 0.209 | BM137: =SUMPRODUCT(R137:AD137,$R$225:$AD$225) -> -0.2067576
A138: CYRE3 | B138: =K138 -> 0 | C138: =B138-E138 -> -0.002 | D138: =B138-K138 -> 0 | E138: =K138-L138 -> 0.002 | F138: 0.616 | G138: 0.702 | H138: pro_cyclicals | I138: =VLOOKUP(A138,Planilha6!$BL$9:$BN$222,2,0) -> homebuilders | J138: =VLOOKUP(A138,Planilha6!$BL$9:$BN$222,3,0) -> very_high_beta | K138: 0 | L138: -0.002 | M138: =VLOOKUP(A138,'Mandato Ibov'!$B$1:$C$215,2,0) -> 0 | N138: =K138-M138 -> 0 | O138: =B138-M138 -> 0 | P138: =VLOOKUP(A138,'Mandato Ibov'!$B$2:$D$215,3,0) -> 0 | Q138: =K138-P138 -> 0 | R138: -0.645 | S138: -0.512 | T138: -0.827 | U138: -0.489 | V138: -0.577 | W138: -0.536 | X138: -0.451 | Y138: -0.443 | Z138: 0.246 | AA138: 0.247 | AB138: 0.723 | AC138: 0.664 | AD138: 0.431 | AE138: -0.483 | AF138: 0.328 | AG138: -0.157 | AH138: -0.642 | AI138: -0.534 | AJ138: -0.828 | AK138: -0.273 | AL138: 0.035 | AM138: -0.383 | AN138: 0.217 | AO138: -0.067 | AP138: 0.273 | AQ138: 0.455 | AR138: 0.183 | AS138: 0.574 | AT138: 0.148 | AU138: -0.069 | AV138: -0.262 | AW138: -0.162 | AX138: -0.172 | AY138: 0.844 | AZ138: 0.098 | BA138: 0.107 | BB138: -0.709 | BC138: -0.613 | BD138: -0.087 | BE138: 0.248 | BF138: 0.064 | BG138: 0.106 | BH138: -0.613 | BI138: 0.808 | BJ138: -0.73 | BK138: -0.387 | BM138: =SUMPRODUCT(R138:AD138,$R$225:$AD$225) -> -0.2096072
A139: UGPA3 | B139: =K139 -> 0 | C139: =B139-E139 -> -0.011 | D139: =B139-K139 -> 0 | E139: =K139-L139 -> 0.011 | F139: 0.615 | G139: 0.94 | H139: pro_cyclicals | I139: =VLOOKUP(A139,Planilha6!$BL$9:$BN$222,2,0) -> consumer_services | J139: =VLOOKUP(A139,Planilha6!$BL$9:$BN$222,3,0) -> very_low_beta | K139: 0 | L139: -0.011 | M139: =VLOOKUP(A139,'Mandato Ibov'!$B$1:$C$215,2,0) -> 0 | N139: =K139-M139 -> 0 | O139: =B139-M139 -> 0 | P139: =VLOOKUP(A139,'Mandato Ibov'!$B$2:$D$215,3,0) -> 0 | Q139: =K139-P139 -> 0 | R139: -0.78 | S139: -0.36 | T139: -0.944 | U139: -0.592 | V139: -0.631 | W139: -0.615 | X139: -0.531 | Y139: -0.546 | Z139: 0.615 | AA139: 0.62 | AB139: 0.575 | AC139: 0.726 | AD139: 0.595 | AE139: -0.647 | AF139: -0.523 | AG139: 0.532 | AH139: -0.911 | AI139: -0.389 | AJ139: -0.952 | AK139: -0.01 | AL139: -0.455 | AM139: -0.475 | AN139: -0.055 | AO139: 0.566 | AP139: 0.914 | AQ139: 0.324 | AR139: -0.63 | AS139: -0.637 | AT139: 0.526 | AU139: -0.493 | AV139: -0.162 | AW139: 0.086 | AX139: -0.224 | AY139: 0.927 | AZ139: -0.267 | BA139: 0.637 | BB139: -0.438 | BC139: -0.642 | BD139: 0.175 | BE139: -0.398 | BF139: 0.297 | BG139: 0.658 | BH139: -0.58 | BI139: -0.576 | BJ139: -0.218 | BK139: -0.389 | BM139: =SUMPRODUCT(R139:AD139,$R$225:$AD$225) -> -0.2103575
A140: SUZB3 | B140: =K140 -> 0 | C140: =B140-E140 -> -0.01 | D140: =B140-K140 -> 0 | E140: =K140-L140 -> 0.01 | F140: 0.612 | G140: 0.913 | H140: commodities | I140: =VLOOKUP(A140,Planilha6!$BL$9:$BN$222,2,0) -> basic_materials | J140: =VLOOKUP(A140,Planilha6!$BL$9:$BN$222,3,0) -> very_low_beta | K140: 0 | L140: -0.01 | M140: =VLOOKUP(A140,'Mandato Ibov'!$B$1:$C$215,2,0) -> 0 | N140: =K140-M140 -> 0 | O140: =B140-M140 -> 0 | P140: =VLOOKUP(A140,'Mandato Ibov'!$B$2:$D$215,3,0) -> 0 | Q140: =K140-P140 -> 0 | R140: -0.857 | S140: -0.591 | T140: -0.981 | U140: -0.714 | V140: -0.748 | W140: -0.505 | X140: -0.136 | Y140: -0.558 | Z140: 0.803 | AA140: 0.807 | AB140: 0.671 | AC140: 0.688 | AD140: 0.446 | AE140: -0.533 | AF140: -0.548 | AG140: -0.149 | AH140: -0.868 | AI140: -0.94 | AJ140: -1 | AK140: 0.132 | AL140: -0.57 | AM140: -0.364 | AN140: 0.099 | AO140: 0.048 | AP140: -0.167 | AQ140: -0.312 | AR140: 0.473 | AS140: 0.023 | AT140: 0.241 | AU140: 0.219 | AV140: -0.239 | AW140: 0.958 | AX140: -0.411 | AY140: 0.387 | AZ140: -1 | BA140: -0.485 | BB140: -0.123 | BC140: -0.263 | BD140: 0.126 | BE140: 1 | BF140: 0.885 | BG140: 0.844 | BH140: -0.244 | BI140: -0.647 | BJ140: -0.342 | BK140: -0.67 | BM140: =SUMPRODUCT(R140:AD140,$R$225:$AD$225) -> -0.2171374
...

Sheet 29
L1: =SUM(L3:L95) -> 26109509 | T1: =SUM(T3:T95) -> 26050660 | U1: =T1-L1 -> -58848.695 | V1: MOVI GUSTAVO | W1: =SUM(W3:W95) -> 26311337 | X1: =W1-T1 -> 260677
A2: Data | B2: Cliente | C2: Codigo | D2: Papel | E2: Bolsa. | F2: Qtde Disp. | G2: Qtde Bloq. | H2: Qtde Total | I2: Emp | J2: Pos | K2: Preço | L2: $ | M2: peso | N2: alvo | O2: dif | P2: Novo | Q2: Pos Fin | R2: Mudança | X2: PESO GUSAVO | Y2: dif alvo | AA2: EMP
A3: 46128 | B3: 29 | C3: ABEV3 | D3: AMBEV S/A ON EX | E3: BOVESPA | F3: 44400 | G3: 300 | H3: 44700 | I3: =SUMIF($E$108:$H$127,C3,$H$108:$H$127) -> 1500 | J3: =I3+H3 -> 46200 | K3: =VLOOKUP(C3,$L$138:$M$230,2,0) -> 15.43 | L3: =K3*J3 -> 712866 | M3: =L3/SUM($L$3:$L$95) -> 0.027302927 | N3: =IFERROR(VLOOKUP(C3,'[1]pesos FIA'!$E$2:$F$74,2,0),0) -> 0.0144245 | O3: =M3-N3 -> 0.012878427 | P3: =N3*$L$1 -> 376616.61 | Q3: =ROUND(P3/K3/100,0)*100 -> 24400 | R3: =(Q3-J3) -> -21800 | S3: =IF(R3+H3<0,1,0) -> 0 | T3: =(R3+J3)*K3 -> 376492 | V3: =J3+VLOOKUP(C3,$AH$3:$AJ$95,3,0) -> 24600 | W3: =V3*K3 -> 379578 | X3: =W3/SUM($W$3:$W$95) -> 0.014426405 | Y3: =X3-N3 -> 1.904861e-06 | AA3: =VLOOKUP(C3,$AH$3:$AJ$95,3,0)+H3 -> 23100 | AE3: 29 | AF3: S | AG3: VENDA | AH3: CMIN3 | AI3: 12100 | AJ3: =IF(AG3="VENDA",-AI3,AI3) -> -12100
A4: 46128 | B4: 29 | C4: ALLD3 | D4: ALLIED ON NM | E4: BOVESPA | F4: 38300 | G4: 200 | H4: 38500 | I4: =SUMIF($E$108:$H$127,C4,$H$108:$H$127) -> 0 | J4: =I4+H4 -> 38500 | K4: =VLOOKUP(C4,$L$138:$M$230,2,0) -> 6.69 | L4: =K4*J4 -> 257565 | M4: =L4/SUM($L$3:$L$95) -> 0.0098647969 | N4: =IFERROR(VLOOKUP(C4,'[1]pesos FIA'!$E$2:$F$74,2,0),0) -> 0.0076365 | O4: =M4-N4 -> 0.0022282969 | P4: =N4*$L$1 -> 199385.26 | Q4: =ROUND(P4/K4/100,0)*100 -> 29800 | R4: =(Q4-J4) -> -8700 | S4: =IF(R4+H4<0,1,0) -> 0 | T4: =(R4+J4)*K4 -> 199362 | V4: =J4+VLOOKUP(C4,$AH$3:$AJ$95,3,0) -> 29600 | W4: =V4*K4 -> 198024 | X4: =W4/SUM($W$3:$W$95) -> 0.0075261854 | Y4: =X4-N4 -> -0.00011031461 | AA4: =VLOOKUP(C4,$AH$3:$AJ$95,3,0)+H4 -> 29600 | AE4: 29 | AF4: S | AG4: VENDA | AH4: HBOR3 | AI4: 37000 | AJ4: =IF(AG4="VENDA",-AI4,AI4) -> -37000
A5: 46128 | B5: 29 | C5: ALOS3 | D5: ALLOS ON NM | E5: BOVESPA | F5: 6000 | G5: 0 | H5: 6000 | I5: =SUMIF($E$108:$H$127,C5,$H$108:$H$127) -> 0 | J5: =I5+H5 -> 6000 | K5: 33.27 | L5: =K5*J5 -> 199620 | M5: =L5/SUM($L$3:$L$95) -> 0.0076454905 | N5: =IFERROR(VLOOKUP(C5,'[1]pesos FIA'!$E$2:$F$74,2,0),0) -> 0.013576 | O5: =M5-N5 -> -0.0059305095 | P5: =N5*$L$1 -> 354462.69 | Q5: =ROUND(P5/K5/100,0)*100 -> 10700 | R5: =(Q5-J5) -> 4700 | S5: =IF(R5+H5<0,1,0) -> 0 | T5: =(R5+J5)*K5 -> 355989 | V5: =J5+VLOOKUP(C5,$AH$3:$AJ$95,3,0) -> 9900 | W5: =V5*K5 -> 329373 | X5: =W5/SUM($W$3:$W$95) -> 0.012518292 | Y5: =X5-N5 -> -0.001057708 | AA5: =VLOOKUP(C5,$AH$3:$AJ$95,3,0)+H5 -> 9900 | AE5: 29 | AF5: S | AG5: VENDA | AH5: BBAS3 | AI5: 10500 | AJ5: =IF(AG5="VENDA",-AI5,AI5) -> -10500
A6: 46128 | B6: 29 | C6: ALPA4 | D6: ALPARGATAS PN EDJ N1 | E6: BOVESPA | F6: 3800 | G6: 0 | H6: 3800 | I6: =SUMIF($E$108:$H$127,C6,$H$108:$H$127) -> 0 | J6: =I6+H6 -> 3800 | K6: =VLOOKUP(C6,$L$138:$M$230,2,0) -> 12.24 | L6: =K6*J6 -> 46512 | M6: =L6/SUM($L$3:$L$95) -> 0.00178142 | N6: =IFERROR(VLOOKUP(C6,'[1]pesos FIA'!$E$2:$F$74,2,0),0) -> 0.0076365 | O6: =M6-N6 -> -0.00585508 | P6: =N6*$L$1 -> 199385.26 | Q6: =ROUND(P6/K6/100,0)*100 -> 16300 | R6: =(Q6-J6) -> 12500 | S6: =IF(R6+H6<0,1,0) -> 0 | T6: =(R6+J6)*K6 -> 199512 | V6: =J6+VLOOKUP(C6,$AH$3:$AJ$95,3,0) -> 14100 | W6: =V6*K6 -> 172584 | X6: =W6/SUM($W$3:$W$95) -> 0.0065593018 | Y6: =X6-N6 -> -0.0010771982 | AA6: =VLOOKUP(C6,$AH$3:$AJ$95,3,0)+H6 -> 14100 | AE6: 29 | AF6: S | AG6: VENDA | AH6: LIGT3 | AI6: 9400 | AJ6: =IF(AG6="VENDA",-AI6,AI6) -> -9400
A7: 46128 | B7: 29 | C7: AXIA3 | D7: AXIA ENERGIAON EB N1 | E7: BOVESPA | F7: 11400 | G7: 0 | H7: 11400 | I7: =SUMIF($E$108:$H$127,C7,$H$108:$H$127) -> 0 | J7: =I7+H7 -> 11400 | K7: =VLOOKUP(C7,$L$138:$M$230,2,0) -> 65.56 | L7: =K7*J7 -> 747384 | M7: =L7/SUM($L$3:$L$95) -> 0.028624974 | N7: =IFERROR(VLOOKUP(C7,'[1]pesos FIA'!$E$2:$F$74,2,0),0) -> 0 | O7: =M7-N7 -> 0.028624974 | P7: =N7*$L$1 -> 0 | Q7: =ROUND(P7/K7/100,0)*100 -> 0 | R7: =(Q7-J7) -> -11400 | S7: =IF(R7+H7<0,1,0) -> 0 | T7: =(R7+J7)*K7 -> 0 | V7: =J7+VLOOKUP(C7,$AH$3:$AJ$95,3,0) -> 0 | W7: =V7*K7 -> 0 | X7: =W7/SUM($W$3:$W$95) -> 0 | Y7: =X7-N7 -> 0 | AA7: =VLOOKUP(C7,$AH$3:$AJ$95,3,0)+H7 -> 0 | AE7: 29 | AF7: S | AG7: VENDA | AH7: BBDC4 | AI7: 25900 | AJ7: =IF(AG7="VENDA",-AI7,AI7) -> -25900
A8: 46128 | B8: 29 | C8: AXIA6 | D8: AXIA ENERGIAPNB EB N1 | E8: BOVESPA | F8: 4500 | G8: 0 | H8: 4500 | I8: =SUMIF($E$108:$H$127,C8,$H$108:$H$127) -> 0 | J8: =I8+H8 -> 4500 | K8: =VLOOKUP(C8,$L$138:$M$230,2,0) -> 71.86 | L8: =K8*J8 -> 323370 | M8: =L8/SUM($L$3:$L$95) -> 0.012385143 | N8: =IFERROR(VLOOKUP(C8,'[1]pesos FIA'!$E$2:$F$74,2,0),0) -> 0.0195155 | O8: =M8-N8 -> -0.007130357 | P8: =N8*$L$1 -> 509540.12 | Q8: =ROUND(P8/K8/100,0)*100 -> 7100 | R8: =(Q8-J8) -> 2600 | S8: =IF(R8+H8<0,1,0) -> 0 | T8: =(R8+J8)*K8 -> 510206 | V8: =J8+VLOOKUP(C8,$AH$3:$AJ$95,3,0) -> 6900 | W8: =V8*K8 -> 495834 | X8: =W8/SUM($W$3:$W$95) -> 0.01884488 | Y8: =X8-N8 -> -0.00067061956 | AA8: =VLOOKUP(C8,$AH$3:$AJ$95,3,0)+H8 -> 6900 | AE8: 29 | AF8: S | AG8: VENDA | AH8: PGMN3 | AI8: 25000 | AJ8: =IF(AG8="VENDA",-AI8,AI8) -> -25000
A9: 46128 | B9: 29 | C9: BBAS3 | D9: BRASIL ON EJ NM | E9: BOVESPA | F9: 10300 | G9: 400 | H9: 10700 | I9: =SUMIF($E$108:$H$127,C9,$H$108:$H$127) -> 24000 | J9: =I9+H9 -> 34700 | K9: =VLOOKUP(C9,$L$138:$M$230,2,0) -> 24.28 | L9: =K9*J9 -> 842516 | M9: =L9/SUM($L$3:$L$95) -> 0.032268551 | N9: =IFERROR(VLOOKUP(C9,'[1]pesos FIA'!$E$2:$F$74,2,0),0) -> 0 | O9: =M9-N9 -> 0.032268551 | P9: =N9*$L$1 -> 0 | Q9: =ROUND(P9/K9/100,0)*100 -> 0 | R9: =(Q9-J9) -> -34700 | S9: =IF(R9+H9<0,1,0) -> 1 | T9: =(R9+J9)*K9 -> 0 | V9: =J9+VLOOKUP(C9,$AH$3:$AJ$95,3,0) -> 24200 | W9: =V9*K9 -> 587576 | X9: =W9/SUM($W$3:$W$95) -> 0.022331666 | Y9: =X9-N9 -> 0.022331666 | AA9: =VLOOKUP(C9,$AH$3:$AJ$95,3,0)+H9 -> 200 | AE9: 29 | AF9: S | AG9: VENDA | AH9: MGLU3 | AI9: 10800 | AJ9: =IF(AG9="VENDA",-AI9,AI9) -> -10800
A10: 46128 | B10: 29 | C10: BBDC3 | D10: BRADESCO ON N1 | E10: BOVESPA | F10: 32500 | G10: 0 | H10: 32500 | I10: =SUMIF($E$108:$H$127,C10,$H$108:$H$127) -> 0 | J10: =I10+H10 -> 32500 | K10: =VLOOKUP(C10,$L$138:$M$230,2,0) -> 18.12 | L10: =K10*J10 -> 588900 | M10: =L10/SUM($L$3:$L$95) -> 0.022555001 | N10: =IFERROR(VLOOKUP(C10,'[1]pesos FIA'!$E$2:$F$74,2,0),0) -> 0.0195155 | O10: =M10-N10 -> 0.0030395012 | P10: =N10*$L$1 -> 509540.12 | Q10: =ROUND(P10/K10/100,0)*100 -> 28100 | R10: =(Q10-J10) -> -4400 | S10: =IF(R10+H10<0,1,0) -> 0 | T10: =(R10+J10)*K10 -> 509172 | V10: =J10+VLOOKUP(C10,$AH$3:$AJ$95,3,0) -> 28000 | W10: =V10*K10 -> 507360 | X10: =W10/SUM($W$3:$W$95) -> 0.019282943 | Y10: =X10-N10 -> -0.00023255744 | AA10: =VLOOKUP(C10,$AH$3:$AJ$95,3,0)+H10 -> 28000 | AE10: 29 | AF10: S | AG10: VENDA | AH10: ABEV3 | AI10: 21600 | AJ10: =IF(AG10="VENDA",-AI10,AI10) -> -21600
A11: 46128 | B11: 29 | C11: BBDC4 | D11: BRADESCO PN N1 | E11: BOVESPA | F11: 25900 | G11: 0 | H11: 25900 | I11: =SUMIF($E$108:$H$127,C11,$H$108:$H$127) -> 0 | J11: =I11+H11 -> 25900 | K11: =VLOOKUP(C11,$L$138:$M$230,2,0) -> 20.85 | L11: =K11*J11 -> 540015 | M11: =L11/SUM($L$3:$L$95) -> 0.020682695 | N11: =IFERROR(VLOOKUP(C11,'[1]pesos FIA'!$E$2:$F$74,2,0),0) -> 0 | O11: =M11-N11 -> 0.020682695 | P11: =N11*$L$1 -> 0 | Q11: =ROUND(P11/K11/100,0)*100 -> 0 | R11: =(Q11-J11) -> -25900 | S11: =IF(R11+H11<0,1,0) -> 0 | T11: =(R11+J11)*K11 -> 0 | V11: =J11+VLOOKUP(C11,$AH$3:$AJ$95,3,0) -> 0 | W11: =V11*K11 -> 0 | X11: =W11/SUM($W$3:$W$95) -> 0 | Y11: =X11-N11 -> 0 | AA11: =VLOOKUP(C11,$AH$3:$AJ$95,3,0)+H11 -> 0 | AE11: 29 | AF11: S | AG11: VENDA | AH11: GOAU4 | AI11: 19466 | AJ11: =IF(AG11="VENDA",-AI11,AI11) -> -19466
A12: 46128 | B12: 29 | C12: BBSE3 | D12: BBSEGURIDADEON EDR NM | E12: BOVESPA | F12: 4400 | G12: 100 | H12: 4500 | I12: =SUMIF($E$108:$H$127,C12,$H$108:$H$127) -> 5500 | J12: =I12+H12 -> 10000 | K12: =VLOOKUP(C12,$L$138:$M$230,2,0) -> 35.01 | L12: =K12*J12 -> 350100 | M12: =L12/SUM($L$3:$L$95) -> 0.013408908 | N12: =IFERROR(VLOOKUP(C12,'[1]pesos FIA'!$E$2:$F$74,2,0),0) -> 0.01697 | O12: =M12-N12 -> -0.003561092 | P12: =N12*$L$1 -> 443078.36 | Q12: =ROUND(P12/K12/100,0)*100 -> 12700 | R12: =(Q12-J12) -> 2700 | S12: =IF(R12+H12<0,1,0) -> 0 | T12: =(R12+J12)*K12 -> 444627 | V12: =J12+VLOOKUP(C12,$AH$3:$AJ$95,3,0) -> 12300 | W12: =V12*K12 -> 430623 | X12: =W12/SUM($W$3:$W$95) -> 0.016366443 | Y12: =X12-N12 -> -0.0006035569 | AA12: =VLOOKUP(C12,$AH$3:$AJ$95,3,0)+H12 -> 6800 | AE12: 29 | AF12: S | AG12: VENDA | AH12: ECOR3 | AI12: 18800 | AJ12: =IF(AG12="VENDA",-AI12,AI12) -> -18800
A13: 46128 | B13: 29 | C13: BMEB4 | D13: MERCANTIL PN N1 | E13: BOVESPA | F13: 3000 | G13: 0 | H13: 3000 | I13: =SUMIF($E$108:$H$127,C13,$H$108:$H$127) -> 0 | J13: =I13+H13 -> 3000 | K13: =VLOOKUP(C13,$L$138:$M$230,2,0) -> 80.3 | L13: =K13*J13 -> 240900 | M13: =L13/SUM($L$3:$L$95) -> 0.0092265237 | N13: =IFERROR(VLOOKUP(C13,'[1]pesos FIA'!$E$2:$F$74,2,0),0) -> 0.006788 | O13: =M13-N13 -> 0.0024385237 | P13: =N13*$L$1 -> 177231.35 | Q13: =ROUND(P13/K13/100,0)*100 -> 2200 | R13: =(Q13-J13) -> -800 | S13: =IF(R13+H13<0,1,0) -> 0 | T13: =(R13+J13)*K13 -> 176660 | V13: =J13+VLOOKUP(C13,$AH$3:$AJ$95,3,0) -> 2300 | W13: =V13*K13 -> 184690 | X13: =W13/SUM($W$3:$W$95) -> 0.0070194076 | Y13: =X13-N13 -> 0.00023140764 | AA13: =VLOOKUP(C13,$AH$3:$AJ$95,3,0)+H13 -> 2300 | AE13: 29 | AF13: S | AG13: VENDA | AH13: BRAP4 | AI13: 17900 | AJ13: =IF(AG13="VENDA",-AI13,AI13) -> -17900
A14: 46128 | B14: 29 | C14: BMGB4 | D14: BANCO BMG PN N1 | E14: BOVESPA | F14: 31900 | G14: 1000 | H14: 32900 | I14: =SUMIF($E$108:$H$127,C14,$H$108:$H$127) -> 0 | J14: =I14+H14 -> 32900 | K14: =VLOOKUP(C14,$L$138:$M$230,2,0) -> 5.53 | L14: =K14*J14 -> 181937 | M14: =L14/SUM($L$3:$L$95) -> 0.0069682276 | N14: =IFERROR(VLOOKUP(C14,'[1]pesos FIA'!$E$2:$F$74,2,0),0) -> 0.008485 | O14: =M14-N14 -> -0.0015167724 | P14: =N14*$L$1 -> 221539.18 | Q14: =ROUND(P14/K14/100,0)*100 -> 40100 | R14: =(Q14-J14) -> 7200 | S14: =IF(R14+H14<0,1,0) -> 0 | T14: =(R14+J14)*K14 -> 221753 | V14: =J14+VLOOKUP(C14,$AH$3:$AJ$95,3,0) -> 39100 | W14: =V14*K14 -> 216223 | X14: =W14/SUM($W$3:$W$95) -> 0.0082178644 | Y14: =X14-N14 -> -0.00026713559 | AA14: =VLOOKUP(C14,$AH$3:$AJ$95,3,0)+H14 -> 39100 | AE14: 29 | AF14: S | AG14: VENDA | AH14: CXSE3 | AI14: 17900 | AJ14: =IF(AG14="VENDA",-AI14,AI14) -> -17900
A15: 46128 | B15: 29 | C15: BOVA11 | D15: ISHARES BOVACI | E15: BOVESPA | F15: 3891 | G15: 0 | H15: 3891 | I15: =SUMIF($E$108:$H$127,C15,$H$108:$H$127) -> 9909 | J15: =I15+H15 -> 13800 | K15: =VLOOKUP(C15,$L$138:$M$230,2,0) -> 193.05 | L15: =K15*J15 -> 2664090 | M15: =L15/SUM($L$3:$L$95) -> 0.10203524 | N15: =IFERROR(VLOOKUP(C15,'[1]pesos FIA'!$E$2:$F$74,2,0),0) -> 0.1 | O15: =M15-N15 -> 0.0020352405 | P15: =N15*$L$1 -> 2610950.9 | Q15: =ROUND(P15/K15/100,0)*100 -> 13500 | R15: =(Q15-J15) -> -300 | S15: =IF(R15+H15<0,1,0) -> 0 | T15: =(R15+J15)*K15 -> 2606175 | V15: =J15+VLOOKUP(C15,$AH$3:$AJ$95,3,0) -> 12800 | W15: =V15*K15 -> 2471040 | X15: =W15/SUM($W$3:$W$95) -> 0.09391541 | Y15: =X15-N15 -> -0.0060845901 | AA15: =VLOOKUP(C15,$AH$3:$AJ$95,3,0)+H15 -> 2891 | AE15: 29 | AF15: S | AG15: VENDA | AH15: MBRF3 | AI15: 5800 | AJ15: =IF(AG15="VENDA",-AI15,AI15) -> -5800
A16: 46128 | B16: 29 | C16: BOVV11 | D16: IT NOW IBOV CI | E16: BOVESPA | F16: 3095 | G16: 200 | H16: 3295 | I16: =SUMIF($E$108:$H$127,C16,$H$108:$H$127) -> 3405 | J16: =I16+H16 -> 6700 | K16: =VLOOKUP(C16,$L$138:$M$230,2,0) -> 202.6 | L16: =K16*J16 -> 1357420 | M16: =L16/SUM($L$3:$L$95) -> 0.051989488 | N16: =IFERROR(VLOOKUP(C16,'[1]pesos FIA'!$E$2:$F$74,2,0),0) -> 0.05 | O16: =M16-N16 -> 0.0019894884 | P16: =N16*$L$1 -> 1305475.4 | Q16: =ROUND(P16/K16/100,0)*100 -> 6400 | R16: =(Q16-J16) -> -300 | S16: =IF(R16+H16<0,1,0) -> 0 | T16: =(R16+J16)*K16 -> 1296640 | V16: =J16+VLOOKUP(C16,$AH$3:$AJ$95,3,0) -> 5900 | W16: =V16*K16 -> 1195340 | X16: =W16/SUM($W$3:$W$95) -> 0.045430607 | Y16: =X16-N16 -> -0.0045693934 | AA16: =VLOOKUP(C16,$AH$3:$AJ$95,3,0)+H16 -> 2495 | AE16: 29 | AF16: S | AG16: VENDA | AH16: ITUB3 | AI16: 8800 | AJ16: =IF(AG16="VENDA",-AI16,AI16) -> -8800
A17: 46128 | B17: 29 | C17: BRAP4 | D17: BRADESPAR PN EDJ N1 | E17: BOVESPA | F17: 22300 | G17: 0 | H17: 22300 | I17: =SUMIF($E$108:$H$127,C17,$H$108:$H$127) -> 0 | J17: =I17+H17 -> 22300 | K17: =VLOOKUP(C17,$L$138:$M$230,2,0) -> 25.05 | L17: =K17*J17 -> 558615 | M17: =L17/SUM($L$3:$L$95) -> 0.021395079 | N17: =IFERROR(VLOOKUP(C17,'[1]pesos FIA'!$E$2:$F$74,2,0),0) -> 0.0042425 | O17: =M17-N17 -> 0.017152579 | P17: =N17*$L$1 -> 110769.59 | Q17: =ROUND(P17/K17/100,0)*100 -> 4400 | R17: =(Q17-J17) -> -17900 | S17: =IF(R17+H17<0,1,0) -> 0 | T17: =(R17+J17)*K17 -> 110220 | V17: =J17+VLOOKUP(C17,$AH$3:$AJ$95,3,0) -> 4400 | W17: =V17*K17 -> 110220 | X17: =W17/SUM($W$3:$W$95) -> 0.0041890688 | Y17: =X17-N17 -> -5.3431235e-05 | AA17: =VLOOKUP(C17,$AH$3:$AJ$95,3,0)+H17 -> 4400 | AE17: 29 | AF17: S | AG17: VENDA | AH17: AXIA3 | AI17: 11400 | AJ17: =IF(AG17="VENDA",-AI17,AI17) -> -11400
... A69: 46128 | B69: 29 | C69: ABCB4 | D69: ABC BRASIL PN N2 | E69: BOVESPA | F69: 6900 | G69: 0 | H69: 6900 | I69: =SUMIF($E$108:$H$127,C69,$H$108:$H$127) -> 0 | J69: =I69+H69 -> 6900 | K69: =VLOOKUP(C69,$L$138:$M$230,2,0) -> 26.7 | L69: =K69*J69 -> 184230 | M69: =L69/SUM($L$3:$L$95) -> 0.00705605 | N69: =IFERROR(VLOOKUP(C69,'[1]pesos FIA'!$E$2:$F$74,2,0),0) -> 0.0127275 | O69: =M69-N69 -> -0.00567145 | P69: =N69*$L$1 -> 332308.77 | Q69: =ROUND(P69/K69/100,0)*100 -> 12400 | R69: =(Q69-J69) -> 5500 | S69: =IF(R69+H69<0,1,0) -> 0 | T69: =(R69+J69)*K69 -> 331080 | V69: =J69+VLOOKUP(C69,$AH$3:$AJ$95,3,0) -> 11600 | W69: =V69*K69 -> 309720 | X69: =W69/SUM($W$3:$W$95) -> 0.011771352 | Y69: =X69-N69 -> -0.00095614836 | AA69: =VLOOKUP(C69,$AH$3:$AJ$95,3,0)+H69 -> 11600 | AE69: 29 | AF69: B | AG69: COMPRA | AH69: ALPA4 | AI69: 10300 | AJ69: =IF(AG69="VENDA",-AI69,AI69) -> 10300
C70: SHUL4 | K70: =VLOOKUP(C70,$L$138:$M$230,2,0) -> 5.33 | L70: =K70*J70 -> 0 | M70: =L70/SUM($L$3:$L$95) -> 0 | N70: =IFERROR(VLOOKUP(C70,'[1]pesos FIA'!$E$2:$F$74,2,0),0) -> 0.010182 | O70: =M70-N70 -> -0.010182 | P70: =N70*$L$1 -> 265847.02 | Q70: =ROUND(P70/K70/100,0)*100 -> 49900 | R70: =(Q70-J70) -> 49900 | S70: =IF(R70+H70<0,1,0) -> 0 | T70: =(R70+J70)*K70 -> 265967 | V70: =J70+VLOOKUP(C70,$AH$3:$AJ$95,3,0) -> 42500 | W70: =V70*K70 -> 226525 | X70: =W70/SUM($W$3:$W$95) -> 0.0086094067 | Y70: =X70-N70 -> -0.0015725933 | AA70: =VLOOKUP(C70,$AH$3:$AJ$95,3,0)+H70 -> 42500 | AE70: 29 | AF70: B | AG70: COMPRA | AH70: ALUP11 | AI70: 10300 | AJ70: =IF(AG70="VENDA",-AI70,AI70) -> 10300
C71: MTRE3 | K71: =VLOOKUP(C71,$L$138:$M$230,2,0) -> 3.86 | L71: =K71*J71 -> 0 | M71: =L71/SUM($L$3:$L$95) -> 0 | N71: =IFERROR(VLOOKUP(C71,'[1]pesos FIA'!$E$2:$F$74,2,0),0) -> 0.011879 | O71: =M71-N71 -> -0.011879 | P71: =N71*$L$1 -> 310154.85 | Q71: =ROUND(P71/K71/100,0)*100 -> 80400 | R71: =(Q71-J71) -> 80400 | S71: =IF(R71+H71<0,1,0) -> 0 | T71: =(R71+J71)*K71 -> 310344 | V71: =J71+VLOOKUP(C71,$AH$3:$AJ$95,3,0) -> 69400 | W71: =V71*K71 -> 267884 | X71: =W71/SUM($W$3:$W$95) -> 0.010181315 | Y71: =X71-N71 -> -0.0016976854 | AA71: =VLOOKUP(C71,$AH$3:$AJ$95,3,0)+H71 -> 69400 | AE71: 29 | AF71: B | AG71: COMPRA | AH71: BRBI11 | AI71: 10400 | AJ71: =IF(AG71="VENDA",-AI71,AI71) -> 10400
C72: PFRM3 | K72: =VLOOKUP(C72,$L$138:$M$230,2,0) -> 8.06 | L72: =K72*J72 -> 0 | M72: =L72/SUM($L$3:$L$95) -> 0 | N72: =IFERROR(VLOOKUP(C72,'[1]pesos FIA'!$E$2:$F$74,2,0),0) -> 0.006788 | O72: =M72-N72 -> -0.006788 | P72: =N72*$L$1 -> 177231.35 | Q72: =ROUND(P72/K72/100,0)*100 -> 22000 | R72: =(Q72-J72) -> 22000 | S72: =IF(R72+H72<0,1,0) -> 0 | T72: =(R72+J72)*K72 -> 177320 | V72: =J72+VLOOKUP(C72,$AH$3:$AJ$95,3,0) -> 18900 | W72: =V72*K72 -> 152334 | X72: =W72/SUM($W$3:$W$95) -> 0.0057896716 | Y72: =X72-N72 -> -0.00099832842 | AA72: =VLOOKUP(C72,$AH$3:$AJ$95,3,0)+H72 -> 18900 | AE72: 29 | AF72: B | AG72: COMPRA | AH72: ODPV3 | AI72: 11900 | AJ72: =IF(AG72="VENDA",-AI72,AI72) -> 11900
C73: DEXP3 | K73: =VLOOKUP(C73,$L$138:$M$230,2,0) -> 7.33 | L73: =K73*J73 -> 0 | M73: =L73/SUM($L$3:$L$95) -> 0 | N73: =IFERROR(VLOOKUP(C73,'[1]pesos FIA'!$E$2:$F$74,2,0),0) -> 0.0093335 | O73: =M73-N73 -> -0.0093335 | P73: =N73*$L$1 -> 243693.1 | Q73: =ROUND(P73/K73/100,0)*100 -> 33200 | R73: =(Q73-J73) -> 33200 | S73: =IF(R73+H73<0,1,0) -> 0 | T73: =(R73+J73)*K73 -> 243356 | V73: =J73+VLOOKUP(C73,$AH$3:$AJ$95,3,0) -> 28200 | W73: =V73*K73 -> 206706 | X73: =W73/SUM($W$3:$W$95) -> 0.0078561572 | Y73: =X73-N73 -> -0.0014773428 | AA73: =VLOOKUP(C73,$AH$3:$AJ$95,3,0)+H73 -> 28200 | AE73: 29 | AF73: B | AG73: COMPRA | AH73: LREN3 | AI73: 12300 | AJ73: =IF(AG73="VENDA",-AI73,AI73) -> 12300
C74: POMO4 | K74: =VLOOKUP(C74,$L$138:$M$230,2,0) -> 6.86 | L74: =K74*J74 -> 0 | M74: =L74/SUM($L$3:$L$95) -> 0 | N74: =IFERROR(VLOOKUP(C74,'[1]pesos FIA'!$E$2:$F$74,2,0),0) -> 0.008485 | O74: =M74-N74 -> -0.008485 | P74: =N74*$L$1 -> 221539.18 | Q74: =ROUND(P74/K74/100,0)*100 -> 32300 | R74: =(Q74-J74) -> 32300 | S74: =IF(R74+H74<0,1,0) -> 0 | T74: =(R74+J74)*K74 -> 221578 | V74: =J74+VLOOKUP(C74,$AH$3:$AJ$95,3,0) -> 27100 | W74: =V74*K74 -> 185906 | X74: =W74/SUM($W$3:$W$95) -> 0.0070656235 | Y74: =X74-N74 -> -0.0014193765 | AA74: =VLOOKUP(C74,$AH$3:$AJ$95,3,0)+H74 -> 27100 | AE74: 29 | AF74: B | AG74: COMPRA | AH74: WIZC3 | AI74: 12400 | AJ74: =IF(AG74="VENDA",-AI74,AI74) -> 12400
C75: LOGG3 | K75: =VLOOKUP(C75,$L$138:$M$230,2,0) -> 27.61 | L75: =K75*J75 -> 0 | M75: =L75/SUM($L$3:$L$95) -> 0 | N75: =IFERROR(VLOOKUP(C75,'[1]pesos FIA'!$E$2:$F$74,2,0),0) -> 0.008485 | O75: =M75-N75 -> -0.008485 | P75: =N75*$L$1 -> 221539.18 | Q75: =ROUND(P75/K75/100,0)*100 -> 8000 | R75: =(Q75-J75) -> 8000 | S75: =IF(R75+H75<0,1,0) -> 0 | T75: =(R75+J75)*K75 -> 220880 | V75: =J75+VLOOKUP(C75,$AH$3:$AJ$95,3,0) -> 6800 | W75: =V75*K75 -> 187748 | X75: =W75/SUM($W$3:$W$95) -> 0.0071356313 | Y75: =X75-N75 -> -0.0013493687 | AA75: =VLOOKUP(C75,$AH$3:$AJ$95,3,0)+H75 -> 6800 | AE75: 29 | AF75: B | AG75: COMPRA | AH75: PNVL3 | AI75: 12580 | AJ75: =IF(AG75="VENDA",-AI75,AI75) -> 12580
C76: ODPV3 | K76: =VLOOKUP(C76,$L$138:$M$230,2,0) -> 15.8 | L76: =K76*J76 -> 0 | M76: =L76/SUM($L$3:$L$95) -> 0 | N76: =IFERROR(VLOOKUP(C76,'[1]pesos FIA'!$E$2:$F$74,2,0),0) -> 0.008485 | O76: =M76-N76 -> -0.008485 | P76: =N76*$L$1 -> 221539.18 | Q76: =ROUND(P76/K76/100,0)*100 -> 14000 | R76: =(Q76-J76) -> 14000 | S76: =IF(R76+H76<0,1,0) -> 0 | T76: =(R76+J76)*K76 -> 221200 | V76: =J76+VLOOKUP(C76,$AH$3:$AJ$95,3,0) -> 11900 | W76: =V76*K76 -> 188020 | X76: =W76/SUM($W$3:$W$95) -> 0.0071459691 | Y76: =X76-N76 -> -0.0013390309 | AA76: =VLOOKUP(C76,$AH$3:$AJ$95,3,0)+H76 -> 11900 | AE76: 29 | AF76: B | AG76: COMPRA | AH76: INTB3 | AI76: 14200 | AJ76: =IF(AG76="VENDA",-AI76,AI76) -> 14200
C77: EVEN3 | K77: =VLOOKUP(C77,$L$138:$M$230,2,0) -> 6.92 | L77: =K77*J77 -> 0 | M77: =L77/SUM($L$3:$L$95) -> 0 | N77: =IFERROR(VLOOKUP(C77,'[1]pesos FIA'!$E$2:$F$74,2,0),0) -> 0.0093335 | O77: =M77-N77 -> -0.0093335 | P77: =N77*$L$1 -> 243693.1 | Q77: =ROUND(P77/K77/100,0)*100 -> 35200 | R77: =(Q77-J77) -> 35200 | S77: =IF(R77+H77<0,1,0) -> 0 | T77: =(R77+J77)*K77 -> 243584 | V77: =J77+VLOOKUP(C77,$AH$3:$AJ$95,3,0) -> 30900 | W77: =V77*K77 -> 213828 | X77: =W77/SUM($W$3:$W$95) -> 0.008126839 | Y77: =X77-N77 -> -0.001206661 | AA77: =VLOOKUP(C77,$AH$3:$AJ$95,3,0)+H77 -> 30900 | AE77: 29 | AF77: B | AG77: COMPRA | AH77: FIQE3 | AI77: 15100 | AJ77: =IF(AG77="VENDA",-AI77,AI77) -> 15100
C78: ITSA3 | K78: =VLOOKUP(C78,$L$138:$M$230,2,0) -> 14.66 | L78: =K78*J78 -> 0 | M78: =L78/SUM($L$3:$L$95) -> 0 | N78: =IFERROR(VLOOKUP(C78,'[1]pesos FIA'!$E$2:$F$74,2,0),0) -> 0.0178185 | O78: =M78-N78 -> -0.0178185 | P78: =N78*$L$1 -> 465232.28 | Q78: =ROUND(P78/K78/100,0)*100 -> 31700 | R78: =(Q78-J78) -> 31700 | S78: =IF(R78+H78<0,1,0) -> 0 | T78: =(R78+J78)*K78 -> 464722 | V78: =J78+VLOOKUP(C78,$AH$3:$AJ$95,3,0) -> 26900 | W78: =V78*K78 -> 394354 | X78: =W78/SUM($W$3:$W$95) -> 0.014987988 | Y78: =X78-N78 -> -0.0028305121 | AA78: =VLOOKUP(C78,$AH$3:$AJ$95,3,0)+H78 -> 26900 | AE78: 29 | AF78: B | AG78: COMPRA | AH78: GRND3 | AI78: 17500 | AJ78: =IF(AG78="VENDA",-AI78,AI78) -> 17500
C79: INTB3 | K79: =VLOOKUP(C79,$L$138:$M$230,2,0) -> 14.39 | L79: =K79*J79 -> 0 | M79: =L79/SUM($L$3:$L$95) -> 0 | N79: =IFERROR(VLOOKUP(C79,'[1]pesos FIA'!$E$2:$F$74,2,0),0) -> 0.0093335 | O79: =M79-N79 -> -0.0093335 | P79: =N79*$L$1 -> 243693.1 | Q79: =ROUND(P79/K79/100,0)*100 -> 16900 | R79: =(Q79-J79) -> 16900 | S79: =IF(R79+H79<0,1,0) -> 0 | T79: =(R79+J79)*K79 -> 243191 | V79: =J79+VLOOKUP(C79,$AH$3:$AJ$95,3,0) -> 14200 | W79: =V79*K79 -> 204338 | X79: =W79/SUM($W$3:$W$95) -> 0.007766158 | Y79: =X79-N79 -> -0.001567342 | AA79: =VLOOKUP(C79,$AH$3:$AJ$95,3,0)+H79 -> 14200 | AE79: 29 | AF79: B | AG79: COMPRA | AH79: FESA4 | AI79: 18600 | AJ79: =IF(AG79="VENDA",-AI79,AI79) -> 18600
C80: MLAS3 | K80: =VLOOKUP(C80,$L$138:$M$230,2,0) -> 1.58 | L80: =K80*J80 -> 0 | M80: =L80/SUM($L$3:$L$95) -> 0 | N80: =IFERROR(VLOOKUP(C80,'[1]pesos FIA'!$E$2:$F$74,2,0),0) -> 0.0059395 | O80: =M80-N80 -> -0.0059395 | P80: =N80*$L$1 -> 155077.43 | Q80: =ROUND(P80/K80/100,0)*100 -> 98200 | R80: =(Q80-J80) -> 98200 | S80: =IF(R80+H80<0,1,0) -> 0 | T80: =(R80+J80)*K80 -> 155156 | V80: =J80+VLOOKUP(C80,$AH$3:$AJ$95,3,0) -> 84000 | W80: =V80*K80 -> 132720 | X80: =W80/SUM($W$3:$W$95) -> 0.0050442135 | Y80: =X80-N80 -> -0.00089528655 | AA80: =VLOOKUP(C80,$AH$3:$AJ$95,3,0)+H80 -> 84000 | AE80: 29 | AF80: B | AG80: COMPRA | AH80: PFRM3 | AI80: 18900 | AJ80: =IF(AG80="VENDA",-AI80,AI80) -> 18900
C81: ALUP11 | K81: =VLOOKUP(C81,$L$138:$M$230,2,0) -> 36.36 | L81: =K81*J81 -> 0 | M81: =L81/SUM($L$3:$L$95) -> 0 | N81: =IFERROR(VLOOKUP(C81,'[1]pesos FIA'!$E$2:$F$74,2,0),0) -> 0.01697 | O81: =M81-N81 -> -0.01697 | P81: =N81*$L$1 -> 443078.36 | Q81: =ROUND(P81/K81/100,0)*100 -> 12200 | R81: =(Q81-J81) -> 12200 | S81: =IF(R81+H81<0,1,0) -> 0 | T81: =(R81+J81)*K81 -> 443592 | V81: =J81+VLOOKUP(C81,$AH$3:$AJ$95,3,0) -> 10300 | W81: =V81*K81 -> 374508 | X81: =W81/SUM($W$3:$W$95) -> 0.014233712 | Y81: =X81-N81 -> -0.0027362877 | AA81: =VLOOKUP(C81,$AH$3:$AJ$95,3,0)+H81 -> 10300 | AE81: 29 | AF81: B | AG81: COMPRA | AH81: RECV3 | AI81: 22000 | AJ81: =IF(AG81="VENDA",-AI81,AI81) -> 22000
... C95: LREN3 | K95: =VLOOKUP(C95,$L$138:$M$230,2,0) -> 15.05 | L95: =K95*J95 -> 0 | M95: =L95/SUM($L$3:$L$95) -> 0 | N95: =IFERROR(VLOOKUP(C95,'[1]pesos FIA'!$E$2:$F$74,2,0),0) -> 0.008485 | O95: =M95-N95 -> -0.008485 | P95: =N95*$L$1 -> 221539.18 | Q95: =ROUND(P95/K95/100,0)*100 -> 14700 | R95: =(Q95-J95) -> 14700 | S95: =IF(R95+H95<0,1,0) -> 0 | T95: =(R95+J95)*K95 -> 221235 | V95: =J95+VLOOKUP(C95,$AH$3:$AJ$95,3,0) -> 12300 | W95: =V95*K95 -> 185115 | X95: =W95/SUM($W$3:$W$95) -> 0.0070355604 | Y95: =X95-N95 -> -0.0014494396 | AA95: =VLOOKUP(C95,$AH$3:$AJ$95,3,0)+H95 -> 12300 | AE95: 29 | AF95: B | AG95: COMPRA | AH95: MLAS3 | AI95: 84000 | AJ95: =IF(AG95="VENDA",-AI95,AI95) -> 84000
A106: RENDA VARIAVEL - EMPRÉSTIMO DE AÇÕES
A107: Cód. Op. | B107: Operação | C107: Dt. Operação | D107: Dt. Vencto. | E107: Cód. | F107: Papel | G107: Bolsa | H107: Quantidade | U107: % S/ Total
A108: 139584 | B108: Doador | C108: 46105 | D108: 46139 | E108: PETR3 | F108: PETROBRAS ON N2 | G108: BOVESPA | H108: 11292 | T108: 0 | U108: 0 | W108: 548 | X108: 2.8e+15 | AE108: 0 | AF108: 1.0160755e+17 | AH108: 0 | AI108: 2.1563037e+16
A109: 139587 | B109: Doador | C109: 46105 | D109: 46139 | E109: CMIN3 | F109: CSNMINERACAOON N2 | G109: BOVESPA | H109: 28400 | T109: 0 | U109: 0 | W109: 242 | X109: 4.8e+15 | AE109: 0 | AF109: 2.4874612e+16 | AH109: 0 | AI109: 5.2788616e+15
A110: 139589 | B110: Doador | C110: 46105 | D110: 46139 | E110: BOVA11 | F110: ISHARES BOVACI | G110: BOVESPA | H110: 150 | T110: 0 | U110: 0 | W110: 10 | X110: 8.4e+16 | AE110: 0 | AF110: 4.7843767e+15 | AH110: 0 | AI110: 1.0153349e+15
A111: 140462 | B111: Doador | C111: 46112 | D111: 46146 | E111: ITUB3 | F111: ITAUUNIBANCOON N1 | G111: BOVESPA | H111: 15800 | T111: 0 | U111: 0 | W111: 36 | X111: 8.6e+16 | AE111: 0 | AF111: 1.1618853e+17 | AH111: 0 | AI111: 2.4657397e+16
A112: 140464 | B112: Doador | C112: 46112 | D112: 46146 | E112: TAEE11 | F112: TAESA UNT N2 | G112: BOVESPA | H112: 1000 | T112: 0 | U112: 0 | W112: 20 | X112: 7.3e+16 | AE112: 0 | AF112: 7.4234165e+15 | AH112: 0 | AI112: 1.5753889e+15
A113: 140465 | B113: Doador | C113: 46112 | D113: 46146 | E113: MBRF3 | F113: MARFRIG GLOBAL FOODS S.A. | G113: BOVESPA | H113: 3472 | T113: 0 | U113: 0 | W113: 959 | X113: 360000000000000 | AE113: 0 | AF113: 1.3852106e+16 | AH113: 0 | AI113: 2.939678e+15
A114: 140466 | B114: Doador | C114: 46112 | D114: 46146 | E114: TAEE11 | F114: TAESA UNT N2 | G114: BOVESPA | H114: 1600 | T114: 0 | U114: 0 | W114: 33 | X114: 1.7e+16 | AE114: 0 | AF114: 1.1877466e+16 | AH114: 0 | AI114: 2.5206223e+15
A115: 140688 | B115: Doador | C115: 46113 | D115: 46146 | E115: ABEV3 | F115: AMBEV S/A ON EX | G115: BOVESPA | H115: 1500 | T115: 0 | U115: 0 | W115: 0 | X115: 9e+17 | AE115: 0 | AF115: 4.0647361e+15 | AH115: 0 | AI115: 862613623625826
A116: 140756 | B116: Doador | C116: 46113 | D116: 46146 | E116: TAEE11 | F116: TAESA UNT N2 | G116: BOVESPA | H116: 400 | T116: 0 | U116: 0 | W116: 7 | X116: 4.1e+17 | AE116: 0 | AF116: 3.0523058e+15 | AH116: 0 | AI116: 647756826606623
A117: 140757 | B117: Doador | C117: 46113 | D117: 46146 | E117: MGLU3 | F117: MAGAZ LUIZA ON NM | G117: BOVESPA | H117: 10700 | T117: 0 | U117: 0 | W117: 980 | X117: 870000000000000 | AE117: 0 | AF117: 1.6429292e+16 | AH117: 0 | AI117: 3.4866054e+15
A118: 140758 | B118: Doador | C118: 46113 | D118: 46146 | E118: MGLU3 | F118: MAGAZ LUIZA ON NM | G118: BOVESPA | H118: 535 | T118: 0 | U118: 0 | W118: 49 | X118: 4e+15 | AE118: 0 | AF118: 821464580910065 | AH118: 0 | AI118: 174330268224100
A119: 141498 | B119: Doador | C119: 46120 | D119: 46153 | E119: LIGT3 | F119: LIGHT S/A ON ES NM | G119: BOVESPA | H119: 22000 | T119: 0 | U119: 0 | W119: 10 | X119: 1.8e+16 | AE119: 0 | AF119: 2.2533009e+16 | AH119: 0 | AI119: 4.7819293e+15
... A127: 142766 | B127: Doador | C127: 46127 | D127: 46160 | E127: MULT3 | F127: MULTIPLAN ON N2 | G127: BOVESPA | H127: 4400 | T127: 0 | U127: 0 | W127: 10 | X127: 5.3e+16 | AE127: 0 | AF127: 2.7055341e+16 | AH127: 0 | AI127: 5.7416534e+15
K138: ABC BRASIL PN N2 - ABCB4 | L138: =RIGHT(K138,5) -> ABCB4 | M138: 26.7
K139: ALLIED ON NM - ALLD3 | L139: =RIGHT(K139,5) -> ALLD3 | M139: 6.69
K140: ALLOS ON NM - ALOS3 | L140: =RIGHT(K140,6) -> ALOS3 | M140: 33.27
K141: ALPARGATAS PN N1 - ALPA4 | L141: =RIGHT(K141,5) -> ALPA4 | M141: 12.24
K142: ALUPAR UNT N2 - ALUP11 | L142: =RIGHT(K142,6) -> ALUP11 | M142: 36.36
K143: AMBEV S.A. ON - ABEV3 | L143: =RIGHT(K143,5) -> ABEV3 | M143: 15.43
K144: AXIA ENERGIAON N1 - AXIA3 | L144: =RIGHT(K144,5) -> AXIA3 | M144: 65.56
K145: AXIA ENERGIAPNB N1 - AXIA6 | L145: =RIGHT(K145,5) -> AXIA6 | M145: 71.86
K146: AZZAS 2154 ON NM - AZZA3 | L146: =RIGHT(K146,5) -> AZZA3 | M146: 22.22
D147: ticker | E147: nome | K147: BANCO BMG PN N1 - BMGB4 | L147: =RIGHT(K147,5) -> BMGB4 | M147: 5.53
D148: WIZC3 | E148: =VLOOKUP(D148,$C$3:$D$69,2,0) -> WIZ CO ON NM | K148: BANRISUL PNB N1 - BRSR6 | L148: =RIGHT(K148,5) -> BRSR6 | M148: 16.6
D149: JHSF3 | E149: =VLOOKUP(D149,$C$3:$D$69,2,0) -> JHSF PART ON NM | K149: BBSEGURIDADE ON NM - BBSE3 | L149: =RIGHT(K149,5) -> BBSE3 | M149: 35.01
D150: BMGB4 | E150: =VLOOKUP(D150,$C$3:$D$69,2,0) -> BANCO BMG PN N1 | K150: BEMOBI TECH ON NM - BMOB3 | L150: =RIGHT(K150,5) -> BMOB3 | M150: 27.67
D151: RIAA3 | E151: =VLOOKUP(D151,$C$3:$D$69,2,0) -> RIACHUELO ON NM | K151: BR PARTNERS UNT N2 - BRBI11 | L151: =RIGHT(K151,6) -> BRBI11 | M151: 19.31
D152: CSED3 | E152: =VLOOKUP(D152,$C$3:$D$69,2,0) -> CRUZEIRO EDUON ED NM | K152: BRADESCO ON N1 - BBDC3 | L152: =RIGHT(K152,5) -> BBDC3 | M152: 18.12
D153: ALLD3 | E153: =VLOOKUP(D153,$C$3:$D$69,2,0) -> ALLIED ON NM | K153: BRADESCO PN N1 - BBDC4 | L153: =RIGHT(K153,5) -> BBDC4 | M153: 20.85
D154: SYNE3 | E154: =VLOOKUP(D154,$C$3:$D$69,2,0) -> SYN PROP TECON ED NM | K154: BRADESPAR PN N1 - BRAP4 | L154: =RIGHT(K154,5) -> BRAP4 | M154: 25.05
D155: POMO3 | E155: =VLOOKUP(D155,$C$3:$D$69,2,0) -> MARCOPOLO ON N2 | K155: BRASIL ON NM - BBAS3 | L155: =RIGHT(K155,5) -> BBAS3 | M155: 24.28
D156: SHUL4 | E156: =VLOOKUP(D156,$C$3:$D$69,2,0) -> #N/A | K156: CAIXA SEGURION NM - CXSE3 | L156: =RIGHT(K156,5) -> CXSE3 | M156: 18.88
D157: FIQE3 | E157: =VLOOKUP(D157,$C$3:$D$69,2,0) -> UNIFIQUE ON NM | K157: CAMIL ON NM - CAML3 | L157: =RIGHT(K157,5) -> CAML3 | M157: 7.26
D158: MTRE3 | E158: =VLOOKUP(D158,$C$3:$D$69,2,0) -> #N/A | K158: CEMIG PN N1 - CMIG4 | L158: =RIGHT(K158,5) -> CMIG4 | M158: 13.52
D159: BRSR6 | E159: =VLOOKUP(D159,$C$3:$D$69,2,0) -> BANRISUL PNB N1 | K159: COPASA ON NM - CSMG3 | L159: =RIGHT(K159,5) -> CSMG3 | M159: 57.4
D160: GRND3 | E160: =VLOOKUP(D160,$C$3:$D$69,2,0) -> GRENDENE ON NM | K160: COPEL ON N1 - CPLE3 | L160: =RIGHT(K160,5) -> CPLE3 | M160: 16.8
D161: TIMS3 | E161: =VLOOKUP(D161,$C$3:$D$69,2,0) -> TIM ON NM | K161: CPFL ENERGIA ON NM - CPFE3 | L161: =RIGHT(K161,5) -> CPFE3 | M161: 56.26
D162: SAPR4 | E162: =VLOOKUP(D162,$C$3:$D$69,2,0) -> SANEPAR PN N2 | K162: CRUZEIRO EDUON NM - CSED3 | L162: =RIGHT(K162,5) -> CSED3 | M162: 6.19
D163: PFRM3 | E163: =VLOOKUP(D163,$C$3:$D$69,2,0) -> #N/A | K163: CSNMINERACAOON N2 - CMIN3 | L163: =RIGHT(K163,5) -> CMIN3 | M163: 4.818507
... D175: CURY3 | E175: =VLOOKUP(D175,$C$3:$D$69,2,0) -> CURY S/A ON ED NM | K175: HELBOR ON NM - HBOR3 | L175: =RIGHT(K175,5) -> HBOR3 | M175: 2.35
D176: ALOS3 | E176: =VLOOKUP(D176,$C$3:$D$69,2,0) -> ALLOS ON NM | K176: IGUATEMI S.AUNT N1 - IGTI11 | L176: =RIGHT(K176,6) -> IGTI11 | M176: 29.82
D177: ITSA3 | E177: =VLOOKUP(D177,$C$3:$D$69,2,0) -> #N/A | K177: INTELBRAS ON NM - INTB3 | L177: =RIGHT(K177,5) -> INTB3 | M177: 14.39
D178: MELK3 | E178: =VLOOKUP(D178,$C$3:$D$69,2,0) -> MELNICK ON ED NM | K178: ISA ENERGIA PN N1 - ISAE4 | L178: =RIGHT(K178,5) -> ISAE4 | M178: 31.34
D179: VLID3 | E179: =VLOOKUP(D179,$C$3:$D$69,2,0) -> VALID ON EJ NM | K179: ISHARES BOVA CI - BOVA11 | L179: =RIGHT(K179,6) -> BOVA11 | M179: 193.05
D180: TRIS3 | E180: =VLOOKUP(D180,$C$3:$D$69,2,0) -> TRISUL ON NM | K180: IT NOW IBOV CI - BOVV11 | L180: =RIGHT(K180,6) -> BOVV11 | M180: 202.6
D181: VULC3 | E181: =VLOOKUP(D181,$C$3:$D$69,2,0) -> VULCABRAS ON NM | K181: ITAUSA ON N1 - ITSA3 | L181: =RIGHT(K181,5) -> ITSA3 | M181: 14.66
D182: INTB3 | E182: =VLOOKUP(D182,$C$3:$D$69,2,0) -> #N/A | K182: ITAUSA PN N1 - ITSA4 | L182: =RIGHT(K182,5) -> ITSA4 | M182: 14.81
D183: BMEB4 | E183: =VLOOKUP(D183,$C$3:$D$69,2,0) -> MERCANTIL PN N1 | K183: ITAUUNIBANCO ON N1 - ITUB3 | L183: =RIGHT(K183,5) -> ITUB3 | M183: 46.86
D184: MLAS3 | E184: =VLOOKUP(D184,$C$3:$D$69,2,0) -> #N/A | K184: ITAUUNIBANCO PN N1 - ITUB4 | L184: =RIGHT(K184,5) -> ITUB4 | M184: 46.98
D185: ALUP11 | E185: =VLOOKUP(D185,$C$3:$D$69,2,0) -> #N/A | K185: JHSF PART ON NM - JHSF3 | L185: =RIGHT(K185,5) -> JHSF3 | M185: 13.26
D186: PNVL3 | E186: =VLOOKUP(D186,$C$3:$D$69,2,0) -> DIMED ON EJ NM | K186: LAVVI ON NM - LAVV3 | L186: =RIGHT(K186,5) -> LAVV3 | M186: 15
D187: RECV3 | E187: =VLOOKUP(D187,$C$3:$D$69,2,0) -> #N/A | K187: LIGHT S.A. ON NM - LIGT3 | L187: =RIGHT(K187,5) -> LIGT3 | M187: 5.35
D188: OPCT3 | E188: =VLOOKUP(D188,$C$3:$D$69,2,0) -> #N/A | K188: LOG COM PROPON NM - LOGG3 | L188: =RIGHT(K188,5) -> LOGG3 | M188: 27.61
D189: LAVV3 | E189: =VLOOKUP(D189,$C$3:$D$69,2,0) -> LAVVI ON NM | K189: LOJAS RENNER ON NM - LREN3 | L189: =RIGHT(K189,5) -> LREN3 | M189: 15.05
D190: VIVT3 | E190: =VLOOKUP(D190,$C$3:$D$69,2,0) -> TELEF BRASILON | K190: MAGAZ LUIZA ON NM - MGLU3 | L190: =RIGHT(K190,5) -> MGLU3 | M190: 9.25
D191: PINE4 | E191: =VLOOKUP(D191,$C$3:$D$69,2,0) -> PINE PN EDJ N2 | K191: MARCOPOLO ON N2 - POMO3 | L191: =RIGHT(K191,5) -> POMO3 | M191: 6.5
D192: BMOB3 | E192: =VLOOKUP(D192,$C$3:$D$69,2,0) -> #N/A | K192: MARCOPOLO PN N2 - POMO4 | L192: =RIGHT(K192,5) -> POMO4 | M192: 6.86
... D212: DIRR3 | E212: =VLOOKUP(D212,$C$3:$D$69,2,0) -> DIRECIONAL ON ED NM | K212: SANEPAR PN - SAPR4 | L212: =RIGHT(K212,5) -> SAPR4 | M212: 7.99
D213: CMIG4 | E213: =VLOOKUP(D213,$C$3:$D$69,2,0) -> CEMIG PN N1 | K213: SANEPAR UNT N2 - SAPR11 | L213: =RIGHT(K213,6) -> SAPR11 | M213: 41.38
D214: FESA4 | E214: =VLOOKUP(D214,$C$3:$D$69,2,0) -> #N/A | K214: SCHULZ PN - SHUL4 | L214: =RIGHT(K214,5) -> SHUL4 | M214: 5.33
D215: LREN3 | E215: =VLOOKUP(D215,$C$3:$D$69,2,0) -> #N/A | K215: SER EDUCA ON NM - SEER3 | L215: =RIGHT(K215,5) -> SEER3 | M215: 13.45
D216: ITUB4 | E216: =VLOOKUP(D216,$C$3:$D$69,2,0) -> ITAUUNIBANCOPN N1 | K216: SYN PROP TECON NM - SYNE3 | L216: =RIGHT(K216,5) -> SYNE3 | M216: 4.22
D217: VALE3 | E217: =VLOOKUP(D217,$C$3:$D$69,2,0) -> VALE ON EDJ NM | K217: TAESA ON N2 - TAEE3 | L217: =RIGHT(K217,5) -> TAEE3 | M217: 14.64
D218: AXIA3 | E218: =VLOOKUP(D218,$C$3:$D$69,2,0) -> AXIA ENERGIAON EB N1 | K218: TAESA PN N2 - TAEE4 | L218: =RIGHT(K218,5) -> TAEE4 | M218: 14.93
D219: BBAS3 | E219: =VLOOKUP(D219,$C$3:$D$69,2,0) -> BRASIL ON EJ NM | K219: TAESA UNT N2 - TAEE11 | L219: =RIGHT(K219,6) -> TAEE11 | M219: 44.3
D220: BBDC4 | E220: =VLOOKUP(D220,$C$3:$D$69,2,0) -> BRADESCO PN N1 | K220: TEGMA ON NM - TGMA3 | L220: =RIGHT(K220,5) -> TGMA3 | M220: 33.62
D221: BOVA11 | E221: =VLOOKUP(D221,$C$3:$D$69,2,0) -> ISHARES BOVACI | K221: TELEF BRASIL ON - VIVT3 | L221: =RIGHT(K221,5) -> VIVT3 | M221: 40.95
...

Sheet 35 - SMLL
B1: =COUNTIF(B9:B222,">0") -> 63 | E1: =COUNTIF(E9:E222,">0") -> 104 | K1: Act Share | L1: Bmk | M1: Mandato | N1: Modelo 2.0 | O1: Meta | S1: Modelos | AF1: Interações | AL1: Clusters
K2: Meta | L2: =SQRT(SUMSQ(L9:L222)^2) -> 0.022994 | M2: =SQRT(SUMSQ(O9:O222)^2) -> 0.0077856705 | N2: =SQRT(SUMSQ(R9:R222)^2) -> 0.022808429
E3: MF - Meta | F3: =SUMPRODUCT($D$9:$D$222,F9:F222) -> 0.0652405 | K3: MF | L3: =SQRT(SUMSQ(C9:C222)^2) -> 0.02094525 | M3: =SQRT(SUMSQ(P9:P222)^2) -> 0.0040880843 | O3: =SQRT(SUMSQ(D9:D222)^2) -> 0.00285125
E4: Meta - 2.0 | F4: =SUMPRODUCT($R$9:$R$222,F9:F222) -> 0.35635341 | R4: MF - Meta | S4: =SUMPRODUCT($D$9:$D$226,S9:S226) -> 0.040441 | T4: =SUMPRODUCT($D$9:$D$226,T9:T226) -> 0.020271 | U4: =SUMPRODUCT($D$9:$D$226,U9:U226) -> 0.0396925 | V4: =SUMPRODUCT($D$9:$D$226,V9:V226) -> 0.044499 | W4: =SUMPRODUCT($D$9:$D$226,W9:W226) -> 0.03756 | X4: =SUMPRODUCT($D$9:$D$226,X9:X226) -> 0.037583 | Y4: =SUMPRODUCT($D$9:$D$226,Y9:Y226) -> 0.04005 | Z4: =SUMPRODUCT($D$9:$D$226,Z9:Z226) -> 0.0339985 | ... BL4: =SUMPRODUCT($D$9:$D$226,BL9:BL226) -> 0.057532
E5: Meta - Mandato | F5: =SUMPRODUCT($O$9:$O$222,F9:F222) -> -0.18713524 | R5: Meta - 2.0 | S5: =SUMPRODUCT($R$9:$R$226,S9:S226) -> 0.28691622 | T5: =SUMPRODUCT($R$9:$R$226,T9:T226) -> 0.05646528 | U5: =SUMPRODUCT($R$9:$R$226,U9:U226) -> 0.35227283 | V5: =SUMPRODUCT($R$9:$R$226,V9:V226) -> 0.16800967 | W5: =SUMPRODUCT($R$9:$R$226,W9:W226) -> 0.18337571 | X5: =SUMPRODUCT($R$9:$R$226,X9:X226) -> 0.17718772 | Y5: =SUMPRODUCT($R$9:$R$226,Y9:Y226) -> 0.086241389 | Z5: =SUMPRODUCT($R$9:$R$226,Z9:Z226) -> 0.14215532 | ... BL5: =SUMPRODUCT($R$9:$R$226,BL9:BL226) -> 0.1350052
E6: Meta - Bmk | F6: =SUMPRODUCT($L$9:$L$222,F9:F222) -> 1.03815 | G6: =SUMPRODUCT($L$9:$L$222,G9:G222) -> 0.810022 | R6: Meta - Mandato | S6: =SUMPRODUCT($O$9:$O$226,S8:S225) -> -0.10209476 | T6: =SUMPRODUCT($O$9:$O$226,T8:T225) -> -0.059367972 | U6: =SUMPRODUCT($O$9:$O$226,U8:U225) -> -0.094299285 | V6: =SUMPRODUCT($O$9:$O$226,V8:V225) -> -0.10674604 | W6: =SUMPRODUCT($O$9:$O$226,W8:W225) -> -0.09032169 | X6: =SUMPRODUCT($O$9:$O$226,X8:X225) -> -0.069053466 | Y6: =SUMPRODUCT($O$9:$O$226,Y8:Y225) -> -0.042702136 | Z6: =SUMPRODUCT($O$9:$O$226,Z8:Z225) -> -0.041836715 | ... BL6: =SUMPRODUCT($O$9:$O$226,BL8:BL225) -> -0.0079018441
B7: =SUM(B9:B222) -> 0.9995 | E7: =SUM(E9:E222) -> 0.998 | K7: =SUM(K9:K222) -> 0.998 | N7: =SUM(N9:N222) -> 1 | Q7: =SUM(Q9:Q222) -> 1 | R7: Meta - Bmk | S7: =SUMPRODUCT($L$9:$L$226,S9:S226) -> 0.620521 | T7: =SUMPRODUCT($L$9:$L$226,T9:T226) -> 0.588298 | U7: =SUMPRODUCT($L$9:$L$226,U9:U226) -> 0.646178 | V7: =SUMPRODUCT($L$9:$L$226,V9:V226) -> 0.561041 | W7: =SUMPRODUCT($L$9:$L$226,W9:W226) -> 0.652158 | X7: =SUMPRODUCT($L$9:$L$226,X9:X226) -> 0.599421 | Y7: =SUMPRODUCT($L$9:$L$226,Y9:Y226) -> 0.534175 | Z7: =SUMPRODUCT($L$9:$L$226,Z9:Z226) -> 0.608619 | ... BL7: =SUMPRODUCT($L$9:$L$226,BL9:BL226) -> 0.136476
A8: tickers | B8: MF | C8: MF - Smll | D8: MF - META | E8: Bmk | F8: exp_ret_score_raw | G8: exp_ret_score | H8: sectors_c2 | I8: sectors_c1 | J8: sectors_dyn | K8: META | L8: act_weights | M8: ibov_rank | N8: mandato | O8: Meta - Mandato | P8: MF - Mandao | Q8: modelo 2.0 | R8: Meta - 2.0 | S8: ew | T8: sw_mom | U8: sw_val | V8: sw_lt_perf | W8: sw_overall | X8: rp_cc | Y8: hrp_cc | Z8: mvo_overall_cc_con | AA8: ols | AB8: glmnet_bayes | AC8: rf_bayes | AD8: xgb_bayes | AE8: nn1_bayes | AF8: qv | AG8: garp | AH8: vm | AI8: sv | AJ8: sm | AK8: smcj | AL8: fac_inc_cs_value | AM8: fac_payout_yield | AN8: fac_bs_cs_value | AO8: fac_ts_value | AP8: fac_interm_momentum | AQ8: fac_st_momentum | AR8: fac_lt_profit_growth | AS8: fac_st_profit_growth | AT8: fac_surprise | AU8: fac_bs_profitability | AV8: fac_profit_margins | AW8: fac_quality | AX8: fac_mkt_risk | AY8: fac_leverage | AZ8: fac_profit_vol | BA8: fac_seasonality | BB8: fac_short_interest | BC8: fac_acc_growth | BD8: fac_accruals | BE8: fac_issuance | BF8: fac_st_reversal | BG8: fac_skewness | BH8: fac_max | BI8: fac_lt_reversal | BJ8: fac_macro | BK8: fac_liquidity | BL8: fac_size
A9: JHSF3 | B9: 0.0225 | C9: =B9-E9 -> 0.0125 | D9: =B9-K9 -> 0.0045 | E9: =K9-L9 -> 0.01 | F9: 3.261 | G9: 4.631 | H9: pro_cyclicals | I9: =VLOOKUP(A9,Planilha6!$BL$9:$BN$222,2,0) -> homebuilders | J9: =VLOOKUP(A9,Planilha6!$BL$9:$BN$222,3,0) -> very_high_beta | K9: 0.018 | L9: 0.008 | M9: 84 | N9: =VLOOKUP(A9,'Mandato Smll'!$A$2:$C$215,2,0) -> 0.03595671 | O9: =K9-N9 -> -0.01795671 | P9: =B9-N9 -> -0.01345671 | Q9: =VLOOKUP(A9,'Mandato Smll'!$A$2:$C$215,3,0) -> 0.031948919 | R9: =K9-Q9 -> -0.013948919 | S9: 1 | T9: 1 | U9: 0.907 | V9: 1 | W9: 1 | X9: 1 | Y9: 1 | Z9: 0.989 | AA9: 0.919 | AB9: 0.922 | AC9: 0.908 | AD9: 0.952 | AE9: 1 | AF9: 1 | AG9: 1 | AH9: 1 | AI9: -0.45 | AJ9: 0.31 | AK9: 0.34 | AL9: 0.287 | AM9: -0.104 | AN9: -0.455 | AO9: 0.136 | AP9: 0.8 | AQ9: 0.769 | AR9: 0.615 | AS9: 0.414 | AT9: 0.976 | AU9: 0.525 | AV9: 0.913 | AW9: 0.997 | AX9: -0.029 | AY9: 0.216 | AZ9: 0.188 | BA9: 0.763 | BB9: 0.149 | BC9: -0.1 | BD9: 0.573 | BE9: 0.306 | BF9: -1 | BG9: 0.248 | BH9: -0.132 | BI9: -0.672 | BJ9: 0.631 | BK9: 0.025 | BL9: -0.268
A10: WIZC3 | B10: =K10 -> 0.016 | C10: =B10-E10 -> 0.016 | D10: =B10-K10 -> 0 | E10: =K10-L10 -> 0 | F10: 3.261 | G10: 3.381 | H10: defensives | I10: =VLOOKUP(A10,Planilha6!$BL$9:$BN$222,2,0) -> financial_services | J10: =VLOOKUP(A10,Planilha6!$BL$9:$BN$222,3,0) -> low_beta | K10: 0.016 | L10: 0.016 | M10: 84 | N10: =VLOOKUP(A10,'Mandato Smll'!$A$2:$C$215,2,0) -> 0.013289 | O10: =K10-N10 -> 0.0027110001 | P10: =B10-N10 -> 0.0027110001 | Q10: =VLOOKUP(A10,'Mandato Smll'!$A$2:$C$215,3,0) -> 0.0085259172 | R10: =K10-Q10 -> 0.0074740828 | S10: 1 | T10: 1 | U10: 1 | V10: 1 | W10: 1 | X10: 1 | Y10: 1 | Z10: 0.903 | AA10: 0.817 | AB10: 0.826 | AC10: 1 | AD10: 1 | AE10: 1 | AF10: 1 | AG10: 0.241 | AH10: 0.49 | AI10: 0.447 | AJ10: 0.841 | AK10: 1 | AL10: 0.477 | AM10: -0.271 | AN10: -0.236 | AO10: -0.056 | AP10: 0.114 | AQ10: 0.015 | AR10: 0.304 | AS10: 0.173 | AT10: 0.233 | AU10: 0.847 | AV10: 0.517 | AW10: 0.759 | AX10: 0.418 | AY10: -0.066 | AZ10: 0.636 | BA10: 1 | BB10: 0.851 | BC10: -0.177 | BD10: 0.006 | BE10: 0.393 | BF10: 0.134 | BG10: 0.783 | BH10: 0.809 | BI10: -0.469 | BJ10: -0.202 | BK10: 0.615 | BL10: 0.798
A11: CSED3 | B11: =K11 -> 0.014 | C11: =B11-E11 -> 0.014 | D11: =B11-K11 -> 0 | E11: =K11-L11 -> 0 | F11: 3.261 | G11: 2.505 | H11: pro_cyclicals | I11: =VLOOKUP(A11,Planilha6!$BL$9:$BN$222,2,0) -> education | J11: =VLOOKUP(A11,Planilha6!$BL$9:$BN$222,3,0) -> high_beta | K11: 0.014 | L11: 0.014 | M11: 84 | N11: =VLOOKUP(A11,'Mandato Smll'!$A$2:$C$215,2,0) -> 0.013289 | O11: =K11-N11 -> 0.00071100013 | P11: =B11-N11 -> 0.00071100013 | Q11: =VLOOKUP(A11,'Mandato Smll'!$A$2:$C$215,3,0) -> 0.0085639137 | R11: =K11-Q11 -> 0.0054360863 | S11: 1 | T11: 1 | U11: 1 | V11: 1 | W11: 1 | X11: 1 | Y11: 0.941 | Z11: 0.768 | AA11: 0.614 | AB11: 0.616 | AC11: 1 | AD11: 0.951 | AE11: 0.935 | AF11: 1 | AG11: 1 | AH11: 0.124 | AI11: 0.206 | AJ11: 0.403 | AK11: 1 | AL11: 0.371 | AM11: 0.099 | AN11: -0.603 | AO11: 0.331 | AP11: 0.06 | AQ11: -0.193 | AR11: 0.8 | AS11: 1 | AT11: 0.849 | AU11: 0.506 | AV11: 0.042 | AW11: 0.926 | AX11: -0.17 | AY11: -0.052 | AZ11: 0.81 | BA11: 0.998 | BB11: 0.872 | BC11: -0.051 | BD11: -0.103 | BE11: 0.232 | BF11: 0.298 | BG11: 1 | BH11: 0.517 | BI11: -0.445 | BJ11: 0.139 | BK11: 0.715 | BL11: 0.318
A12: RIAA3 | B12: =K12 -> 0.013 | C12: =B12-E12 -> 0.011 | D12: =B12-K12 -> 0 | E12: =K12-L12 -> 0.002 | F12: 3.261 | G12: 2.522 | H12: pro_cyclicals | I12: =VLOOKUP(A12,Planilha6!$BL$9:$BN$222,2,0) -> apparel | J12: =VLOOKUP(A12,Planilha6!$BL$9:$BN$222,3,0) -> very_high_beta | K12: 0.013 | L12: 0.011 | M12: 84 | N12: =VLOOKUP(A12,'Mandato Smll'!$A$2:$C$215,2,0) -> 0.015633943 | O12: =K12-N12 -> -0.0026339435 | P12: =B12-N12 -> -0.0026339435 | Q12: =VLOOKUP(A12,'Mandato Smll'!$A$2:$C$215,3,0) -> 0.012699691 | R12: =K12-Q12 -> 0.00030030881 | S12: 1 | T12: 1 | U12: 1 | V12: 1 | W12: 1 | X12: 0.975 | Y12: 0.688 | Z12: 0.586 | AA12: 0.955 | AB12: 0.959 | AC12: 0.804 | AD12: 0.855 | AE12: 0.968 | AF12: 1 | AG12: 1 | AH12: 0.652 | AI12: 0.03 | AJ12: 0.265 | AK12: 0.681 | AL12: 0.459 | AM12: 0.101 | AN12: -0.148 | AO12: 0.505 | AP12: 0.282 | AQ12: 0.441 | AR12: 0.612 | AS12: 0.999 | AT12: 0.662 | AU12: 0.657 | AV12: 0.118 | AW12: 0.782 | AX12: -0.567 | AY12: 0.214 | AZ12: 0.626 | BA12: 0.553 | BB12: -0.497 | BC12: 0.179 | BD12: 0.057 | BE12: 0.609 | BF12: -0.773 | BG12: -0.537 | BH12: 0.242 | BI12: -0.523 | BJ12: 0.428 | BK12: 0.235 | BL12: 0.131
A13: BMGB4 | B13: =K13 -> 0.012 | C13: =B13-E13 -> 0.012 | D13: =B13-K13 -> 0 | E13: =K13-L13 -> 0 | F13: 3.261 | G13: 3.259 | H13: pro_cyclicals | I13: =VLOOKUP(A13,Planilha6!$BL$9:$BN$222,2,0) -> banks | J13: =VLOOKUP(A13,Planilha6!$BL$9:$BN$222,3,0) -> high_beta | K13: 0.012 | L13: 0.012 | M13: 84 | N13: =VLOOKUP(A13,'Mandato Smll'!$A$2:$C$215,2,0) -> 0.013289 | O13: =K13-N13 -> -0.0012889999 | P13: =B13-N13 -> -0.0012889999 | Q13: =VLOOKUP(A13,'Mandato Smll'!$A$2:$C$215,3,0) -> 0.011807787 | R13: =K13-Q13 -> 0.00019221292 | S13: 0.916 | T13: 0.882 | U13: 0.789 | V13: 0.877 | W13: 0.975 | X13: 0.701 | Y13: 0.542 | Z13: 0.732 | AA13: 1 | AB13: 1 | AC13: 1 | AD13: 0.973 | AE13: 1 | AF13: 0.053 | AG13: 1 | AH13: 1 | AI13: 0.061 | AJ13: 0.609 | AK13: 0.345 | AL13: 0.076 | AM13: 0.43 | AN13: 0.453 | AO13: 0.057 | AP13: 0.652 | AQ13: 0.106 | AR13: 0.544 | AS13: 1 | AT13: -0.031 | AU13: 0.056 | AV13: -0.204 | AW13: -0.217 | AX13: 0.525 | AY13: -0.14 | AZ13: 0.812 | BA13: 0.15 | BB13: -0.238 | BC13: 0.064 | BD13: 0.001 | BE13: 0.647 | BF13: -0.457 | BG13: -0.309 | BH13: 0.337 | BI13: -0.754 | BJ13: 0.07 | BK13: 0.654 | BL13: 0.642
A14: ALLD3 | B14: =K14 -> 0.007 | C14: =B14-E14 -> 0.007 | D14: =B14-K14 -> 0 | E14: =K14-L14 -> 0 | F14: 3.261 | G14: 2.46 | H14: pro_cyclicals | I14: =VLOOKUP(A14,Planilha6!$BL$9:$BN$222,2,0) -> consumer_durables | J14: =VLOOKUP(A14,Planilha6!$BL$9:$BN$222,3,0) -> very_low_beta | K14: 0.007 | L14: 0.007 | M14: 84 | N14: =VLOOKUP(A14,'Mandato Smll'!$A$2:$C$215,2,0) -> 0.013289 | O14: =K14-N14 -> -0.0062889999 | P14: =B14-N14 -> -0.0062889999 | Q14: =VLOOKUP(A14,'Mandato Smll'!$A$2:$C$215,3,0) -> 0.0073549029 | R14: =K14-Q14 -> -0.00035490292 | S14: 1 | T14: 0.906 | U14: 1 | V14: 1 | W14: 1 | X14: 1 | Y14: 1 | Z14: 1 | AA14: 1 | AB14: 1 | AC14: 0.847 | AD14: 0.809 | AE14: 0.966 | AF14: 1 | AG14: 1 | AH14: 0.174 | AI14: 1 | AJ14: -0.036 | AK14: 1 | AL14: 0.893 | AM14: 1 | AN14: 0.503 | AO14: 0.722 | AP14: -0.354 | AQ14: -0.493 | AR14: 0.369 | AS14: -0.124 | AT14: -0.006 | AU14: 0.808 | AV14: -0.377 | AW14: 0.637 | AX14: 0.361 | AY14: 0.097 | AZ14: 0.674 | BA14: 0.223 | BB14: 0.655 | BC14: 0.318 | BD14: 0.317 | BE14: 0.509 | BF14: 0.864 | BG14: 1 | BH14: 0.732 | BI14: -0.456 | BJ14: -0.442 | BK14: 0.471 | BL14: 0.792
A15: SYNE3 | B15: =K15 -> 0.012 | C15: =B15-E15 -> 0.012 | D15: =B15-K15 -> 0 | E15: =K15-L15 -> 0 | F15: 3.257 | G15: 2.484 | H15: bond_proxies | I15: =VLOOKUP(A15,Planilha6!$BL$9:$BN$222,2,0) -> real_estate | J15: =VLOOKUP(A15,Planilha6!$BL$9:$BN$222,3,0) -> neutral_beta | K15: 0.012 | L15: 0.012 | M15: 84 | N15: =VLOOKUP(A15,'Mandato Smll'!$A$2:$C$215,2,0) -> 0.013709757 | O15: =K15-N15 -> -0.0017097566 | P15: =B15-N15 -> -0.0017097566 | Q15: =VLOOKUP(A15,'Mandato Smll'!$A$2:$C$215,3,0) -> 0 | R15: =K15-Q15 -> 0.012 | S15: 0.977 | T15: 0.59 | U15: 1 | V15: 0.907 | W15: 0.966 | X15: 0.964 | Y15: 0.959 | Z15: 0.973 | AA15: 0.642 | AB15: 0.642 | AC15: 0.626 | AD15: 0.457 | AE15: 0.799 | AF15: 1 | AG15: 1 | AH15: -0.379 | AI15: 1 | AJ15: 0.193 | AK15: 1 | AL15: 0.334 | AM15: 1 | AN15: 0.199 | AO15: -0.225 | AP15: -0.224 | AQ15: -0.278 | AR15: 0.719 | AS15: -0.751 | AT15: 0.011 | AU15: 0.004 | AV15: 0.18 | AW15: 0.533 | AX15: 0.247 | AY15: -0.371 | AZ15: 0.352 | BA15: 0.256 | BB15: 0.145 | BC15: 0.686 | BD15: 1 | BE15: 0.72 | BF15: 0.834 | BG15: 1 | BH15: 0.335 | BI15: -0.906 | BJ15: 0.26 | BK15: 0.618 | BL15: 0.771
A16: POMO3 | B16: =K16 -> 0.013 | C16: =B16-E16 -> 0.013 | D16: =B16-K16 -> 0 | E16: =K16-L16 -> 0 | F16: 3.228 | G16: 2.869 | H16: industrials | I16: =VLOOKUP(A16,Planilha6!$BL$9:$BN$222,2,0) -> capital_goods | J16: =VLOOKUP(A16,Planilha6!$BL$9:$BN$222,3,0) -> neutral_beta | K16: 0.013 | L16: 0.013 | M16: 84 | N16: =VLOOKUP(A16,'Mandato Smll'!$A$2:$C$215,2,0) -> 0.013155857 | O16: =K16-N16 -> -0.0001558568 | P16: =B16-N16 -> -0.0001558568 | Q16: =VLOOKUP(A16,'Mandato Smll'!$A$2:$C$215,3,0) -> 0 | R16: =K16-Q16 -> 0.013 | S16: 0.839 | T16: 0.877 | U16: 0.672 | V16: 0.932 | W16: 1 | X16: 1 | Y16: 1 | Z16: 1 | AA16: 0.642 | AB16: 0.647 | AC16: 0.808 | AD16: 0.756 | AE16: 0.704 | AF16: 1 | AG16: 1 | AH16: -0.197 | AI16: -0.419 | AJ16: -0.261 | AK16: 0.405 | AL16: -0.003 | AM16: 0.601 | AN16: -0.614 | AO16: 0.429 | AP16: -0.103 | AQ16: 0.286 | AR16: 0.941 | AS16: 0.126 | AT16: -0.527 | AU16: 0.719 | AV16: -0.029 | AW16: 0.539 | AX16: 0.42 | AY16: 0.163 | AZ16: 0.91 | BA16: 1 | BB16: 0.581 | BC16: -0.046 | BD16: -0.167 | BE16: 0.22 | BF16: -0.345 | BG16: -0.617 | BH16: 0.563 | BI16: -0.989 | BJ16: 0.355 | BK16: 0.72 | BL16: -0.209
A17: SHUL4 | B17: =K17 -> 0.013 | C17: =B17-E17 -> 0.013 | D17: =B17-K17 -> 0 | E17: =K17-L17 -> 0 | F17: 3.132 | G17: 3.882 | H17: industrials | I17: =VLOOKUP(A17,Planilha6!$BL$9:$BN$222,2,0) -> capital_goods | J17: =VLOOKUP(A17,Planilha6!$BL$9:$BN$222,3,0) -> low_beta | K17: 0.013 | L17: 0.013 | M17: 84 | N17: =VLOOKUP(A17,'Mandato Smll'!$A$2:$C$215,2,0) -> 0.012765525 | O17: =K17-N17 -> 0.00023447489 | P17: =B17-N17 -> 0.00023447489 | Q17: =VLOOKUP(A17,'Mandato Smll'!$A$2:$C$215,3,0) -> 0.0068349328 | R17: =K17-Q17 -> 0.0061650672 | S17: 0.721 | T17: 0.878 | U17: 0.708 | V17: 0.282 | W17: 0.706 | X17: 0.778 | Y17: 0.84 | Z17: 0.77 | AA17: 0.982 | AB17: 0.982 | AC17: 0.921 | AD17: 0.974 | AE17: 0.976 | AF17: -0.334 | AG17: -0.296 | AH17: 0.308 | AI17: 0.127 | AJ17: 0.947 | AK17: -0.135 | AL17: -0.046 | AM17: 0.33 | AN17: -0.426 | AO17: 0.436 | AP17: 0.439 | AQ17: 0.294 | AR17: -0.044 | AS17: 0.28 | AT17: 0.169 | AU17: 0.36 | AV17: -0.143 | AW17: -0.152 | AX17: 0.733 | AY17: 0.494 | AZ17: 0.905 | BA17: 0.706 | BB17: 0.814 | BC17: -0.144 | BD17: -0.183 | BE17: -0.045 | BF17: 0.269 | BG17: 0.31 | BH17: 1 | BI17: -0.443 | BJ17: -0.023 | BK17: 0.858 | BL17: 0.286
A18: FIQE3 | B18: =K18 -> 0.014 | C18: =B18-E18 -> 0.014 | D18: =B18-K18 -> 0 | E18: =K18-L18 -> 0 | F18: 3.082 | G18: 3.104 | H18: bond_proxies | I18: =VLOOKUP(A18,Planilha6!$BL$9:$BN$222,2,0) -> telecom | J18: =VLOOKUP(A18,Planilha6!$BL$9:$BN$222,3,0) -> low_beta | K18: 0.014 | L18: 0.014 | M18: 84 | N18: =VLOOKUP(A18,'Mandato Smll'!$A$2:$C$215,2,0) -> 0.012561229 | O18: =K18-N18 -> 0.0014387715 | P18: =B18-N18 -> 0.0014387715 | Q18: =VLOOKUP(A18,'Mandato Smll'!$A$2:$C$215,3,0) -> 0.011807787 | R18: =K18-Q18 -> 0.0021922129 | S18: 0.886 | T18: 0.823 | U18: 0.713 | V18: 0.994 | W18: 0.952 | X18: 0.642 | Y18: 0.616 | Z18: 0.585 | AA18: 0.668 | AB18: 0.676 | AC18: 1 | AD18: 1 | AE18: 1 | AF18: 0.629 | AG18: -0.012 | AH18: 0.847 | AI18: -0.234 | AJ18: 1 | AK18: 1 | AL18: -0.23 | AM18: 0.091 | AN18: -0.768 | AO18: 0.009 | AP18: 0.871 | AQ18: 0.813 | AR18: 0.298 | AS18: 0.199 | AT18: 0.439 | AU18: 0.523 | AV18: 0.36 | AW18: 0.722 | AX18: 0.446 | AY18: -0.068 | AZ18: 0.93 | BA18: -0.661 | BB18: 0.851 | BC18: -0.161 | BD18: -0.297 | BE18: 0.597 | BF18: -1 | BG18: -0.32 | BH18: -0.17 | BI18: -0.541 | BJ18: -0.361 | BK18: 0.7 | BL18: 0.468
A19: MTRE3 | B19: =K19 -> 0.019 | C19: =B19-E19 -> 0.019 | D19: =B19-K19 -> 0 | E19: =K19-L19 -> 0 | F19: 3.077 | G19: 3.02 | H19: pro_cyclicals | I19: =VLOOKUP(A19,Planilha6!$BL$9:$BN$222,2,0) -> homebuilders | J19: =VLOOKUP(A19,Planilha6!$BL$9:$BN$222,3,0) -> neutral_beta | K19: 0.019 | L19: 0.019 | M19: 84 | N19: =VLOOKUP(A19,'Mandato Smll'!$A$2:$C$215,2,0) -> 0.012541412 | O19: =K19-N19 -> 0.006458588 | P19: =B19-N19 -> 0.006458588 | Q19: =VLOOKUP(A19,'Mandato Smll'!$A$2:$C$215,3,0) -> 0.0072027054 | R19: =K19-Q19 -> 0.011797295 | S19: 0.879 | T19: 0.604 | U19: 0.947 | V19: 0.578 | W19: 0.76 | X19: 0.77 | Y19: 0.732 | Z19: 0.685 | AA19: 0.685 | AB19: 0.687 | AC19: 1 | AD19: 0.953 | AE19: 0.917 | AF19: 0.527 | AG19: 0.465 | AH19: 0.502 | AI19: 1 | AJ19: 0.966 | AK19: 0.018 | AL19: -0.107 | AM19: 0.714 | AN19: 0.319 | AO19: 0.349 | AP19: 0.011 | AQ19: 0.21 | AR19: 0.263 | AS19: 0.136 | AT19: -0.081 | AU19: 0.013 | AV19: -0.221 | AW19: 0.077 | AX19: -0.064 | AY19: -0.285 | AZ19: 0.765 | BA19: 0.183 | BB19: 0.558 | BC19: 0.048 | BD19: -0.275 | BE19: 0.131 | BF19: 0.064 | BG19: 0.003 | BH19: 0.917 | BI19: -0.142 | BJ19: 0.233 | BK19: 0.595 | BL19: 0.837
A20: BRSR6 | B20: 0.02 | C20: =B20-E20 -> 0.01 | D20: =B20-K20 -> 0.006 | E20: =K20-L20 -> 0.01 | F20: 3.053 | G20: 4.722 | H20: pro_cyclicals | I20: =VLOOKUP(A20,Planilha6!$BL$9:$BN$222,2,0) -> banks | J20: =VLOOKUP(A20,Planilha6!$BL$9:$BN$222,3,0) -> high_beta | K20: 0.014 | L20: 0.004 | M20: 84 | N20: =VLOOKUP(A20,'Mandato Smll'!$A$2:$C$215,2,0) -> 0.032247887 | O20: =K20-N20 -> -0.018247887 | P20: =B20-N20 -> -0.012247887 | Q20: =VLOOKUP(A20,'Mandato Smll'!$A$2:$C$215,3,0) -> 0.028259776 | R20: =K20-Q20 -> -0.014259776 | S20: 0.722 | T20: 0.822 | U20: 0.383 | V20: 0.77 | W20: 0.835 | X20: 0.662 | Y20: 0.569 | Z20: 0.682 | AA20: 1 | AB20: 1 | AC20: 0.957 | AD20: 0.985 | AE20: 1 | AF20: 0.002 | AG20: 0.92 | AH20: 1 | AI20: -0.092 | AJ20: 0.3 | AK20: -0.516 | AL20: 0.067 | AM20: 0.284 | AN20: 0.456 | AO20: 0.401 | AP20: 0.626 | AQ20: 0.129 | AR20: 0.239 | AS20: 0.566 | AT20: 0.683 | AU20: 0.074 | AV20: -0.176 | AW20: -0.128 | AX20: 0.455 | AY20: -0.563 | AZ20: 0.714 | BA20: 0.397 | BB20: 0.39 | BC20: -0.151 | BD20: -0.066 | BE20: 0.454 | BF20: 0.494 | BG20: 1 | BH20: 0.466 | BI20: -0.58 | BJ20: 0.035 | BK20: 0.207 | BL20: 0.403
A21: GRND3 | B21: =K21 -> 0.012 | C21: =B21-E21 -> 0.009 | D21: =B21-K21 -> 0 | E21: =K21-L21 -> 0.003 | F21: 3.007 | G21: 3.452 | H21: pro_cyclicals | I21: =VLOOKUP(A21,Planilha6!$BL$9:$BN$222,2,0) -> apparel | J21: =VLOOKUP(A21,Planilha6!$BL$9:$BN$222,3,0) -> very_low_beta | K21: 0.012 | L21: 0.009 | M21: 84 | N21: =VLOOKUP(A21,'Mandato Smll'!$A$2:$C$215,2,0) -> 0.01593344 | O21: =K21-N21 -> -0.0039334397 | P21: =B21-N21 -> -0.0039334397 | Q21: =VLOOKUP(A21,'Mandato Smll'!$A$2:$C$215,3,0) -> 0.0092750914 | R21: =K21-Q21 -> 0.0027249086 | S21: 0.69 | T21: 0.625 | U21: 0.448 | V21: 0.532 | W21: 0.623 | X21: 0.907 | Y21: 1 | Z21: 1 | AA21: 0.59 | AB21: 0.597 | AC21: 0.791 | AD21: 0.77 | AE21: 0.747 | AF21: 0.934 | AG21: -0.051 | AH21: -0.365 | AI21: -0.082 | AJ21: -0.23 | AK21: 1 | AL21: -0.094 | AM21: 0.948 | AN21: -0.506 | AO21: 0.657 | AP21: 0.14 | AQ21: 0.013 | AR21: 0.081 | AS21: -0.001 | AT21: -0.467 | AU21: 0.308 | AV21: -0.007 | AW21: 0.386 | AX21: 0.495 | AY21: 0.835 | AZ21: 0.66 | BA21: -0.102 | BB21: 0.446 | BC21: 0.826 | BD21: 0.453 | BE21: 0.583 | BF21: 0.176 | BG21: 0.005 | BH21: 0.93 | BI21: -0.235 | BJ21: -0.371 | BK21: 0.129 | BL21: 0.293
A22: TIMS3 | B22: =K22 -> 0.015 | C22: =B22-E22 -> 0.015 | D22: =B22-K22 -> 0 | E22: =K22-L22 -> 0 | F22: 2.998 | G22: 3.442 | H22: bond_proxies | I22: =VLOOKUP(A22,Planilha6!$BL$9:$BN$222,2,0) -> telecom | J22: =VLOOKUP(A22,Planilha6!$BL$9:$BN$222,3,0) -> very_low_beta | K22: 0.015 | L22: 0.015 | M22: 31 | N22: =VLOOKUP(A22,'Mandato Smll'!$A$2:$C$215,2,0) -> 0.012218405 | O22: =K22-N22 -> 0.0027815949 | P22: =B22-N22 -> 0.0027815949 | Q22: =VLOOKUP(A22,'Mandato Smll'!$A$2:$C$215,3,0) -> 0.010024327 | R22: =K22-Q22 -> 0.0049756734 | S22: 0.542 | T22: 1 | U22: -0.201 | V22: 0.855 | W22: 0.795 | X22: 1 | Y22: 1 | Z22: 0.898 | AA22: 0.802 | AB22: 0.81 | AC22: 0.85 | AD22: 0.845 | AE22: 0.79 | AF22: 0.838 | AG22: 0.034 | AH22: 0.287 | AI22: -0.92 | AJ22: -0.582 | AK22: -0.423 | AL22: 0.231 | AM22: -0.068 | AN22: -0.848 | AO22: -0.478 | AP22: 0.382 | AQ22: 0.671 | AR22: 0.579 | AS22: 0.237 | AT22: 0.149 | AU22: 0.552 | AV22: 0.407 | AW22: 1 | AX22: 0.766 | AY22: 0.163 | AZ22: 0.846 | BA22: 0.277 | BB22: 0.813 | BC22: 0.36 | BD22: 0.37 | BE22: 0.67 | BF22: 0.271 | BG22: 0.39 | BH22: 0.946 | BI22: -0.771 | BJ22: -0.359 | BK22: -0.017 | BL22: -0.547
A23: SAPR4 | B23: =K23 -> 0.014 | C23: =B23-E23 -> 0.014 | D23: =B23-K23 -> 0 | E23: =K23-L23 -> 0 | F23: 2.933 | G23: 3.113 | H23: bond_proxies | I23: =VLOOKUP(A23,Planilha6!$BL$9:$BN$222,2,0) -> utilities | J23: =VLOOKUP(A23,Planilha6!$BL$9:$BN$222,3,0) -> low_beta | K23: 0.014 | L23: 0.014 | M23: 84 | N23: =VLOOKUP(A23,'Mandato Smll'!$A$2:$C$215,2,0) -> 0.01195589 | O23: =K23-N23 -> 0.00204411 | P23: =B23-N23 -> 0.00204411 | Q23: =VLOOKUP(A23,'Mandato Smll'!$A$2:$C$215,3,0) -> 0.0081879269 | R23: =K23-Q23 -> 0.0058120731 | S23: 0.575 | T23: 0.876 | U23: 0.247 | V23: 0.806 | W23: 0.885 | X23: 0.812 | Y23: 0.899 | Z23: 0.776 | AA23: 0.753 | AB23: 0.763 | AC23: 0.863 | AD23: 0.846 | AE23: 0.795 | AF23: 0.875 | AG23: 0.438 | AH23: 0.582 | AI23: -0.452 | AJ23: -0.556 | AK23: -0.145 | AL23: 0.484 | AM23: -0.202 | AN23: -0.316 | AO23: -0.052 | AP23: 0.212 | AQ23: -0.205 | AR23: 0.276 | AS23: -0.09 | AT23: -0.061 | AU23: 0.395 | AV23: 0.424 | AW23: 0.532 | AX23: 0.756 | AY23: -0.08 | AZ23: 0.149 | BA23: 0.837 | BB23: 0.898 | BC23: -0.133 | BD23: 0.179 | BE23: 0.183 | BF23: 0.246 | BG23: 1 | BH23: 0.439 | BI23: -0.752 | BJ23: -0.085 | BK23: 0.6 | BL23: 0.118
A24: PFRM3 | B24: =K24 -> 0.012 | C24: =B24-E24 -> 0.012 | D24: =B24-K24 -> 0 | E24: =K24-L24 -> 0 | F24: 2.887 | G24: 2.241 | H24: defensives | I24: =VLOOKUP(A24,Planilha6!$BL$9:$BN$222,2,0) -> healthcare | J24: =VLOOKUP(A24,Planilha6!$BL$9:$BN$222,3,0) -> high_beta | K24: 0.012 | L24: 0.012 | M24: 84 | N24: =VLOOKUP(A24,'Mandato Smll'!$A$2:$C$215,2,0) -> 0.011765829 | O24: =K24-N24 -> 0.00023417114 | P24: =B24-N24 -> 0.00023417114 | Q24: =VLOOKUP(A24,'Mandato Smll'!$A$2:$C$215,3,0) -> 0 | R24: =K24-Q24 -> 0.012 | S24: 1 | T24: 0.464 | U24: 1 | V24: 1 | W24: 0.93 | X24: 0.613 | Y24: 0.377 | Z24: 0.37 | AA24: 0.624 | AB24: 0.63 | AC24: 0.947 | AD24: 0.819 | AE24: 0.926 | AF24: 1 | AG24: 0.977 | AH24: 0.581 | AI24: 1 | AJ24: 0.694 | AK24: 0.719 | AL24: 0.655 | AM24: 0.1 | AN24: 0.107 | AO24: 0.075 | AP24: 0.138 | AQ24: -0.038 | AR24: 0.417 | AS24: 0.118 | AT24: -0.218 | AU24: 0.475 | AV24: -0.481 | AW24: 0.457 | AX24: 0.291 | AY24: -0.128 | AZ24: 0.919 | BA24: -0.172 | BB24: 0.741 | BC24: -0.122 | BD24: -0.038 | BE24: 0.101 | BF24: 0.463 | BG24: -0.099 | BH24: 0.161 | BI24: -0.688 | BJ24: 0.081 | BK24: 0.815 | BL24: 0.715
A25: SAPR3 | B25: 0 | C25: =B25-E25 -> 0 | D25: =B25-K25 -> -0.011 | E25: =K25-L25 -> 0 | F25: 2.85 | G25: 2.386 | H25: bond_proxies | I25: =VLOOKUP(A25,Planilha6!$BL$9:$BN$222,2,0) -> utilities | J25: =VLOOKUP(A25,Planilha6!$BL$9:$BN$222,3,0) -> high_beta | K25: 0.011 | L25: 0.011 | M25: 84 | N25: =VLOOKUP(A25,'Mandato Smll'!$A$2:$C$215,2,0) -> 0.01161736 | O25: =K25-N25 -> -0.00061735973 | P25: =B25-N25 -> -0.01161736 | Q25: =VLOOKUP(A25,'Mandato Smll'!$A$2:$C$215,3,0) -> 0.0085507014 | R25: =K25-Q25 -> 0.0024492986 | S25: 0.558 | T25: 0.864 | U25: 0.327 | V25: 0.802 | W25: 0.903 | X25: 0.689 | Y25: 0.706 | Z25: 0.667 | AA25: 0.835 | AB25: 0.845 | AC25: 0.874 | AD25: 0.814 | AE25: 0.827 | AF25: 0.811 | AG25: 0.4 | AH25: 0.739 | AI25: -0.467 | AJ25: -0.518 | AK25: -0.145 | AL25: 0.484 | AM25: -0.333 | AN25: -0.316 | AO25: -0.103 | AP25: 0.304 | AQ25: -0.214 | AR25: 0.276 | AS25: -0.09 | AT25: -0.061 | AU25: 0.395 | AV25: 0.424 | AW25: 0.532 | AX25: 0.648 | AY25: -0.08 | AZ25: 0.149 | BA25: 0.954 | BB25: 0.456 | BC25: -0.133 | BD25: 0.179 | BE25: 0.293 | BF25: 0.008 | BG25: 0.449 | BH25: 0.239 | BI25: -0.872 | BJ25: 0.109 | BK25: 0.962 | BL25: 0.118
A26: DEXP3 | B26: =K26 -> 0.013 | C26: =B26-E26 -> 0.013 | D26: =B26-K26 -> 0 | E26: =K26-L26 -> 0 | F26: 2.829 | G26: 2.62 | H26: industrials | I26: =VLOOKUP(A26,Planilha6!$BL$9:$BN$222,2,0) -> chemicals | J26: =VLOOKUP(A26,Planilha6!$BL$9:$BN$222,3,0) -> very_low_beta | K26: 0.013 | L26: 0.013 | M26: 84 | N26: =VLOOKUP(A26,'Mandato Smll'!$A$2:$C$215,2,0) -> 0.011529106 | O26: =K26-N26 -> 0.0014708937 | P26: =B26-N26 -> 0.0014708937 | Q26: =VLOOKUP(A26,'Mandato Smll'!$A$2:$C$215,3,0) -> 0 | R26: =K26-Q26 -> 0.013 | S26: 0.69 | T26: 0.584 | U26: 0.855 | V26: 0.288 | W26: 0.627 | X26: 0.639 | Y26: 0.652 | Z26: 0.613 | AA26: 0.885 | AB26: 0.89 | AC26: 0.865 | AD26: 0.777 | AE26: 0.838 | AF26: 0.547 | AG26: -0.463 | AH26: -0.245 | AI26: 0.75 | AJ26: 0.262 | AK26: 0.52 | AL26: 0.352 | AM26: 0.183 | AN26: -0.093 | AO26: 0.36 | AP26: 0.096 | AQ26: -0.436 | AR26: -0.057 | AS26: -0.17 | AT26: -0.479 | AU26: 0.551 | AV26: -0.246 | AW26: 0.248 | AX26: 0.583 | AY26: 0.479 | AZ26: 0.869 | BA26: 0.773 | BB26: 0.881 | BC26: -0.037 | BD26: -0.094 | BE26: 0.248 | BF26: 0.272 | BG26: -0.091 | BH26: 0.918 | BI26: -0.312 | BJ26: -0.254 | BK26: 0.927 | BL26: 0.883
A27: PETR4 | B27: =K27 -> 0 | C27: =B27-E27 -> 0 | D27: =B27-K27 -> 0 | E27: =K27-L27 -> 0 | F27: 2.806 | G27: 3.222 | H27: commodities | I27: =VLOOKUP(A27,Planilha6!$BL$9:$BN$222,2,0) -> crude_oil | J27: =VLOOKUP(A27,Planilha6!$BL$9:$BN$222,3,0) -> very_low_beta | K27: 0 | L27: 0 | M27: 3 | N27: =VLOOKUP(A27,'Mandato Smll'!$A$2:$C$215,2,0) -> 0 | O27: =K27-N27 -> 0 | P27: =B27-N27 -> 0 | Q27: =VLOOKUP(A27,'Mandato Smll'!$A$2:$C$215,3,0) -> 0 | R27: =K27-Q27 -> 0 | S27: 0.112 | T27: 1 | U27: -0.544 | V27: 0.651 | W27: 0.729 | X27: 0.842 | Y27: 0.869 | Z27: 1 | AA27: 1 | AB27: 1 | AC27: 0.644 | AD27: 0.867 | AE27: 0.912 | AF27: 0.399 | AG27: -0.306 | AH27: 1 | AI27: -0.912 | AJ27: -0.555 | AK27: -0.906 | AL27: 0.218 | AM27: 0.453 | AN27: -0.514 | AO27: -0.652 | AP27: 0.985 | AQ27: 1 | AR27: -0.241 | AS27: 0.669 | AT27: 0.465 | AU27: 0.465 | AV27: 0.344 | AW27: 0.372 | AX27: 0.496 | AY27: -0.231 | AZ27: 0.814 | BA27: 0.629 | BB27: 0.479 | BC27: -0.148 | BD27: -0.273 | BE27: 0.338 | BF27: 0.191 | BG27: 0.744 | BH27: 0.708 | BI27: -0.954 | BJ27: -0.997 | BK27: -0.259 | BL27: -0.89
A28: LEVE3 | B28: =K28 -> 0.012 | C28: =B28-E28 -> 0.007 | D28: =B28-K28 -> 0 | E28: =K28-L28 -> 0.005 | F28: 2.696 | G28: 4.038 | H28: industrials | I28: =VLOOKUP(A28,Planilha6!$BL$9:$BN$222,2,0) -> capital_goods | J28: =VLOOKUP(A28,Planilha6!$BL$9:$BN$222,3,0) -> very_low_beta | K28: 0.012 | L28: 0.007 | M28: 84 | N28: =VLOOKUP(A28,'Mandato Smll'!$A$2:$C$215,2,0) -> 0.018972621 | O28: =K28-N28 -> -0.0069726208 | P28: =B28-N28 -> -0.0069726208 | Q28: =VLOOKUP(A28,'Mandato Smll'!$A$2:$C$215,3,0) -> 0.018464717 | R28: =K28-Q28 -> -0.0064647167 | S28: 0.303 | T28: 0.75 | U28: 0.358 | V28: 0.359 | W28: 0.72 | X28: 0.556 | Y28: 0.698 | Z28: 0.825 | AA28: 0.883 | AB28: 0.888 | AC28: 0.781 | AD28: 0.804 | AE28: 0.788 | AF28: 0.036 | AG28: -0.326 | AH28: 0.117 | AI28: -0.488 | AJ28: 0.317 | AK28: 0.437 | AL28: -0.13 | AM28: 0.264 | AN28: -0.795 | AO28: -0.089 | AP28: 0.503 | AQ28: 0.221 | AR28: 0.323 | AS28: 0.151 | AT28: -0.072 | AU28: 0.989 | AV28: -0.065 | AW28: 0.357 | AX28: 0.664 | AY28: -0.057 | AZ28: 0.804 | BA28: 1 | BB28: 0.4 | BC28: -0.203 | BD28: -0.465 | BE28: -0.421 | BF28: 0.114 | BG28: -0.403 | BH28: 0.802 | BI28: -0.604 | BJ28: -0.108 | BK28: 0.451 | BL28: -0.034
A29: PETR3 | B29: =K29 -> 0 | C29: =B29-E29 -> 0 | D29: =B29-K29 -> 0 | E29: =K29-L29 -> 0 | F29: 2.686 | G29: 2.833 | H29: commodities | I29: =VLOOKUP(A29,Planilha6!$BL$9:$BN$222,2,0) -> crude_oil | J29: =VLOOKUP(A29,Planilha6!$BL$9:$BN$222,3,0) -> very_low_beta | K29: 0 | L29: 0 | M29: 4 | N29: =VLOOKUP(A29,'Mandato Smll'!$A$2:$C$215,2,0) -> 0 | O29: =K29-N29 -> 0 | P29: =B29-N29 -> 0 | Q29: =VLOOKUP(A29,'Mandato Smll'!$A$2:$C$215,3,0) -> 0 | R29: =K29-Q29 -> 0 | S29: 0.005 | T29: 0.981 | U29: -0.562 | V29: 0.586 | W29: 0.679 | X29: 0.731 | Y29: 0.753 | Z29: 1 | AA29: 1 | AB29: 1 | AC29: 0.679 | AD29: 0.79 | AE29: 0.899 | AF29: 0.348 | AG29: -0.325 | AH29: 1 | AI29: -0.916 | AJ29: -0.569 | AK29: -0.911 | AL29: 0.218 | AM29: 0.413 | AN29: -0.514 | AO29: -0.658 | AP29: 0.985 | AQ29: 1 | AR29: -0.241 | AS29: 0.669 | AT29: 0.465 | AU29: 0.465 | AV29: 0.344 | AW29: 0.365 | AX29: 0.411 | AY29: -0.231 | AZ29: 0.814 | BA29: 0.654 | BB29: -0.157 | BC29: -0.148 | BD29: -0.273 | BE29: 0.354 | BF29: 0.225 | BG29: 0.997 | BH29: 0.696 | BI29: -0.93 | BJ29: -0.997 | BK29: -0.111 | BL29: -0.89
A30: ABCB4 | B30: =K30 -> 0.017 | C30: =B30-E30 -> 0.011 | D30: =B30-K30 -> 0 | E30: =K30-L30 -> 0.006 | F30: 2.667 | G30: 4.503 | H30: pro_cyclicals | I30: =VLOOKUP(A30,Planilha6!$BL$9:$BN$222,2,0) -> banks | J30: =VLOOKUP(A30,Planilha6!$BL$9:$BN$222,3,0) -> neutral_beta | K30: 0.017 | L30: 0.011 | M30: 84 | N30: =VLOOKUP(A30,'Mandato Smll'!$A$2:$C$215,2,0) -> 0.020375717 | O30: =K30-N30 -> -0.0033757171 | P30: =B30-N30 -> -0.0033757171 | Q30: =VLOOKUP(A30,'Mandato Smll'!$A$2:$C$215,3,0) -> 0.014535756 | R30: =K30-Q30 -> 0.0024642437 | S30: 0.364 | T30: 0.748 | U30: 0.063 | V30: 0.314 | W30: 0.534 | X30: 0.517 | Y30: 0.561 | Z30: 0.61 | AA30: 1 | AB30: 1 | AC30: 0.908 | AD30: 0.93 | AE30: 0.994 | AF30: -0.446 | AG30: 0.492 | AH30: 1 | AI30: -0.262 | AJ30: 0.597 | AK30: -0.727 | AL30: -0.052 | AM30: 0.23 | AN30: -0.009 | AO30: 0.214 | AP30: 0.585 | AQ30: 0.458 | AR30: 0.102 | AS30: 0.169 | AT30: -0.314 | AU30: -0.006 | AV30: -0.224 | AW30: -0.281 | AX30: 0.654 | AY30: -0.396 | AZ30: 0.818 | BA30: 0.432 | BB30: 0.576 | BC30: 0.065 | BD30: 0.038 | BE30: 0.392 | BF30: 0.122 | BG30: -0.167 | BH30: 0.875 | BI30: -0.641 | BJ30: -0.095 | BK30: 0.431 | BL30: 0.43
A31: ALPA4 | B31: =K31 -> 0.012 | C31: =B31-E31 -> 0.008 | D31: =B31-K31 -> 0 | E31: =K31-L31 -> 0.004 | F31: 2.612 | G31: 2.366 | H31: pro_cyclicals | I31: =VLOOKUP(A31,Planilha6!$BL$9:$BN$222,2,0) -> apparel | J31: =VLOOKUP(A31,Planilha6!$BL$9:$BN$222,3,0) -> high_beta | K31: 0.012 | L31: 0.008 | M31: 84 | N31: =VLOOKUP(A31,'Mandato Smll'!$A$2:$C$215,2,0) -> 0.016652978 | O31: =K31-N31 -> -0.0046529777 | P31: =B31-N31 -> -0.0046529777 | Q31: =VLOOKUP(A31,'Mandato Smll'!$A$2:$C$215,3,0) -> 0.010913832 | R31: =K31-Q31 -> 0.0010861678 | S31: 0.769 | T31: 0.503 | U31: 0.539 | V31: 0.854 | W31: 0.765 | X31: 0.622 | Y31: 0.521 | Z31: 0.392 | AA31: 0.46 | AB31: 0.462 | AC31: 0.846 | AD31: 0.818 | AE31: 0.794 | AF31: 1 | AG31: 0.947 | AH31: -0.199 | AI31: -0.518 | AJ31: -0.122 | AK31: 0.311 | AL31: -0.406 | AM31: -0.083 | AN31: -0.771 | AO31: 0.575 | AP31: 0.373 | AQ31: -0.366 | AR31: 0.714 | AS31: 1 | AT31: 0.997 | AU31: 0.325 | AV31: -0.056 | AW31: 0.778 | AX31: 0.015 | AY31: -0.052 | AZ31: 0.261 | BA31: 0.362 | BB31: 0.471 | BC31: 0.457 | BD31: -0.16 | BE31: 0.703 | BF31: 0.062 | BG31: -0.297 | BH31: 0.377 | BI31: -0.188 | BJ31: 0.093 | BK31: 0.201 | BL31: -0.211
A32: SAPR11 | B32: 0.035 | C32: =B32-E32 -> 0.011 | D32: =B32-K32 -> 0.021 | E32: =K32-L32 -> 0.024 | F32: 2.581 | G32: 5.123 | H32: bond_proxies | I32: =VLOOKUP(A32,Planilha6!$BL$9:$BN$222,2,0) -> utilities | J32: =VLOOKUP(A32,Planilha6!$BL$9:$BN$222,3,0) -> neutral_beta | K32: 0.014 | L32: -0.01 | M32: 84 | N32: =VLOOKUP(A32,'Mandato Smll'!$A$2:$C$215,2,0) -> 0.057444843 | O32: =K32-N32 -> -0.043444843 | P32: =B32-N32 -> -0.022444843 | Q32: =VLOOKUP(A32,'Mandato Smll'!$A$2:$C$215,3,0) -> 0.045854787 | R32: =K32-Q32 -> -0.031854787 | S32: 0.34 | T32: 0.749 | U32: -0.043 | V32: 0.709 | W32: 0.738 | X32: 0.64 | Y32: 0.76 | Z32: 0.676 | AA32: 0.724 | AB32: 0.733 | AC32: 0.793 | AD32: 0.823 | AE32: 0.73 | AF32: 0.853 | AG32: 0.427 | AH32: 0.612 | AI32: -0.457 | AJ32: -0.553 | AK32: -0.148 | AL32: 0.484 | AM32: -0.228 | AN32: -0.316 | AO32: -0.075 | AP32: 0.21 | AQ32: -0.219 | AR32: 0.276 | AS32: -0.09 | AT32: -0.061 | AU32: 0.395 | AV32: 0.424 | AW32: 0.53 | AX32: 0.726 | AY32: -0.08 | AZ32: 0.149 | BA32: 0.78 | BB32: 0.212 | BC32: -0.133 | BD32: 0.179 | BE32: 0.209 | BF32: 0.131 | BG32: 1 | BH32: 0.423 | BI32: -0.833 | BJ32: -0.006 | BK32: -0.032 | BL32: 0.118
A33: POMO4 | B33: 0.025 | C33: =B33-E33 -> 0.011 | D33: =B33-K33 -> 0.011 | E33: =K33-L33 -> 0.014 | F33: 2.564 | G33: 3.723 | H33: industrials | I33: =VLOOKUP(A33,Planilha6!$BL$9:$BN$222,2,0) -> capital_goods | J33: =VLOOKUP(A33,Planilha6!$BL$9:$BN$222,3,0) -> high_beta | K33: 0.014 | L33: 0 | M33: 64 | N33: =VLOOKUP(A33,'Mandato Smll'!$A$2:$C$215,2,0) -> 0.037478796 | O33: =K33-N33 -> -0.023478796 | P33: =B33-N33 -> -0.012478796 | Q33: =VLOOKUP(A33,'Mandato Smll'!$A$2:$C$215,3,0) -> 0 | R33: =K33-Q33 -> 0.014 | S33: 0.558 | T33: 0.607 | U33: 0.207 | V33: 0.686 | W33: 0.684 | X33: 0.801 | Y33: 0.852 | Z33: 0.796 | AA33: 0.269 | AB33: 0.275 | AC33: 0.698 | AD33: 0.645 | AE33: 0.536 | AF33: 0.977 | AG33: 1 | AH33: -0.373 | AI33: -0.438 | AJ33: -0.404 | AK33: 0.405 | AL33: -0.003 | AM33: 0.384 | AN33: -0.614 | AO33: 0.468 | AP33: -0.364 | AQ33: 0.378 | AR33: 0.941 | AS33: 0.126 | AT33: -0.527 | AU33: 0.719 | AV33: -0.029 | AW33: 0.539 | AX33: 0.409 | AY33: 0.163 | AZ33: 0.91 | BA33: 1 | BB33: 0.837 | BC33: -0.046 | BD33: -0.167 | BE33: 0.084 | BF33: -0.345 | BG33: -0.598 | BH33: 0.554 | BI33: -0.923 | BJ33: 0.354 | BK33: -0.494 | BL33: -0.209
A34: LOGG3 | B34: =K34 -> 0.014 | C34: =B34-E34 -> 0.01 | D34: =B34-K34 -> 0 | E34: =K34-L34 -> 0.004 | F34: 2.512 | G34: 3.187 | H34: bond_proxies | I34: =VLOOKUP(A34,Planilha6!$BL$9:$BN$222,2,0) -> real_estate | J34: =VLOOKUP(A34,Planilha6!$BL$9:$BN$222,3,0) -> low_beta | K34: 0.014 | L34: 0.01 | M34: 84 | N34: =VLOOKUP(A34,'Mandato Smll'!$A$2:$C$215,2,0) -> 0.014551403 | O34: =K34-N34 -> -0.00055140341 | P34: =B34-N34 -> -0.00055140341 | Q34: =VLOOKUP(A34,'Mandato Smll'!$A$2:$C$215,3,0) -> 0 | R34: =K34-Q34 -> 0.014 | S34: 0.234 | T34: 0.711 | U34: 0.135 | V34: 0.235 | W34: 0.525 | X34: 0.44 | Y34: 0.755 | Z34: 0.617 | AA34: 0.758 | AB34: 0.764 | AC34: 0.928 | AD34: 0.849 | AE34: 0.899 | AF34: -0.115 | AG34: -0.275 | AH34: 1 | AI34: 0.248 | AJ34: 1 | AK34: -0.239 | AL34: -0.305 | AM34: 0.283 | AN34: -0.155 | AO34: -0.081 | AP34: 0.747 | AQ34: 0.064 | AR34: -0.126 | AS34: -0.043 | AT34: -0.039 | AU34: -0.077 | AV34: 0.688 | AW34: -0.158 | AX34: 0.345 | AY34: -0.782 | AZ34: 0.314 | BA34: -0.012 | BB34: -0.189 | BC34: 0.181 | BD34: 0.235 | BE34: 0.356 | BF34: 0.084 | BG34: -0.185 | BH34: 0.721 | BI34: -0.512 | BJ34: 0.063 | BK34: 0.333 | BL34: 0.283
A35: ODPV3 | B35: 0.02 | C35: =B35-E35 -> 0.009 | D35: =B35-K35 -> 0.01 | E35: =K35-L35 -> 0.011 | F35: 2.474 | G35: 3.361 | H35: defensives | I35: =VLOOKUP(A35,Planilha6!$BL$9:$BN$222,2,0) -> healthcare | J35: =VLOOKUP(A35,Planilha6!$BL$9:$BN$222,3,0) -> very_low_beta | K35: 0.01 | L35: -0.001 | M35: 84 | N35: =VLOOKUP(A35,'Mandato Smll'!$A$2:$C$215,2,0) -> 0.029881869 | O35: =K35-N35 -> -0.019881869 | P35: =B35-N35 -> -0.0098818695 | Q35: =VLOOKUP(A35,'Mandato Smll'!$A$2:$C$215,3,0) -> 0.018867324 | R35: =K35-Q35 -> -0.0088673244 | S35: 0.341 | T35: 0.755 | U35: 0.043 | V35: 0.326 | W35: 0.516 | X35: 0.642 | Y35: 0.921 | Z35: 0.699 | AA35: 0.543 | AB35: 0.549 | AC35: 0.69 | AD35: 0.702 | AE35: 0.679 | AF35: 0.549 | AG35: -0.607 | AH35: -0.312 | AI35: -0.751 | AJ35: -0.03 | AK35: 0.378 | AL35: -0.315 | AM35: -0.045 | AN35: -0.93 | AO35: -0.345 | AP35: 0.12 | AQ35: 1 | AR35: 0.004 | AS35: 0.134 | AT35: -0.309 | AU35: 0.969 | AV35: 0.426 | AW35: 1 | AX35: 0.764 | AY35: 0.427 | AZ35: 0.745 | BA35: 0.646 | BB35: 0.948 | BC35: 0.186 | BD35: -0.13 | BE35: 0.31 | BF35: -0.506 | BG35: -0.221 | BH35: 0.687 | BI35: -0.484 | BJ35: -0.431 | BK35: -0.028 | BL35: -0.122
A36: EVEN3 | B36: =K36 -> 0.018 | C36: =B36-E36 -> 0.014 | D36: =B36-K36 -> 0 | E36: =K36-L36 -> 0.004 | F36: 2.352 | G36: 2.766 | H36: pro_cyclicals | I36: =VLOOKUP(A36,Planilha6!$BL$9:$BN$222,2,0) -> homebuilders | J36: =VLOOKUP(A36,Planilha6!$BL$9:$BN$222,3,0) -> high_beta | K36: 0.018 | L36: 0.014 | M36: 84 | N36: =VLOOKUP(A36,'Mandato Smll'!$A$2:$C$215,2,0) -> 0.013019416 | O36: =K36-N36 -> 0.0049805839 | P36: =B36-N36 -> 0.0049805839 | Q36: =VLOOKUP(A36,'Mandato Smll'!$A$2:$C$215,3,0) -> 0 | R36: =K36-Q36 -> 0.018 | S36: 0.59 | T36: 0.187 | U36: 0.708 | V36: 0.431 | W36: 0.506 | X36: 0.459 | Y36: 0.34 | Z36: 0.301 | AA36: 0.554 | AB36: 0.556 | AC36: 0.841 | AD36: 0.924 | AE36: 0.776 | AF36: 0.691 | AG36: 0.635 | AH36: -0.165 | AI36: 0.395 | AJ36: 0.196 | AK36: -0.015 | AL36: -0.202 | AM36: 0.257 | AN36: -0.034 | AO36: 0.219 | AP36: -0.191 | AQ36: -0.15 | AR36: 0.405 | AS36: 0.92 | AT36: 0.84 | AU36: 0.016 | AV36: -0.342 | AW36: 0.313 | AX36: 0.061 | AY36: 0.027 | AZ36: 0.757 | BA36: 0.448 | BB36: 0.166 | BC36: -0.021 | BD36: -0.289 | BE36: -0.073 | BF36: 0.466 | BG36: -0.125 | BH36: 0.625 | BI36: -0.393 | BJ36: 0.359 | BK36: 0.485 | BL36: 0.411
A37: CURY3 | B37: 0.02 | C37: =B37-E37 -> 0.004 | D37: =B37-K37 -> 0.004 | E37: =K37-L37 -> 0.016 | F37: 2.352 | G37: 3.91 | H37: pro_cyclicals | I37: =VLOOKUP(A37,Planilha6!$BL$9:$BN$222,2,0) -> homebuilders | J37: =VLOOKUP(A37,Planilha6!$BL$9:$BN$222,3,0) -> low_beta | K37: 0.016 | L37: 0 | M37: 63 | N37: =VLOOKUP(A37,'Mandato Smll'!$A$2:$C$215,2,0) -> 0.039071906 | O37: =K37-N37 -> -0.023071906 | P37: =B37-N37 -> -0.019071906 | Q37: =VLOOKUP(A37,'Mandato Smll'!$A$2:$C$215,3,0) -> 0.025954032 | R37: =K37-Q37 -> -0.0099540323 | S37: 0.231 | T37: 0.503 | U37: -0.049 | V37: 0.509 | W37: 0.564 | X37: 0.494 | Y37: 0.537 | Z37: 0.721 | AA37: 0.622 | AB37: 0.627 | AC37: 0.794 | AD37: 0.796 | AE37: 0.656 | AF37: 0.712 | AG37: 0.257 | AH37: -0.238 | AI37: -0.628 | AJ37: -0.21 | AK37: -0.034 | AL37: -0.137 | AM37: 0.385 | AN37: -0.856 | AO37: 0.119 | AP37: 0.177 | AQ37: 0.465 | AR37: 0.449 | AS37: 0.193 | AT37: 0.385 | AU37: 1 | AV37: 0.102 | AW37: 0.546 | AX37: 0.144 | AY37: 0.31 | AZ37: 0.841 | BA37: 0.963 | BB37: 0.326 | BC37: -0.759 | BD37: -0.295 | BE37: -0.274 | BF37: 0.573 | BG37: -0.043 | BH37: 0.335 | BI37: -0.981 | BJ37: 0.172 | BK37: -0.427 | BL37: -0.336
A38: ALOS3 | B38: 0.04 | C38: =B38-E38 -> -0.003 | D38: =B38-K38 -> 0.015 | E38: =K38-L38 -> 0.043 | F38: 2.348 | G38: 5.059 | H38: bond_proxies | I38: =VLOOKUP(A38,Planilha6!$BL$9:$BN$222,2,0) -> real_estate | J38: =VLOOKUP(A38,Planilha6!$BL$9:$BN$222,3,0) -> high_beta | K38: 0.025 | L38: -0.018 | M38: 38 | N38: =VLOOKUP(A38,'Mandato Smll'!$A$2:$C$215,2,0) -> 0.052260977 | O38: =K38-N38 -> -0.027260977 | P38: =B38-N38 -> -0.012260977 | Q38: =VLOOKUP(A38,'Mandato Smll'!$A$2:$C$215,3,0) -> 0.050045507 | R38: =K38-Q38 -> -0.025045507 | S38: 0.19 | T38: 0.836 | U38: -0.35 | V38: 0.447 | W38: 0.505 | X38: 0.613 | Y38: 0.906 | Z38: 0.58 | AA38: 0.67 | AB38: 0.675 | AC38: 0.757 | AD38: 0.723 | AE38: 0.693 | AF38: 0.628 | AG38: -0.127 | AH38: 0.518 | AI38: -0.772 | AJ38: -0.114 | AK38: -0.293 | AL38: -0.079 | AM38: -0.193 | AN38: -0.513 | AO38: 0.018 | AP38: 0.598 | AQ38: 0.472 | AR38: 0.265 | AS38: 0.286 | AT38: -0.136 | AU38: 0.015 | AV38: 0.87 | AW38: 0.656 | AX38: 0.319 | AY38: 0.293 | AZ38: 0.577 | BA38: 0.419 | BB38: -0.7 | BC38: -0.048 | BD38: -0.143 | BE38: 0.363 | BF38: -0.388 | BG38: 0.155 | BH38: 0.749 | BI38: -0.489 | BJ38: 0.381 | BK38: -0.587 | BL38: -0.416
A39: ITSA3 | B39: =K39 -> 0.02 | C39: =B39-E39 -> 0.02 | D39: =B39-K39 -> 0 | E39: =K39-L39 -> 0 | F39: 2.334 | G39: 3.173 | H39: pro_cyclicals | I39: =VLOOKUP(A39,Planilha6!$BL$9:$BN$222,2,0) -> banks | J39: =VLOOKUP(A39,Planilha6!$BL$9:$BN$222,3,0) -> neutral_beta | K39: 0.02 | L39: 0.02 | M39: 84 | N39: =VLOOKUP(A39,'Mandato Smll'!$A$2:$C$215,2,0) -> 0.0095137957 | O39: =K39-N39 -> 0.010486204 | P39: =B39-N39 -> 0.010486204 | Q39: =VLOOKUP(A39,'Mandato Smll'!$A$2:$C$215,3,0) -> 0.0098111596 | R39: =K39-Q39 -> 0.01018884 | S39: 0.126 | T39: 0.664 | U39: -0.309 | V39: 0.276 | W39: 0.389 | X39: 0.442 | Y39: 0.616 | Z39: 0.61 | AA39: 0.752 | AB39: 0.76 | AC39: 0.8 | AD39: 0.886 | AE39: 0.873 | AF39: 0.106 | AG39: -0.297 | AH39: 0.557 | AI39: -0.966 | AJ39: -0.636 | AK39: -0.845 | AL39: -0.149 | AM39: 0.186 | AN39: -0.665 | AO39: -0.399 | AP39: 0.671 | AQ39: 0.685 | AR39: -0.01 | AS39: 0.171 | AT39: 0.41 | AU39: 0.058 | AV39: 0.051 | AW39: 0.294 | AX39: 0.502 | AY39: -0.451 | AZ39: 0.936 | BA39: 0.252 | BB39: 0.911 | BC39: -0.023 | BD39: 0.321 | BE39: 0.521 | BF39: -0.231 | BG39: -0.275 | BH39: 0.832 | BI39: -0.668 | BJ39: -0.017 | BK39: 0.885 | BL39: -0.689
A40: MELK3 | B40: =K40 -> 0.014 | C40: =B40-E40 -> 0.014 | D40: =B40-K40 -> 0 | E40: =K40-L40 -> 0 | F40: 2.315 | G40: 2.504 | H40: pro_cyclicals | I40: =VLOOKUP(A40,Planilha6!$BL$9:$BN$222,2,0) -> homebuilders | J40: =VLOOKUP(A40,Planilha6!$BL$9:$BN$222,3,0) -> neutral_beta | K40: 0.014 | L40: 0.014 | M40: 84 | N40: =VLOOKUP(A40,'Mandato Smll'!$A$2:$C$215,2,0) -> 0.0094367895 | O40: =K40-N40 -> 0.0045632105 | P40: =B40-N40 -> 0.0045632105 | Q40: =VLOOKUP(A40,'Mandato Smll'!$A$2:$C$215,3,0) -> 0 | R40: =K40-Q40 -> 0.014 | S40: 0.201 | T40: 0.158 | U40: 0.57 | V40: 0.021 | W40: 0.365 | X40: 0.364 | Y40: 0.486 | Z40: 0.733 | AA40: 0.636 | AB40: 0.637 | AC40: 0.825 | AD40: 0.699 | AE40: 0.749 | AF40: 0.156 | AG40: -0.116 | AH40: -0.124 | AI40: 0.978 | AJ40: 0.649 | AK40: -0.077 | AL40: -0.165 | AM40: 0.986 | AN40: -0.031 | AO40: -0.049 | AP40: -0.128 | AQ40: -0.022 | AR40: 0.021 | AS40: -0.13 | AT40: -0.125 | AU40: 0.016 | AV40: -0.412 | AW40: -0.064 | AX40: 0.598 | AY40: -0.367 | AZ40: 0.678 | BA40: 0.411 | BB40: 0.231 | BC40: -0.029 | BD40: -0.434 | BE40: -0.499 | BF40: 0.43 | BG40: 0.671 | BH40: 0.881 | BI40: -0.404 | BJ40: 0.265 | BK40: 0.729 | BL40: 0.638
A41: VLID3 | B41: =K41 -> 0.017 | C41: =B41-E41 -> 0.012 | D41: =B41-K41 -> 0 | E41: =K41-L41 -> 0.005 | F41: 2.277 | G41: 2.73 | H41: pro_cyclicals | I41: =VLOOKUP(A41,Planilha6!$BL$9:$BN$222,2,0) -> tech | J41: =VLOOKUP(A41,Planilha6!$BL$9:$BN$222,3,0) -> low_beta | K41: 0.017 | L41: 0.012 | M41: 84 | N41: =VLOOKUP(A41,'Mandato Smll'!$A$2:$C$215,2,0) -> 0.013954819 | O41: =K41-N41 -> 0.0030451813 | P41: =B41-N41 -> 0.0030451813 | Q41: =VLOOKUP(A41,'Mandato Smll'!$A$2:$C$215,3,0) -> 0.011657193 | R41: =K41-Q41 -> 0.0053428066 | S41: 0.459 | T41: 0.329 | U41: 0.609 | V41: 0.231 | W41: 0.442 | X41: 0.459 | Y41: 0.496 | Z41: 0.317 | AA41: 0.585 | AB41: 0.592 | AC41: 0.824 | AD41: 0.795 | AE41: 0.742 | AF41: 0.208 | AG41: 0.34 | AH41: -0.365 | AI41: 0.246 | AJ41: -0.139 | AK41: 1 | AL41: 0.245 | AM41: 0.089 | AN41: -0.326 | AO41: -0.038 | AP41: -0.137 | AQ41: -0.088 | AR41: 0.47 | AS41: 0.275 | AT41: 0.1 | AU41: 0.428 | AV41: -0.036 | AW41: -0.041 | AX41: 0.442 | AY41: 0.223 | AZ41: 0.733 | BA41: 0.469 | BB41: 0.797 | BC41: -0.083 | BD41: -0.056 | BE41: -0.021 | BF41: 0.3 | BG41: -0.092 | BH41: 0.75 | BI41: -0.785 | BJ41: -0.164 | BK41: 0.5 | BL41: 0.349
A42: TRIS3 | B42: =K42 -> 0.007 | C42: =B42-E42 -> 0.007 | D42: =B42-K42 -> 0 | E42: =K42-L42 -> 0 | F42: 2.228 | G42: 1.602 | H42: pro_cyclicals | I42: =VLOOKUP(A42,Planilha6!$BL$9:$BN$222,2,0) -> homebuilders | J42: =VLOOKUP(A42,Planilha6!$BL$9:$BN$222,3,0) -> high_beta | K42: 0.007 | L42: 0.007 | M42: 84 | N42: =VLOOKUP(A42,'Mandato Smll'!$A$2:$C$215,2,0) -> 0.0090793781 | O42: =K42-N42 -> -0.0020793781 | P42: =B42-N42 -> -0.0020793781 | Q42: =VLOOKUP(A42,'Mandato Smll'!$A$2:$C$215,3,0) -> 0 | R42: =K42-Q42 -> 0.007 | S42: 0.576 | T42: 0.225 | U42: 0.71 | V42: 0.357 | W42: 0.483 | X42: 0.404 | Y42: 0.292 | Z42: 0.304 | AA42: 0.369 | AB42: 0.367 | AC42: 0.876 | AD42: 0.737 | AE42: 0.718 | AF42: 0.579 | AG42: 0.806 | AH42: -0.356 | AI42: 0.406 | AJ42: 0.338 | AK42: 0.348 | AL42: -0.186 | AM42: 0.315 | AN42: -0.306 | AO42: 0.588 | AP42: 0.137 | AQ42: -0.187 | AR42: 0.604 | AS42: -0.009 | AT42: -0.339 | AU42: 0.092 | AV42: -0.106 | AW42: 0.251 | AX42: -0.26 | AY42: 0.034 | AZ42: 0.671 | BA42: 0.612 | BB42: 0.804 | BC42: -0.004 | BD42: -0.325 | BE42: 0.099 | BF42: 0.641 | BG42: -0.541 | BH42: 0.375 | BI42: -0.559 | BJ42: 0.603 | BK42: 0.757 | BL42: 0.413
A43: VULC3 | B43: =K43 -> 0.019 | C43: =B43-E43 -> 0.013 | D43: =B43-K43 -> 0 | E43: =K43-L43 -> 0.006 | F43: 2.224 | G43: 3.083 | H43: pro_cyclicals | I43: =VLOOKUP(A43,Planilha6!$BL$9:$BN$222,2,0) -> apparel | J43: =VLOOKUP(A43,Planilha6!$BL$9:$BN$222,3,0) -> low_beta | K43: 0.019 | L43: 0.013 | M43: 84 | N43: =VLOOKUP(A43,'Mandato Smll'!$A$2:$C$215,2,0) -> 0.015389821 | O43: =K43-N43 -> 0.0036101788 | P43: =B43-N43 -> 0.0036101788 | Q43: =VLOOKUP(A43,'Mandato Smll'!$A$2:$C$215,3,0) -> 0 | R43: =K43-Q43 -> 0.019 | S43: -0.101 | T43: 0.229 | U43: 0.038 | V43: 0.215 | W43: 0.454 | X43: 0.487 | Y43: 0.823 | Z43: 1 | AA43: 0.613 | AB43: 0.619 | AC43: 0.748 | AD43: 0.643 | AE43: 0.474 | AF43: 0.758 | AG43: 0.219 | AH43: -0.642 | AI43: -0.236 | AJ43: -0.575 | AK43: 0.381 | AL43: -0.273 | AM43: 1 | AN43: -0.745 | AO43: 0.552 | AP43: -0.275 | AQ43: -0.514 | AR43: 0.288 | AS43: -0.057 | AT43: -0.397 | AU43: 0.831 | AV43: 0.138 | AW43: 0.366 | AX43: 0.373 | AY43: -0.058 | AZ43: 0.724 | BA43: 1 | BB43: 0.073 | BC43: -0.709 | BD43: -0.767 | BE43: -0.525 | BF43: 0.109 | BG43: -0.056 | BH43: 0.797 | BI43: -0.746 | BJ43: -0.25 | BK43: 0.171 | BL43: 0.089
A44: INTB3 | B44: =K44 -> 0.017 | C44: =B44-E44 -> 0.012 | D44: =B44-K44 -> 0 | E44: =K44-L44 -> 0.005 | F44: 2.221 | G44: 2.509 | H44: pro_cyclicals | I44: =VLOOKUP(A44,Planilha6!$BL$9:$BN$222,2,0) -> tech | J44: =VLOOKUP(A44,Planilha6!$BL$9:$BN$222,3,0) -> high_beta | K44: 0.017 | L44: 0.012 | M44: 84 | N44: =VLOOKUP(A44,'Mandato Smll'!$A$2:$C$215,2,0) -> 0.01383122 | O44: =K44-N44 -> 0.0031687803 | P44: =B44-N44 -> 0.0031687803 | Q44: =VLOOKUP(A44,'Mandato Smll'!$A$2:$C$215,3,0) -> 0.0098315964 | R44: =K44-Q44 -> 0.0071684036 | S44: 0.563 | T44: 0.544 | U44: 0.256 | V44: 0.334 | W44: 0.404 | X44: 0.393 | Y44: 0.308 | Z44: 0.174 | AA44: 0.533 | AB44: 0.537 | AC44: 0.833 | AD44: 0.852 | AE44: 0.821 | AF44: 0.285 | AG44: -0.339 | AH44: 0.348 | AI44: -0.327 | AJ44: 0.589 | AK44: 0.078 | AL44: 0.095 | AM44: -0.242 | AN44: -0.645 | AO44: 0.766 | AP44: 0.359 | AQ44: 0.789 | AR44: 0.075 | AS44: 0.135 | AT44: 0.173 | AU44: 0.532 | AV44: -0.093 | AW44: 0.353 | AX44: 0.208 | AY44: 0.38 | AZ44: 0.817 | BA44: 0.293 | BB44: 0.164 | BC44: 0.12 | BD44: 0.09 | BE44: 0.386 | BF44: 0.304 | BG44: 0.443 | BH44: 0.464 | BI44: 0.03 | BJ44: 0.09 | BK44: 0.002 | BL44: -0.111
A45: BMEB4 | B45: =K45 -> 0.007 | C45: =B45-E45 -> 0.007 | D45: =B45-K45 -> 0 | E45: =K45-L45 -> 0 | F45: 2.182 | G45: 1.577 | H45: pro_cyclicals | I45: =VLOOKUP(A45,Planilha6!$BL$9:$BN$222,2,0) -> banks | J45: =VLOOKUP(A45,Planilha6!$BL$9:$BN$222,3,0) -> high_beta | K45: 0.007 | L45: 0.007 | M45: 84 | N45: =VLOOKUP(A45,'Mandato Smll'!$A$2:$C$215,2,0) -> 0.0088927912 | O45: =K45-N45 -> -0.0018927912 | P45: =B45-N45 -> -0.0018927912 | Q45: =VLOOKUP(A45,'Mandato Smll'!$A$2:$C$215,3,0) -> 0.0077057478 | R45: =K45-Q45 -> -0.0007057478 | S45: 0.311 | T45: 0.549 | U45: 0.414 | V45: 0.177 | W45: 0.504 | X45: 0.172 | Y45: 0.007 | Z45: 0.139 | AA45: 0.888 | AB45: 0.889 | AC45: 0.962 | AD45: 0.932 | AE45: 0.968 | AF45: -0.517 | AG45: 0.051 | AH45: 0.466 | AI45: -0.718 | AJ45: 0.615 | AK45: -0.055 | AL45: -0.097 | AM45: -0.406 | AN45: -0.587 | AO45: -0.613 | AP45: 0.713 | AQ45: 0.805 | AR45: 0.324 | AS45: 1 | AT45: 0.681 | AU45: 0.363 | AV45: -0.084 | AW45: -0.053 | AX45: 0.382 | AY45: 0.089 | AZ45: 0.62 | BA45: 1 | BB45: 0.233 | BC45: -0.535 | BD45: -0.208 | BE45: -0.461 | BF45: 0.477 | BG45: 0.174 | BH45: 0.328 | BI45: -1 | BJ45: 0.306 | BK45: 0.906 | BL45: 0.399
A46: MLAS3 | B46: =K46 -> 0.012 | C46: =B46-E46 -> 0.012 | D46: =B46-K46 -> 0 | E46: =K46-L46 -> 0 | F46: 2.15 | G46: 1.579 | H46: pro_cyclicals | I46: =VLOOKUP(A46,Planilha6!$BL$9:$BN$222,2,0) -> tech | J46: =VLOOKUP(A46,Planilha6!$BL$9:$BN$222,3,0) -> neutral_beta | K46: 0.012 | L46: 0.012 | M46: 84 | N46: =VLOOKUP(A46,'Mandato Smll'!$A$2:$C$215,2,0) -> 0.0087606885 | O46: =K46-N46 -> 0.0032393115 | P46: =B46-N46 -> 0.0032393115 | Q46: =VLOOKUP(A46,'Mandato Smll'!$A$2:$C$215,3,0) -> 0 | R46: =K46-Q46 -> 0.012 | S46: 0.946 | T46: 0.209 | U46: 0.956 | V46: 0.491 | W46: 0.448 | X46: 0.177 | Y46: -0.253 | Z46: -0.459 | AA46: 0.719 | AB46: 0.721 | AC46: 0.983 | AD46: 1 | AE46: 1 | AF46: 0.592 | AG46: 0.402 | AH46: 0.474 | AI46: 0.266 | AJ46: 0.381 | AK46: 0.307 | AL46: -0.221 | AM46: -0.791 | AN46: 0.558 | AO46: 0.31 | AP46: 0.412 | AQ46: -0.161 | AR46: 0.285 | AS46: 1 | AT46: 0.803 | AU46: 0.001 | AV46: -0.315 | AW46: 0.383 | AX46: -0.457 | AY46: 0.371 | AZ46: 0.614 | BA46: -0.004 | BB46: 0.885 | BC46: 0.308 | BD46: -0.192 | BE46: 0.664 | BF46: -0.495 | BG46: 0.131 | BH46: 0.217 | BI46: 0.498 | BJ46: -0.127 | BK46: 0.887 | BL46: 0.482
A47: ALUP11 | B47: =K47 -> 0.016 | C47: =B47-E47 -> 0 | D47: =B47-K47 -> 0 | E47: =K47-L47 -> 0.016 | F47: 2.081 | G47: 4.482 | H47: bond_proxies | I47: =VLOOKUP(A47,Planilha6!$BL$9:$BN$222,2,0) -> utilities | J47: =VLOOKUP(A47,Planilha6!$BL$9:$BN$222,3,0) -> very_low_beta | K47: 0.016 | L47: 0 | M47: 84 | N47: =VLOOKUP(A47,'Mandato Smll'!$A$2:$C$215,2,0) -> 0.034045299 | O47: =K47-N47 -> -0.018045299 | P47: =B47-N47 -> -0.018045299 | Q47: =VLOOKUP(A47,'Mandato Smll'!$A$2:$C$215,3,0) -> 0.030900746 | R47: =K47-Q47 -> -0.014900746 | S47: -0.121 | T47: 0.68 | U47: -0.33 | V47: 0.019 | W47: 0.337 | X47: 0.383 | Y47: 0.725 | Z47: 0.479 | AA47: 0.88 | AB47: 0.886 | AC47: 0.704 | AD47: 0.902 | AE47: 0.744 | AF47: 0.101 | AG47: -0.581 | AH47: 0.371 | AI47: -0.705 | AJ47: -0.306 | AK47: -0.756 | AL47: -0.049 | AM47: -0.428 | AN47: -0.287 | AO47: -0.368 | AP47: 0.347 | AQ47: 0.403 | AR47: -0.109 | AS47: 0.07 | AT47: 0.307 | AU47: 0.06 | AV47: 0.708 | AW47: 0.278 | AX47: 0.791 | AY47: -0.504 | AZ47: 0.818 | BA47: 1 | BB47: 0.021 | BC47: 0.03 | BD47: -0.223 | BE47: 0.284 | BF47: 0.147 | BG47: -0.233 | BH47: 0.937 | BI47: -0.494 | BJ47: -0.403 | BK47: 0.298 | BL47: 0.118
A48: PNVL3 | B48: =K48 -> 0.019 | C48: =B48-E48 -> 0.016 | D48: =B48-K48 -> 0 | E48: =K48-L48 -> 0.003 | F48: 2.065 | G48: 2.502 | H48: defensives | I48: =VLOOKUP(A48,Planilha6!$BL$9:$BN$222,2,0) -> healthcare | J48: =VLOOKUP(A48,Planilha6!$BL$9:$BN$222,3,0) -> neutral_beta | K48: 0.019 | L48: 0.016 | M48: 84 | N48: =VLOOKUP(A48,'Mandato Smll'!$A$2:$C$215,2,0) -> 0.010514988 | O48: =K48-N48 -> 0.008485012 | P48: =B48-N48 -> 0.008485012 | Q48: =VLOOKUP(A48,'Mandato Smll'!$A$2:$C$215,3,0) -> 0.011859946 | R48: =K48-Q48 -> 0.0071400543 | S48: 0.451 | T48: 0.491 | U48: 0.285 | V48: 0.336 | W48: 0.41 | X48: 0.276 | Y48: 0.274 | Z48: -0.087 | AA48: 0.556 | AB48: 0.56 | AC48: 0.898 | AD48: 1 | AE48: 0.915 | AF48: -0.145 | AG48: -0.352 | AH48: 0.782 | AI48: -0.374 | AJ48: 1 | AK48: 0.352 | AL48: -0.173 | AM48: -0.6 | AN48: -0.581 | AO48: 0.095 | AP48: 0.719 | AQ48: 0.665 | AR48: 0.332 | AS48: 0.214 | AT48: 0.475 | AU48: 0.526 | AV48: -0.321 | AW48: 0.467 | AX48: 0.398 | AY48: -0.129 | AZ48: 0.999 | BA48: -0.28 | BB48: 0.779 | BC48: -0.285 | BD48: -0.276 | BE48: 0.166 | BF48: 0.299 | BG48: -0.692 | BH48: 0.672 | BI48: -0.306 | BJ48: -0.034 | BK48: 0.269 | BL48: 0.402
